Workbook

Sheet Payment Entry
A1: Amended From | B1: ID | C1: Series | D1: Payment Type | E1: Posting Date | F1: Company | G1: Account Paid From | H1: Account Currency (From) | I1: Account Paid To | J1: Account Currency (To) | K1: Paid Amount | L1: Source Exchange Rate | M1: Paid Amount (Company Currency) | N1: Received Amount | O1: Target Exchange Rate | P1: Received Amount (Company Currency) | Q1: Workflow State | R1: Payment Order Status | S1: Mode of Payment | T1: Party Type | U1: Party | V1: Party Name | W1: Book Advance Payments in Separate Party Account | X1: Reconcile on Advance Payment Date | Y1: Company Bank Account | Z1: Party Bank Account | AA1: Contact | AB1: Email | AC1: Party Balance | AD1: Paid From Account Type | AE1: Account Balance (From) | AF1: Paid To Account Type | AG1: Account Balance (To) | AH1: Paid Amount After Tax | AI1: Paid Amount After Tax (Company Currency) | AJ1: Received Amount After Tax | AK1: Received Amount After Tax (Company Currency) | AL1: Total Allocated Amount | AM1: Total Allocated Amount (Company Currency) | AN1: Unallocated Amount | AO1: Difference Amount (Company Currency) | AP1: Purchase Taxes and Charges Template | AQ1: Sales Taxes and Charges Template | AR1: Apply Tax Withholding Amount | AS1: Tax Withholding Category | AT1: Total Taxes and Charges (Company Currency) | AU1: Total Taxes and Charges | AV1: Company Address | AW1: Company GSTIN | AX1: Place of Supply | AY1: Customer Address | AZ1: Customer GSTIN | BA1: GST Category | BB1: Cheque/Reference No | BC1: Cheque/Reference Date | BD1: Clearance Date | BE1: Project | BF1: Branch | BG1: Cost Center | BH1: Status | BI1: Custom Remarks | BJ1: Remarks | BK1: In Words (Company Currency) | BL1: Is Opening | BM1: Letter Head | BN1: Print Heading | BO1: Bank | BP1: Bank Account No | BQ1: Payment Order | BR1: In Words | BS1: Auto Repeat | BT1: Title | BU1: ID (Payment References) | BV1: Account (Payment References) | BW1: Account Type (Payment References) | BX1: Allocated (Payment References) | BY1: Due Date (Payment References) | BZ1: Exchange Gain/Loss (Payment References) | CA1: Exchange Rate (Payment References) | CB1: Grand Total (Payment References) | CC1: Name (Payment References) | CD1: Outstanding (Payment References) | CE1: Payment Request (Payment References) | CF1: Payment Term (Payment References) | CG1: Payment Term Outstanding (Payment References) | CH1: Payment Type (Payment References) | CI1: Reconcile Effect On (Payment References) | CJ1: Supplier Invoice No (Payment References) | CK1: Type (Payment References) | CL1: ID (Advance Taxes and Charges) | CM1: Account Currency (Advance Taxes and Charges) | CN1: Account Head (Advance Taxes and Charges) | CO1: Add Or Deduct (Advance Taxes and Charges) | CP1: Allocated Amount (Advance Taxes and Charges) | CQ1: Amount (Advance Taxes and Charges) | CR1: Amount (Company Currency) (Advance Taxes and Charges) | CS1: Considered In Paid Amount (Advance Taxes and Charges) | CT1: Cost Center (Advance Taxes and Charges) | CU1: Description (Advance Taxes and Charges) | CV1: GST Tax Type (Advance Taxes and Charges) | CW1: Reference Row # (Advance Taxes and Charges) | CX1: Tax Rate (Advance Taxes and Charges) | CY1: Total (Advance Taxes and Charges) | CZ1: Total (Company Currency) (Advance Taxes and Charges) | DA1: Type (Advance Taxes and Charges) | DB1: ID (Payment Deductions or Loss) | DC1: Account (Payment Deductions or Loss) | DD1: Amount (Company Currency) (Payment Deductions or Loss) | DE1: Branch (Payment Deductions or Loss) | DF1: Cost Center (Payment Deductions or Loss) | DG1: Description (Payment Deductions or Loss) | DH1: Is Exchange Gain / Loss? (Payment Deductions or Loss)
A2: PAY/G/25-26/1538 | B2: PAY/G/25-26/1538-1 | C2: PAY/G/23-24/.#### | D2: Pay | E2: 45869 | F2: G. C. Foods Pvt. Ltd. | G2: 9210300223943516 - Axis Bank Ltd. CC Tronica - GCF | H2: INR | I2: Creditors - GCF | J2: INR | K2: 87439 | L2: 1 | M2: 87439 | N2: 87439 | O2: 1 | P2: 87439 | Q2: Approved | R2: Initiated | S2: NEFT/RTGS | T2: Supplier | U2: Axis Bank (Term Loan 921060054746668) | V2: Axis Bank (Term Loan 921060054746668) | W2: 0 | X2: 0 | Y2: AXIS BANK 921030023943516 - GZB | AC2: 2135865 | AD2: Bank | AE2: 11209075 | AF2: Payable | AG2: 2135865 | AH2: 87439 | AI2: 87439 | AJ2: 87439 | AK2: 87439 | AL2: 0 | AM2: 0 | AN2: 87439 | AO2: 0 | AR2: 0 | AT2: 0 | AU2: 0 | AV2: G.C. Foods Pvt. Ltd.Ghaziabad - Uttar Pradesh-Billing | AW2: 09AACCG2244H1ZS | BB2: N/A | BC2: 45869 | BF2: Ghaziabad | BH2: Cancelled | BI2: 0 | BJ2: Amount INR 87439.0 to Axis Bank (Term Loan 921060054746668) Transaction reference no N/A dated 2025-07-31 | BK2: INR Eighty Seven Thousand, Four Hundred And Thirty Nine only. | BL2: No | BM2: GCF Letterhead | BO2: AXIS BANK | BP2: 921030023943516 | BR2: INR Eighty Seven Thousand, Four Hundred And Thirty Nine only. | BT2: Axis Bank (Term Loan 921060054746668)
A3: PAY/G/25-26/1537 | B3: PAY/G/25-26/1537-1 | C3: PAY/G/23-24/.#### | D3: Pay | E3: 45759 | F3: G. C. Foods Pvt. Ltd. | G3: 922020051221442 - Axis Bank - GZB - GCF | H3: INR | I3: Creditors - GCF | J3: INR | K3: 40000 | L3: 1 | M3: 40000 | N3: 40000 | O3: 1 | P3: 40000 | Q3: Approved | R3: Initiated | T3: Supplier | U3: Freight Outward Non TDS | V3: Freight Outward Non TDS | W3: 0 | X3: 0 | Y3: AXIS BANK 922020051221442 - GZB | AC3: -43600 | AD3: Bank | AE3: 101269.38 | AF3: Payable | AG3: -43600 | AH3: 40000 | AI3: 40000 | AJ3: 40000 | AK3: 40000 | AL3: 0 | AM3: 0 | AN3: 40000 | AO3: 0 | AR3: 0 | AT3: 0 | AU3: 0 | AV3: G.C. Foods Pvt. Ltd.Ghaziabad - Uttar Pradesh-Billing | AW3: 09AACCG2244H1ZS | BB3: NA | BC3: 45749 | BF3: Ghaziabad | BH3: Cancelled | BI3: 0 | BJ3: Amount INR 40000 to Freight Outward Non TDS Transaction reference no NA dated 2025-04-02 | BK3: INR Forty Thousand only. | BL3: No | BM3: GCF Letterhead | BO3: AXIS BANK | BP3: 922020051221442 | BR3: INR Forty Thousand only. | BT3: Freight Outward Non TDS
A4: PAY/M/25-26/0946 | B4: PAY/M/25-26/0946-1 | C4: PAY/G/23-24/.#### | D4: Receive | E4: 45869 | F4: G. C. Foods Pvt. Ltd. | G4: Debtors - GCF | H4: INR | I4: 9210300223943516 - Axis Bank Ltd. CC Tronica - GCF | J4: INR | K4: 400000 | L4: 1 | M4: 400000 | N4: 400000 | O4: 1 | P4: 400000 | Q4: Approved | R4: Initiated | S4: NEFT/RTGS | T4: Customer | U4: G.C.foods Pvt Ltd (T) | V4: G.C.foods Pvt Ltd (T) | W4: 0 | X4: 0 | Y4: AXIS BANK 921030023943516 - GZB | AC4: -33308502 | AD4: Receivable | AE4: -33308502 | AF4: Bank | AG4: -56190692 | AH4: 400000 | AI4: 400000 | AJ4: 400000 | AK4: 400000 | AL4: 0 | AM4: 0 | AN4: 400000 | AO4: 0 | AR4: 0 | AT4: 0 | AU4: 0 | AV4: GC Foods Muzaffarpur-Billing | AW4: 10AACCG2244H1Z9 | AX4: 09-Uttar Pradesh | AY4: G.C.foods Pvt Ltd (T)-Billing | AZ4: 09AACCG2244H1ZS | BA4: Registered Regular | BB4: N/A | BC4: 45869 | BF4: Muzaffarpur | BH4: Cancelled | BI4: 0 | BJ4: Amount INR 400000 received from G.C.foods Pvt Ltd (T) Transaction reference no N/A dated 2025-07-31 | BK4: INR Four Lakh only. | BL4: No | BM4: GCF Letterhead | BO4: AXIS BANK | BP4: 921030023943516 | BR4: INR Four Lakh only. | BT4: G.C.foods Pvt Ltd (T)
A5: PAY/G/25-26/1502 | B5: PAY/G/25-26/1502-1 | C5: PAY/G/23-24/.#### | D5: Pay | E5: 45867 | F5: G. C. Foods Pvt. Ltd. | G5: 9210300223943516 - Axis Bank Ltd. CC Tronica - GCF | H5: INR | I5: Creditors - GCF | J5: INR | K5: 18195 | L5: 1 | M5: 18195 | N5: 18195 | O5: 1 | P5: 18195 | Q5: Approved | R5: Initiated | S5: NEFT/RTGS | T5: Supplier | U5: Harish C. Khosla & Co. | V5: Harish C Khosla & Co. | W5: 0 | X5: 0 | Y5: AXIS BANK 921030023943516 - GZB | AC5: -0.4 | AD5: Bank | AE5: -52358625 | AF5: Payable | AG5: -0.4 | AH5: 18195 | AI5: 18195 | AJ5: 18195 | AK5: 18195 | AL5: 0 | AM5: 0 | AN5: 18195 | AO5: 0 | AR5: 0 | AT5: 0 | AU5: 0 | AV5: G.C. Foods Pvt. Ltd.Ghaziabad - Uttar Pradesh-Billing | AW5: 09AACCG2244H1ZS | BB5: N/A | BC5: 45867 | BF5: Ghaziabad | BH5: Cancelled | BI5: 1 | BJ5: Being PAyment Agst-HK/25-26/1106 | BK5: INR Eighteen Thousand, One Hundred And Ninety Five only. | BL5: No | BM5: GCF Letterhead | BO5: AXIS BANK | BP5: 921030023943516 | BR5: INR Eighteen Thousand, One Hundred And Ninety Five only. | BT5: Harish C. Khosla & Co.
A6: PAY/G/25-26/1494 | B6: PAY/G/25-26/1494-1 | C6: PAY/G/23-24/.#### | D6: Receive | E6: 45868 | F6: G. C. Foods Pvt. Ltd. | G6: Debtors - GCF | H6: INR | I6: 9210300223943516 - Axis Bank Ltd. CC Tronica - GCF | J6: INR | K6: 200000 | L6: 1 | M6: 200000 | N6: 200000 | O6: 1 | P6: 200000 | Q6: Approved | R6: Initiated | S6: NEFT/RTGS | T6: Customer | U6: CASH | V6: CASH | W6: 0 | X6: 0 | Y6: AXIS BANK 921030023943516 - GZB | AC6: 89638.06 | AD6: Receivable | AE6: 89638.06 | AF6: Bank | AG6: -49378142 | AH6: 200000 | AI6: 200000 | AJ6: 200000 | AK6: 200000 | AL6: 0 | AM6: 0 | AN6: 200000 | AO6: 0 | AR6: 0 | AT6: 0 | AU6: 0 | AV6: G.C. Foods Pvt. Ltd.Ghaziabad - Uttar Pradesh-Billing | AW6: 09AACCG2244H1ZS | AX6: 10-Bihar | BA6: Unregistered | BB6: N/A | BC6: 45867 | BF6: Ghaziabad | BH6: Cancelled | BI6: 1 | BJ6: Cash Deposit | BK6: INR Two Lakh only. | BL6: No | BM6: GCF Letterhead | BO6: AXIS BANK | BP6: 921030023943516 | BR6: INR Two Lakh only. | BT6: CASH
A7: PAY/M/25-26/0940 | B7: PAY/M/25-26/0940-1 | C7: PAY/G/23-24/.#### | D7: Receive | E7: 45867 | F7: G. C. Foods Pvt. Ltd. | G7: Debtors - GCF | H7: INR | I7: 923020053773708 - Axis Bank - Bihar - GCF | J7: INR | K7: 32752 | L7: 1 | M7: 32752 | N7: 32752 | O7: 1 | P7: 32752 | Q7: Approved | R7: Initiated | S7: NEFT/RTGS | T7: Customer | U7: G.C.Wilmar Private Limited | V7: GC Wilmar Private Limited | W7: 0 | X7: 0 | Y7: AXIS BANK 923020053773708 - BIHAR | AA7: G.C.Wilmar Private Limited-G.C.Wilmar Private Limited | AC7: -4460946.5 | AD7: Receivable | AE7: -4460946.5 | AF7: Bank | AG7: 615.1 | AH7: 32752 | AI7: 32752 | AJ7: 32752 | AK7: 32752 | AL7: 0 | AM7: 0 | AN7: 32752 | AO7: 0 | AR7: 0 | AT7: 0 | AU7: 0 | AV7: GC Foods Muzaffarpur-Billing | AW7: 10AACCG2244H1Z9 | AX7: 10-Bihar | AY7: G.C.Wilmar Private Limited-Billing | AZ7: 10AAICG5386J1ZH | BA7: Registered Regular | BB7: N/A | BC7: 45867 | BF7: Muzaffarpur | BH7: Cancelled | BI7: 0 | BJ7: Amount INR 32752 received from G.C.Wilmar Private Limited Transaction reference no N/A dated 2025-07-29 | BK7: INR Thirty Two Thousand, Seven Hundred And Fifty Two only. | BL7: No | BM7: GCF Letterhead | BO7: AXIS BANK | BP7: 923020053773708 | BR7: INR Thirty Two Thousand, Seven Hundred And Fifty Two only. | BT7: G.C.Wilmar Private Limited
A8: PAY/M/25-26/0937 | B8: PAY/M/25-26/0937-1 | C8: PAY/G/23-24/.#### | D8: Receive | E8: 45866 | F8: G. C. Foods Pvt. Ltd. | G8: Debtors - GCF | H8: INR | I8: 921030030087773 - Axis Bank Ltd. CC Bihar - GCF | J8: INR | K8: 5000 | L8: 1 | M8: 5000 | N8: 5000 | O8: 1 | P8: 5000 | Q8: Approved | R8: Initiated | S8: NEFT/RTGS | T8: Customer | U8: Sujeet Kumar,Kanti | V8: Sujeet Kumar, Kanti | W8: 0 | X8: 0 | Y8: AXIS BANK 921030030087773 - BIHAR | AC8: 59738 | AD8: Receivable | AE8: 59738 | AF8: Bank | AG8: -18267971 | AH8: 5000 | AI8: 5000 | AJ8: 5000 | AK8: 5000 | AL8: 0 | AM8: 0 | AN8: 5000 | AO8: 0 | AR8: 0 | AT8: 0 | AU8: 0 | AV8: GC Foods Muzaffarpur-Billing | AW8: 10AACCG2244H1Z9 | AX8: 10-Bihar | AY8: Sujeet Kumar,Kanti-Billing | BA8: Unregistered | BB8: N/A | BC8: 45866 | BF8: Muzaffarpur | BH8: Cancelled | BI8: 0 | BJ8: Amount INR 5000 received from Sujeet Kumar,Kanti Transaction reference no N/A dated 2025-07-28 | BK8: INR Five Thousand only. | BL8: No | BM8: GCF Letterhead | BO8: AXIS BANK | BP8: 921030030087773 | BR8: INR Five Thousand only. | BT8: Sujeet Kumar,Kanti
A9: PAY/M/25-26/0916 | B9: PAY/M/25-26/0916-1 | C9: PAY/G/23-24/.#### | D9: Pay | E9: 45860 | F9: G. C. Foods Pvt. Ltd. | G9: 921030030087773 - Axis Bank Ltd. CC Bihar - GCF | H9: INR | I9: Creditors - GCF | J9: INR | K9: 750000 | L9: 1 | M9: 750000 | N9: 750000 | O9: 1 | P9: 750000 | Q9: Approved | R9: Initiated | S9: NEFT/RTGS | T9: Employee | U9: Rajesh Kumar Chaudhry (M) | V9: Rajesh Kumar Chaudhry (M) | W9: 0 | X9: 0 | AC9: 230000 | AD9: Bank | AE9: -18602992 | AF9: Payable | AG9: 230000 | AH9: 750000 | AI9: 750000 | AJ9: 750000 | AK9: 750000 | AL9: 0 | AM9: 0 | AN9: 750000 | AO9: 0 | AR9: 0 | AT9: 0 | AU9: 0 | AV9: GC Foods Muzaffarpur-Billing | AW9: 10AACCG2244H1Z9 | BB9: N/A | BC9: 45860 | BF9: Muzaffarpur | BH9: Cancelled | BI9: 0 | BJ9: Amount INR 750000 to Rajesh Kumar Chaudhry (M) Transaction reference no N/A dated 2025-07-22 | BK9: INR Seven Lakh, Fifty Thousand only. | BL9: No | BM9: GCF Letterhead | BR9: INR Seven Lakh, Fifty Thousand only. | BT9: Rajesh Kumar Chaudhry (M)
A10: PAY/G/25-26/1460 | B10: PAY/G/25-26/1460-1 | C10: PAY/G/23-24/.#### | D10: Receive | E10: 45862 | F10: G. C. Foods Pvt. Ltd. | G10: Debtors - GCF | H10: INR | I10: 9210300223943516 - Axis Bank Ltd. CC Tronica - GCF | J10: INR | K10: 32300 | L10: 1 | M10: 32300 | N10: 32300 | O10: 1 | P10: 32300 | Q10: Approved | R10: Initiated | S10: NEFT/RTGS | T10: Customer | U10: Chacha Tau Chap | V10: Chacha Tau Chap | W10: 0 | X10: 0 | Y10: AXIS BANK 921030023943516 - GZB | AC10: -38902 | AD10: Receivable | AE10: -38902 | AF10: Bank | AG10: -52039112 | AH10: 32300 | AI10: 32300 | AJ10: 32300 | AK10: 32300 | AL10: 0 | AM10: 0 | AN10: 32300 | AO10: 0 | AR10: 0 | AT10: 0 | AU10: 0 | AV10: G.C. Foods Pvt. Ltd.Ghaziabad - Uttar Pradesh-Billing | AW10: 09AACCG2244H1ZS | AX10: 07-Delhi | AY10: Chacha Tau Chap-Billing | AZ10: 07DCJPA3280A1Z5 | BA10: Registered Regular | BB10: N/A | BC10: 45862 | BF10: Ghaziabad | BH10: Cancelled | BI10: 1 | BJ10: Pay In Advance | BK10: INR Thirty Two Thousand, Three Hundred only. | BL10: No | BM10: GCF Letterhead | BO10: AXIS BANK | BP10: 921030023943516 | BR10: INR Thirty Two Thousand, Three Hundred only. | BT10: Chacha Tau Chap
A11: PAY/G/23-24/0882 | B11: PAY/G/23-24/0882-1 | C11: PAY/G/23-24/.#### | D11: Pay | E11: 45860 | F11: G. C. Foods Pvt. Ltd. | G11: 923020053773708 - Axis Bank - Bihar - GCF | H11: INR | I11: Creditors - GCF | J11: INR | K11: 750000 | L11: 1 | M11: 750000 | N11: 750000 | O11: 1 | P11: 750000 | Q11: Approved | R11: Initiated | S11: NEFT/RTGS | T11: Employee | U11: Rajesh Kumar Chaudhry (M) | V11: Rajesh Kumar Chaudhry (M) | W11: 0 | X11: 0 | Y11: AXIS BANK 923020053773708 - BIHAR | AC11: 230000 | AD11: Bank | AE11: 570.1 | AF11: Payable | AG11: 230000 | AH11: 750000 | AI11: 750000 | AJ11: 750000 | AK11: 750000 | AL11: 0 | AM11: 0 | AN11: 750000 | AO11: 0 | AR11: 0 | AT11: 0 | AU11: 0 | AV11: GC Foods Muzaffarpur-Billing | AW11: 10AACCG2244H1Z9 | BB11: N/A | BC11: 45860 | BF11: Muzaffarpur | BH11: Cancelled | BI11: 0 | BJ11: Amount INR 750000 to Rajesh Kumar Chaudhry (M) Transaction reference no N/A dated 2025-07-22 | BK11: INR Seven Lakh, Fifty Thousand only. | BL11: No | BM11: GCF Letterhead | BO11: AXIS BANK | BP11: 923020053773708 | BR11: INR Seven Lakh, Fifty Thousand only. | BT11: Rajesh Kumar Chaudhry (M)
A12: PAY/M/25-26/0911 | B12: PAY/M/25-26/0911-1 | C12: PAY/G/23-24/.#### | D12: Receive | E12: 45861 | F12: G. C. Foods Pvt. Ltd. | G12: Debtors - GCF | H12: INR | I12: 923020053773708 - Axis Bank - Bihar - GCF | J12: INR | K12: 1000000 | L12: 1 | M12: 1000000 | N12: 1000000 | O12: 1 | P12: 1000000 | Q12: Approved | R12: Initiated | S12: NEFT/RTGS | T12: Customer | U12: G.C.Wilmar Private Limited | V12: GC Wilmar Private Limited | W12: 0 | X12: 0 | Y12: AXIS BANK 923020053773708 - BIHAR | AA12: G.C.Wilmar Private Limited-G.C.Wilmar Private Limited | AC12: -2863732.7 | AD12: Receivable | AE12: -2863732.7 | AF12: Bank | AG12: 570.1 | AH12: 1000000 | AI12: 1000000 | AJ12: 1000000 | AK12: 1000000 | AL12: 0 | AM12: 0 | AN12: 1000000 | AO12: 0 | AR12: 0 | AT12: 0 | AU12: 0 | AV12: GC Foods Muzaffarpur-Billing | AW12: 10AACCG2244H1Z9 | AX12: 10-Bihar | AY12: G.C.Wilmar Private Limited-Billing | AZ12: 10AHOPS6771R1ZF | BA12: Registered Regular | BB12: N/A | BC12: 45861 | BF12: Muzaffarpur | BH12: Cancelled | BI12: 0 | BJ12: Amount INR 1000000 received from G.C.Wilmar Private Limited Transaction reference no N/A dated 2025-07-23 | BK12: INR Ten Lakh only. | BL12: No | BM12: GCF Letterhead | BO12: AXIS BANK | BP12: 923020053773708 | BR12: INR Ten Lakh only. | BT12: G.C.Wilmar Private Limited
A13: PAY/G/23-24/0881 | B13: PAY/G/23-24/0881-1 | C13: PAY/G/23-24/.#### | D13: Pay | E13: 45859 | F13: G. C. Foods Pvt. Ltd. | G13: 9210300223943516 - Axis Bank Ltd. CC Tronica - GCF | H13: INR | I13: Creditors - GCF | J13: INR | K13: 21000 | L13: 1 | M13: 21000 | N13: 21000 | O13: 1 | P13: 21000 | Q13: Approved | R13: Initiated | S13: NEFT/RTGS | T13: Supplier | U13: G.C.WILMAR Private Limited | V13: G.C.WILMAR Private Limited | W13: 0 | X13: 0 | Y13: AXIS BANK 921030023943516 - GZB | AC13: -630600 | AD13: Bank | AE13: -51845742 | AF13: Payable | AG13: 68580934 | AH13: 21000 | AI13: 21000 | AJ13: 21000 | AK13: 21000 | AL13: 0 | AM13: 0 | AN13: 21000 | AO13: 0 | AR13: 0 | AT13: 0 | AU13: 0 | AV13: GC Foods Muzaffarpur-Billing | AW13: 10AACCG2244H1Z9 | BB13: N/A | BC13: 45859 | BF13: Muzaffarpur | BH13: Cancelled | BI13: 0 | BJ13: Amount INR 21000 to G.C.WILMAR Private Limited Transaction reference no N/A dated 2025-07-21 | BK13: INR Twenty One Thousand only. | BL13: No | BM13: GCF Letterhead | BO13: AXIS BANK | BP13: 921030023943516 | BR13: INR Twenty One Thousand only. | BT13: G.C.WILMAR Private Limited
A14: PAY/N/25-26/0572 | B14: PAY/N/25-26/0572-1 | C14: PAY/G/23-24/.#### | D14: Pay | E14: 45861 | F14: G. C. Foods Pvt. Ltd. | G14: 921030030087786 - Axis Bank Ltd. CC Noida - GCF | H14: INR | I14: Creditors - GCF | J14: INR | K14: 20000 | L14: 1 | M14: 20000 | N14: 20000 | O14: 1 | P14: 20000 | Q14: Approved | R14: Initiated | S14: NEFT/RTGS | T14: Supplier | U14: Frontier Automobiles Private Limited | V14: Frontier Automobiles Private Limited | W14: 0 | X14: 0 | Y14: AXIS BANK 921030030087786 - NOIDA | AC14: 444943 | AD14: Bank | AE14: -4854404.6 | AF14: Payable | AG14: 444943 | AH14: 20000 | AI14: 20000 | AJ14: 20000 | AK14: 20000 | AL14: 0 | AM14: 0 | AN14: 20000 | AO14: 0 | AR14: 0 | AT14: 0 | AU14: 0 | AV14: G.C. Foods Pvt. Ltd. Noida - Uttar Pradesh (Shipping) | AW14: 09AACCG2244H1ZS | BB14: N/A | BC14: 45861 | BF14: Noida | BH14: Cancelled | BI14: 0 | BJ14: Amount INR 20000 to Frontier Automobiles Private Limited Transaction reference no N/A dated 2025-07-23 | BK14: INR Twenty Thousand only. | BL14: No | BM14: GCF Letterhead | BO14: AXIS BANK | BP14: 921030030087786 | BR14: INR Twenty Thousand only. | BT14: Frontier Automobiles Private Limited
A15: PAY/G/25-26/1391 | B15: PAY/G/25-26/1391-1 | C15: PAY/G/23-24/.#### | D15: Receive | E15: 45856 | F15: G. C. Foods Pvt. Ltd. | G15: Debtors - GCF | H15: INR | I15: 9210300223943516 - Axis Bank Ltd. CC Tronica - GCF | J15: INR | K15: 145000 | L15: 1 | M15: 145000 | N15: 145000 | O15: 1 | P15: 145000 | Q15: Approved | R15: Initiated | S15: NEFT/RTGS | T15: Customer | U15: M/S Puja Enterprises | V15: M/S Puja Enterprises | W15: 0 | X15: 0 | Y15: AXIS BANK 921030023943516 - GZB | AC15: 41223 | AD15: Receivable | AE15: 41223 | AF15: Bank | AG15: -52328248 | AH15: 145000 | AI15: 145000 | AJ15: 145000 | AK15: 145000 | AL15: 0 | AM15: 0 | AN15: 145000 | AO15: 0 | AR15: 0 | AT15: 0 | AU15: 0 | AV15: G.C. Foods Pvt. Ltd.Ghaziabad - Uttar Pradesh-Billing | AW15: 09AACCG2244H1ZS | AX15: 07-Delhi | AY15: M/S Puja Enterprises-Billing | AZ15: 07BRPPJ6469M1ZV | BA15: Registered Regular | BB15: N/A | BC15: 45858 | BF15: Ghaziabad | BH15: Cancelled | BI15: 0 | BJ15: Amount INR 145000 received from M/S Puja Enterprises Transaction reference no N/A dated 2025-07-20 | BK15: INR One Lakh, Forty Five Thousand only. | BL15: No | BO15: AXIS BANK | BP15: 921030023943516 | BR15: INR One Lakh, Forty Five Thousand only. | BT15: M/S Puja Enterprises
A16: PAY/G/25-26/1379 | B16: PAY/G/25-26/1379-1 | C16: PAY/G/23-24/.#### | D16: Receive | E16: 45857 | F16: G. C. Foods Pvt. Ltd. | G16: Debtors - GCF | H16: INR | I16: 9210300223943516 - Axis Bank Ltd. CC Tronica - GCF | J16: INR | K16: 10000 | L16: 1 | M16: 10000 | N16: 10000 | O16: 1 | P16: 10000 | Q16: Approved | R16: Initiated | S16: NEFT/RTGS | T16: Customer | U16: J.K. Traders | V16: J.K. Traders | W16: 0 | X16: 0 | Y16: AXIS BANK 921030023943516 - GZB | AC16: -34641 | AD16: Receivable | AE16: -34641 | AF16: Bank | AG16: -51738887 | AH16: 10000 | AI16: 10000 | AJ16: 10000 | AK16: 10000 | AL16: 0 | AM16: 0 | AN16: 10000 | AO16: 0 | AR16: 0 | AT16: 0 | AU16: 0 | AV16: G.C. Foods Pvt. Ltd.Ghaziabad - Uttar Pradesh-Billing | AW16: 09AACCG2244H1ZS | AX16: 07-Delhi | AY16: J.K. Traders-Billing | BA16: Unregistered | BB16: N/A | BC16: 45857 | BF16: Ghaziabad | BH16: Cancelled | BI16: 0 | BJ16: Amount INR 10000 received from J.K. Traders Transaction reference no N/A dated 2025-07-19 | BK16: INR Ten Thousand only. | BL16: No | BO16: AXIS BANK | BP16: 921030023943516 | BR16: INR Ten Thousand only. | BT16: J.K. Traders
A17: PAY/N/25-26/0554 | B17: PAY/N/25-26/0554-1 | C17: PAY/G/23-24/.#### | D17: Receive | E17: 45849 | F17: G. C. Foods Pvt. Ltd. | G17: Debtors - GCF | H17: INR | I17: 921030030087786 - Axis Bank Ltd. CC Noida - GCF | J17: INR | K17: 339140 | L17: 1 | M17: 339140 | N17: 339140 | O17: 1 | P17: 339140 | Q17: Approved | R17: Initiated | S17: NEFT/RTGS | T17: Customer | U17: E-powertech | V17: E-powertech | W17: 0 | X17: 0 | Y17: AXIS BANK 921030030087786 - NOIDA | AC17: 0 | AD17: Receivable | AE17: -16957861 | AF17: Bank | AG17: -4861280.3 | AH17: 339140 | AI17: 339140 | AJ17: 339140 | AK17: 339140 | AL17: 0 | AM17: 0 | AN17: 339140 | AO17: 0 | AR17: 0 | AT17: 0 | AU17: 0 | AV17: G.C. Foods Pvt. Ltd. Noida - Uttar Pradesh (Shipping) | AW17: 09AACCG2244H1ZS | AX17: 10-Bihar | BA17: Unregistered | BB17: N/A | BC17: 45849 | BF17: Noida | BH17: Cancelled | BI17: 0 | BJ17: Amount INR 339140 received from E-powertech Transaction reference no N/A dated 2025-07-11 | BK17: INR Three Lakh, Thirty Nine Thousand, One Hundred And Forty only. | BL17: No | BO17: AXIS BANK | BP17: 921030030087786 | BR17: INR Three Lakh, Thirty Nine Thousand, One Hundred And Forty only. | BT17: E-powertech
A18: PAY/M/25-26/0862 | B18: PAY/M/25-26/0862-1 | C18: PAY/G/23-24/.#### | D18: Pay | E18: 45769 | F18: G. C. Foods Pvt. Ltd. | G18: 921030030087773 - Axis Bank Ltd. CC Bihar - GCF | H18: INR | I18: Creditors - GCF | J18: INR | K18: 48000 | L18: 1 | M18: 48000 | N18: 48000 | O18: 1 | P18: 48000 | Q18: Approved | R18: Initiated | S18: NEFT/RTGS | T18: Employee | U18: Shashi Kant Bhalla (M) | V18: Shashi Kant Bhalla (M) | W18: 0 | X18: 0 | AC18: 0 | AD18: Bank | AE18: -19973354 | AF18: Payable | AG18: -5936117.7 | AH18: 48000 | AI18: 48000 | AJ18: 48000 | AK18: 48000 | AL18: 0 | AM18: 0 | AN18: 48000 | AO18: 0 | AR18: 0 | AT18: 0 | AU18: 0 | AV18: GC Foods Muzaffarpur-Billing | AW18: 10AACCG2244H1Z9 | BB18: N/A | BC18: 45769 | BF18: Muzaffarpur | BH18: Cancelled | BI18: 0 | BJ18: Amount INR 48000 to Shashi Kant Bhalla (M) Transaction reference no N/A dated 2025-04-22 | BK18: INR Forty Eight Thousand only. | BL18: No | BR18: INR Forty Eight Thousand only. | BT18: Shashi Kant Bhalla (M)
A19: PAY/M/25-26/0844-2 | B19: PAY/M/25-26/0844-2-1 | C19: PAY/G/23-24/.#### | D19: Receive | E19: 45855 | F19: G. C. Foods Pvt. Ltd. | G19: Debtors - GCF | H19: INR | I19: 921030030087773 - Axis Bank Ltd. CC Bihar - GCF | J19: INR | K19: 119892 | L19: 1 | M19: 119892 | N19: 119892 | O19: 1 | P19: 119892 | Q19: Approved | R19: Initiated | S19: NEFT/RTGS | T19: Customer | U19: Jay Mata TranportPan.No.AHUPT5943Q | V19: Jay Mata TranportPan.No.AHUPT5943Q | W19: 0 | X19: 0 | Y19: AXIS BANK 921030030087773 - BIHAR | AC19: 0 | AD19: Receivable | AE19: -16202970 | AF19: Bank | AG19: -19646286 | AH19: 119892 | AI19: 119892 | AJ19: 119892 | AK19: 119892 | AL19: 0 | AM19: 0 | AN19: 119892 | AO19: 0 | AR19: 0 | AT19: 0 | AU19: 0 | AV19: GC Foods Muzaffarpur-Billing | AW19: 10AACCG2244H1Z9 | AX19: 10-Bihar | BA19: Unregistered | BB19: N/A | BC19: 45855 | BF19: Muzaffarpur | BH19: Cancelled | BI19: 0 | BJ19: Amount INR 119892 received from Jay Mata TranportPan.No.AHUPT5943Q Transaction reference no N/A dated 2025-07-17 | BK19: INR One Lakh, Nineteen Thousand, Eight Hundred And Ninety Two only. | BL19: No | BO19: AXIS BANK | BP19: 921030030087773 | BR19: INR One Lakh, Nineteen Thousand, Eight Hundred And Ninety Two only. | BT19: Jay Mata TranportPan.No.AHUPT5943Q
A20: PAY/M/25-26/0844-1 | B20: PAY/M/25-26/0844-2 | C20: PAY/G/23-24/.#### | D20: Receive | E20: 45855 | F20: G. C. Foods Pvt. Ltd. | G20: Debtors - GCF | H20: INR | I20: 9210300223943516 - Axis Bank Ltd. CC Tronica - GCF | J20: INR | K20: 119892 | L20: 1 | M20: 119892 | N20: 119892 | O20: 1 | P20: 119892 | Q20: Approved | R20: Initiated | S20: NEFT/RTGS | T20: Customer | U20: Jay Mata TranportPan.No.AHUPT5943Q | V20: Jay Mata TranportPan.No.AHUPT5943Q | W20: 0 | X20: 0 | Y20: AXIS BANK 921030030087773 - BIHAR | AC20: 0 | AD20: Receivable | AE20: -16202970 | AF20: Bank | AG20: -54154327 | AH20: 119892 | AI20: 119892 | AJ20: 119892 | AK20: 119892 | AL20: 0 | AM20: 0 | AN20: 119892 | AO20: 0 | AR20: 0 | AT20: 0 | AU20: 0 | AV20: GC Foods Muzaffarpur-Billing | AW20: 10AACCG2244H1Z9 | AX20: 10-Bihar | BA20: Unregistered | BB20: N/A | BC20: 45855 | BF20: Muzaffarpur | BH20: Cancelled | BI20: 0 | BJ20: Amount INR 119892 received from Jay Mata TranportPan.No.AHUPT5943Q Transaction reference no N/A dated 2025-07-17 | BK20: INR One Lakh, Nineteen Thousand, Eight Hundred And Ninety Two only. | BL20: No | BO20: AXIS BANK | BP20: 921030030087773 | BR20: INR One Lakh, Nineteen Thousand, Eight Hundred And Ninety Two only. | BT20: Jay Mata TranportPan.No.AHUPT5943Q
A21: PAY/M/25-26/0844 | B21: PAY/M/25-26/0844-1 | C21: PAY/G/23-24/.#### | D21: Receive | E21: 45856 | F21: G. C. Foods Pvt. Ltd. | G21: Debtors - GCF | H21: INR | I21: 921030030087773 - Axis Bank Ltd. CC Bihar - GCF | J21: INR | K21: 119892 | L21: 1 | M21: 119892 | N21: 119892 | O21: 1 | P21: 119892 | Q21: Approved | R21: Initiated | T21: Customer | U21: Jay Mata TranportPan.No.AHUPT5943Q | V21: Jay Mata TranportPan.No.AHUPT5943Q | W21: 0 | X21: 0 | Y21: AXIS BANK 921030030087773 - BIHAR | AC21: 0 | AD21: Receivable | AE21: -16202970 | AF21: Bank | AG21: -18873949 | AH21: 119892 | AI21: 119892 | AJ21: 119892 | AK21: 119892 | AL21: 0 | AM21: 0 | AN21: 119892 | AO21: 0 | AR21: 0 | AT21: 0 | AU21: 0 | AV21: GC Foods Muzaffarpur-Billing | AW21: 10AACCG2244H1Z9 | AX21: 10-Bihar | BA21: Unregistered | BB21: N/A | BC21: 45855 | BF21: Muzaffarpur | BH21: Cancelled | BI21: 0 | BJ21: Amount INR 119892 received from Jay Mata TranportPan.No.AHUPT5943Q Transaction reference no N/A dated 2025-07-17 | BK21: INR One Lakh, Nineteen Thousand, Eight Hundred And Ninety Two only. | BL21: No | BO21: AXIS BANK | BP21: 921030030087773 | BR21: INR One Lakh, Nineteen Thousand, Eight Hundred And Ninety Two only. | BT21: Jay Mata TranportPan.No.AHUPT5943Q
A22: PAY/G/25-26/1360 | B22: PAY/G/25-26/1360-1 | C22: PAY/G/23-24/.#### | D22: Pay | E22: 45855 | F22: G. C. Foods Pvt. Ltd. | G22: 9210300223943516 - Axis Bank Ltd. CC Tronica - GCF | H22: INR | I22: Creditors - GCF | J22: INR | K22: 27080 | L22: 1 | M22: 27080 | N22: 27080 | O22: 1 | P22: 27080 | Q22: Approved | R22: Initiated | S22: NEFT/RTGS | T22: Supplier | U22: Mahaadev Traders | V22: Mahaadev Traders | W22: 0 | X22: 0 | Y22: AXIS BANK 921030023943516 - GZB | AC22: -1655649.8 | AD22: Bank | AE22: -52588746 | AF22: Payable | AG22: -1655649.8 | AH22: 27080 | AI22: 27080 | AJ22: 27080 | AK22: 27080 | AL22: 0 | AM22: 0 | AN22: 27080 | AO22: 0 | AR22: 0 | AT22: 0 | AU22: 0 | AV22: G.C. Foods Pvt. Ltd.Ghaziabad - Uttar Pradesh-Billing | AW22: 09AACCG2244H1ZS | BB22: N/A | BC22: 45855 | BF22: Ghaziabad | BH22: Cancelled | BI22: 0 | BJ22: Amount INR 27080 to Mahaadev Traders Transaction reference no N/A dated 2025-07-17 | BK22: INR Twenty Seven Thousand And Eighty only. | BL22: No | BO22: AXIS BANK | BP22: 921030023943516 | BR22: INR Twenty Seven Thousand And Eighty only. | BT22: Mahaadev Traders
A23: PAY/G/25-26/1355 | B23: PAY/G/25-26/1355-1 | C23: PAY/G/23-24/.#### | D23: Pay | E23: 45855 | F23: G. C. Foods Pvt. Ltd. | G23: 9210300223943516 - Axis Bank Ltd. CC Tronica - GCF | H23: INR | I23: Creditors - GCF | J23: INR | K23: 1328158 | L23: 1 | M23: 1328158 | N23: 1328158 | O23: 1 | P23: 1328158 | Q23: Approved | R23: Initiated | S23: NEFT/RTGS | T23: Supplier | U23: Mahaadev Traders | V23: Mahaadev Traders | W23: 0 | X23: 0 | Y23: AXIS BANK 921030023943516 - GZB | AC23: -2983807.8 | AD23: Bank | AE23: -53318128 | AF23: Payable | AG23: -2983807.8 | AH23: 1328158 | AI23: 1328158 | AJ23: 1328158 | AK23: 1328158 | AL23: 0 | AM23: 0 | AN23: 1328158 | AO23: 0 | AR23: 0 | AT23: 0 | AU23: 0 | AV23: G.C. Foods Pvt. Ltd.Ghaziabad - Uttar Pradesh-Billing | AW23: 09AACCG2244H1ZS | BB23: N/A | BC23: 45855 | BF23: Ghaziabad | BH23: Cancelled | BI23: 0 | BJ23: Amount INR 1328158 to Mahaadev Traders Transaction reference no N/A dated 2025-07-17 | BK23: INR Thirteen Lakh, Twenty Eight Thousand, One Hundred And Fifty Eight only. | BL23: No | BO23: AXIS BANK | BP23: 921030023943516 | BR23: INR Thirteen Lakh, Twenty Eight Thousand, One Hundred And Fifty Eight only. | BT23: Mahaadev Traders
A24: PAY/M/25-26/0826 | B24: PAY/M/25-26/0826-1 | C24: PAY/G/23-24/.#### | D24: Pay | E24: 45850 | F24: G. C. Foods Pvt. Ltd. | G24: 921030030087773 - Axis Bank Ltd. CC Bihar - GCF | H24: INR | I24: Creditors - GCF | J24: INR | K24: 38709 | L24: 1 | M24: 38709 | N24: 38709 | O24: 1 | P24: 38709 | Q24: Approved | R24: Initiated | S24: NEFT/RTGS | T24: Supplier | U24: GC foods Pvt Ltd (T) | V24: GC foods Pvt Ltd (T) | W24: 0 | X24: 0 | Y24: AXIS BANK 921030030087773 - BIHAR | AC24: 42792485 | AD24: Bank | AE24: -19738705 | AF24: Payable | AG24: 42792485 | AH24: 38709 | AI24: 38709 | AJ24: 38709 | AK24: 38709 | AL24: 0 | AM24: 0 | AN24: 38709 | AO24: 0 | AR24: 0 | AT24: 0 | AU24: 0 | AV24: GC Foods Muzaffarpur-Billing | AW24: 10AACCG2244H1Z9 | BB24: N/A | BC24: 45850 | BF24: Muzaffarpur | BH24: Cancelled | BI24: 0 | BJ24: Amount INR 38709 to GC foods Pvt Ltd (T) Transaction reference no N/A dated 2025-07-12 | BK24: INR Thirty Eight Thousand, Seven Hundred And Nine only. | BL24: No | BO24: AXIS BANK | BP24: 921030030087773 | BR24: INR Thirty Eight Thousand, Seven Hundred And Nine only. | BT24: GC foods Pvt Ltd (T)
A25: PAY/N/25-26/0522 | B25: PAY/N/25-26/0522-1 | C25: PAY/G/23-24/.#### | D25: Receive | E25: 45846 | F25: G. C. Foods Pvt. Ltd. | G25: Debtors - GCF | H25: INR | I25: 923020017959018 - Axis Bank - NOIDA - GCF | J25: INR | K25: 1771.89 | L25: 1 | M25: 1771.89 | N25: 1771.89 | O25: 1 | P25: 1771.89 | Q25: Approved | R25: Initiated | S25: NEFT/RTGS | T25: Customer | U25: DTDC EXPRESS (Courier) | V25: DTDC EXPRESS (Courier) | W25: 0 | X25: 0 | Y25: AXIS BANK 923020017959018 -NOIDA | AA25: Amrit Varsha-DTDC EXPRESS SERVICE | AC25: 4125.22 | AD25: Receivable | AE25: 4125.22 | AF25: Bank | AG25: 24288.68 | AH25: 1771.89 | AI25: 1771.89 | AJ25: 1771.89 | AK25: 1771.89 | AL25: 0 | AM25: 0 | AN25: 1771.89 | AO25: 0 | AR25: 0 | AT25: 0 | AU25: 0 | AV25: G.C. Foods Pvt. Ltd. Noida - Uttar Pradesh (Shipping) | AW25: 09AACCG2244H1ZS | AX25: 27-Maharashtra | AY25: DTDC EXPRESS SERVICE-Billing-18 | BA25: Unregistered | BB25: N/A | BC25: 45846 | BF25: Noida | BH25: Cancelled | BI25: 0 | BJ25: Amount INR 1771.89 received from DTDC EXPRESS (Courier) Transaction reference no N/A dated 2025-07-08 | BK25: INR One Thousand, Seven Hundred And Seventy One and Eighty Nine Paisa only. | BL25: No | BO25: AXIS BANK | BP25: 923020017959018 | BR25: INR One Thousand, Seven Hundred And Seventy One and Eighty Nine Paisa only. | BT25: DTDC EXPRESS (Courier)
A26: PAY/M/25-26/0769-1 | B26: PAY/M/25-26/0769-2 | C26: PAY/G/23-24/.#### | D26: Pay | E26: 45845 | F26: G. C. Foods Pvt. Ltd. | G26: 921030030087773 - Axis Bank Ltd. CC Bihar - GCF | H26: INR | I26: Creditors - GCF | J26: INR | K26: 30600 | L26: 1 | M26: 30600 | N26: 30600 | O26: 1 | P26: 30600 | Q26: Approved | R26: Initiated | S26: NEFT/RTGS | T26: Supplier | U26: Jogendra jee, Patna | V26: Jogendra jee, Patna | W26: 0 | X26: 0 | Y26: AXIS BANK 921030030087773 - BIHAR | AC26: -30000 | AD26: Bank | AE26: -18051699 | AF26: Payable | AG26: -30000 | AH26: 30600 | AI26: 30600 | AJ26: 30600 | AK26: 30600 | AL26: 0 | AM26: 0 | AN26: 30600 | AO26: 0 | AR26: 0 | AT26: 0 | AU26: 0 | AV26: GC Foods Muzaffarpur-Billing | AW26: 10AACCG2244H1Z9 | BB26: N/A | BC26: 45845 | BF26: Muzaffarpur | BH26: Cancelled | BI26: 0 | BJ26: Amount INR 30600 to Jogendra jee, Patna Transaction reference no N/A dated 2025-07-07 | BK26: INR Thirty Thousand, Six Hundred only. | BL26: No | BO26: AXIS BANK | BP26: 921030030087773 | BR26: INR Thirty Thousand, Six Hundred only. | BT26: Jogendra jee, Patna
A27: PAY/N/25-26/0513 | B27: PAY/N/25-26/0513-1 | C27: PAY/G/23-24/.#### | D27: Pay | E27: 45848 | F27: G. C. Foods Pvt. Ltd. | G27: 921030030087786 - Axis Bank Ltd. CC Noida - GCF | H27: INR | I27: Creditors - GCF | J27: INR | K27: 339140 | L27: 1 | M27: 339140 | N27: 339140 | O27: 1 | P27: 339140 | Q27: Approved | R27: Initiated | S27: NEFT/RTGS | T27: Supplier | U27: E Powertech | V27: E Power Technologies | W27: 0 | X27: 0 | Y27: AXIS BANK 921030030087786 - NOIDA | AC27: 772380 | AD27: Bank | AE27: -4857980.3 | AF27: Payable | AG27: 772380 | AH27: 339140 | AI27: 339140 | AJ27: 339140 | AK27: 339140 | AL27: 0 | AM27: 0 | AN27: 339140 | AO27: 0 | AR27: 0 | AT27: 0 | AU27: 0 | AV27: G.C. Foods Pvt. Ltd. Noida - Uttar Pradesh (Shipping) | AW27: 09AACCG2244H1ZS | BB27: N/A | BC27: 45848 | BF27: Noida | BH27: Cancelled | BI27: 0 | BJ27: Amount INR 339140 to E Power Technologies Transaction reference no N/A dated 2025-07-10 | BK27: INR Three Lakh, Thirty Nine Thousand, One Hundred And Forty only. | BL27: No | BO27: AXIS BANK | BP27: 921030030087786 | BR27: INR Three Lakh, Thirty Nine Thousand, One Hundred And Forty only. | BT27: E Power Technologies
A28: PAY/N/25-26/0505 | B28: PAY/N/25-26/0505-1 | C28: PAY/G/23-24/.#### | D28: Pay | E28: 45847 | F28: G. C. Foods Pvt. Ltd. | G28: 921030030087786 - Axis Bank Ltd. CC Noida - GCF | H28: INR | I28: Creditors - GCF | J28: INR | K28: 6333 | L28: 1 | M28: 6333 | N28: 6333 | O28: 1 | P28: 6333 | Q28: Approved | R28: Initiated | S28: NEFT/RTGS | T28: Employee | U28: Ankit Kumar - Staff Noida | V28: Ankit Kumar - Staff Noida | W28: 0 | X28: 0 | AC28: 0 | AD28: Bank | AE28: -4914951.3 | AF28: Payable | AG28: 68176968 | AH28: 6333 | AI28: 6333 | AJ28: 6333 | AK28: 6333 | AL28: 0 | AM28: 0 | AN28: 6333 | AO28: 0 | AR28: 0 | AT28: 0 | AU28: 0 | AV28: G.C. Foods Pvt. Ltd. Noida - Uttar Pradesh (Shipping) | AW28: 09AACCG2244H1ZS | BB28: N/A | BC28: 45847 | BF28: Noida | BH28: Cancelled | BI28: 0 | BJ28: Amount INR 6333 to Ankit Kumar - Staff Noida Transaction reference no N/A dated 2025-07-09 | BK28: INR Six Thousand, Three Hundred And Thirty Three only. | BL28: No | BR28: INR Six Thousand, Three Hundred And Thirty Three only. | BT28: Ankit Kumar - Staff Noida
A29: PAY/N/25-26/0478 | B29: PAY/N/25-26/0478-1 | C29: PAY/G/23-24/.#### | D29: Pay | E29: 45846 | F29: G. C. Foods Pvt. Ltd. | G29: 921030030087786 - Axis Bank Ltd. CC Noida - GCF | H29: INR | I29: Creditors - GCF | J29: INR | K29: 31500 | L29: 1 | M29: 31500 | N29: 31500 | O29: 1 | P29: 31500 | Q29: Approved | R29: Initiated | S29: NEFT/RTGS | T29: Supplier | U29: GC foods Pvt Ltd Bihar | V29: GC foods Pvt Ltd Bihar | W29: 0 | X29: 0 | Y29: AXIS BANK 921030030087786 - NOIDA | AC29: 5195000 | AD29: Bank | AE29: -4896731.3 | AF29: Payable | AG29: 5195000 | AH29: 31500 | AI29: 31500 | AJ29: 31500 | AK29: 31500 | AL29: 0 | AM29: 0 | AN29: 31500 | AO29: 0 | AR29: 0 | AT29: 0 | AU29: 0 | AV29: G.C. Foods Pvt. Ltd. Noida - Uttar Pradesh (Shipping) | AW29: 09AACCG2244H1ZS | BB29: N/A | BC29: 45846 | BF29: Noida | BH29: Cancelled | BI29: 0 | BJ29: Amount INR 31500 to GC foods Pvt Ltd Bihar Transaction reference no N/A dated 2025-07-08 | BK29: INR Thirty One Thousand, Five Hundred only. | BL29: No | BO29: AXIS BANK | BP29: 921030030087786 | BR29: INR Thirty One Thousand, Five Hundred only. | BT29: GC foods Pvt Ltd Bihar
A30: PAY/N/25-26/0462 | B30: PAY/N/25-26/0462-1 | C30: PAY/G/23-24/.#### | D30: Pay | E30: 45845 | F30: G. C. Foods Pvt. Ltd. | G30: 9210300223943516 - Axis Bank Ltd. CC Tronica - GCF | H30: INR | I30: Creditors - GCF | J30: INR | K30: 3300 | L30: 1 | M30: 3300 | N30: 3300 | O30: 1 | P30: 3300 | Q30: Approved | R30: Initiated | S30: NEFT/RTGS | T30: Employee | U30: Kanhiya Lal Sales - NCR | V30: Kanhiya Lal Sales - NCR | W30: 0 | X30: 0 | AC30: 10875 | AD30: Bank | AE30: -53173281 | AF30: Payable | AG30: 10875 | AH30: 3300 | AI30: 3300 | AJ30: 3300 | AK30: 3300 | AL30: 0 | AM30: 0 | AN30: 3300 | AO30: 0 | AR30: 0 | AT30: 0 | AU30: 0 | AV30: G.C. Foods Pvt. Ltd. Noida - Uttar Pradesh (Shipping) | AW30: 09AACCG2244H1ZS | BB30: N/A | BC30: 45845 | BF30: Noida | BH30: Cancelled | BI30: 0 | BJ30: Amount INR 3300 to Kanhiya Lal Sales - NCR Transaction reference no N/A dated 2025-07-07 | BK30: INR Three Thousand, Three Hundred only. | BL30: No | BR30: INR Three Thousand, Three Hundred only. | BT30: Kanhiya Lal Sales - NCR
A31: PAY/N/25-26/0455-1 | B31: PAY/N/25-26/0455-2 | C31: PAY/G/23-24/.#### | D31: Pay | E31: 45843 | F31: G. C. Foods Pvt. Ltd. | G31: 921030030087786 - Axis Bank Ltd. CC Noida - GCF | H31: INR | I31: Creditors - GCF | J31: INR | K31: 34043 | L31: 1 | M31: 34043 | N31: 34043 | O31: 1 | P31: 34043 | Q31: Approved | R31: Initiated | S31: NEFT/RTGS | T31: Supplier | U31: Galaxy Sivtek Private Limited | V31: Galaxy Sivtek Private Limited | W31: 0 | X31: 0 | Y31: AXIS BANK 921030030087786 - NOIDA | AC31: 0 | AD31: Bank | AE31: -5133173.3 | AF31: Payable | AG31: 61551320 | AH31: 34043 | AI31: 34043 | AJ31: 34043 | AK31: 34043 | AL31: 0 | AM31: 0 | AN31: 34043 | AO31: 0 | AR31: 0 | AT31: 0 | AU31: 0 | AV31: G.C. Foods Pvt. Ltd. Noida - Uttar Pradesh (Shipping) | AW31: 09AACCG2244H1ZS | BB31: N/A | BC31: 45843 | BF31: Noida | BH31: Cancelled | BI31: 0 | BJ31: Amount INR 34043 to Galaxy Sivtek Private Limited Transaction reference no N/A dated 2025-07-05 | BK31: INR Thirty Four Thousand And Forty Three only. | BL31: No | BO31: AXIS BANK | BP31: 921030030087786 | BR31: INR Thirty Four Thousand And Forty Three only. | BT31: Galaxy Sivtek Private Limited
A32: PAY/N/25-26/0456 | B32: PAY/N/25-26/0456-1 | C32: PAY/G/23-24/.#### | D32: Pay | E32: 45842 | F32: G. C. Foods Pvt. Ltd. | G32: 921030030087786 - Axis Bank Ltd. CC Noida - GCF | H32: INR | I32: Creditors - GCF | J32: INR | K32: 9038 | L32: 1 | M32: 9038 | N32: 9038 | O32: 1 | P32: 9038 | Q32: Approved | R32: Initiated | S32: NEFT/RTGS | T32: Supplier | U32: Gogia Chemical Industries (P) Ltd | V32: Gogia Chemical Industries (P) Ltd | W32: 0 | X32: 0 | Y32: AXIS BANK 921030030087786 - NOIDA | AC32: -9038 | AD32: Bank | AE32: -5167216.3 | AF32: Payable | AG32: -9038 | AH32: 9038 | AI32: 9038 | AJ32: 9038 | AK32: 9038 | AL32: 0 | AM32: 0 | AN32: 9038 | AO32: 0 | AR32: 0 | AT32: 0 | AU32: 0 | AV32: G.C. Foods Pvt. Ltd. Noida - Uttar Pradesh (Shipping) | AW32: 09AACCG2244H1ZS | BB32: N/A | BC32: 45842 | BF32: Noida | BH32: Cancelled | BI32: 0 | BJ32: Amount INR 9038 to Gogia Chemical Industries (P) Ltd Transaction reference no N/A dated 2025-07-04 | BK32: INR Nine Thousand And Thirty Eight only. | BL32: No | BO32: AXIS BANK | BP32: 921030030087786 | BR32: INR Nine Thousand And Thirty Eight only. | BT32: Gogia Chemical Industries (P) Ltd
A33: PAY/N/25-26/0455 | B33: PAY/N/25-26/0455-1 | C33: PAY/G/23-24/.#### | D33: Pay | E33: 45842 | F33: G. C. Foods Pvt. Ltd. | G33: 921030030087786 - Axis Bank Ltd. CC Noida - GCF | H33: INR | I33: Creditors - GCF | J33: INR | K33: 34043 | L33: 1 | M33: 34043 | N33: 34043 | O33: 1 | P33: 34043 | Q33: Approved | R33: Initiated | S33: NEFT/RTGS | T33: Supplier | U33: Galaxy Sivtek Private Limited | V33: Galaxy Sivtek Private Limited | W33: 0 | X33: 0 | Y33: AXIS BANK 921030030087786 - NOIDA | AC33: 0 | AD33: Bank | AE33: -5133173.3 | AF33: Payable | AG33: 61551320 | AH33: 34043 | AI33: 34043 | AJ33: 34043 | AK33: 34043 | AL33: 0 | AM33: 0 | AN33: 34043 | AO33: 0 | AR33: 0 | AT33: 0 | AU33: 0 | AV33: G.C. Foods Pvt. Ltd. Noida - Uttar Pradesh (Shipping) | AW33: 09AACCG2244H1ZS | BB33: N/A | BC33: 45842 | BF33: Noida | BH33: Cancelled | BI33: 0 | BJ33: Amount INR 34043 to Galaxy Sivtek Private Limited Transaction reference no N/A dated 2025-07-04 | BK33: INR Thirty Four Thousand And Forty Three only. | BL33: No | BO33: AXIS BANK | BP33: 921030030087786 | BR33: INR Thirty Four Thousand And Forty Three only. | BT33: Galaxy Sivtek Private Limited
A34: PAY/N/25-26/0454 | B34: PAY/N/25-26/0454-1 | C34: PAY/G/23-24/.#### | D34: Pay | E34: 45842 | F34: G. C. Foods Pvt. Ltd. | G34: 921030030087786 - Axis Bank Ltd. CC Noida - GCF | H34: INR | I34: Creditors - GCF | J34: INR | K34: 130956 | L34: 1 | M34: 130956 | N34: 130956 | O34: 1 | P34: 130956 | Q34: Approved | R34: Initiated | S34: NEFT/RTGS | T34: Supplier | U34: Daulat Ram Rakesh Kumar | V34: Daulat Ram Rakesh Kumar | W34: 0 | X34: 0 | Y34: AXIS BANK 921030030087786 - NOIDA | AC34: -160697.45 | AD34: Bank | AE34: -5002217.3 | AF34: Payable | AG34: -160697.45 | AH34: 130956 | AI34: 130956 | AJ34: 130956 | AK34: 130956 | AL34: 0 | AM34: 0 | AN34: 130956 | AO34: 0 | AR34: 0 | AT34: 0 | AU34: 0 | AV34: G.C. Foods Pvt. Ltd. Noida - Uttar Pradesh (Shipping) | AW34: 09AACCG2244H1ZS | BB34: N/A | BC34: 45842 | BF34: Noida | BH34: Cancelled | BI34: 0 | BJ34: Amount INR 130956 to Daulat Ram Rakesh Kumar Transaction reference no N/A dated 2025-07-04 | BK34: INR One Lakh, Thirty Thousand, Nine Hundred And Fifty Six only. | BL34: No | BO34: AXIS BANK | BP34: 921030030087786 | BR34: INR One Lakh, Thirty Thousand, Nine Hundred And Fifty Six only. | BT34: Daulat Ram Rakesh Kumar
A35: PAY/N/25-26/0453 | B35: PAY/N/25-26/0453-1 | C35: PAY/G/23-24/.#### | D35: Pay | E35: 45842 | F35: G. C. Foods Pvt. Ltd. | G35: 921030030087786 - Axis Bank Ltd. CC Noida - GCF | H35: INR | I35: Creditors - GCF | J35: INR | K35: 34250 | L35: 1 | M35: 34250 | N35: 34250 | O35: 1 | P35: 34250 | Q35: Approved | R35: Initiated | S35: NEFT/RTGS | T35: Supplier | U35: Bajrang Traders | V35: Bajrang Traders | W35: 0 | X35: 0 | Y35: AXIS BANK 921030030087786 - NOIDA | AC35: -66628 | AD35: Bank | AE35: -4967967.3 | AF35: Payable | AG35: -66628 | AH35: 34250 | AI35: 34250 | AJ35: 34250 | AK35: 34250 | AL35: 0 | AM35: 0 | AN35: 34250 | AO35: 0 | AR35: 0 | AT35: 0 | AU35: 0 | AV35: G.C. Foods Pvt. Ltd. Noida - Uttar Pradesh (Shipping) | AW35: 09AACCG2244H1ZS | BB35: N/A | BC35: 45842 | BF35: Noida | BH35: Cancelled | BI35: 0 | BJ35: Amount INR 34250 to Bajrang Traders Transaction reference no N/A dated 2025-07-04 | BK35: INR Thirty Four Thousand, Two Hundred And Fifty only. | BL35: No | BO35: AXIS BANK | BP35: 921030030087786 | BR35: INR Thirty Four Thousand, Two Hundred And Fifty only. | BT35: Bajrang Traders
A36: PAY/N/25-26/0452 | B36: PAY/N/25-26/0452-1 | C36: PAY/G/23-24/.#### | D36: Pay | E36: 45842 | F36: G. C. Foods Pvt. Ltd. | G36: 921030030087786 - Axis Bank Ltd. CC Noida - GCF | H36: INR | I36: Creditors - GCF | J36: INR | K36: 1858.5 | L36: 1 | M36: 1858.5 | N36: 1858.5 | O36: 1 | P36: 1858.5 | Q36: Approved | R36: Initiated | S36: NEFT/RTGS | T36: Supplier | U36: AG Enviro Infra Projects Pvt Ltd. | V36: AG Enviro Infra Projects Pvt Ltd. | W36: 0 | X36: 0 | Y36: AXIS BANK 921030030087786 - NOIDA | AC36: 0 | AD36: Bank | AE36: -4966108.8 | AF36: Payable | AG36: 61392923 | AH36: 1858.5 | AI36: 1858.5 | AJ36: 1858.5 | AK36: 1858.5 | AL36: 0 | AM36: 0 | AN36: 1858.5 | AO36: 0 | AR36: 0 | AT36: 0 | AU36: 0 | AV36: G.C. Foods Pvt. Ltd. Noida - Uttar Pradesh (Shipping) | AW36: 09AACCG2244H1ZS | BB36: N/A | BC36: 45842 | BF36: Noida | BH36: Cancelled | BI36: 0 | BJ36: Amount INR 1858.5 to AG Enviro Infra Projects Pvt Ltd. Transaction reference no N/A dated 2025-07-04 | BK36: INR One Thousand, Eight Hundred And Fifty Eight and Fifty Paisa only. | BL36: No | BO36: AXIS BANK | BP36: 921030030087786 | BR36: INR One Thousand, Eight Hundred And Fifty Eight and Fifty Paisa only. | BT36: AG Enviro Infra Projects Pvt Ltd.
A37: PAY/N/25-26/0451 | B37: PAY/N/25-26/0451-1 | C37: PAY/G/23-24/.#### | D37: Pay | E37: 45842 | F37: G. C. Foods Pvt. Ltd. | G37: 921030030087786 - Axis Bank Ltd. CC Noida - GCF | H37: INR | I37: Creditors - GCF | J37: INR | K37: 9137.63 | L37: 1 | M37: 9137.63 | N37: 9137.63 | O37: 1 | P37: 9137.63 | Q37: Approved | R37: Initiated | S37: NEFT/RTGS | T37: Supplier | U37: DTDC Express Limited - Billing | V37: DTDC Express Limited | W37: 0 | X37: 0 | Y37: AXIS BANK 921030030087786 - NOIDA | AC37: 16376.93 | AD37: Bank | AE37: -4956971.2 | AF37: Payable | AG37: 16376.93 | AH37: 9137.63 | AI37: 9137.63 | AJ37: 9137.63 | AK37: 9137.63 | AL37: 0 | AM37: 0 | AN37: 9137.63 | AO37: 0 | AR37: 0 | AT37: 0 | AU37: 0 | AV37: G.C. Foods Pvt. Ltd. Noida - Uttar Pradesh (Shipping) | AW37: 09AACCG2244H1ZS | BB37: N/A | BC37: 45842 | BF37: Noida | BH37: Cancelled | BI37: 0 | BJ37: Amount INR 9137.63 to DTDC Express Limited Transaction reference no N/A dated 2025-07-04 | BK37: INR Nine Thousand, One Hundred And Thirty Seven and Sixty Three Paisa only. | BL37: No | BO37: AXIS BANK | BP37: 921030030087786 | BR37: INR Nine Thousand, One Hundred And Thirty Seven and Sixty Three Paisa only. | BT37: DTDC Express Limited
A38: PAY/N/25-26/0450 | B38: PAY/N/25-26/0450-1 | C38: PAY/G/23-24/.#### | D38: Pay | E38: 45842 | F38: G. C. Foods Pvt. Ltd. | G38: 921030030087786 - Axis Bank Ltd. CC Noida - GCF | H38: INR | I38: Creditors - GCF | J38: INR | K38: 27720 | L38: 1 | M38: 27720 | N38: 27720 | O38: 1 | P38: 27720 | Q38: Approved | R38: Initiated | S38: NEFT/RTGS | T38: Supplier | U38: Royal Securitas | V38: Royal Securitas | W38: 0 | X38: 0 | Y38: AXIS BANK 921030030087786 - NOIDA | AC38: 27720 | AD38: Bank | AE38: -4929251.2 | AF38: Payable | AG38: 27720 | AH38: 27720 | AI38: 27720 | AJ38: 27720 | AK38: 27720 | AL38: 0 | AM38: 0 | AN38: 27720 | AO38: 0 | AR38: 0 | AT38: 0 | AU38: 0 | AV38: G.C. Foods Pvt. Ltd. Noida - Uttar Pradesh (Shipping) | AW38: 09AACCG2244H1ZS | BB38: N/A | BC38: 45842 | BF38: Noida | BH38: Cancelled | BI38: 0 | BJ38: Amount INR 27720 to Royal Securitas Transaction reference no N/A dated 2025-07-04 | BK38: INR Twenty Seven Thousand, Seven Hundred And Twenty only. | BL38: No | BO38: AXIS BANK | BP38: 921030030087786 | BR38: INR Twenty Seven Thousand, Seven Hundred And Twenty only. | BT38: Royal Securitas
A39: PAY/G/25-26/1311 | B39: PAY/G/25-26/1311-1 | C39: PAY/G/23-24/.#### | D39: Pay | E39: 45850 | F39: G. C. Foods Pvt. Ltd. | G39: 9210300223943516 - Axis Bank Ltd. CC Tronica - GCF | H39: INR | I39: Creditors - GCF | J39: INR | K39: 45639 | L39: 1 | M39: 45639 | N39: 45639 | O39: 1 | P39: 45639 | Q39: Approved | R39: Initiated | S39: NEFT/RTGS | T39: Supplier | U39: GC foods Pvt Ltd Bihar | V39: GC foods Pvt Ltd Bihar | W39: 0 | X39: 0 | Y39: AXIS BANK 921030023943516 - GZB | AC39: 5195000 | AD39: Bank | AE39: -53344451 | AF39: Payable | AG39: 5195000 | AH39: 45639 | AI39: 45639 | AJ39: 45639 | AK39: 45639 | AL39: 0 | AM39: 0 | AN39: 45639 | AO39: 0 | AR39: 0 | AT39: 0 | AU39: 0 | AV39: G.C. Foods Pvt. Ltd.Ghaziabad - Uttar Pradesh-Billing | AW39: 09AACCG2244H1ZS | BB39: N/A | BC39: 45850 | BF39: Ghaziabad | BH39: Cancelled | BI39: 0 | BJ39: Amount INR 45639 to GC foods Pvt Ltd Bihar Transaction reference no N/A dated 2025-07-12 | BK39: INR Forty Five Thousand, Six Hundred And Thirty Nine only. | BL39: No | BO39: AXIS BANK | BP39: 921030023943516 | BR39: INR Forty Five Thousand, Six Hundred And Thirty Nine only. | BT39: GC foods Pvt Ltd Bihar
A40: PAY/G/25-26/1253 | B40: PAY/G/25-26/1253-1 | C40: PAY/G/23-24/.#### | D40: Pay | E40: 45848 | F40: G. C. Foods Pvt. Ltd. | G40: 9210300223943516 - Axis Bank Ltd. CC Tronica - GCF | H40: INR | I40: Creditors - GCF | J40: INR | K40: 620465.46 | L40: 1 | M40: 620465.46 | N40: 620465.46 | O40: 1 | P40: 620465.46 | Q40: Approved | R40: Initiated | S40: NEFT/RTGS | T40: Supplier | U40: Mahaadev Traders | V40: Mahaadev Traders | W40: 0 | X40: 0 | Y40: AXIS BANK 921030023943516 - GZB | AC40: 576960.12 | AD40: Bank | AE40: -53513900 | AF40: Payable | AG40: 576960.12 | AH40: 620465.46 | AI40: 620465.46 | AJ40: 620465.46 | AK40: 620465.46 | AL40: 0 | AM40: 0 | AN40: 620465.46 | AO40: 0 | AR40: 0 | AT40: 0 | AU40: 0 | AV40: G.C. Foods Pvt. Ltd.Ghaziabad - Uttar Pradesh-Billing | AW40: 09AACCG2244H1ZS | BB40: N/A | BC40: 45848 | BF40: Ghaziabad | BH40: Cancelled | BI40: 0 | BJ40: Amount INR 620465.46 to Mahaadev Traders Transaction reference no N/A dated 2025-07-10 | BK40: INR Six Lakh, Twenty Thousand, Four Hundred And Sixty Five and Forty Six Paisa only. | BL40: No | BO40: AXIS BANK | BP40: 921030023943516 | BR40: INR Six Lakh, Twenty Thousand, Four Hundred And Sixty Five and Forty Six Paisa only. | BT40: Mahaadev Traders
A41: PAY/N/25-26/0448 | B41: PAY/N/25-26/0448-1 | C41: PAY/G/23-24/.#### | D41: Receive | E41: 45848 | F41: G. C. Foods Pvt. Ltd. | G41: Debtors - GCF | H41: INR | I41: 9210300223943516 - Axis Bank Ltd. CC Tronica - GCF | J41: INR | K41: 1000000 | L41: 1 | M41: 1000000 | N41: 1000000 | O41: 1 | P41: 1000000 | Q41: Approved | R41: Initiated | S41: NEFT/RTGS | T41: Customer | U41: Sanjay Trading Company | V41: Sanjay Trading Company | W41: 0 | X41: 0 | Y41: AXIS BANK 921030023943516 - GZB | AC41: 821394.34 | AD41: Receivable | AE41: 821394.34 | AF41: Bank | AG41: -52648582 | AH41: 1000000 | AI41: 1000000 | AJ41: 1000000 | AK41: 1000000 | AL41: 0 | AM41: 0 | AN41: 1000000 | AO41: 0 | AR41: 0 | AT41: 0 | AU41: 0 | AV41: G.C. Foods Pvt. Ltd. Noida - Uttar Pradesh (Shipping) | AW41: 09AACCG2244H1ZS | AX41: 10-Bihar | AY41: Sanjay Trading Company-Billing | AZ41: 10AUUPK5490N2ZZ | BA41: Registered Regular | BB41: N/A | BC41: 45848 | BF41: Noida | BH41: Cancelled | BI41: 0 | BJ41: Amount INR 1000000 received from Sanjay Trading Company Transaction reference no N/A dated 2025-07-10 | BK41: INR Ten Lakh only. | BL41: No | BO41: AXIS BANK | BP41: 921030023943516 | BR41: INR Ten Lakh only. | BT41: Sanjay Trading Company
A42: PAY/G/25-26/1240-1 | B42: PAY/G/25-26/1240-2 | C42: PAY/G/23-24/.#### | D42: Receive | E42: 45847 | F42: G. C. Foods Pvt. Ltd. | G42: Debtors - GCF | H42: INR | I42: 9210300223943516 - Axis Bank Ltd. CC Tronica - GCF | J42: INR | K42: 522375 | L42: 1 | M42: 522375 | N42: 522375 | O42: 1 | P42: 522375 | Q42: Approved | R42: Initiated | T42: Customer | U42: Naveen Trading Company | V42: Naveen Trading Company | W42: 0 | X42: 0 | Y42: AXIS BANK 921030023943516 - GZB | AC42: 0 | AD42: Receivable | AE42: -39369616 | AF42: Bank | AG42: -52164419 | AH42: 522375 | AI42: 522375 | AJ42: 522375 | AK42: 522375 | AL42: 0 | AM42: 0 | AN42: 522375 | AO42: 0 | AR42: 0 | AT42: 0 | AU42: 0 | AV42: G.C. Foods Pvt. Ltd.Ghaziabad - Uttar Pradesh-Billing | AW42: 09AACCG2244H1ZS | AX42: 08-Rajasthan | AZ42: 08ACHPS6047E1ZF | BA42: Registered Regular | BB42: N/A | BC42: 45847 | BF42: Ghaziabad | BH42: Cancelled | BI42: 0 | BJ42: Amount INR 522375 received from Naveen Trading Company Transaction reference no N/A dated 2025-07-09 | BK42: INR Five Lakh, Twenty Two Thousand, Three Hundred And Seventy Five only. | BL42: No | BO42: AXIS BANK | BP42: 921030023943516 | BR42: INR Five Lakh, Twenty Two Thousand, Three Hundred And Seventy Five only. | BT42: Naveen Trading Company
A43: PAY/G/25-26/1240 | B43: PAY/G/25-26/1240-1 | C43: PAY/G/23-24/.#### | D43: Receive | E43: 45817 | F43: G. C. Foods Pvt. Ltd. | G43: Debtors - GCF | H43: INR | I43: 9210300223943516 - Axis Bank Ltd. CC Tronica - GCF | J43: INR | K43: 522375 | L43: 1 | M43: 522375 | N43: 522375 | O43: 1 | P43: 522375 | Q43: Approved | R43: Initiated | T43: Customer | U43: Naveen Trading Company | V43: Naveen Trading Company | W43: 0 | X43: 0 | Y43: AXIS BANK 921030023943516 - GZB | AC43: 0 | AD43: Receivable | AE43: -39369616 | AF43: Bank | AG43: -52164419 | AH43: 522375 | AI43: 522375 | AJ43: 522375 | AK43: 522375 | AL43: 0 | AM43: 0 | AN43: 522375 | AO43: 0 | AR43: 0 | AT43: 0 | AU43: 0 | AV43: G.C. Foods Pvt. Ltd.Ghaziabad - Uttar Pradesh-Billing | AW43: 09AACCG2244H1ZS | AX43: 08-Rajasthan | AZ43: 08ACHPS6047E1ZF | BA43: Registered Regular | BB43: N/A | BC43: 45847 | BF43: Ghaziabad | BH43: Cancelled | BI43: 0 | BJ43: Amount INR 522375 received from Naveen Trading Company Transaction reference no N/A dated 2025-07-09 | BK43: INR Five Lakh, Twenty Two Thousand, Three Hundred And Seventy Five only. | BL43: No | BO43: AXIS BANK | BP43: 921030023943516 | BR43: INR Five Lakh, Twenty Two Thousand, Three Hundred And Seventy Five only. | BT43: Naveen Trading Company
A44: PAY/M/25-26/0769 | B44: PAY/M/25-26/0769-1 | C44: PAY/G/23-24/.#### | D44: Pay | E44: 45845 | F44: G. C. Foods Pvt. Ltd. | G44: 921030030087773 - Axis Bank Ltd. CC Bihar - GCF | H44: INR | I44: Creditors - GCF | J44: INR | K44: 30600 | L44: 1 | M44: 30600 | N44: 30600 | O44: 1 | P44: 30600 | Q44: Approved | R44: Initiated | S44: NEFT/RTGS | T44: Supplier | U44: Jogi Jee Patna | V44: Jogi Jee Patna | W44: 0 | X44: 0 | Y44: AXIS BANK 921030030087773 - BIHAR | AC44: 0 | AD44: Bank | AE44: -18051699 | AF44: Payable | AG44: 68336946 | AH44: 30600 | AI44: 30600 | AJ44: 30600 | AK44: 30600 | AL44: 0 | AM44: 0 | AN44: 30600 | AO44: 0 | AR44: 0 | AT44: 0 | AU44: 0 | AV44: GC Foods Muzaffarpur-Billing | AW44: 10AACCG2244H1Z9 | BB44: N/A | BC44: 45845 | BF44: Muzaffarpur | BH44: Cancelled | BI44: 0 | BJ44: Amount INR 30600 to Jogi Jee Patna Transaction reference no N/A dated 2025-07-07 | BK44: INR Thirty Thousand, Six Hundred only. | BL44: No | BO44: AXIS BANK | BP44: 921030030087773 | BR44: INR Thirty Thousand, Six Hundred only. | BT44: Jogi Jee Patna
A45: PAY/G/25-26/1222 | B45: PAY/G/25-26/1222-1 | C45: PAY/G/23-24/.#### | D45: Receive | E45: 45845 | F45: G. C. Foods Pvt. Ltd. | G45: Debtors - GCF | H45: INR | I45: 921030030087773 - Axis Bank Ltd. CC Bihar - GCF | J45: INR | K45: 51215 | L45: 1 | M45: 51215 | N45: 51215 | O45: 1 | P45: 51215 | Q45: Approved | R45: Initiated | S45: NEFT/RTGS | T45: Customer | U45: M/s Govind Kirana ,Sevaipati | V45: Govind Kirana, Sevaipati | W45: 0 | X45: 0 | Y45: AXIS BANK 921030030087773 - BIHAR | AA45: M/s Govind Kirana ,Sevaipati-M/s Govind Kirana ,Sevaipati | AC45: -51217 | AD45: Receivable | AE45: -51217 | AF45: Bank | AG45: -18819204 | AH45: 51215 | AI45: 51215 | AJ45: 51215 | AK45: 51215 | AL45: 0 | AM45: 0 | AN45: 51215 | AO45: 0 | AR45: 0 | AT45: 0 | AU45: 0 | AV45: GC Foods Muzaffarpur-Billing | AW45: 10AACCG2244H1Z9 | AX45: 10-Bihar | AY45: M/s Govind Kirana ,Sevaipati-Billing | AZ45: 10COKPK3572F1Z6 | BA45: Registered Regular | BB45: N/A | BC45: 45845 | BF45: Muzaffarpur | BH45: Cancelled | BI45: 0 | BJ45: Amount INR 51215 received from M/s Govind Kirana ,Sevaipati Transaction reference no N/A dated 2025-07-07 | BK45: INR Fifty One Thousand, Two Hundred And Fifteen only. | BL45: No | BO45: AXIS BANK | BP45: 921030030087773 | BR45: INR Fifty One Thousand, Two Hundred And Fifteen only. | BT45: M/s Govind Kirana ,Sevaipati
A46: PAY/M/25-26/0756 | B46: PAY/M/25-26/0756-1 | C46: PAY/G/23-24/.#### | D46: Receive | E46: 45843 | F46: G. C. Foods Pvt. Ltd. | G46: Debtors - GCF | H46: INR | I46: 921030030087773 - Axis Bank Ltd. CC Bihar - GCF | J46: INR | K46: 500000 | L46: 1 | M46: 500000 | N46: 500000 | O46: 1 | P46: 500000 | Q46: Approved | R46: Initiated | S46: NEFT/RTGS | T46: Customer | U46: G.C.Wilmar Private Limited | V46: GC Wilmar Private Limited | W46: 0 | X46: 0 | Y46: AXIS BANK 921030030087773 - BIHAR | AA46: G.C.Wilmar Private Limited-G.C.Wilmar Private Limited | AC46: -27318300 | AD46: Receivable | AE46: -27318300 | AF46: Bank | AG46: -19160701 | AH46: 500000 | AI46: 500000 | AJ46: 500000 | AK46: 500000 | AL46: 0 | AM46: 0 | AN46: 500000 | AO46: 0 | AR46: 0 | AT46: 0 | AU46: 0 | AV46: GC Foods Muzaffarpur-Billing | AW46: 10AACCG2244H1Z9 | AX46: 10-Bihar | AY46: G.C.Wilmar Private Limited-Billing | AZ46: 10AAICG5386J1ZH | BA46: Registered Regular | BB46: N/A | BC46: 45843 | BF46: Muzaffarpur | BH46: Cancelled | BI46: 0 | BJ46: Amount INR 500000 received from G.C.Wilmar Private Limited Transaction reference no N/A dated 2025-07-05 | BK46: INR Five Lakh only. | BL46: No | BO46: AXIS BANK | BP46: 921030030087773 | BR46: INR Five Lakh only. | BT46: G.C.Wilmar Private Limited
A47: PAY/M/25-26/0746 | B47: PAY/M/25-26/0746-1 | C47: PAY/G/23-24/.#### | D47: Receive | E47: 45842 | F47: G. C. Foods Pvt. Ltd. | G47: Debtors - GCF | H47: INR | I47: 923020053773708 - Axis Bank - Bihar - GCF | J47: INR | K47: 50000 | L47: 1 | M47: 50000 | N47: 50000 | O47: 1 | P47: 50000 | Q47: Approved | R47: Initiated | S47: NEFT/RTGS | T47: Customer | U47: G.C.Wilmar Private Limited | V47: GC Wilmar Private Limited | W47: 0 | X47: 0 | Y47: AXIS BANK 923020053773708 - BIHAR | AA47: G.C.Wilmar Private Limited-G.C.Wilmar Private Limited | AC47: -31295776 | AD47: Receivable | AE47: -31295776 | AF47: Bank | AG47: 606.45 | AH47: 50000 | AI47: 50000 | AJ47: 50000 | AK47: 50000 | AL47: 0 | AM47: 0 | AN47: 50000 | AO47: 0 | AR47: 0 | AT47: 0 | AU47: 0 | AV47: GC Foods Muzaffarpur-Billing | AW47: 10AACCG2244H1Z9 | AX47: 10-Bihar | AY47: G.C.Wilmar Private Limited-Billing | AZ47: 10AAICG5386J1ZH | BA47: Registered Regular | BB47: N/A | BC47: 45842 | BF47: Muzaffarpur | BH47: Cancelled | BI47: 0 | BJ47: Amount INR 50000 received from G.C.Wilmar Private Limited Transaction reference no N/A dated 2025-07-04 | BK47: INR Fifty Thousand only. | BL47: No | BO47: AXIS BANK | BP47: 923020053773708 | BR47: INR Fifty Thousand only. | BT47: G.C.Wilmar Private Limited
A48: PAY/G/25-26/1185 | B48: PAY/G/25-26/1185-1 | C48: PAY/G/23-24/.#### | D48: Pay | E48: 45842 | F48: G. C. Foods Pvt. Ltd. | G48: 9210300223943516 - Axis Bank Ltd. CC Tronica - GCF | H48: INR | I48: Creditors - GCF | J48: INR | K48: 30000 | L48: 1 | M48: 30000 | N48: 30000 | O48: 1 | P48: 30000 | Q48: Approved | R48: Initiated | S48: NEFT/RTGS | T48: Supplier | U48: Suspense A/c | V48: Suspense A/c | W48: 0 | X48: 0 | Y48: AXIS BANK 921030023943516 - GZB | AC48: 0 | AD48: Bank | AE48: -52189519 | AF48: Payable | AG48: 68175945 | AH48: 30000 | AI48: 30000 | AJ48: 30000 | AK48: 30000 | AL48: 0 | AM48: 0 | AN48: 30000 | AO48: 0 | AR48: 0 | AT48: 0 | AU48: 0 | AV48: G.C. Foods Pvt. Ltd.Ghaziabad - Uttar Pradesh-Billing | AW48: 09AACCG2244H1ZS | BB48: N/A | BC48: 45842 | BF48: Ghaziabad | BH48: Cancelled | BI48: 0 | BJ48: Amount INR 30000 to Suspense A/c Transaction reference no N/A dated 2025-07-04 | BK48: INR Thirty Thousand only. | BL48: No | BO48: AXIS BANK | BP48: 921030023943516 | BR48: INR Thirty Thousand only. | BT48: Suspense A/c
A49: PAY/M/25-26/0727 | B49: PAY/M/25-26/0727-1 | C49: PAY/G/23-24/.#### | D49: Receive | E49: 45841 | F49: G. C. Foods Pvt. Ltd. | G49: Debtors - GCF | H49: INR | I49: 9210300223943516 - Axis Bank Ltd. CC Tronica - GCF | J49: INR | K49: 50841 | L49: 1 | M49: 50841 | N49: 50841 | O49: 1 | P49: 50841 | Q49: Approved | R49: Initiated | S49: NEFT/RTGS | T49: Customer | U49: Ansh Trading Madhubani | V49: Ansh Trading Madhubani | W49: 0 | X49: 0 | Y49: AXIS BANK 921030030087773 - BIHAR | AA49: Ans Trading Madhubani-Ans Trading Madhubani | AC49: -383250 | AD49: Receivable | AE49: -383250 | AF49: Bank | AG49: -52907658 | AH49: 50841 | AI49: 50841 | AJ49: 50841 | AK49: 50841 | AL49: 0 | AM49: 0 | AN49: 50841 | AO49: 0 | AR49: 0 | AT49: 0 | AU49: 0 | AV49: GC Foods Muzaffarpur-Billing | AW49: 10AACCG2244H1Z9 | AX49: 10-Bihar | AY49: Ans Trading Madhubani-Billing | AZ49: 10DNWPP5708L1ZF | BA49: Registered Regular | BB49: N/A | BC49: 45841 | BF49: Muzaffarpur | BH49: Cancelled | BI49: 0 | BJ49: Amount INR 50841 received from Ansh Trading Madhubani Transaction reference no N/A dated 2025-07-03 | BK49: INR Fifty Thousand, Eight Hundred And Forty One only. | BL49: No | BO49: AXIS BANK | BP49: 921030030087773 | BR49: INR Fifty Thousand, Eight Hundred And Forty One only. | BT49: Ansh Trading Madhubani
A50: PAY/G/25-26/1178 | B50: PAY/G/25-26/1178-1 | C50: PAY/G/23-24/.#### | D50: Receive | E50: 45841 | F50: G. C. Foods Pvt. Ltd. | G50: Debtors - GCF | H50: INR | I50: 9210300223943516 - Axis Bank Ltd. CC Tronica - GCF | J50: INR | K50: 83295 | L50: 1 | M50: 83295 | N50: 83295 | O50: 1 | P50: 83295 | Q50: Approved | R50: Initiated | S50: NEFT/RTGS | T50: Customer | U50: RRR Traders | V50: RRR Traders | W50: 0 | X50: 0 | Y50: AXIS BANK 921030023943516 - GZB | AC50: 3315 | AD50: Receivable | AE50: 3315 | AF50: Bank | AG50: -52900399 | AH50: 83295 | AI50: 83295 | AJ50: 83295 | AK50: 83295 | AL50: 0 | AM50: 0 | AN50: 83295 | AO50: 0 | AR50: 0 | AT50: 0 | AU50: 0 | AV50: G.C. Foods Pvt. Ltd.Ghaziabad - Uttar Pradesh-Billing | AW50: 09AACCG2244H1ZS | AX50: 09-Uttar Pradesh | AY50: RRR Traders-Billing | AZ50: 09ABEFR8587N1Z4 | BA50: Registered Regular | BB50: N/A | BC50: 45841 | BF50: Ghaziabad | BH50: Cancelled | BI50: 0 | BJ50: Amount INR 83295 received from RRR Traders Transaction reference no N/A dated 2025-07-03 | BK50: INR Eighty Three Thousand, Two Hundred And Ninety Five only. | BL50: No | BO50: AXIS BANK | BP50: 921030023943516 | BR50: INR Eighty Three Thousand, Two Hundred And Ninety Five only. | BT50: RRR Traders
A51: PAY/G/25-26/1177 | B51: PAY/G/25-26/1177-1 | C51: PAY/G/23-24/.#### | D51: Receive | E51: 45841 | F51: G. C. Foods Pvt. Ltd. | G51: Debtors - GCF | H51: INR | I51: 9210300223943516 - Axis Bank Ltd. CC Tronica - GCF | J51: INR | K51: 7259 | L51: 1 | M51: 7259 | N51: 7259 | O51: 1 | P51: 7259 | Q51: Approved | R51: Initiated | S51: NEFT/RTGS | T51: Customer | U51: RRR Traders | V51: RRR Traders | W51: 0 | X51: 0 | Y51: AXIS BANK 921030023943516 - GZB | AC51: 10574 | AD51: Receivable | AE51: 10574 | AF51: Bank | AG51: -52907658 | AH51: 7259 | AI51: 7259 | AJ51: 7259 | AK51: 7259 | AL51: 0 | AM51: 0 | AN51: 7259 | AO51: 0 | AR51: 0 | AT51: 0 | AU51: 0 | AV51: G.C. Foods Pvt. Ltd.Ghaziabad - Uttar Pradesh-Billing | AW51: 09AACCG2244H1ZS | AX51: 09-Uttar Pradesh | AY51: RRR Traders-Billing | AZ51: 09ABEFR8587N1Z4 | BA51: Registered Regular | BB51: N/A | BC51: 45841 | BF51: Ghaziabad | BH51: Cancelled | BI51: 0 | BJ51: Amount INR 7259 received from RRR Traders Transaction reference no N/A dated 2025-07-03 | BK51: INR Seven Thousand, Two Hundred And Fifty Nine only. | BL51: No | BO51: AXIS BANK | BP51: 921030023943516 | BR51: INR Seven Thousand, Two Hundred And Fifty Nine only. | BT51: RRR Traders
A52: PAY/G/23-24/0879 | B52: PAY/G/23-24/0879-1 | C52: PAY/G/23-24/.#### | D52: Pay | E52: 45841 | F52: G. C. Foods Pvt. Ltd. | G52: 9210300223943516 - Axis Bank Ltd. CC Tronica - GCF | H52: INR | I52: Creditors - GCF | J52: INR | K52: 4130 | L52: 1 | M52: 4130 | N52: 4130 | O52: 1 | P52: 4130 | Q52: Approved | R52: Initiated | S52: NEFT/RTGS | T52: Supplier | U52: Global WMC India Pvt Ltd | V52: Global WMC India Pvt Ltd | W52: 0 | X52: 0 | Y52: AXIS BANK 921030023943516 - GZB | AC52: 8260 | AD52: Bank | AE52: -53523958 | AF52: Payable | AG52: 8260 | AH52: 4130 | AI52: 4130 | AJ52: 4130 | AK52: 4130 | AL52: 0 | AM52: 0 | AN52: 4130 | AO52: 0 | AR52: 0 | AT52: 0 | AU52: 0 | AV52: G.C. Foods Pvt. Ltd.Ghaziabad - Uttar Pradesh-Billing | AW52: 09AACCG2244H1ZS | BB52: N/A | BC52: 45841 | BF52: Ghaziabad | BH52: Cancelled | BI52: 0 | BJ52: Amount INR 4130 to Global WMC India Pvt Ltd Transaction reference no N/A dated 2025-07-03 | BK52: INR Four Thousand, One Hundred And Thirty only. | BL52: No | BO52: AXIS BANK | BP52: 921030023943516 | BR52: INR Four Thousand, One Hundred And Thirty only. | BT52: Global WMC India Pvt Ltd
A53: PAY/N/25-26/0441 | B53: PAY/N/25-26/0441-1 | C53: PAY/G/23-24/.#### | D53: Receive | E53: 45838 | F53: G. C. Foods Pvt. Ltd. | G53: Debtors - GCF | H53: INR | I53: 923020017959018 - Axis Bank - NOIDA - GCF | J53: INR | K53: 3174.08 | L53: 1 | M53: 3174.08 | N53: 3174.08 | O53: 1 | P53: 3174.08 | Q53: Approved | R53: Initiated | S53: NEFT/RTGS | T53: Customer | U53: Amazon Courier | V53: Amazon Courier | W53: 0 | X53: 0 | Y53: AXIS BANK 923020017959018 -NOIDA | AC53: 31789.77 | AD53: Receivable | AE53: 31789.77 | AF53: Bank | AG53: 66961.95 | AH53: 3174.08 | AI53: 3174.08 | AJ53: 3174.08 | AK53: 3174.08 | AL53: 0 | AM53: 0 | AN53: 3174.08 | AO53: 0 | AR53: 0 | AT53: 0 | AU53: 0 | AV53: G.C. Foods Pvt. Ltd. Noida - Uttar Pradesh (Shipping) | AW53: 09AACCG2244H1ZS | AX53: 30-Goa | AY53: Amazon Courier-Billing-12 | BA53: Unregistered | BB53: N/A | BC53: 45838 | BF53: Noida | BH53: Cancelled | BI53: 0 | BJ53: Amount INR 3174.08 received from Amazon Courier Transaction reference no N/A dated 2025-06-30 | BK53: INR Three Thousand, One Hundred And Seventy Four and Eight Paisa only. | BL53: No | BO53: AXIS BANK | BP53: 923020017959018 | BR53: INR Three Thousand, One Hundred And Seventy Four and Eight Paisa only. | BT53: Amazon Courier
A54: PAY/G/25-26/1149 | B54: PAY/G/25-26/1149-1 | C54: PAY/G/23-24/.#### | D54: Pay | E54: 45835 | F54: G. C. Foods Pvt. Ltd. | G54: 921030030087786 - Axis Bank Ltd. CC Noida - GCF | H54: INR | I54: Creditors - GCF | J54: INR | K54: 9440 | L54: 1 | M54: 9440 | N54: 9440 | O54: 1 | P54: 9440 | Q54: Approved | R54: Initiated | S54: NEFT/RTGS | T54: Supplier | U54: Centriik | V54: Centriik | W54: 0 | X54: 0 | Y54: AXIS BANK 921030030087786 - NOIDA | AC54: -9440 | AD54: Bank | AE54: -4909727.1 | AF54: Payable | AG54: -9440 | AH54: 9440 | AI54: 9440 | AJ54: 9440 | AK54: 9440 | AL54: 0 | AM54: 0 | AN54: 9440 | AO54: 0 | AR54: 0 | AT54: 0 | AU54: 0 | AV54: G.C. Foods Pvt. Ltd.Ghaziabad - Uttar Pradesh-Billing | AW54: 09AACCG2244H1ZS | BB54: N/A | BC54: 45835 | BF54: Ghaziabad | BH54: Cancelled | BI54: 0 | BJ54: Amount INR 9440 to Centriik Transaction reference no N/A dated 2025-06-27 | BK54: INR Nine Thousand, Four Hundred And Forty only. | BL54: No | BO54: AXIS BANK | BP54: 921030030087786 | BR54: INR Nine Thousand, Four Hundred And Forty only. | BT54: Centriik
A55: PAY/M/25-26/0694 | B55: PAY/M/25-26/0694-1 | C55: PAY/G/23-24/.#### | D55: Pay | E55: 45838 | F55: G. C. Foods Pvt. Ltd. | G55: 921030030087773 - Axis Bank Ltd. CC Bihar - GCF | H55: INR | I55: Creditors - GCF | J55: INR | K55: 32831 | L55: 1 | M55: 32831 | N55: 32831 | O55: 1 | P55: 32831 | Q55: Approved | R55: Initiated | S55: NEFT/RTGS | T55: Supplier | U55: Axis Bank Machine Loan (924060051423271) | V55: Axis Bank Machine Loan (924060051423271) | W55: 0 | X55: 0 | Y55: AXIS BANK 921030030087773 - BIHAR | AC55: 753992 | AD55: Bank | AE55: -19179090 | AF55: Payable | AG55: 753992 | AH55: 32831 | AI55: 32831 | AJ55: 32831 | AK55: 32831 | AL55: 0 | AM55: 0 | AN55: 32831 | AO55: 0 | AR55: 0 | AT55: 0 | AU55: 0 | AV55: GC Foods Muzaffarpur-Billing | AW55: 10AACCG2244H1Z9 | BB55: N/A | BC55: 45838 | BF55: Muzaffarpur | BH55: Cancelled | BI55: 0 | BJ55: Amount INR 32831 to Axis Bank Machine Loan (924060051423271) Transaction reference no N/A dated 2025-06-30 | BK55: INR Thirty Two Thousand, Eight Hundred And Thirty One only. | BL55: No | BO55: AXIS BANK | BP55: 921030030087773 | BR55: INR Thirty Two Thousand, Eight Hundred And Thirty One only. | BT55: Axis Bank Machine Loan (924060051423271)
A56: PAY/M/25-26/0678 | B56: PAY/M/25-26/0678-1 | C56: PAY/G/23-24/.#### | D56: Pay | E56: 45756 | F56: G. C. Foods Pvt. Ltd. | G56: 9210300223943516 - Axis Bank Ltd. CC Tronica - GCF | H56: INR | I56: Creditors - GCF | J56: INR | K56: 20000 | L56: 1 | M56: 20000 | N56: 20000 | O56: 1 | P56: 20000 | Q56: Approved | R56: Initiated | S56: NEFT/RTGS | T56: Supplier | U56: Cash (Sattu) | V56: Cash (Sattu) | W56: 0 | X56: 0 | Y56: AXIS BANK 923020053917139 - BIHAR | AC56: 3657 | AD56: Bank | AE56: -52010567 | AF56: Payable | AG56: 3657 | AH56: 20000 | AI56: 20000 | AJ56: 20000 | AK56: 20000 | AL56: 0 | AM56: 0 | AN56: 20000 | AO56: 0 | AR56: 0 | AT56: 0 | AU56: 0 | AV56: GC Foods Muzaffarpur-Billing | AW56: 10AACCG2244H1Z9 | BB56: N/A | BC56: 45756 | BF56: Muzaffarpur | BH56: Cancelled | BI56: 0 | BJ56: Amount INR 20000 to Cash (Sattu) Transaction reference no N/A dated 2025-04-09 | BK56: INR Twenty Thousand only. | BL56: No | BO56: AXIS BANK | BP56: 923020053917139 | BR56: INR Twenty Thousand only. | BT56: Cash (Sattu)
A57: PAY/M/25-26/0667 | B57: PAY/M/25-26/0667-1 | C57: PAY/G/23-24/.#### | D57: Receive | E57: 45834 | F57: G. C. Foods Pvt. Ltd. | G57: Debtors - GCF | H57: INR | I57: 9210300223943516 - Axis Bank Ltd. CC Tronica - GCF | J57: INR | K57: 159962 | L57: 1 | M57: 159962 | N57: 159962 | O57: 1 | P57: 159962 | Q57: Approved | R57: Initiated | S57: NEFT/RTGS | T57: Customer | U57: Maheshwari Trading Co Samastipur | V57: Maheshwari Trading Co Samastipur | W57: 0 | X57: 0 | Y57: AXIS BANK 921030023943516 - GZB | AC57: -3752291 | AD57: Receivable | AE57: -3752291 | AF57: Bank | AG57: -54107486 | AH57: 159962 | AI57: 159962 | AJ57: 159962 | AK57: 159962 | AL57: 0 | AM57: 0 | AN57: 159962 | AO57: 0 | AR57: 0 | AT57: 0 | AU57: 0 | AV57: GC Foods Muzaffarpur-Billing | AW57: 10AACCG2244H1Z9 | AX57: 10-Bihar | AY57: Maheshwari Trading Co Samastipur-Billing | AZ57: 10ABNFM9898C1ZW | BA57: Registered Regular | BB57: N/A | BC57: 45834 | BF57: Muzaffarpur | BH57: Cancelled | BI57: 0 | BJ57: Amount INR 159962 received from Maheshwari Trading Co Samastipur Transaction reference no N/A dated 2025-06-26 | BK57: INR One Lakh, Fifty Nine Thousand, Nine Hundred And Sixty Two only. | BL57: No | BO57: AXIS BANK | BP57: 921030023943516 | BR57: INR One Lakh, Fifty Nine Thousand, Nine Hundred And Sixty Two only. | BT57: Maheshwari Trading Co Samastipur
A58: PAY/G/25-26/1111 | B58: PAY/G/25-26/1111-1 | C58: PAY/G/23-24/.#### | D58: Pay | E58: 45834 | F58: G. C. Foods Pvt. Ltd. | G58: 9210300223943516 - Axis Bank Ltd. CC Tronica - GCF | H58: INR | I58: Creditors - GCF | J58: INR | K58: 71250 | L58: 1 | M58: 71250 | N58: 71250 | O58: 1 | P58: 71250 | Q58: Approved | R58: Initiated | S58: NEFT/RTGS | T58: Supplier | U58: Marudhara Polypack Industries | V58: Marudhara Polypack Industries (Noida) | W58: 0 | X58: 0 | Y58: AXIS BANK 921030023943516 - GZB | AC58: 821677 | AD58: Bank | AE58: -54036236 | AF58: Payable | AG58: 821677 | AH58: 71250 | AI58: 71250 | AJ58: 71250 | AK58: 71250 | AL58: 0 | AM58: 0 | AN58: 71250 | AO58: 0 | AR58: 0 | AT58: 0 | AU58: 0 | AV58: G.C. Foods Pvt. Ltd.Ghaziabad - Uttar Pradesh-Billing | AW58: 09AACCG2244H1ZS | BB58: N/A | BC58: 45834 | BF58: Ghaziabad | BH58: Cancelled | BI58: 0 | BJ58: Amount INR 71250 to Marudhara Polypack Industries Transaction reference no N/A dated 2025-06-26 | BK58: INR Seventy One Thousand, Two Hundred And Fifty only. | BL58: No | BO58: AXIS BANK | BP58: 921030023943516 | BR58: INR Seventy One Thousand, Two Hundred And Fifty only. | BT58: Marudhara Polypack Industries
A59: PAY/G/25-26/1110 | B59: PAY/G/25-26/1110-1 | C59: PAY/G/23-24/.#### | D59: Pay | E59: 45834 | F59: G. C. Foods Pvt. Ltd. | G59: 9210300223943516 - Axis Bank Ltd. CC Tronica - GCF | H59: INR | I59: Creditors - GCF | J59: INR | K59: 506248 | L59: 1 | M59: 506248 | N59: 506248 | O59: 1 | P59: 506248 | Q59: Approved | R59: Initiated | S59: NEFT/RTGS | T59: Supplier | U59: Marudhara Polypack Industries | V59: Marudhara Polypack Industries (Noida) | W59: 0 | X59: 0 | Y59: AXIS BANK 921030023943516 - GZB | AC59: 315429 | AD59: Bank | AE59: -53529988 | AF59: Payable | AG59: 315429 | AH59: 506248 | AI59: 506248 | AJ59: 506248 | AK59: 506248 | AL59: 0 | AM59: 0 | AN59: 506248 | AO59: 0 | AR59: 0 | AT59: 0 | AU59: 0 | AV59: G.C. Foods Pvt. Ltd.Ghaziabad - Uttar Pradesh-Billing | AW59: 09AACCG2244H1ZS | BB59: N/A | BC59: 45834 | BF59: Ghaziabad | BH59: Cancelled | BI59: 0 | BJ59: Amount INR 506248 to Marudhara Polypack Industries Transaction reference no N/A dated 2025-06-26 | BK59: INR Five Lakh, Six Thousand, Two Hundred And Forty Eight only. | BL59: No | BO59: AXIS BANK | BP59: 921030023943516 | BR59: INR Five Lakh, Six Thousand, Two Hundred And Forty Eight only. | BT59: Marudhara Polypack Industries
A60: PAY/M/25-26/0665 | B60: PAY/M/25-26/0665-1 | C60: PAY/G/23-24/.#### | D60: Internal Transfer | E60: 45826 | F60: G. C. Foods Pvt. Ltd. | G60: 923020053917139 - Axis Bank - BIHAR - GCF | H60: INR | I60: Cash - GCF | J60: INR | K60: 20000 | L60: 1 | M60: 20000 | N60: 20000 | O60: 1 | P60: 20000 | Q60: Approved | R60: Initiated | S60: NEFT/RTGS | W60: 0 | X60: 0 | AC60: 0 | AD60: Bank | AE60: 20251.8 | AF60: Cash | AG60: 180000 | AH60: 20000 | AI60: 20000 | AJ60: 20000 | AK60: 20000 | AL60: 0 | AM60: 0 | AN60: 0 | AO60: 0 | AR60: 0 | AT60: 0 | AU60: 0 | AV60: GC Foods Muzaffarpur-Billing | AW60: 10AACCG2244H1Z9 | BB60: N/A | BC60: 45826 | BF60: Muzaffarpur | BH60: Cancelled | BI60: 0 | BJ60: Amount INR 20000 transferred from 923020053917139 - Axis Bank - BIHAR - GCF to Cash - GCF Transaction reference no N/A dated 2025-06-18 | BK60: INR Twenty Thousand only. | BL60: No | BR60: INR Twenty Thousand only. | BT60: 923020053917139 - Axis Bank - BIHAR - GCF - Cash - GCF
A61: PAY/M/25-26/0658 | B61: PAY/M/25-26/0658-1 | C61: PAY/G/23-24/.#### | D61: Pay | E61: 45832 | F61: G. C. Foods Pvt. Ltd. | G61: 921030030087773 - Axis Bank Ltd. CC Bihar - GCF | H61: INR | I61: Creditors - GCF | J61: INR | K61: 46800 | L61: 1 | M61: 46800 | N61: 46800 | O61: 1 | P61: 46800 | Q61: Approved | R61: Initiated | S61: NEFT/RTGS | T61: Supplier | U61: Suspense A/c | V61: Suspense A/c | W61: 0 | X61: 0 | Y61: AXIS BANK 921030030087773 - BIHAR | AC61: 0 | AD61: Bank | AE61: -19664769 | AF61: Payable | AG61: 63042492 | AH61: 46800 | AI61: 46800 | AJ61: 46800 | AK61: 46800 | AL61: 0 | AM61: 0 | AN61: 46800 | AO61: 0 | AR61: 0 | AT61: 0 | AU61: 0 | AV61: GC Foods Muzaffarpur-Billing | AW61: 10AACCG2244H1Z9 | BB61: N/A | BC61: 45832 | BF61: Muzaffarpur | BH61: Cancelled | BI61: 0 | BJ61: Amount INR 46800 to Suspense A/c Transaction reference no N/A dated 2025-06-24 | BK61: INR Forty Six Thousand, Eight Hundred only. | BL61: No | BO61: AXIS BANK | BP61: 921030030087773 | BR61: INR Forty Six Thousand, Eight Hundred only. | BT61: Suspense A/c
A62: PAY/G/25-26/1030 | B62: PAY/G/25-26/1030-1 | C62: PAY/G/23-24/.#### | D62: Pay | E62: 45829 | F62: G. C. Foods Pvt. Ltd. | G62: 9210300223943516 - Axis Bank Ltd. CC Tronica - GCF | H62: INR | I62: Creditors - GCF | J62: INR | K62: 3237 | L62: 1 | M62: 3237 | N62: 3237 | O62: 1 | P62: 3237 | Q62: Approved | R62: Initiated | S62: NEFT/RTGS | T62: Supplier | U62: Bajrang Traders | V62: Bajrang Traders | W62: 0 | X62: 0 | Y62: AXIS BANK 921030023943516 - GZB | AC62: -465 | AD62: Bank | AE62: -53620841 | AF62: Payable | AG62: -465 | AH62: 3237 | AI62: 3237 | AJ62: 3237 | AK62: 3237 | AL62: 0 | AM62: 0 | AN62: 3237 | AO62: 0 | AR62: 0 | AT62: 0 | AU62: 0 | AV62: G.C. Foods Pvt. Ltd.Ghaziabad - Uttar Pradesh-Billing | AW62: 09AACCG2244H1ZS | BB62: N/A | BC62: 45829 | BF62: Ghaziabad | BH62: Cancelled | BI62: 0 | BJ62: Amount INR 3237 to Bajrang Traders Transaction reference no N/A dated 2025-06-21 | BK62: INR Three Thousand, Two Hundred And Thirty Seven only. | BL62: No | BO62: AXIS BANK | BP62: 921030023943516 | BR62: INR Three Thousand, Two Hundred And Thirty Seven only. | BT62: Bajrang Traders
A63: PAY/G/25-26/1027 | B63: PAY/G/25-26/1027-1 | C63: PAY/G/23-24/.#### | D63: Pay | E63: 45828 | F63: G. C. Foods Pvt. Ltd. | G63: 923020053773708 - Axis Bank - Bihar - GCF | H63: INR | I63: Creditors - GCF | J63: INR | K63: 21452 | L63: 1 | M63: 21452 | N63: 21452 | O63: 1 | P63: 21452 | Q63: Approved | R63: Initiated | S63: NEFT/RTGS | T63: Employee | U63: Manish Kumar Mishra (M) | V63: Manish Kumar Mishra (M) | W63: 0 | X63: 0 | AC63: 36894 | AD63: Bank | AE63: 80971.45 | AF63: Payable | AG63: 36894 | AH63: 21452 | AI63: 21452 | AJ63: 21452 | AK63: 21452 | AL63: 0 | AM63: 0 | AN63: 21452 | AO63: 0 | AR63: 0 | AT63: 0 | AU63: 0 | AV63: G.C. Foods Pvt. Ltd.Ghaziabad - Uttar Pradesh-Billing | AW63: 09AACCG2244H1ZS | BB63: N/A | BC63: 45828 | BF63: Ghaziabad | BH63: Cancelled | BI63: 0 | BJ63: Amount INR 21452 to Manish Kumar Mishra (M) Transaction reference no N/A dated 2025-06-20 | BK63: INR Twenty One Thousand, Four Hundred And Fifty Two only. | BL63: No | BR63: INR Twenty One Thousand, Four Hundred And Fifty Two only. | BT63: Manish Kumar Mishra (M)
A64: PAY/G/25-26/1017 | B64: PAY/G/25-26/1017-1 | C64: PAY/G/23-24/.#### | D64: Internal Transfer | E64: 45828 | F64: G. C. Foods Pvt. Ltd. | G64: Cash - GCF | H64: INR | I64: 9210300223943516 - Axis Bank Ltd. CC Tronica - GCF | J64: INR | K64: 500000 | L64: 1 | M64: 500000 | N64: 500000 | O64: 1 | P64: 500000 | Q64: Approved | R64: Initiated | S64: NEFT/RTGS | W64: 0 | X64: 0 | AC64: 0 | AD64: Cash | AE64: 200000 | AF64: Bank | AG64: -54034469 | AH64: 500000 | AI64: 500000 | AJ64: 500000 | AK64: 500000 | AL64: 0 | AM64: 0 | AN64: 0 | AO64: 0 | AR64: 0 | AT64: 0 | AU64: 0 | AV64: G.C. Foods Pvt. Ltd.Ghaziabad - Uttar Pradesh-Billing | AW64: 09AACCG2244H1ZS | BB64: N/A | BC64: 45828 | BF64: Ghaziabad | BH64: Cancelled | BI64: 0 | BJ64: Amount INR 500000 transferred from Cash - GCF to 9210300223943516 - Axis Bank Ltd. CC Tronica - GCF Transaction reference no N/A dated 2025-06-20 | BK64: INR Five Lakh only. | BL64: No | BR64: INR Five Lakh only. | BT64: Cash - GCF - 9210300223943516 - Axis Bank Ltd. CC Tronica - GCF
A65: PAY/G/25-26/1009 | B65: PAY/G/25-26/1009-1 | C65: PAY/G/23-24/.#### | D65: Receive | E65: 45827 | F65: G. C. Foods Pvt. Ltd. | G65: Debtors - GCF | H65: INR | I65: 9210300223943516 - Axis Bank Ltd. CC Tronica - GCF | J65: INR | K65: 7788 | L65: 1 | M65: 7788 | N65: 7788 | O65: 1 | P65: 7788 | Q65: Approved | R65: Initiated | S65: NEFT/RTGS | T65: Customer | U65: Jove Synthochem Private Limited | V65: Jove Synthochem Private Limited | W65: 0 | X65: 0 | Y65: AXIS BANK 921030023943516 - GZB | AC65: 0 | AD65: Receivable | AE65: -85768888 | AF65: Bank | AG65: -53550246 | AH65: 7788 | AI65: 7788 | AJ65: 7788 | AK65: 7788 | AL65: 0 | AM65: 0 | AN65: 7788 | AO65: 0 | AR65: 0 | AT65: 0 | AU65: 0 | AV65: G.C. Foods Pvt. Ltd.Ghaziabad - Uttar Pradesh-Billing | AW65: 09AACCG2244H1ZS | AX65: 09-Uttar Pradesh | AY65: Jove Synthochem Private Limited-Billing | AZ65: 09AABCJ2066R1Z1 | BA65: Registered Regular | BB65: N/A | BC65: 45827 | BF65: Ghaziabad | BH65: Cancelled | BI65: 0 | BJ65: Amount INR 7788 received from Jove Synthochem Private Limited Transaction reference no N/A dated 2025-06-19 | BK65: INR Seven Thousand, Seven Hundred And Eighty Eight only. | BL65: No | BO65: AXIS BANK | BP65: 921030023943516 | BR65: INR Seven Thousand, Seven Hundred And Eighty Eight only. | BT65: Jove Synthochem Private Limited
A66: PAY/M/25-26/0614 | B66: PAY/M/25-26/0614-1 | C66: PAY/G/23-24/.#### | D66: Pay | E66: 45824 | F66: G. C. Foods Pvt. Ltd. | G66: 923020053773708 - Axis Bank - Bihar - GCF | H66: INR | I66: Creditors - GCF | J66: INR | K66: 48000 | L66: 1 | M66: 48000 | N66: 48000 | O66: 1 | P66: 48000 | Q66: Approved | R66: Initiated | S66: NEFT/RTGS | T66: Supplier | U66: Shashi Kant Bhalla | V66: Shashi Kant Bhalla | W66: 0 | X66: 0 | Y66: AXIS BANK 923020053773708 - BIHAR | AC66: 96000 | AD66: Bank | AE66: 77493.45 | AF66: Payable | AG66: 96000 | AH66: 48000 | AI66: 48000 | AJ66: 48000 | AK66: 48000 | AL66: 0 | AM66: 0 | AN66: 48000 | AO66: 0 | AR66: 0 | AT66: 0 | AU66: 0 | AV66: GC Foods Muzaffarpur-Billing | AW66: 10AACCG2244H1Z9 | BB66: N/A | BC66: 45824 | BF66: Muzaffarpur | BH66: Cancelled | BI66: 0 | BJ66: Amount INR 48000 to Shashi Kant Bhalla Transaction reference no N/A dated 2025-06-16 | BK66: INR Forty Eight Thousand only. | BL66: No | BO66: AXIS BANK | BP66: 923020053773708 | BR66: INR Forty Eight Thousand only. | BT66: Shashi Kant Bhalla
A67: PAY/M/25-26/0612 | B67: PAY/M/25-26/0612-1 | C67: PAY/G/23-24/.#### | D67: Pay | E67: 45822 | F67: G. C. Foods Pvt. Ltd. | G67: 9210300223943516 - Axis Bank Ltd. CC Tronica - GCF | H67: INR | I67: Creditors - GCF | J67: INR | K67: 26613 | L67: 1 | M67: 26613 | N67: 26613 | O67: 1 | P67: 26613 | Q67: Approved | R67: Initiated | S67: NEFT/RTGS | T67: Employee | U67: Ritesh Kumar (M) | V67: Ritesh Kumar (M) | W67: 0 | X67: 0 | AC67: 51893 | AD67: Bank | AE67: -54251851 | AF67: Payable | AG67: 51893 | AH67: 26613 | AI67: 26613 | AJ67: 26613 | AK67: 26613 | AL67: 0 | AM67: 0 | AN67: 26613 | AO67: 0 | AR67: 0 | AT67: 0 | AU67: 0 | AV67: GC Foods Muzaffarpur-Billing | AW67: 10AACCG2244H1Z9 | BB67: N/A | BC67: 45822 | BF67: Muzaffarpur | BH67: Cancelled | BI67: 0 | BJ67: Amount INR 26613 to Ritesh Kumar (M) Transaction reference no N/A dated 2025-06-14 | BK67: INR Twenty Six Thousand, Six Hundred And Thirteen only. | BL67: No | BR67: INR Twenty Six Thousand, Six Hundred And Thirteen only. | BT67: Ritesh Kumar (M)
A68: PAY/M/25-26/0588 | B68: PAY/M/25-26/0588-1 | C68: PAY/G/23-24/.#### | D68: Pay | E68: 45754 | F68: G. C. Foods Pvt. Ltd. | G68: 921030030087773 - Axis Bank Ltd. CC Bihar - GCF | H68: INR | I68: Creditors - GCF | J68: INR | K68: 1400000 | L68: 1 | M68: 1400000 | N68: 1400000 | O68: 1 | P68: 1400000 | Q68: Approved | R68: Initiated | S68: NEFT/RTGS | T68: Supplier | U68: GC foods Pvt Ltd (T) | V68: G.C.foods Pvt Ltd (T) | W68: 0 | X68: 0 | Y68: AXIS BANK 921030030087773 - BIHAR | AC68: 654457 | AD68: Bank | AE68: -18246567 | AF68: Payable | AG68: 654457 | AH68: 1400000 | AI68: 1400000 | AJ68: 1400000 | AK68: 1400000 | AL68: 0 | AM68: 0 | AN68: 1400000 | AO68: 0 | AR68: 0 | AT68: 0 | AU68: 0 | AV68: GC Foods Muzaffarpur-Billing | AW68: 10AACCG2244H1Z9 | BB68: N/A | BC68: 45754 | BF68: Muzaffarpur | BH68: Cancelled | BI68: 0 | BJ68: Amount INR 1400000 to G.C.foods Pvt Ltd (T) Transaction reference no N/A dated 2025-04-07 | BK68: INR Fourteen Lakh only. | BL68: No | BO68: AXIS BANK | BP68: 921030030087773 | BR68: INR Fourteen Lakh only. | BT68: G.C.foods Pvt Ltd (T)
A69: PAY/M/25-26/0587 | B69: PAY/M/25-26/0587-1 | C69: PAY/G/23-24/.#### | D69: Pay | E69: 45754 | F69: G. C. Foods Pvt. Ltd. | G69: 9210300223943516 - Axis Bank Ltd. CC Tronica - GCF | H69: INR | I69: Creditors - GCF | J69: INR | K69: 1400000 | L69: 1 | M69: 1400000 | N69: 1400000 | O69: 1 | P69: 1400000 | Q69: Approved | R69: Initiated | S69: NEFT/RTGS | T69: Supplier | U69: GC foods Pvt Ltd (T) | V69: G.C.foods Pvt Ltd (T) | W69: 0 | X69: 0 | Y69: AXIS BANK 921030023943516 - GZB | AC69: -745543 | AD69: Bank | AE69: -50698506 | AF69: Payable | AG69: -745543 | AH69: 1400000 | AI69: 1400000 | AJ69: 1400000 | AK69: 1400000 | AL69: 0 | AM69: 0 | AN69: 1400000 | AO69: 0 | AR69: 0 | AT69: 0 | AU69: 0 | AV69: GC Foods Muzaffarpur-Billing | AW69: 10AACCG2244H1Z9 | BB69: N/A | BC69: 45754 | BF69: Muzaffarpur | BH69: Cancelled | BI69: 0 | BJ69: Amount INR 1400000 to G.C.foods Pvt Ltd (T) Transaction reference no N/A dated 2025-04-07 | BK69: INR Fourteen Lakh only. | BL69: No | BO69: AXIS BANK | BP69: 921030023943516 | BR69: INR Fourteen Lakh only. | BT69: G.C.foods Pvt Ltd (T)
A70: PAY/N/25-26/0379 | B70: PAY/N/25-26/0379-1 | C70: PAY/G/23-24/.#### | D70: Pay | E70: 45824 | F70: G. C. Foods Pvt. Ltd. | G70: 9210300223943516 - Axis Bank Ltd. CC Tronica - GCF | H70: INR | I70: Creditors - GCF | J70: INR | K70: 2000 | L70: 1 | M70: 2000 | N70: 2000 | O70: 1 | P70: 2000 | Q70: Approved | R70: Initiated | S70: NEFT/RTGS | T70: Employee | U70: Lal Babu - Staff Operator | V70: Lal Babu - Staff Operator | W70: 0 | X70: 0 | AC70: -742 | AD70: Bank | AE70: -54150385 | AF70: Payable | AG70: -742 | AH70: 2000 | AI70: 2000 | AJ70: 2000 | AK70: 2000 | AL70: 0 | AM70: 0 | AN70: 2000 | AO70: 0 | AR70: 0 | AT70: 0 | AU70: 0 | AV70: G.C. Foods Pvt. Ltd. Noida - Uttar Pradesh (Shipping) | AW70: 09AACCG2244H1ZS | BB70: N/A | BC70: 45824 | BF70: Noida | BH70: Cancelled | BI70: 0 | BJ70: Amount INR 2000 to Lal Babu - Staff Operator Transaction reference no N/A dated 2025-06-16 | BK70: INR Two Thousand only. | BL70: No | BR70: INR Two Thousand only. | BT70: Lal Babu - Staff Operator
A71: PAY/N/25-26/0378 | B71: PAY/N/25-26/0378-1 | C71: PAY/G/23-24/.#### | D71: Pay | E71: 45820 | F71: G. C. Foods Pvt. Ltd. | G71: 921030030087773 - Axis Bank Ltd. CC Bihar - GCF | H71: INR | I71: Creditors - GCF | J71: INR | K71: 20000 | L71: 1 | M71: 20000 | N71: 20000 | O71: 1 | P71: 20000 | Q71: Approved | R71: Initiated | S71: NEFT/RTGS | T71: Employee | U71: Siddhartha Guha Sir Noida -Staff | V71: Siddhartha Guha Sir Noida -Staff | W71: 0 | X71: 0 | AC71: 135000 | AD71: Bank | AE71: -18584465 | AF71: Payable | AG71: 135000 | AH71: 20000 | AI71: 20000 | AJ71: 20000 | AK71: 20000 | AL71: 0 | AM71: 0 | AN71: 20000 | AO71: 0 | AR71: 0 | AT71: 0 | AU71: 0 | AV71: G.C. Foods Pvt. Ltd. Noida - Uttar Pradesh (Shipping) | AW71: 09AACCG2244H1ZS | BB71: N/A | BC71: 45820 | BF71: Noida | BH71: Cancelled | BI71: 0 | BJ71: Amount INR 20000 to Siddhartha Guha Sir Noida -Staff Transaction reference no N/A dated 2025-06-12 | BK71: INR Twenty Thousand only. | BL71: No | BR71: INR Twenty Thousand only. | BT71: Siddhartha Guha Sir Noida -Staff
A72: PAY/N/25-26/0377 | B72: PAY/N/25-26/0377-1 | C72: PAY/G/23-24/.#### | D72: Receive | E72: 45820 | F72: G. C. Foods Pvt. Ltd. | G72: Creditors - GCF | H72: INR | I72: 921030030087786 - Axis Bank Ltd. CC Noida - GCF | J72: INR | K72: 24425 | L72: 1 | M72: 24425 | N72: 24425 | O72: 1 | P72: 24425 | Q72: Approved | R72: Initiated | S72: NEFT/RTGS | T72: Employee | U72: Pradeep Carpenter - Noida | V72: Pradeep Carpenter - Noida | W72: 0 | X72: 0 | AC72: -24425 | AD72: Payable | AE72: -24425 | AF72: Bank | AG72: -4949135.4 | AH72: 24425 | AI72: 24425 | AJ72: 24425 | AK72: 24425 | AL72: 0 | AM72: 0 | AN72: 24425 | AO72: 0 | AR72: 0 | AT72: 0 | AU72: 0 | AV72: G.C. Foods Pvt. Ltd. Noida - Uttar Pradesh (Shipping) | AW72: 09AACCG2244H1ZS | BB72: N/A | BC72: 45820 | BF72: Noida | BH72: Cancelled | BI72: 0 | BJ72: Amount INR 24425 received from Pradeep Carpenter - Noida Transaction reference no N/A dated 2025-06-12 | BK72: INR Twenty Four Thousand, Four Hundred And Twenty Five only. | BL72: No | BR72: INR Twenty Four Thousand, Four Hundred And Twenty Five only. | BT72: Pradeep Carpenter - Noida
A73: PAY/N/25-26/0376 | B73: PAY/N/25-26/0376-1 | C73: PAY/G/23-24/.#### | D73: Pay | E73: 45820 | F73: G. C. Foods Pvt. Ltd. | G73: 921030030087786 - Axis Bank Ltd. CC Noida - GCF | H73: INR | I73: Creditors - GCF | J73: INR | K73: 45540.95 | L73: 1 | M73: 45540.95 | N73: 45540.95 | O73: 1 | P73: 45540.95 | Q73: Approved | R73: Initiated | S73: NEFT/RTGS | T73: Supplier | U73: Dreamplug Technologies Pvt Ltd | V73: Dreamplug Technologies Pvt Ltd | W73: 0 | X73: 0 | Y73: AXIS BANK 921030030087786 - NOIDA | AC73: 707007.73 | AD73: Bank | AE73: -4903594.4 | AF73: Payable | AG73: 707007.73 | AH73: 45540.95 | AI73: 45540.95 | AJ73: 45540.95 | AK73: 45540.95 | AL73: 0 | AM73: 0 | AN73: 45540.95 | AO73: 0 | AR73: 0 | AT73: 0 | AU73: 0 | AV73: G.C. Foods Pvt. Ltd. Noida - Uttar Pradesh (Shipping) | AW73: 09AACCG2244H1ZS | BB73: N/A | BC73: 45820 | BF73: Noida | BH73: Cancelled | BI73: 0 | BJ73: Amount INR 45540.95 to Dreamplug Technologies Pvt Ltd Transaction reference no N/A dated 2025-06-12 | BK73: INR Forty Five Thousand, Five Hundred And Forty and Ninety Five Paisa only. | BL73: No | BO73: AXIS BANK | BP73: 921030030087786 | BR73: INR Forty Five Thousand, Five Hundred And Forty and Ninety Five Paisa only. | BT73: Dreamplug Technologies Pvt Ltd
A74: PAY/M/25-26/0576 | B74: PAY/M/25-26/0576-1 | C74: PAY/G/23-24/.#### | D74: Pay | E74: 45822 | F74: G. C. Foods Pvt. Ltd. | G74: 921030030087773 - Axis Bank Ltd. CC Bihar - GCF | H74: INR | I74: Creditors - GCF | J74: INR | K74: 800000 | L74: 1 | M74: 800000 | N74: 800000 | O74: 1 | P74: 800000 | Q74: Approved | R74: Initiated | S74: NEFT/RTGS | T74: Supplier | U74: GC foods Pvt Ltd Bihar | V74: G.C.foods Pvt Ltd Bihar | W74: 0 | X74: 0 | Y74: AXIS BANK 921030030087773 - BIHAR | AC74: 6955000 | AD74: Bank | AE74: -19175308 | AF74: Payable | AG74: 6955000 | AH74: 800000 | AI74: 800000 | AJ74: 800000 | AK74: 800000 | AL74: 0 | AM74: 0 | AN74: 800000 | AO74: 0 | AR74: 0 | AT74: 0 | AU74: 0 | AV74: GC Foods Muzaffarpur-Billing | AW74: 10AACCG2244H1Z9 | BB74: N/A | BC74: 45822 | BF74: Muzaffarpur | BH74: Cancelled | BI74: 0 | BJ74: Amount INR 800000 to G.C.foods Pvt Ltd Bihar Transaction reference no N/A dated 2025-06-14 | BK74: INR Eight Lakh only. | BL74: No | BO74: AXIS BANK | BP74: 921030030087773 | BR74: INR Eight Lakh only. | BT74: G.C.foods Pvt Ltd Bihar
A75: PAY/G/25-26/0951 | B75: PAY/G/25-26/0951-1 | C75: PAY/G/23-24/.#### | D75: Receive | E75: 45824 | F75: G. C. Foods Pvt. Ltd. | G75: Debtors - GCF | H75: INR | I75: 9210300223943516 - Axis Bank Ltd. CC Tronica - GCF | J75: INR | K75: 179163 | L75: 1 | M75: 179163 | N75: 179163 | O75: 1 | P75: 179163 | Q75: Approved | R75: Initiated | S75: NEFT/RTGS | T75: Customer | U75: Hariom Trading Company | V75: Hariom Trading Company | W75: 0 | X75: 0 | Y75: AXIS BANK 921030023943516 - GZB | AC75: 49113 | AD75: Receivable | AE75: 49113 | AF75: Bank | AG75: -54827635 | AH75: 179163 | AI75: 179163 | AJ75: 179163 | AK75: 179163 | AL75: 0 | AM75: 0 | AN75: 179163 | AO75: 0 | AR75: 0 | AT75: 0 | AU75: 0 | AV75: G.C. Foods Pvt. Ltd.Ghaziabad - Uttar Pradesh-Billing | AW75: 09AACCG2244H1ZS | AX75: 07-Delhi | AY75: Hariom Trading Company-Billing | AZ75: 07AWSPG1770B1ZN | BA75: Registered Regular | BB75: N/A | BC75: 45821 | BF75: Ghaziabad | BH75: Cancelled | BI75: 0 | BJ75: Amount INR 179163 received from Hariom Trading Company Transaction reference no N/A dated 2025-06-13 | BK75: INR One Lakh, Seventy Nine Thousand, One Hundred And Sixty Three only. | BL75: No | BO75: AXIS BANK | BP75: 921030023943516 | BR75: INR One Lakh, Seventy Nine Thousand, One Hundred And Sixty Three only. | BT75: Hariom Trading Company
A76: PAY/G/25-26/0941 | B76: PAY/G/25-26/0941-1 | C76: PAY/G/23-24/.#### | D76: Pay | E76: 45820 | F76: G. C. Foods Pvt. Ltd. | G76: 9210300223943516 - Axis Bank Ltd. CC Tronica - GCF | H76: INR | I76: Creditors - GCF | J76: INR | K76: 108000 | L76: 1 | M76: 108000 | N76: 108000 | O76: 1 | P76: 108000 | Q76: Approved | R76: Initiated | S76: NEFT/RTGS | T76: Supplier | U76: Digitalis Technologies | V76: Digitalis Technologies | W76: 0 | X76: 0 | Y76: AXIS BANK 921030023943516 - GZB | AC76: 0 | AD76: Bank | AE76: -54409066 | AF76: Payable | AG76: 46525765 | AH76: 108000 | AI76: 108000 | AJ76: 108000 | AK76: 108000 | AL76: 0 | AM76: 0 | AN76: 108000 | AO76: 0 | AR76: 0 | AT76: 0 | AU76: 0 | AV76: G.C. Foods Pvt. Ltd.Ghaziabad - Uttar Pradesh-Billing | AW76: 09AACCG2244H1ZS | BB76: N/A | BC76: 45820 | BF76: Ghaziabad | BH76: Cancelled | BI76: 0 | BJ76: Amount INR 108000 to Digitalis Technologies Transaction reference no N/A dated 2025-06-12 | BK76: INR One Lakh, Eight Thousand only. | BL76: No | BO76: AXIS BANK | BP76: 921030023943516 | BR76: INR One Lakh, Eight Thousand only. | BT76: Digitalis Technologies
A77: PAY/M/25-26/0564 | B77: PAY/M/25-26/0564-1 | C77: PAY/G/23-24/.#### | D77: Pay | E77: 45819 | F77: G. C. Foods Pvt. Ltd. | G77: 921030030087773 - Axis Bank Ltd. CC Bihar - GCF | H77: INR | I77: Creditors - GCF | J77: INR | K77: 2000000 | L77: 1 | M77: 2000000 | N77: 2000000 | O77: 1 | P77: 2000000 | Q77: Approved | R77: Initiated | S77: NEFT/RTGS | T77: Supplier | U77: GC foods Pvt Ltd Bihar | V77: G.C.foods Pvt Ltd Bihar | W77: 0 | X77: 0 | Y77: AXIS BANK 921030030087773 - BIHAR | AC77: 4955000 | AD77: Bank | AE77: -17191266 | AF77: Payable | AG77: 4955000 | AH77: 2000000 | AI77: 2000000 | AJ77: 2000000 | AK77: 2000000 | AL77: 0 | AM77: 0 | AN77: 2000000 | AO77: 0 | AR77: 0 | AT77: 0 | AU77: 0 | AV77: GC Foods Muzaffarpur-Billing | AW77: 10AACCG2244H1Z9 | AX77: 06-Haryana | AY77: Keshav Enterprises-Billing | AZ77: 06ASFPM1572Q1Z9 | BA77: Registered Regular | BB77: N/A | BC77: 45819 | BF77: Muzaffarpur | BH77: Cancelled | BI77: 0 | BJ77: Amount INR 2000000 to G.C.foods Pvt Ltd Bihar Transaction reference no N/A dated 2025-06-11 | BK77: INR Twenty Lakh only. | BL77: No | BO77: AXIS BANK | BP77: 921030030087773 | BR77: INR Twenty Lakh only. | BT77: G.C.foods Pvt Ltd Bihar
A78: PAY/G/25-26/0928 | B78: PAY/G/25-26/0928-1 | C78: PAY/G/23-24/.#### | D78: Receive | E78: 45819 | F78: G. C. Foods Pvt. Ltd. | G78: Debtors - GCF | H78: INR | I78: 9210300223943516 - Axis Bank Ltd. CC Tronica - GCF | J78: INR | K78: 35000 | L78: 1 | M78: 35000 | N78: 35000 | O78: 1 | P78: 35000 | Q78: Approved | R78: Initiated | S78: NEFT/RTGS | T78: Customer | U78: Pratima Enterprises | V78: Pratima Enterprises | W78: 0 | X78: 0 | Y78: AXIS BANK 921030023943516 - GZB | AC78: 1620 | AD78: Receivable | AE78: 1620 | AF78: Bank | AG78: -54968513 | AH78: 35000 | AI78: 35000 | AJ78: 35000 | AK78: 35000 | AL78: 0 | AM78: 0 | AN78: 35000 | AO78: 0 | AR78: 0 | AT78: 0 | AU78: 0 | AV78: G.C. Foods Pvt. Ltd.Ghaziabad - Uttar Pradesh-Billing | AW78: 09AACCG2244H1ZS | AX78: 07-Delhi | AY78: Pratima Enterprises-Billing | AZ78: 07AKKPJ5961D1Z3 | BA78: Registered Regular | BB78: N/A | BC78: 45819 | BF78: Ghaziabad | BH78: Cancelled | BI78: 0 | BJ78: Amount INR 35000 received from Pratima Enterprises Transaction reference no N/A dated 2025-06-11 | BK78: INR Thirty Five Thousand only. | BL78: No | BO78: AXIS BANK | BP78: 921030023943516 | BR78: INR Thirty Five Thousand only. | BT78: Pratima Enterprises
A79: PAY/M/25-26/0547 | B79: PAY/M/25-26/0547-1 | C79: PAY/G/23-24/.#### | D79: Internal Transfer | E79: 45815 | F79: G. C. Foods Pvt. Ltd. | G79: 921030030087773 - Axis Bank Ltd. CC Bihar - GCF | H79: INR | I79: 923020053917139 - Axis Bank - BIHAR - GCF | J79: INR | K79: 100000 | L79: 1 | M79: 100000 | N79: 100000 | O79: 1 | P79: 100000 | Q79: Approved | R79: Initiated | S79: NEFT/RTGS | W79: 0 | X79: 0 | AC79: 0 | AD79: Bank | AE79: -19933719 | AF79: Bank | AG79: 20251.8 | AH79: 100000 | AI79: 100000 | AJ79: 100000 | AK79: 100000 | AL79: 0 | AM79: 0 | AN79: 0 | AO79: 0 | AR79: 0 | AT79: 0 | AU79: 0 | AV79: GC Foods Muzaffarpur-Billing | AW79: 10AACCG2244H1Z9 | BB79: N/A | BC79: 45815 | BF79: Muzaffarpur | BH79: Cancelled | BI79: 0 | BJ79: Amount INR 100000 transferred from 921030030087773 - Axis Bank Ltd. CC Bihar - GCF to 923020053917139 - Axis Bank - BIHAR - GCF Transaction reference no N/A dated 2025-06-07 | BK79: INR One Lakh only. | BL79: No | BR79: INR One Lakh only. | BT79: 921030030087773 - Axis Bank Ltd. CC Bihar - GCF - 923020053917139 - Axis Bank - BIHAR - GCF
A80: PAY/N/25-26/0316 | B80: PAY/N/25-26/0316-1 | C80: PAY/G/23-24/.#### | D80: Receive | E80: 45761 | F80: G. C. Foods Pvt. Ltd. | G80: Debtors - GCF | H80: INR | I80: 923020017959018 - Axis Bank - NOIDA - GCF | J80: INR | K80: 3001.39 | L80: 1 | M80: 3001.39 | N80: 3001.39 | O80: 1 | P80: 3001.39 | Q80: Approved | R80: Initiated | S80: NEFT/RTGS | T80: Customer | U80: Amazon Courier | V80: Amazon Courier | W80: 0 | X80: 0 | Y80: AXIS BANK 923020017959018 -NOIDA | AC80: -768.77 | AD80: Receivable | AE80: -768.77 | AF80: Bank | AG80: 11690.12 | AH80: 3001.39 | AI80: 3001.39 | AJ80: 3001.39 | AK80: 3001.39 | AL80: 0 | AM80: 0 | AN80: 3001.39 | AO80: 0 | AR80: 0 | AT80: 0 | AU80: 0 | AV80: G.C. Foods Pvt. Ltd. Noida - Uttar Pradesh (Shipping) | AW80: 09AACCG2244H1ZS | AX80: 10-Bihar | AY80: Amazon Courier-Billing-28 | BA80: Unregistered | BB80: N/A | BC80: 45761 | BF80: Noida | BH80: Cancelled | BI80: 0 | BJ80: Amount INR 3001.39 received from Amazon Courier Transaction reference no N/A dated 2025-04-14 | BK80: INR Three Thousand And One and Thirty Nine Paisa only. | BL80: No | BO80: AXIS BANK | BP80: 923020017959018 | BR80: INR Three Thousand And One and Thirty Nine Paisa only. | BT80: Amazon Courier
A81: PAY/N/25-26/0310 | B81: PAY/N/25-26/0310-1 | C81: PAY/G/23-24/.#### | D81: Internal Transfer | E81: 45814 | F81: G. C. Foods Pvt. Ltd. | G81: 921030030087786 - Axis Bank Ltd. CC Noida - GCF | H81: INR | I81: Cash - GCF | J81: INR | K81: 20000 | L81: 1 | M81: 20000 | N81: 20000 | O81: 1 | P81: 20000 | Q81: Approved | R81: Initiated | S81: NEFT/RTGS | W81: 0 | X81: 0 | AC81: 0 | AD81: Bank | AE81: -4961752.7 | AF81: Cash | AG81: -1771580 | AH81: 20000 | AI81: 20000 | AJ81: 20000 | AK81: 20000 | AL81: 0 | AM81: 0 | AN81: 0 | AO81: 0 | AR81: 0 | AT81: 0 | AU81: 0 | AV81: G.C. Foods Pvt. Ltd. Noida - Uttar Pradesh (Shipping) | AW81: 09AACCG2244H1ZS | BB81: N/A | BC81: 45814 | BF81: Noida | BH81: Cancelled | BI81: 0 | BJ81: Amount INR 20000 transferred from 921030030087786 - Axis Bank Ltd. CC Noida - GCF to Cash - GCF Transaction reference no N/A dated 2025-06-06 | BK81: INR Twenty Thousand only. | BL81: No | BR81: INR Twenty Thousand only. | BT81: 921030030087786 - Axis Bank Ltd. CC Noida - GCF - Cash - GCF
A82: PAY/N/25-26/0290 | B82: PAY/N/25-26/0290-1 | C82: PAY/G/23-24/.#### | D82: Pay | E82: 45814 | F82: G. C. Foods Pvt. Ltd. | G82: 921030030087786 - Axis Bank Ltd. CC Noida - GCF | H82: INR | I82: Creditors - GCF | J82: INR | K82: 5000 | L82: 1 | M82: 5000 | N82: 5000 | O82: 1 | P82: 5000 | Q82: Approved | R82: Initiated | S82: NEFT/RTGS | T82: Supplier | U82: Suspense A/c | V82: Suspense A/c | W82: 0 | X82: 0 | Y82: AXIS BANK 921030030087786 - NOIDA | AC82: 27647 | AD82: Bank | AE82: -4900099.7 | AF82: Payable | AG82: 27647 | AH82: 5000 | AI82: 5000 | AJ82: 5000 | AK82: 5000 | AL82: 0 | AM82: 0 | AN82: 5000 | AO82: 0 | AR82: 0 | AT82: 0 | AU82: 0 | AV82: G.C. Foods Pvt. Ltd. Noida - Uttar Pradesh (Shipping) | AW82: 09AACCG2244H1ZS | BB82: N/A | BC82: 45814 | BF82: Noida | BH82: Cancelled | BI82: 0 | BJ82: Amount INR 5000 to Suspense A/c Transaction reference no N/A dated 2025-06-06 | BK82: INR Five Thousand only. | BL82: No | BO82: AXIS BANK | BP82: 921030030087786 | BR82: INR Five Thousand only. | BT82: Suspense A/c
A83: PAY/N/25-26/0092-2 | B83: PAY/N/25-26/0092-2-1 | C83: PAY/G/23-24/.#### | D83: Pay | E83: 45763 | F83: G. C. Foods Pvt. Ltd. | G83: 9210300223943516 - Axis Bank Ltd. CC Tronica - GCF | H83: INR | I83: Creditors - GCF | J83: INR | K83: 1667.34 | L83: 1 | M83: 1667.34 | N83: 1667.34 | O83: 1 | P83: 1667.34 | Q83: Approved | R83: Initiated | S83: NEFT/RTGS | T83: Supplier | U83: Vodafone Idea Ltd | V83: Vodafone Idea Ltd | W83: 0 | X83: 0 | Y83: AXIS BANK 921030030087786 - NOIDA | AC83: 0 | AD83: Bank | AE83: -53163642 | AF83: Payable | AG83: 1703754.9 | AH83: 1667.34 | AI83: 1667.34 | AJ83: 1667.34 | AK83: 1667.34 | AL83: 0 | AM83: 0 | AN83: 1667.34 | AO83: 0 | AR83: 0 | AT83: 0 | AU83: 0 | AV83: G.C. Foods Pvt. Ltd. Noida - Uttar Pradesh (Shipping) | AW83: 09AACCG2244H1ZS | BB83: N/A | BC83: 45763 | BF83: Noida | BH83: Cancelled | BI83: 0 | BJ83: Amount INR 1667.34 to Vodafone Idea Ltd Transaction reference no N/A dated 2025-04-16 | BK83: INR One Thousand, Six Hundred And Sixty Seven and Thirty Four Paisa only. | BL83: No | BM83: GCF Letterhead | BO83: AXIS BANK | BP83: 921030030087786 | BR83: INR One Thousand, Six Hundred And Sixty Seven and Thirty Four Paisa only. | BT83: Vodafone Idea Ltd
A84: PAY/N/25-26/0092-1 | B84: PAY/N/25-26/0092-2 | C84: PAY/G/23-24/.#### | D84: Pay | E84: 45763 | F84: G. C. Foods Pvt. Ltd. | G84: 921030030087786 - Axis Bank Ltd. CC Noida - GCF | H84: INR | I84: Creditors - GCF | J84: INR | K84: 1667.34 | L84: 1 | M84: 1667.34 | N84: 1667.34 | O84: 1 | P84: 1667.34 | Q84: Approved | R84: Initiated | T84: Supplier | U84: Vodafone Idea Ltd | V84: Vodafone Idea Ltd | W84: 0 | X84: 0 | Y84: AXIS BANK 921030030087786 - NOIDA | AC84: 0 | AD84: Bank | AE84: -4995752.7 | AF84: Payable | AG84: 1703754.9 | AH84: 1667.34 | AI84: 1667.34 | AJ84: 1667.34 | AK84: 1667.34 | AL84: 0 | AM84: 0 | AN84: 1667.34 | AO84: 0 | AR84: 0 | AT84: 0 | AU84: 0 | AV84: G.C. Foods Pvt. Ltd. Noida - Uttar Pradesh (Shipping) | AW84: 09AACCG2244H1ZS | BB84: N/A | BC84: 45763 | BF84: Noida | BH84: Cancelled | BI84: 0 | BJ84: Amount INR 1667.34 to Vodafone Idea Ltd Transaction reference no N/A dated 2025-04-16 | BK84: INR One Thousand, Six Hundred And Sixty Seven and Thirty Four Paisa only. | BL84: No | BM84: GCF Letterhead | BO84: AXIS BANK | BP84: 921030030087786 | BR84: INR One Thousand, Six Hundred And Sixty Seven and Thirty Four Paisa only. | BT84: Vodafone Idea Ltd
A85: PAY/N/25-26/0273 | B85: PAY/N/25-26/0273-1 | C85: PAY/G/23-24/.#### | D85: Receive | E85: 45803 | F85: G. C. Foods Pvt. Ltd. | G85: Debtors - GCF | H85: INR | I85: 921030030087786 - Axis Bank Ltd. CC Noida - GCF | J85: INR | K85: 71561 | L85: 1 | M85: 71561 | N85: 71561 | O85: 1 | P85: 71561 | Q85: Approved | R85: Initiated | S85: NEFT/RTGS | T85: Customer | U85: Singla Engravures Private Limited | V85: Singla Engravures Private Limited | W85: 0 | X85: 0 | Y85: AXIS BANK 921030030087786 - NOIDA | AC85: 0 | AD85: Receivable | AE85: -50002114 | AF85: Bank | AG85: -4974680 | AH85: 71561 | AI85: 71561 | AJ85: 71561 | AK85: 71561 | AL85: 0 | AM85: 0 | AN85: 71561 | AO85: 0 | AR85: 0 | AT85: 0 | AU85: 0 | AV85: G.C. Foods Pvt. Ltd. Noida - Uttar Pradesh (Shipping) | AW85: 09AACCG2244H1ZS | AX85: 09-Uttar Pradesh | AY85: Singla Engravures Private Limited-Billing-1 | AZ85: 09AAECS2511H1ZK | BA85: Registered Regular | BB85: N/A | BC85: 45803 | BF85: Noida | BH85: Cancelled | BI85: 0 | BJ85: Amount INR 71561 received from Singla Engravures Private Limited Transaction reference no N/A dated 2025-05-26 | BK85: INR Seventy One Thousand, Five Hundred And Sixty One only. | BL85: No | BO85: AXIS BANK | BP85: 921030030087786 | BR85: INR Seventy One Thousand, Five Hundred And Sixty One only. | BT85: Singla Engravures Private Limited
A86: PAY/N/25-26/0272 | B86: PAY/N/25-26/0272-1 | C86: PAY/G/23-24/.#### | D86: Pay | E86: 45802 | F86: G. C. Foods Pvt. Ltd. | G86: 921030030087786 - Axis Bank Ltd. CC Noida - GCF | H86: INR | I86: Creditors - GCF | J86: INR | K86: 16700 | L86: 1 | M86: 16700 | N86: 16700 | O86: 1 | P86: 16700 | Q86: Approved | R86: Initiated | S86: NEFT/RTGS | T86: Supplier | U86: Indraprastha Gas Ltd - Noida | V86: Indraprastha Gas Ltd - Noida | W86: 0 | X86: 0 | Y86: AXIS BANK 921030030087786 - NOIDA | AC86: 121726.81 | AD86: Bank | AE86: -4957980 | AF86: Payable | AG86: 121726.81 | AH86: 16700 | AI86: 16700 | AJ86: 16700 | AK86: 16700 | AL86: 0 | AM86: 0 | AN86: 16700 | AO86: 0 | AR86: 0 | AT86: 0 | AU86: 0 | AV86: G.C. Foods Pvt. Ltd. Noida - Uttar Pradesh (Shipping) | AW86: 09AACCG2244H1ZS | BB86: N/A | BC86: 45802 | BF86: Noida | BH86: Cancelled | BI86: 0 | BJ86: Amount INR 16700 to Indraprastha Gas Ltd - Noida Transaction reference no N/A dated 2025-05-25 | BK86: INR Sixteen Thousand, Seven Hundred only. | BL86: No | BO86: AXIS BANK | BP86: 921030030087786 | BR86: INR Sixteen Thousand, Seven Hundred only. | BT86: Indraprastha Gas Ltd - Noida
A87: PAY/N/25-26/0266 | B87: PAY/N/25-26/0266-1 | C87: PAY/G/23-24/.#### | D87: Pay | E87: 45801 | F87: G. C. Foods Pvt. Ltd. | G87: 921030030087786 - Axis Bank Ltd. CC Noida - GCF | H87: INR | I87: Creditors - GCF | J87: INR | K87: 2469.74 | L87: 1 | M87: 2469.74 | N87: 2469.74 | O87: 1 | P87: 2469.74 | Q87: Approved | R87: Initiated | S87: NEFT/RTGS | T87: Supplier | U87: Telephone - Airtel 9289328820 | V87: Telephone - Airtel 9289328820 | W87: 0 | X87: 0 | Y87: AXIS BANK 921030030087786 - NOIDA | AC87: 6612.73 | AD87: Bank | AE87: -4889316.7 | AF87: Payable | AG87: 6612.73 | AH87: 2469.74 | AI87: 2469.74 | AJ87: 2469.74 | AK87: 2469.74 | AL87: 0 | AM87: 0 | AN87: 2469.74 | AO87: 0 | AR87: 0 | AT87: 0 | AU87: 0 | AV87: G.C. Foods Pvt. Ltd. Noida - Uttar Pradesh (Shipping) | AW87: 09AACCG2244H1ZS | BB87: N/A | BC87: 45801 | BF87: Noida | BH87: Cancelled | BI87: 0 | BJ87: Amount INR 2469.74 to Telephone - Airtel 9289328820 Transaction reference no N/A dated 2025-05-24 | BK87: INR Two Thousand, Four Hundred And Sixty Nine and Seventy Four Paisa only. | BL87: No | BO87: AXIS BANK | BP87: 921030030087786 | BR87: INR Two Thousand, Four Hundred And Sixty Nine and Seventy Four Paisa only. | BT87: Telephone - Airtel 9289328820
A88: PAY/N/25-26/0249 | B88: PAY/N/25-26/0249-1 | C88: PAY/G/23-24/.#### | D88: Pay | E88: 45796 | F88: G. C. Foods Pvt. Ltd. | G88: 921030030087786 - Axis Bank Ltd. CC Noida - GCF | H88: INR | I88: Creditors - GCF | J88: INR | K88: 17464 | L88: 1 | M88: 17464 | N88: 17464 | O88: 1 | P88: 17464 | Q88: Approved | R88: Initiated | S88: NEFT/RTGS | T88: Supplier | U88: Vidyut Engineers | V88: Vidyut Engineers | W88: 0 | X88: 0 | Y88: AXIS BANK 921030030087786 - NOIDA | AC88: 0 | AD88: Bank | AE88: -4579941.7 | AF88: Payable | AG88: 29405898 | AH88: 17464 | AI88: 17464 | AJ88: 17464 | AK88: 17464 | AL88: 0 | AM88: 0 | AN88: 17464 | AO88: 0 | AR88: 0 | AT88: 0 | AU88: 0 | AV88: G.C. Foods Pvt. Ltd. Noida - Uttar Pradesh (Shipping) | AW88: 09AACCG2244H1ZS | BB88: N/A | BC88: 45796 | BF88: Noida | BH88: Cancelled | BI88: 0 | BJ88: Amount INR 17464 to Vidyut Engineers Transaction reference no N/A dated 2025-05-19 | BK88: INR Seventeen Thousand, Four Hundred And Sixty Four only. | BL88: No | BO88: AXIS BANK | BP88: 921030030087786 | BR88: INR Seventeen Thousand, Four Hundred And Sixty Four only. | BT88: Vidyut Engineers
A89: PAY/N/25-26/0247 | B89: PAY/N/25-26/0247-1 | C89: PAY/G/23-24/.#### | D89: Receive | E89: 45796 | F89: G. C. Foods Pvt. Ltd. | G89: Debtors - GCF | H89: INR | I89: 921030030087786 - Axis Bank Ltd. CC Noida - GCF | J89: INR | K89: 239962 | L89: 1 | M89: 239962 | N89: 239962 | O89: 1 | P89: 239962 | Q89: Approved | R89: Initiated | S89: NEFT/RTGS | T89: Customer | U89: Herbum Associates LLP | V89: Herbum Associates LLP | W89: 0 | X89: 0 | Y89: AXIS BANK 921030030087786 - NOIDA | AC89: 239962 | AD89: Receivable | AE89: 239962 | AF89: Bank | AG89: -4869903.7 | AH89: 239962 | AI89: 239962 | AJ89: 239962 | AK89: 239962 | AL89: 0 | AM89: 0 | AN89: 239962 | AO89: 0 | AR89: 0 | AT89: 0 | AU89: 0 | AV89: G.C. Foods Pvt. Ltd. Noida - Uttar Pradesh (Shipping) | AW89: 09AACCG2244H1ZS | AX89: 09-Uttar Pradesh | AY89: Herbum Associates LLP-Billing | AZ89: 09AAQFH8571H1ZP | BA89: Registered Regular | BB89: N/A | BC89: 45794 | BF89: Noida | BH89: Cancelled | BI89: 0 | BJ89: Amount INR 239962 received from Herbum Associates LLP Transaction reference no N/A dated 2025-05-17 | BK89: INR Two Lakh, Thirty Nine Thousand, Nine Hundred And Sixty Two only. | BL89: No | BO89: AXIS BANK | BP89: 921030030087786 | BR89: INR Two Lakh, Thirty Nine Thousand, Nine Hundred And Sixty Two only. | BT89: Herbum Associates LLP
A90: PAY/N/25-26/0128-1 | B90: PAY/N/25-26/0128-2 | C90: PAY/N/23-24/.#### | D90: Pay | E90: 45782 | F90: G. C. Foods Pvt. Ltd. | G90: 9210300223943516 - Axis Bank Ltd. CC Tronica - GCF | H90: INR | I90: Creditors - GCF | J90: INR | K90: 26600 | L90: 1 | M90: 26600 | N90: 26600 | O90: 1 | P90: 26600 | Q90: Approved | R90: Initiated | S90: NEFT/RTGS | T90: Supplier | U90: Shree Ji Protein | V90: Shree Ji Protein | W90: 0 | X90: 0 | Y90: AXIS BANK 921030030087786 - NOIDA | AC90: -26600 | AD90: Bank | AE90: -1.166303e+08 | AF90: Payable | AG90: -26600 | AH90: 26600 | AI90: 26600 | AJ90: 26600 | AK90: 26600 | AL90: 0 | AM90: 0 | AN90: 26600 | AO90: 0 | AR90: 0 | AT90: 0 | AU90: 0 | AV90: G.C. Foods Pvt. Ltd. Noida - Uttar Pradesh (Shipping) | AW90: 09AACCG2244H1ZS | BB90: N/A | BC90: 45782 | BF90: Noida | BH90: Cancelled | BI90: 0 | BJ90: Amount INR 26600 to Shree Ji Protein Transaction reference no N/A dated 2025-05-05 | BK90: INR Twenty Six Thousand, Six Hundred only. | BL90: No | BO90: AXIS BANK | BP90: 921030030087786 | BR90: INR Twenty Six Thousand, Six Hundred only. | BT90: Shree Ji Protein
A91: PAY/N/25-26/0236-1 | B91: PAY/N/25-26/0236-2 | C91: PAY/N/23-24/.#### | D91: Pay | E91: 45781 | F91: G. C. Foods Pvt. Ltd. | G91: 921030030087786 - Axis Bank Ltd. CC Noida - GCF | H91: INR | I91: Creditors - GCF | J91: INR | K91: 41102.26 | L91: 1 | M91: 41102.26 | N91: 41102.26 | O91: 1 | P91: 41102.26 | Q91: Approved | R91: Initiated | S91: NEFT/RTGS | T91: Supplier | U91: Vodafone Idea Ltd | V91: Vodafone Idea Ltd | W91: 0 | X91: 0 | Y91: AXIS BANK 921030030087786 - NOIDA | AC91: 0 | AD91: Bank | AE91: -4905339.5 | AF91: Payable | AG91: -79580485 | AH91: 41102.26 | AI91: 41102.26 | AJ91: 41102.26 | AK91: 41102.26 | AL91: 0 | AM91: 0 | AN91: 41102.26 | AO91: 0 | AR91: 0 | AT91: 0 | AU91: 0 | AV91: G.C. Foods Pvt. Ltd. Noida - Uttar Pradesh (Shipping) | AW91: 09AACCG2244H1ZS | BB91: NA | BC91: 45781 | BF91: Noida | BH91: Cancelled | BI91: 0 | BJ91: Amount INR 41102.26 to Vodafone Idea Ltd Transaction reference no NA dated 2025-05-04 | BK91: INR Forty One Thousand, One Hundred And Two and Twenty Six Paisa only. | BL91: No | BO91: AXIS BANK | BP91: 921030030087786 | BR91: INR Forty One Thousand, One Hundred And Two and Twenty Six Paisa only. | BT91: Vodafone Idea Ltd
A92: PAY/N/25-26/0235-1 | B92: PAY/N/25-26/0235-2 | C92: PAY/N/23-24/.#### | D92: Pay | E92: 45779 | F92: G. C. Foods Pvt. Ltd. | G92: 921030030087786 - Axis Bank Ltd. CC Noida - GCF | H92: INR | I92: Creditors - GCF | J92: INR | K92: 2587.74 | L92: 1 | M92: 2587.74 | N92: 2587.74 | O92: 1 | P92: 2587.74 | Q92: Approved | R92: Initiated | S92: NEFT/RTGS | T92: Supplier | U92: Telephone - Airtel 9289328820 | V92: Telephone - Airtel 9289328820 | W92: 0 | X92: 0 | Y92: AXIS BANK 921030030087786 - NOIDA | AC92: 1667.35 | AD92: Bank | AE92: -4905339.5 | AF92: Payable | AG92: 1667.35 | AH92: 2587.74 | AI92: 2587.74 | AJ92: 2587.74 | AK92: 2587.74 | AL92: 0 | AM92: 0 | AN92: 2587.74 | AO92: 0 | AR92: 0 | AT92: 0 | AU92: 0 | AV92: G.C. Foods Pvt. Ltd. Noida - Uttar Pradesh (Shipping) | AW92: 09AACCG2244H1ZS | BB92: NA | BC92: 45779 | BF92: Noida | BH92: Cancelled | BI92: 0 | BJ92: Amount INR 2587.74 to Telephone - Airtel 9289328820 Transaction reference no NA dated 2025-05-02 | BK92: INR Two Thousand, Five Hundred And Eighty Seven and Seventy Four Paisa only. | BL92: No | BO92: AXIS BANK | BP92: 921030030087786 | BR92: INR Two Thousand, Five Hundred And Eighty Seven and Seventy Four Paisa only. | BT92: Telephone - Airtel 9289328820
A93: PAY/N/25-26/0241 | B93: PAY/N/25-26/0241-1 | C93: PAY/G/23-24/.#### | D93: Pay | E93: 45778 | F93: G. C. Foods Pvt. Ltd. | G93: 921030030087786 - Axis Bank Ltd. CC Noida - GCF | H93: INR | I93: Creditors - GCF | J93: INR | K93: 1178.82 | L93: 1 | M93: 1178.82 | N93: 1178.82 | O93: 1 | P93: 1178.82 | Q93: Approved | R93: Initiated | S93: NEFT/RTGS | T93: Supplier | U93: Telephone - Airtel 9289328820 | V93: Telephone - Airtel 9289328820 | W93: 0 | X93: 0 | Y93: AXIS BANK 921030030087786 - NOIDA | AC93: 4024.99 | AD93: Bank | AE93: -4907697.1 | AF93: Payable | AG93: 4024.99 | AH93: 1178.82 | AI93: 1178.82 | AJ93: 1178.82 | AK93: 1178.82 | AL93: 0 | AM93: 0 | AN93: 1178.82 | AO93: 0 | AR93: 0 | AT93: 0 | AU93: 0 | AV93: G.C. Foods Pvt. Ltd. Noida - Uttar Pradesh (Shipping) | AW93: 09AACCG2244H1ZS | BB93: N/A | BC93: 45778 | BF93: Noida | BH93: Cancelled | BI93: 0 | BJ93: Amount INR 1178.82 to Telephone - Airtel 9289328820 Transaction reference no N/A dated 2025-05-01 | BK93: INR One Thousand, One Hundred And Seventy Eight and Eighty Two Paisa only. | BL93: No | BO93: AXIS BANK | BP93: 921030030087786 | BR93: INR One Thousand, One Hundred And Seventy Eight and Eighty Two Paisa only. | BT93: Telephone - Airtel 9289328820
A94: PAY/M/25-26/0543 | B94: PAY/M/25-26/0543-1 | C94: PAY/G/23-24/.#### | D94: Pay | E94: 45815 | F94: G. C. Foods Pvt. Ltd. | G94: 9210300223943516 - Axis Bank Ltd. CC Tronica - GCF | H94: INR | I94: Creditors - GCF | J94: INR | K94: 4452 | L94: 1 | M94: 4452 | N94: 4452 | O94: 1 | P94: 4452 | Q94: Approved | R94: Initiated | S94: NEFT/RTGS | T94: Employee | U94: Sujeet Kumar (M) | V94: Sujeet Kumar (M) | W94: 0 | X94: 0 | AC94: 32894 | AD94: Bank | AE94: -52052312 | AF94: Payable | AG94: 32894 | AH94: 4452 | AI94: 4452 | AJ94: 4452 | AK94: 4452 | AL94: 0 | AM94: 0 | AN94: 4452 | AO94: 0 | AR94: 0 | AT94: 0 | AU94: 0 | AV94: GC Foods Muzaffarpur-Billing | AW94: 10AACCG2244H1Z9 | BB94: N/A | BC94: 45815 | BF94: Muzaffarpur | BH94: Cancelled | BI94: 0 | BJ94: Amount INR 4452 to Sujeet Kumar (M) Transaction reference no N/A dated 2025-06-07 | BK94: INR Four Thousand, Four Hundred And Fifty Two only. | BL94: No | BR94: INR Four Thousand, Four Hundred And Fifty Two only. | BT94: Sujeet Kumar (M)
A95: PAY/M/25-26/0530-1 | B95: PAY/M/25-26/0530-2 | C95: PAY/G/23-24/.#### | D95: Internal Transfer | E95: 45785 | F95: G. C. Foods Pvt. Ltd. | G95: 923020053917139 - Axis Bank - BIHAR - GCF | H95: INR | I95: Cash - GCF | J95: INR | K95: 20000 | L95: 1 | M95: 20000 | N95: 20000 | O95: 1 | P95: 20000 | Q95: Approved | R95: Initiated | S95: NEFT/RTGS | W95: 0 | X95: 0 | AC95: 0 | AD95: Bank | AE95: 83047.8 | AF95: Cash | AG95: -1141580 | AH95: 20000 | AI95: 20000 | AJ95: 20000 | AK95: 20000 | AL95: 0 | AM95: 0 | AN95: 0 | AO95: 0 | AR95: 0 | AT95: 0 | AU95: 0 | AV95: GC Foods Muzaffarpur-Billing | AW95: 10AACCG2244H1Z9 | BB95: N/A | BC95: 45785 | BF95: Muzaffarpur | BH95: Cancelled | BI95: 0 | BJ95: Amount INR 20000 transferred from 923020053917139 - Axis Bank - BIHAR - GCF to Cash - GCF Transaction reference no N/A dated 2025-05-08 | BK95: INR Twenty Thousand only. | BL95: No | BR95: INR Twenty Thousand only. | BT95: 923020053917139 - Axis Bank - BIHAR - GCF - Cash - GCF
A96: PAY/M/25-26/0529-1 | B96: PAY/M/25-26/0529-2 | C96: PAY/G/23-24/.#### | D96: Internal Transfer | E96: 45785 | F96: G. C. Foods Pvt. Ltd. | G96: 923020053917139 - Axis Bank - BIHAR - GCF | H96: INR | I96: Cash - GCF | J96: INR | K96: 20000 | L96: 1 | M96: 20000 | N96: 20000 | O96: 1 | P96: 20000 | Q96: Approved | R96: Initiated | S96: NEFT/RTGS | W96: 0 | X96: 0 | AC96: 0 | AD96: Bank | AE96: 123047.8 | AF96: Cash | AG96: -1181580 | AH96: 20000 | AI96: 20000 | AJ96: 20000 | AK96: 20000 | AL96: 0 | AM96: 0 | AN96: 0 | AO96: 0 | AR96: 0 | AT96: 0 | AU96: 0 | AV96: GC Foods Muzaffarpur-Billing | AW96: 10AACCG2244H1Z9 | BB96: N/A | BC96: 45785 | BF96: Muzaffarpur | BH96: Cancelled | BI96: 0 | BJ96: Amount INR 20000 transferred from 923020053917139 - Axis Bank - BIHAR - GCF to Cash - GCF Transaction reference no N/A dated 2025-05-08 | BK96: INR Twenty Thousand only. | BL96: No | BR96: INR Twenty Thousand only. | BT96: 923020053917139 - Axis Bank - BIHAR - GCF - Cash - GCF
A97: PAY/M/25-26/0530 | B97: PAY/M/25-26/0530-1 | C97: PAY/G/23-24/.#### | D97: Internal Transfer | E97: 45785 | F97: G. C. Foods Pvt. Ltd. | G97: Cash - GCF | H97: INR | I97: 923020053917139 - Axis Bank - BIHAR - GCF | J97: INR | K97: 20000 | L97: 1 | M97: 20000 | N97: 20000 | O97: 1 | P97: 20000 | Q97: Approved | R97: Initiated | S97: NEFT/RTGS | W97: 0 | X97: 0 | AC97: 0 | AD97: Cash | AE97: -1181580 | AF97: Bank | AG97: 123047.8 | AH97: 20000 | AI97: 20000 | AJ97: 20000 | AK97: 20000 | AL97: 0 | AM97: 0 | AN97: 0 | AO97: 0 | AR97: 0 | AT97: 0 | AU97: 0 | AV97: GC Foods Muzaffarpur-Billing | AW97: 10AACCG2244H1Z9 | BB97: N/A | BC97: 45785 | BF97: Muzaffarpur | BH97: Cancelled | BI97: 0 | BJ97: Amount INR 20000 transferred from Cash - GCF to 923020053917139 - Axis Bank - BIHAR - GCF Transaction reference no N/A dated 2025-05-08 | BK97: INR Twenty Thousand only. | BL97: No | BR97: INR Twenty Thousand only. | BT97: Cash - GCF - 923020053917139 - Axis Bank - BIHAR - GCF
A98: PAY/M/25-26/0529 | B98: PAY/M/25-26/0529-1 | C98: PAY/G/23-24/.#### | D98: Internal Transfer | E98: 45785 | F98: G. C. Foods Pvt. Ltd. | G98: Cash - GCF | H98: INR | I98: 923020053917139 - Axis Bank - BIHAR - GCF | J98: INR | K98: 20000 | L98: 1 | M98: 20000 | N98: 20000 | O98: 1 | P98: 20000 | Q98: Approved | R98: Initiated | S98: NEFT/RTGS | W98: 0 | X98: 0 | AC98: 0 | AD98: Cash | AE98: -1161580 | AF98: Bank | AG98: 103047.8 | AH98: 20000 | AI98: 20000 | AJ98: 20000 | AK98: 20000 | AL98: 0 | AM98: 0 | AN98: 0 | AO98: 0 | AR98: 0 | AT98: 0 | AU98: 0 | AV98: GC Foods Muzaffarpur-Billing | AW98: 10AACCG2244H1Z9 | BB98: N/A | BC98: 45785 | BF98: Muzaffarpur | BH98: Cancelled | BI98: 0 | BJ98: Amount INR 20000 transferred from Cash - GCF to 923020053917139 - Axis Bank - BIHAR - GCF Transaction reference no N/A dated 2025-05-08 | BK98: INR Twenty Thousand only. | BL98: No | BR98: INR Twenty Thousand only. | BT98: Cash - GCF - 923020053917139 - Axis Bank - BIHAR - GCF
A99: PAY/M/25-26/0463 | B99: PAY/M/25-26/0463-1 | C99: PAY/G/23-24/.#### | D99: Pay | E99: 45805 | F99: G. C. Foods Pvt. Ltd. | G99: 923020053773708 - Axis Bank - Bihar - GCF | H99: INR | I99: Creditors - GCF | J99: INR | K99: 17333 | L99: 1 | M99: 17333 | N99: 17333 | O99: 1 | P99: 17333 | Q99: Approved | R99: Initiated | S99: NEFT/RTGS | T99: Employee | U99: Manish Kumar Mishra (M) | V99: Manish Kumar Mishra (M) | W99: 0 | X99: 0 | AC99: 19161 | AD99: Bank | AE99: 36228.99 | AF99: Payable | AG99: 19161 | AH99: 17333 | AI99: 17333 | AJ99: 17333 | AK99: 17333 | AL99: 0 | AM99: 0 | AN99: 17333 | AO99: 0 | AR99: 0 | AT99: 0 | AU99: 0 | AV99: GC Foods Muzaffarpur-Billing | AW99: 10AACCG2244H1Z9 | BB99: N/A | BC99: 45805 | BF99: Muzaffarpur | BH99: Cancelled | BI99: 0 | BJ99: Amount INR 17333 to Manish Kumar Mishra (M) Transaction reference no N/A dated 2025-05-28 | BK99: INR Seventeen Thousand, Three Hundred And Thirty Three only. | BL99: No | BR99: INR Seventeen Thousand, Three Hundred And Thirty Three only. | BT99: Manish Kumar Mishra (M)
A100: PAY/M/25-26/0437 | B100: PAY/M/25-26/0437-1 | C100: PAY/G/23-24/.#### | D100: Pay | E100: 45797 | F100: G. C. Foods Pvt. Ltd. | G100: 923020053773708 - Axis Bank - Bihar - GCF | H100: INR | I100: Creditors - GCF | J100: INR | K100: 48000 | L100: 1 | M100: 48000 | N100: 48000 | O100: 1 | P100: 48000 | Q100: Approved | R100: Initiated | S100: NEFT/RTGS | T100: Supplier | U100: Shashi Kant Bhalla | V100: Shashi Kant Bhalla | W100: 0 | X100: 0 | Y100: AXIS BANK 923020053773708 - BIHAR | AC100: 48000 | AD100: Bank | AE100: 44234.99 | AF100: Payable | AG100: 48000 | AH100: 48000 | AI100: 48000 | AJ100: 48000 | AK100: 48000 | AL100: 0 | AM100: 0 | AN100: 48000 | AO100: 0 | AR100: 0 | AT100: 0 | AU100: 0 | AV100: GC Foods Muzaffarpur-Billing | AW100: 10AACCG2244H1Z9 | BB100: N/A | BC100: 45797 | BF100: Muzaffarpur | BH100: Cancelled | BI100: 0 | BJ100: Amount INR 48000 to Shashi Kant Bhalla Transaction reference no N/A dated 2025-05-20 | BK100: INR Forty Eight Thousand only. | BL100: No | BO100: AXIS BANK | BP100: 923020053773708 | BR100: INR Forty Eight Thousand only. | BT100: Shashi Kant Bhalla
...

Sheet Old Status
A1: Sr | B1: ID | C1: Status | D1: docstatus | E1: Payment Type | F1: Posting Date | G1: Mode of Payment | H1: Party Type | I1: Party | J1: owner
A2: 1 | B2: PAY/G/25-26/1502-1 | C2: Submitted | D2: 1 | E2: Pay | F2: 45867 | G2: NEFT/RTGS | H2: Supplier | I2: Harish C. Khosla & Co. | J2: umagoswami77@gmail.com
A3: 2 | B3: PAY/G/25-26/1502 | C3: Cancelled | D3: 2 | E3: Pay | F3: 45867 | G3: NEFT/RTGS | H3: Supplier | I3: Harish C. Khosla & Co. | J3: umagoswami77@gmail.com
A4: 3 | B4: PAY/G/25-26/1507 | C4: Submitted | D4: 1 | E4: Pay | F4: 45867 | G4: NEFT/RTGS | H4: Employee | I4: Tanveeer Painter (T) | J4: umagoswami77@gmail.com
A5: 4 | B5: PAY/G/25-26/1506 | C5: Submitted | D5: 1 | E5: Pay | F5: 45867 | G5: NEFT/RTGS | H5: Supplier | I5: Blue Sky Cargo Movers | J5: umagoswami77@gmail.com
A6: 5 | B6: PAY/G/25-26/1505 | C6: Submitted | D6: 1 | E6: Pay | F6: 45867 | G6: NEFT/RTGS | H6: Supplier | I6: Ashu Communications | J6: umagoswami77@gmail.com
A7: 6 | B7: PAY/G/25-26/1504 | C7: Submitted | D7: 1 | E7: Pay | F7: 45867 | G7: NEFT/RTGS | H7: Supplier | I7: Victoria Foods Pvt. Ltd | J7: umagoswami77@gmail.com
A8: 7 | B8: PAY/G/25-26/1503 | C8: Submitted | D8: 1 | E8: Pay | F8: 45867 | G8: NEFT/RTGS | H8: Supplier | I8: Marudhara Polypack Industries | J8: umagoswami77@gmail.com
A9: 8 | B9: PAY/G/25-26/1501 | C9: Submitted | D9: 1 | E9: Pay | F9: 45867 | G9: NEFT/RTGS | H9: Supplier | I9: Genesis Pro Pac | J9: umagoswami77@gmail.com
A10: 9 | B10: PAY/G/25-26/1500 | C10: Submitted | D10: 1 | E10: Pay | F10: 45867 | G10: NEFT/RTGS | H10: Supplier | I10: Genesis Pro Pac | J10: umagoswami77@gmail.com
A11: 10 | B11: PAY/G/25-26/1499 | C11: Submitted | D11: 1 | E11: Pay | F11: 45867 | G11: NEFT/RTGS | H11: Supplier | I11: Genesis Pro Pac | J11: umagoswami77@gmail.com
A12: 11 | B12: PAY/G/25-26/1498 | C12: Submitted | D12: 1 | E12: Pay | F12: 45867 | G12: NEFT/RTGS | H12: Supplier | I12: Genesis Pro Pac | J12: umagoswami77@gmail.com
A13: 12 | B13: PAY/G/25-26/1497 | C13: Submitted | D13: 1 | E13: Pay | F13: 45867 | G13: NEFT/RTGS | H13: Supplier | I13: Gufa Overseas | J13: umagoswami77@gmail.com
... A46: 45 | B46: PAY/G/25-26/1478 | C46: Submitted | D46: 1 | E46: Receive | F46: 45866 | G46: NEFT/RTGS | H46: Customer | I46: krishan Dairy - Barola | J46: umagoswami77@gmail.com
A47: 46 | B47: PAY/G/25-26/1477 | C47: Submitted | D47: 1 | E47: Internal Transfer | F47: 45864 | G47: NEFT/RTGS | J47: umagoswami77@gmail.com
A48: 47 | B48: PAY/G/25-26/1476 | C48: Submitted | D48: 1 | E48: Receive | F48: 45864 | G48: NEFT/RTGS | H48: Customer | I48: Shree Shyam Traders | J48: umagoswami77@gmail.com
A49: 48 | B49: PAY/N/25-26/0577 | C49: Submitted | D49: 1 | E49: Pay | F49: 45863 | G49: NEFT/RTGS | H49: Supplier | I49: CASH ROJNAMCHA NOIDA | J49: umagoswami77@gmail.com
A50: 49 | B50: PAY/N/25-26/0576 | C50: Submitted | D50: 1 | E50: Pay | F50: 45863 | G50: NEFT/RTGS | H50: Employee | I50: Lal Babu - Staff Operator | J50: umagoswami77@gmail.com
A51: 50 | B51: PAY/N/25-26/0575 | C51: Submitted | D51: 1 | E51: Pay | F51: 45863 | G51: NEFT/RTGS | H51: Supplier | I51: Woxan Packaging Solutions Pvt Ltd | J51: umagoswami77@gmail.com
A52: 51 | B52: PAY/M/25-26/0928 | C52: Submitted | D52: 1 | E52: Pay | F52: 45863 | G52: NEFT/RTGS | H52: Supplier | I52: Steel Centre | J52: umagoswami77@gmail.com
A53: 52 | B53: PAY/M/25-26/0927 | C53: Submitted | D53: 1 | E53: Receive | F53: 45863 | G53: NEFT/RTGS | H53: Customer | I53: G.C.Wilmar Private Limited | J53: umagoswami77@gmail.com
A54: 53 | B54: PAY/M/25-26/0926 | C54: Submitted | D54: 1 | E54: Pay | F54: 45862 | G54: NEFT/RTGS | H54: Supplier | I54: Dev Shri Road Line | J54: umagoswami77@gmail.com
A55: 54 | B55: PAY/M/25-26/0925 | C55: Submitted | D55: 1 | E55: Pay | F55: 45862 | G55: NEFT/RTGS | H55: Supplier | I55: Mansaka Transport Company | J55: umagoswami77@gmail.com
A56: 55 | B56: PAY/M/25-26/0924 | C56: Submitted | D56: 1 | E56: Receive | F56: 45862 | G56: NEFT/RTGS | H56: Customer | I56: G.C.Wilmar Private Limited | J56: umagoswami77@gmail.com
A57: 56 | B57: PAY/M/25-26/0911 | C57: Cancelled | D57: 2 | E57: Receive | F57: 45861 | G57: NEFT/RTGS | H57: Customer | I57: G.C.Wilmar Private Limited | J57: juliemandal96@gmail.com
A58: 57 | B58: PAY/M/25-26/0913 | C58: Submitted | D58: 1 | E58: Pay | F58: 45861 | G58: NEFT/RTGS | H58: Supplier | I58: Prakash Pipes Limited | J58: juliemandal96@gmail.com
A59: 58 | B59: PAY/M/25-26/0912 | C59: Submitted | D59: 1 | E59: Pay | F59: 45861 | G59: NEFT/RTGS | H59: Supplier | I59: Shiv Vegpro Pvt Ltd | J59: juliemandal96@gmail.com
... A66: 65 | B66: PAY/G/25-26/1474 | C66: Submitted | D66: 1 | E66: Pay | F66: 45863 | G66: NEFT/RTGS | H66: Supplier | I66: Amit Enterprises | J66: umagoswami77@gmail.com
A67: 66 | B67: PAY/G/25-26/1473 | C67: Submitted | D67: 1 | E67: Internal Transfer | F67: 45863 | G67: NEFT/RTGS | J67: umagoswami77@gmail.com
A68: 67 | B68: PAY/G/25-26/1472 | C68: Submitted | D68: 1 | E68: Receive | F68: 45863 | G68: NEFT/RTGS | H68: Customer | I68: Narendra Traders | J68: umagoswami77@gmail.com
A69: 68 | B69: PAY/G/25-26/1471 | C69: Submitted | D69: 1 | E69: Receive | F69: 45863 | G69: NEFT/RTGS | H69: Customer | I69: Maheshwari Sales Agency | J69: umagoswami77@gmail.com
A70: 69 | B70: PAY/G/25-26/1470 | C70: Submitted | D70: 1 | E70: Receive | F70: 45863 | G70: NEFT/RTGS | H70: Customer | I70: A R Traders | J70: umagoswami77@gmail.com
A71: 70 | B71: PAY/G/25-26/1469 | C71: Submitted | D71: 1 | E71: Receive | F71: 45863 | G71: NEFT/RTGS | H71: Customer | I71: RRR Traders | J71: umagoswami77@gmail.com
A72: 71 | B72: PAY/G/25-26/1468 | C72: Submitted | D72: 1 | E72: Receive | F72: 45863 | G72: NEFT/RTGS | H72: Customer | I72: RRR Traders | J72: umagoswami77@gmail.com
A73: 72 | B73: PAY/G/25-26/1467 | C73: Submitted | D73: 1 | E73: Receive | F73: 45863 | G73: NEFT/RTGS | H73: Customer | I73: Saawariya Trading Company | J73: umagoswami77@gmail.com
A74: 73 | B74: PAY/G/25-26/1466 | C74: Submitted | D74: 1 | E74: Receive | F74: 45863 | G74: NEFT/RTGS | H74: Customer | I74: Abhishek Trading Co. | J74: umagoswami77@gmail.com
A75: 74 | B75: PAY/G/25-26/1465 | C75: Submitted | D75: 1 | E75: Receive | F75: 45863 | G75: NEFT/RTGS | H75: Customer | I75: Gita Agency | J75: umagoswami77@gmail.com
A76: 75 | B76: PAY/G/25-26/1464 | C76: Submitted | D76: 1 | E76: Receive | F76: 45863 | G76: NEFT/RTGS | H76: Customer | I76: Vardhman Cattle Feed | J76: umagoswami77@gmail.com
A77: 76 | B77: PAY/N/25-26/0574 | C77: Submitted | D77: 1 | E77: Receive | F77: 45859 | G77: NEFT/RTGS | H77: Customer | I77: Amazon Courier | J77: umagoswami77@gmail.com
A78: 77 | B78: PAY/N/25-26/0554-1 | C78: Submitted | D78: 1 | E78: Receive | F78: 45848 | G78: NEFT/RTGS | H78: Customer | I78: E-powertech | J78: umagoswami77@gmail.com
A79: 78 | B79: PAY/N/25-26/0554 | C79: Cancelled | D79: 2 | E79: Receive | F79: 45849 | G79: NEFT/RTGS | H79: Customer | I79: E-powertech | J79: umagoswami77@gmail.com
... A129: 128 | B129: PAY/M/25-26/0907 | C129: Submitted | D129: 1 | E129: Pay | F129: 45861 | G129: NEFT/RTGS | H129: Supplier | I129: GC foods Pvt Ltd (T) | J129: umagoswami77@gmail.com
A130: 129 | B130: PAY/M/25-26/0906 | C130: Submitted | D130: 1 | E130: Internal Transfer | F130: 45861 | G130: NEFT/RTGS | J130: umagoswami77@gmail.com
A131: 130 | B131: PAY/M/25-26/0905 | C131: Submitted | D131: 1 | E131: Pay | F131: 45861 | G131: NEFT/RTGS | H131: Supplier | I131: E Powertech | J131: umagoswami77@gmail.com
A132: 131 | B132: PAY/M/25-26/0904 | C132: Submitted | D132: 1 | E132: Receive | F132: 45861 | G132: NEFT/RTGS | H132: Customer | I132: Ansh Trading Madhubani | J132: umagoswami77@gmail.com
A133: 132 | B133: PAY/M/25-26/0903 | C133: Submitted | D133: 1 | E133: Receive | F133: 45861 | G133: NEFT/RTGS | H133: Customer | I133: Ajay Enterprises,Ahiyapur | J133: umagoswami77@gmail.com
A134: 133 | B134: PAY/M/25-26/0902 | C134: Submitted | D134: 1 | E134: Receive | F134: 45861 | G134: NEFT/RTGS | H134: Customer | I134: Aruna Traders | J134: umagoswami77@gmail.com
A135: 134 | B135: PAY/M/25-26/0901 | C135: Submitted | D135: 1 | E135: Internal Transfer | F135: 45860 | G135: NEFT/RTGS | J135: umagoswami77@gmail.com
A136: 135 | B136: PAY/M/25-26/0900 | C136: Submitted | D136: 1 | E136: Receive | F136: 45860 | G136: NEFT/RTGS | H136: Customer | I136: Sanjay Kumar/Satish Kumar,Jhanjharpur | J136: umagoswami77@gmail.com
A137: 136 | B137: PAY/M/25-26/0899 | C137: Submitted | D137: 1 | E137: Receive | F137: 45860 | G137: NEFT/RTGS | H137: Customer | I137: M/s Nav Durga Enterprises,Gola | J137: umagoswami77@gmail.com
A138: 137 | B138: PAY/G/25-26/1445 | C138: Submitted | D138: 1 | E138: Pay | F138: 45861 | G138: NEFT/RTGS | H138: Supplier | I138: Khanuja Traders | J138: umagoswami77@gmail.com
A139: 138 | B139: PAY/G/25-26/1444 | C139: Submitted | D139: 1 | E139: Pay | F139: 45861 | G139: NEFT/RTGS | H139: Supplier | I139: Mahaadev Traders | J139: umagoswami77@gmail.com
A140: 139 | B140: PAY/G/25-26/1443 | C140: Submitted | D140: 1 | E140: Receive | F140: 45861 | G140: NEFT/RTGS | H140: Customer | I140: G.C. Foods Pvt Ltd - Bihar | J140: umagoswami77@gmail.com
A141: 140 | B141: PAY/G/25-26/1442 | C141: Submitted | D141: 1 | E141: Receive | F141: 45861 | G141: NEFT/RTGS | H141: Customer | I141: J.K. Traders | J141: umagoswami77@gmail.com
A142: 141 | B142: PAY/G/25-26/1441 | C142: Submitted | D142: 1 | E142: Receive | F142: 45861 | G142: NEFT/RTGS | H142: Customer | I142: J.K. Traders | J142: umagoswami77@gmail.com
A143: 142 | B143: PAY/G/25-26/1440 | C143: Submitted | D143: 1 | E143: Receive | F143: 45861 | G143: NEFT/RTGS | H143: Customer | I143: Makhija Traders | J143: umagoswami77@gmail.com
A144: 143 | B144: PAY/G/25-26/1439 | C144: Submitted | D144: 1 | E144: Receive | F144: 45861 | G144: NEFT/RTGS | H144: Customer | I144: Anil Store | J144: umagoswami77@gmail.com
A145: 144 | B145: PAY/G/25-26/1438 | C145: Submitted | D145: 1 | E145: Receive | F145: 45861 | G145: NEFT/RTGS | H145: Customer | I145: Madhu Traders | J145: umagoswami77@gmail.com
A146: 145 | B146: PAY/G/25-26/1437 | C146: Submitted | D146: 1 | E146: Receive | F146: 45861 | G146: NEFT/RTGS | H146: Customer | I146: Krishna Stores | J146: umagoswami77@gmail.com
A147: 146 | B147: PAY/G/25-26/1436 | C147: Submitted | D147: 1 | E147: Receive | F147: 45861 | G147: NEFT/RTGS | H147: Customer | I147: Krishna Stores | J147: umagoswami77@gmail.com
... A149: 148 | B149: PAY/G/25-26/1435 | C149: Submitted | D149: 1 | E149: Receive | F149: 45860 | G149: NEFT/RTGS | H149: Customer | I149: Om Traders | J149: pragyagupta129@gmail.com
A150: 149 | B150: PAY/G/25-26/1434 | C150: Submitted | D150: 1 | E150: Internal Transfer | F150: 45860 | G150: NEFT/RTGS | J150: pragyagupta129@gmail.com
A151: 150 | B151: PAY/G/25-26/1433 | C151: Submitted | D151: 1 | E151: Internal Transfer | F151: 45860 | G151: NEFT/RTGS | J151: umagoswami77@gmail.com
A152: 151 | B152: PAY/G/25-26/1432 | C152: Submitted | D152: 1 | E152: Pay | F152: 45860 | G152: NEFT/RTGS | H152: Employee | I152: Virendra Singh (T) | J152: pragyagupta129@gmail.com
A153: 152 | B153: PAY/G/25-26/1431 | C153: Submitted | D153: 1 | E153: Pay | F153: 45860 | G153: NEFT/RTGS | H153: Employee | I153: Vinod Kumar (T) | J153: pragyagupta129@gmail.com
A154: 153 | B154: PAY/G/25-26/1430 | C154: Submitted | D154: 1 | E154: Pay | F154: 45860 | G154: NEFT/RTGS | H154: Employee | I154: Laxman Thakur (T) | J154: pragyagupta129@gmail.com
A155: 154 | B155: PAY/G/25-26/1429 | C155: Submitted | D155: 1 | E155: Pay | F155: 45860 | G155: NEFT/RTGS | H155: Employee | I155: Saroj Kumar (T) | J155: pragyagupta129@gmail.com
A156: 155 | B156: PAY/G/25-26/1428 | C156: Submitted | D156: 1 | E156: Pay | F156: 45860 | G156: NEFT/RTGS | H156: Employee | I156: Rahul Kumar Singh (T) | J156: pragyagupta129@gmail.com
A157: 156 | B157: PAY/G/25-26/1427 | C157: Submitted | D157: 1 | E157: Pay | F157: 45860 | G157: NEFT/RTGS | H157: Employee | I157: Ramashray Singh (T) | J157: pragyagupta129@gmail.com
A158: 157 | B158: PAY/G/25-26/1426 | C158: Submitted | D158: 1 | E158: Pay | F158: 45860 | G158: NEFT/RTGS | H158: Employee | I158: Moseen (T) | J158: pragyagupta129@gmail.com
A159: 158 | B159: PAY/G/25-26/1425 | C159: Submitted | D159: 1 | E159: Pay | F159: 45860 | G159: NEFT/RTGS | H159: Employee | I159: Putti Lal (T) | J159: pragyagupta129@gmail.com
A160: 159 | B160: PAY/G/25-26/1424 | C160: Submitted | D160: 1 | E160: Pay | F160: 45860 | G160: NEFT/RTGS | H160: Employee | I160: Ravi Kumar (T) | J160: pragyagupta129@gmail.com
A161: 160 | B161: PAY/G/25-26/1423 | C161: Submitted | D161: 1 | E161: Pay | F161: 45860 | G161: NEFT/RTGS | H161: Employee | I161: Manjay Yadav (T) | J161: pragyagupta129@gmail.com
A162: 161 | B162: PAY/G/25-26/1422 | C162: Submitted | D162: 1 | E162: Pay | F162: 45860 | G162: NEFT/RTGS | H162: Employee | I162: Lala (T) | J162: pragyagupta129@gmail.com
A163: 162 | B163: PAY/G/25-26/1421 | C163: Submitted | D163: 1 | E163: Pay | F163: 45860 | G163: NEFT/RTGS | H163: Employee | I163: Ismail (T) | J163: pragyagupta129@gmail.com
... A210: 209 | B210: PAY/M/25-26/0887 | C210: Submitted | D210: 1 | E210: Receive | F210: 45859 | G210: NEFT/RTGS | H210: Customer | I210: G.C.Wilmar Private Limited | J210: umagoswami77@gmail.com
A211: 210 | B211: PAY/M/25-26/0886 | C211: Submitted | D211: 1 | E211: Internal Transfer | F211: 45859 | G211: NEFT/RTGS | J211: umagoswami77@gmail.com
A212: 211 | B212: PAY/M/25-26/0885 | C212: Submitted | D212: 1 | E212: Receive | F212: 45859 | G212: NEFT/RTGS | H212: Customer | I212: Kailash Sah ,Benipatti | J212: umagoswami77@gmail.com
A213: 212 | B213: PAY/M/25-26/0884 | C213: Submitted | D213: 1 | E213: Receive | F213: 45859 | G213: NEFT/RTGS | H213: Customer | I213: Ashok Kumar Amit Kumar | J213: umagoswami77@gmail.com
A214: 213 | B214: PAY/G/25-26/1398 | C214: Submitted | D214: 1 | E214: Internal Transfer | F214: 45859 | G214: NEFT/RTGS | J214: umagoswami77@gmail.com
A215: 214 | B215: PAY/G/25-26/1397 | C215: Submitted | D215: 1 | E215: Receive | F215: 45859 | G215: NEFT/RTGS | H215: Customer | I215: Rinku Raj & Company | J215: umagoswami77@gmail.com
A216: 215 | B216: PAY/G/25-26/1396 | C216: Submitted | D216: 1 | E216: Receive | F216: 45859 | G216: NEFT/RTGS | H216: Customer | I216: Vaishnavi Agency | J216: umagoswami77@gmail.com
A217: 216 | B217: PAY/G/25-26/1395 | C217: Submitted | D217: 1 | E217: Receive | F217: 45859 | G217: NEFT/RTGS | H217: Customer | I217: Milapchand Hiralall & Sons | J217: umagoswami77@gmail.com
A218: 217 | B218: PAY/G/25-26/1394 | C218: Submitted | D218: 1 | E218: Receive | F218: 45859 | G218: NEFT/RTGS | H218: Customer | I218: Shri Bala Ji Distribution | J218: umagoswami77@gmail.com
A219: 218 | B219: PAY/G/25-26/1393 | C219: Submitted | D219: 1 | E219: Receive | F219: 45859 | G219: NEFT/RTGS | H219: Customer | I219: Dharampal Enterprises | J219: umagoswami77@gmail.com
A220: 219 | B220: PAY/G/25-26/1392 | C220: Submitted | D220: 1 | E220: Receive | F220: 45859 | G220: NEFT/RTGS | H220: Customer | I220: Dharampal Enterprises | J220: umagoswami77@gmail.com
A221: 220 | B221: PAY/G/25-26/1391-1 | C221: Submitted | D221: 1 | E221: Receive | F221: 45858 | G221: NEFT/RTGS | H221: Customer | I221: M/S Puja Enterprises | J221: umagoswami77@gmail.com
A222: 221 | B222: PAY/G/25-26/1391 | C222: Cancelled | D222: 2 | E222: Receive | F222: 45856 | G222: NEFT/RTGS | H222: Customer | I222: M/S Puja Enterprises | J222: umagoswami77@gmail.com
A223: 222 | B223: PAY/G/25-26/0049 | C223: Submitted | D223: 1 | E223: Receive | F223: 45753 | G223: NEFT/RTGS | H223: Customer | I223: Dharmendra & sons | J223: umagoswami77@gmail.com
A224: 223 | B224: PAY/N/25-26/0556 | C224: Submitted | D224: 1 | E224: Receive | F224: 45856 | G224: NEFT/RTGS | H224: Customer | I224: DTDC EXPRESS (Courier) | J224: umagoswami77@gmail.com
A225: 224 | B225: PAY/N/25-26/0555 | C225: Submitted | D225: 1 | E225: Receive | F225: 45852 | G225: NEFT/RTGS | H225: Customer | I225: Amazon Courier | J225: umagoswami77@gmail.com
A226: 225 | B226: PAY/N/25-26/0522-1 | C226: Submitted | D226: 1 | E226: Receive | F226: 45849 | G226: NEFT/RTGS | H226: Customer | I226: DTDC EXPRESS (Courier) | J226: umagoswami77@gmail.com
... A243: 242 | B243: PAY/G/25-26/1384 | C243: Submitted | D243: 1 | E243: Receive | F243: 45857 | G243: NEFT/RTGS | H243: Customer | I243: J.K. Traders | J243: umagoswami77@gmail.com
A244: 243 | B244: PAY/G/25-26/1383 | C244: Submitted | D244: 1 | E244: Internal Transfer | F244: 45857 | G244: NEFT/RTGS | J244: umagoswami77@gmail.com
A245: 244 | B245: PAY/G/25-26/1382 | C245: Submitted | D245: 1 | E245: Receive | F245: 45857 | G245: NEFT/RTGS | H245: Customer | I245: Laxmi Enterprises | J245: umagoswami77@gmail.com
A246: 245 | B246: PAY/G/25-26/1381 | C246: Submitted | D246: 1 | E246: Receive | F246: 45857 | G246: NEFT/RTGS | H246: Customer | I246: S. P. Traders | J246: umagoswami77@gmail.com
A247: 246 | B247: PAY/G/25-26/1380 | C247: Submitted | D247: 1 | E247: Pay | F247: 45857 | G247: NEFT/RTGS | H247: Supplier | I247: Mahaadev Traders | J247: umagoswami77@gmail.com
A248: 247 | B248: PAY/G/25-26/1378 | C248: Submitted | D248: 1 | E248: Receive | F248: 45857 | G248: NEFT/RTGS | H248: Customer | I248: Brijesh Kumar & Sons | J248: umagoswami77@gmail.com
A249: 248 | B249: PAY/G/25-26/1377 | C249: Submitted | D249: 1 | E249: Receive | F249: 45857 | G249: NEFT/RTGS | H249: Customer | I249: Milapchand Hiralall & Sons | J249: umagoswami77@gmail.com
A250: 249 | B250: PAY/G/25-26/1376 | C250: Submitted | D250: 1 | E250: Receive | F250: 45857 | G250: NEFT/RTGS | H250: Customer | I250: GCM Food Products | J250: umagoswami77@gmail.com
...

Sheet Payment Entry Working
A1: Amended From | B1: ID | C1: Old Status | D1: Series | E1: Payment Type | F1: Posting Date | G1: Company | H1: Account Paid From | I1: Account Currency (From) | J1: Account Paid To | K1: Account Currency (To) | L1: Paid Amount | M1: Source Exchange Rate | N1: Paid Amount (Company Currency) | O1: Received Amount | P1: Target Exchange Rate | Q1: Received Amount (Company Currency) | R1: Workflow State | S1: Payment Order Status | T1: Mode of Payment | U1: Party Type | V1: Party | W1: Party Name | X1: Book Advance Payments in Separate Party Account | Y1: Reconcile on Advance Payment Date | Z1: Company Bank Account | AA1: Party Bank Account | AB1: Contact | AC1: Email | AD1: Party Balance | AE1: Paid From Account Type | AF1: Account Balance (From) | AG1: Paid To Account Type | AH1: Account Balance (To) | AI1: Paid Amount After Tax | AJ1: Paid Amount After Tax (Company Currency) | AK1: Received Amount After Tax | AL1: Received Amount After Tax (Company Currency) | AM1: Total Allocated Amount | AN1: Total Allocated Amount (Company Currency) | AO1: Unallocated Amount | AP1: Difference Amount (Company Currency) | AQ1: Purchase Taxes and Charges Template | AR1: Sales Taxes and Charges Template | AS1: Apply Tax Withholding Amount | AT1: Tax Withholding Category | AU1: Total Taxes and Charges (Company Currency) | AV1: Total Taxes and Charges | AW1: Company Address | AX1: Company GSTIN | AY1: Place of Supply | AZ1: Customer Address | BA1: Customer GSTIN | BB1: GST Category | BC1: Cheque/Reference No | BD1: Cheque/Reference Date | BE1: Clearance Date | BF1: Project | BG1: Branch | BH1: Cost Center | BI1: Status | BJ1: Custom Remarks | BK1: Remarks | BL1: In Words (Company Currency) | BM1: Is Opening | BN1: Letter Head | BO1: Print Heading | BP1: Bank | BQ1: Bank Account No | BR1: Payment Order | BS1: In Words | BT1: Auto Repeat | BU1: Title | BV1: ID (Payment References) | BW1: Account (Payment References) | BX1: Account Type (Payment References) | BY1: Allocated (Payment References) | BZ1: Due Date (Payment References) | CA1: Exchange Gain/Loss (Payment References) | CB1: Exchange Rate (Payment References) | CC1: Grand Total (Payment References) | CD1: Name (Payment References) | CE1: Outstanding (Payment References) | CF1: Payment Request (Payment References) | CG1: Payment Term (Payment References) | CH1: Payment Term Outstanding (Payment References) | CI1: Payment Type (Payment References) | CJ1: Reconcile Effect On (Payment References) | CK1: Supplier Invoice No (Payment References) | CL1: Type (Payment References) | CM1: ID (Advance Taxes and Charges) | CN1: Account Currency (Advance Taxes and Charges) | CO1: Account Head (Advance Taxes and Charges) | CP1: Add Or Deduct (Advance Taxes and Charges) | CQ1: Allocated Amount (Advance Taxes and Charges) | CR1: Amount (Advance Taxes and Charges) | CS1: Amount (Company Currency) (Advance Taxes and Charges) | CT1: Considered In Paid Amount (Advance Taxes and Charges) | CU1: Cost Center (Advance Taxes and Charges) | CV1: Description (Advance Taxes and Charges) | CW1: GST Tax Type (Advance Taxes and Charges) | CX1: Reference Row # (Advance Taxes and Charges) | CY1: Tax Rate (Advance Taxes and Charges) | CZ1: Total (Advance Taxes and Charges) | DA1: Total (Company Currency) (Advance Taxes and Charges) | DB1: Type (Advance Taxes and Charges) | DC1: ID (Payment Deductions or Loss) | DD1: Account (Payment Deductions or Loss) | DE1: Amount (Company Currency) (Payment Deductions or Loss) | DF1: Branch (Payment Deductions or Loss) | DG1: Cost Center (Payment Deductions or Loss) | DH1: Description (Payment Deductions or Loss) | DI1: Is Exchange Gain / Loss? (Payment Deductions or Loss)
A2: PAY/G/25-26/1538 | B2: PAY/G/25-26/1538-1 | C2: =VLOOKUP(A2,'Old Status'!B:C,2,0) -> #N/A | D2: PAY/G/23-24/.#### | E2: Pay | F2: 45869 | G2: G. C. Foods Pvt. Ltd. | H2: 9210300223943516 - Axis Bank Ltd. CC Tronica - GCF | I2: INR | J2: Creditors - GCF | K2: INR | L2: 87439 | M2: 1 | N2: 87439 | O2: 87439 | P2: 1 | Q2: 87439 | R2: Approved | S2: Initiated | T2: NEFT/RTGS | U2: Supplier | V2: Axis Bank (Term Loan 921060054746668) | W2: Axis Bank (Term Loan 921060054746668) | X2: 0 | Y2: 0 | Z2: AXIS BANK 921030023943516 - GZB | AD2: 2135865 | AE2: Bank | AF2: 11209075 | AG2: Payable | AH2: 2135865 | AI2: 87439 | AJ2: 87439 | AK2: 87439 | AL2: 87439 | AM2: 0 | AN2: 0 | AO2: 87439 | AP2: 0 | AS2: 0 | AU2: 0 | AV2: 0 | AW2: G.C. Foods Pvt. Ltd.Ghaziabad - Uttar Pradesh-Billing | AX2: 09AACCG2244H1ZS | BC2: N/A | BD2: 45869 | BG2: Ghaziabad | BI2: Cancelled | BJ2: 0 | BK2: Amount INR 87439.0 to Axis Bank (Term Loan 921060054746668) Transaction reference no N/A dated 2025-07-31 | BL2: INR Eighty Seven Thousand, Four Hundred And Thirty Nine only. | BM2: No | BN2: GCF Letterhead | BP2: AXIS BANK | BQ2: 921030023943516 | BS2: INR Eighty Seven Thousand, Four Hundred And Thirty Nine only. | BU2: Axis Bank (Term Loan 921060054746668)
A3: PAY/G/25-26/1537 | B3: PAY/G/25-26/1537-1 | C3: =VLOOKUP(A3,'Old Status'!B:C,2,0) -> #N/A | D3: PAY/G/23-24/.#### | E3: Pay | F3: 45759 | G3: G. C. Foods Pvt. Ltd. | H3: 922020051221442 - Axis Bank - GZB - GCF | I3: INR | J3: Creditors - GCF | K3: INR | L3: 40000 | M3: 1 | N3: 40000 | O3: 40000 | P3: 1 | Q3: 40000 | R3: Approved | S3: Initiated | U3: Supplier | V3: Freight Outward Non TDS | W3: Freight Outward Non TDS | X3: 0 | Y3: 0 | Z3: AXIS BANK 922020051221442 - GZB | AD3: -43600 | AE3: Bank | AF3: 101269.38 | AG3: Payable | AH3: -43600 | AI3: 40000 | AJ3: 40000 | AK3: 40000 | AL3: 40000 | AM3: 0 | AN3: 0 | AO3: 40000 | AP3: 0 | AS3: 0 | AU3: 0 | AV3: 0 | AW3: G.C. Foods Pvt. Ltd.Ghaziabad - Uttar Pradesh-Billing | AX3: 09AACCG2244H1ZS | BC3: NA | BD3: 45749 | BG3: Ghaziabad | BI3: Cancelled | BJ3: 0 | BK3: Amount INR 40000 to Freight Outward Non TDS Transaction reference no NA dated 2025-04-02 | BL3: INR Forty Thousand only. | BM3: No | BN3: GCF Letterhead | BP3: AXIS BANK | BQ3: 922020051221442 | BS3: INR Forty Thousand only. | BU3: Freight Outward Non TDS
A4: PAY/M/25-26/0946 | B4: PAY/M/25-26/0946-1 | C4: =VLOOKUP(A4,'Old Status'!B:C,2,0) -> #N/A | D4: PAY/G/23-24/.#### | E4: Receive | F4: 45869 | G4: G. C. Foods Pvt. Ltd. | H4: Debtors - GCF | I4: INR | J4: 9210300223943516 - Axis Bank Ltd. CC Tronica - GCF | K4: INR | L4: 400000 | M4: 1 | N4: 400000 | O4: 400000 | P4: 1 | Q4: 400000 | R4: Approved | S4: Initiated | T4: NEFT/RTGS | U4: Customer | V4: G.C.foods Pvt Ltd (T) | W4: G.C.foods Pvt Ltd (T) | X4: 0 | Y4: 0 | Z4: AXIS BANK 921030023943516 - GZB | AD4: -33308502 | AE4: Receivable | AF4: -33308502 | AG4: Bank | AH4: -56190692 | AI4: 400000 | AJ4: 400000 | AK4: 400000 | AL4: 400000 | AM4: 0 | AN4: 0 | AO4: 400000 | AP4: 0 | AS4: 0 | AU4: 0 | AV4: 0 | AW4: GC Foods Muzaffarpur-Billing | AX4: 10AACCG2244H1Z9 | AY4: 09-Uttar Pradesh | AZ4: G.C.foods Pvt Ltd (T)-Billing | BA4: 09AACCG2244H1ZS | BB4: Registered Regular | BC4: N/A | BD4: 45869 | BG4: Muzaffarpur | BI4: Cancelled | BJ4: 0 | BK4: Amount INR 400000 received from G.C.foods Pvt Ltd (T) Transaction reference no N/A dated 2025-07-31 | BL4: INR Four Lakh only. | BM4: No | BN4: GCF Letterhead | BP4: AXIS BANK | BQ4: 921030023943516 | BS4: INR Four Lakh only. | BU4: G.C.foods Pvt Ltd (T)
A5: PAY/G/25-26/1502 | B5: PAY/G/25-26/1502-1 | C5: =VLOOKUP(A5,'Old Status'!B:C,2,0) -> Cancelled | D5: PAY/G/23-24/.#### | E5: Pay | F5: 45867 | G5: G. C. Foods Pvt. Ltd. | H5: 9210300223943516 - Axis Bank Ltd. CC Tronica - GCF | I5: INR | J5: Creditors - GCF | K5: INR | L5: 18195 | M5: 1 | N5: 18195 | O5: 18195 | P5: 1 | Q5: 18195 | R5: Approved | S5: Initiated | T5: NEFT/RTGS | U5: Supplier | V5: Harish C. Khosla & Co. | W5: Harish C Khosla & Co. | X5: 0 | Y5: 0 | Z5: AXIS BANK 921030023943516 - GZB | AD5: -0.4 | AE5: Bank | AF5: -52358625 | AG5: Payable | AH5: -0.4 | AI5: 18195 | AJ5: 18195 | AK5: 18195 | AL5: 18195 | AM5: 0 | AN5: 0 | AO5: 18195 | AP5: 0 | AS5: 0 | AU5: 0 | AV5: 0 | AW5: G.C. Foods Pvt. Ltd.Ghaziabad - Uttar Pradesh-Billing | AX5: 09AACCG2244H1ZS | BC5: N/A | BD5: 45867 | BG5: Ghaziabad | BI5: Cancelled | BJ5: 1 | BK5: Being PAyment Agst-HK/25-26/1106 | BL5: INR Eighteen Thousand, One Hundred And Ninety Five only. | BM5: No | BN5: GCF Letterhead | BP5: AXIS BANK | BQ5: 921030023943516 | BS5: INR Eighteen Thousand, One Hundred And Ninety Five only. | BU5: Harish C. Khosla & Co.
A6: PAY/G/25-26/1494 | B6: PAY/G/25-26/1494-1 | C6: =VLOOKUP(A6,'Old Status'!B:C,2,0) -> Cancelled | D6: PAY/G/23-24/.#### | E6: Receive | F6: 45868 | G6: G. C. Foods Pvt. Ltd. | H6: Debtors - GCF | I6: INR | J6: 9210300223943516 - Axis Bank Ltd. CC Tronica - GCF | K6: INR | L6: 200000 | M6: 1 | N6: 200000 | O6: 200000 | P6: 1 | Q6: 200000 | R6: Approved | S6: Initiated | T6: NEFT/RTGS | U6: Customer | V6: CASH | W6: CASH | X6: 0 | Y6: 0 | Z6: AXIS BANK 921030023943516 - GZB | AD6: 89638.06 | AE6: Receivable | AF6: 89638.06 | AG6: Bank | AH6: -49378142 | AI6: 200000 | AJ6: 200000 | AK6: 200000 | AL6: 200000 | AM6: 0 | AN6: 0 | AO6: 200000 | AP6: 0 | AS6: 0 | AU6: 0 | AV6: 0 | AW6: G.C. Foods Pvt. Ltd.Ghaziabad - Uttar Pradesh-Billing | AX6: 09AACCG2244H1ZS | AY6: 10-Bihar | BB6: Unregistered | BC6: N/A | BD6: 45867 | BG6: Ghaziabad | BI6: Cancelled | BJ6: 1 | BK6: Cash Deposit | BL6: INR Two Lakh only. | BM6: No | BN6: GCF Letterhead | BP6: AXIS BANK | BQ6: 921030023943516 | BS6: INR Two Lakh only. | BU6: CASH
A7: PAY/M/25-26/0940 | B7: PAY/M/25-26/0940-1 | C7: =VLOOKUP(A7,'Old Status'!B:C,2,0) -> Cancelled | D7: PAY/G/23-24/.#### | E7: Receive | F7: 45867 | G7: G. C. Foods Pvt. Ltd. | H7: Debtors - GCF | I7: INR | J7: 923020053773708 - Axis Bank - Bihar - GCF | K7: INR | L7: 32752 | M7: 1 | N7: 32752 | O7: 32752 | P7: 1 | Q7: 32752 | R7: Approved | S7: Initiated | T7: NEFT/RTGS | U7: Customer | V7: G.C.Wilmar Private Limited | W7: GC Wilmar Private Limited | X7: 0 | Y7: 0 | Z7: AXIS BANK 923020053773708 - BIHAR | AB7: G.C.Wilmar Private Limited-G.C.Wilmar Private Limited | AD7: -4460946.5 | AE7: Receivable | AF7: -4460946.5 | AG7: Bank | AH7: 615.1 | AI7: 32752 | AJ7: 32752 | AK7: 32752 | AL7: 32752 | AM7: 0 | AN7: 0 | AO7: 32752 | AP7: 0 | AS7: 0 | AU7: 0 | AV7: 0 | AW7: GC Foods Muzaffarpur-Billing | AX7: 10AACCG2244H1Z9 | AY7: 10-Bihar | AZ7: G.C.Wilmar Private Limited-Billing | BA7: 10AAICG5386J1ZH | BB7: Registered Regular | BC7: N/A | BD7: 45867 | BG7: Muzaffarpur | BI7: Cancelled | BJ7: 0 | BK7: Amount INR 32752 received from G.C.Wilmar Private Limited Transaction reference no N/A dated 2025-07-29 | BL7: INR Thirty Two Thousand, Seven Hundred And Fifty Two only. | BM7: No | BN7: GCF Letterhead | BP7: AXIS BANK | BQ7: 923020053773708 | BS7: INR Thirty Two Thousand, Seven Hundred And Fifty Two only. | BU7: G.C.Wilmar Private Limited
A8: PAY/M/25-26/0937 | B8: PAY/M/25-26/0937-1 | C8: =VLOOKUP(A8,'Old Status'!B:C,2,0) -> Cancelled | D8: PAY/G/23-24/.#### | E8: Receive | F8: 45866 | G8: G. C. Foods Pvt. Ltd. | H8: Debtors - GCF | I8: INR | J8: 921030030087773 - Axis Bank Ltd. CC Bihar - GCF | K8: INR | L8: 5000 | M8: 1 | N8: 5000 | O8: 5000 | P8: 1 | Q8: 5000 | R8: Approved | S8: Initiated | T8: NEFT/RTGS | U8: Customer | V8: Sujeet Kumar,Kanti | W8: Sujeet Kumar, Kanti | X8: 0 | Y8: 0 | Z8: AXIS BANK 921030030087773 - BIHAR | AD8: 59738 | AE8: Receivable | AF8: 59738 | AG8: Bank | AH8: -18267971 | AI8: 5000 | AJ8: 5000 | AK8: 5000 | AL8: 5000 | AM8: 0 | AN8: 0 | AO8: 5000 | AP8: 0 | AS8: 0 | AU8: 0 | AV8: 0 | AW8: GC Foods Muzaffarpur-Billing | AX8: 10AACCG2244H1Z9 | AY8: 10-Bihar | AZ8: Sujeet Kumar,Kanti-Billing | BB8: Unregistered | BC8: N/A | BD8: 45866 | BG8: Muzaffarpur | BI8: Cancelled | BJ8: 0 | BK8: Amount INR 5000 received from Sujeet Kumar,Kanti Transaction reference no N/A dated 2025-07-28 | BL8: INR Five Thousand only. | BM8: No | BN8: GCF Letterhead | BP8: AXIS BANK | BQ8: 921030030087773 | BS8: INR Five Thousand only. | BU8: Sujeet Kumar,Kanti
A9: PAY/M/25-26/0916 | B9: PAY/M/25-26/0916-1 | C9: =VLOOKUP(A9,'Old Status'!B:C,2,0) -> Cancelled | D9: PAY/G/23-24/.#### | E9: Pay | F9: 45860 | G9: G. C. Foods Pvt. Ltd. | H9: 921030030087773 - Axis Bank Ltd. CC Bihar - GCF | I9: INR | J9: Creditors - GCF | K9: INR | L9: 750000 | M9: 1 | N9: 750000 | O9: 750000 | P9: 1 | Q9: 750000 | R9: Approved | S9: Initiated | T9: NEFT/RTGS | U9: Employee | V9: Rajesh Kumar Chaudhry (M) | W9: Rajesh Kumar Chaudhry (M) | X9: 0 | Y9: 0 | AD9: 230000 | AE9: Bank | AF9: -18602992 | AG9: Payable | AH9: 230000 | AI9: 750000 | AJ9: 750000 | AK9: 750000 | AL9: 750000 | AM9: 0 | AN9: 0 | AO9: 750000 | AP9: 0 | AS9: 0 | AU9: 0 | AV9: 0 | AW9: GC Foods Muzaffarpur-Billing | AX9: 10AACCG2244H1Z9 | BC9: N/A | BD9: 45860 | BG9: Muzaffarpur | BI9: Cancelled | BJ9: 0 | BK9: Amount INR 750000 to Rajesh Kumar Chaudhry (M) Transaction reference no N/A dated 2025-07-22 | BL9: INR Seven Lakh, Fifty Thousand only. | BM9: No | BN9: GCF Letterhead | BS9: INR Seven Lakh, Fifty Thousand only. | BU9: Rajesh Kumar Chaudhry (M)
A10: PAY/G/25-26/1460 | B10: PAY/G/25-26/1460-1 | C10: =VLOOKUP(A10,'Old Status'!B:C,2,0) -> Cancelled | D10: PAY/G/23-24/.#### | E10: Receive | F10: 45862 | G10: G. C. Foods Pvt. Ltd. | H10: Debtors - GCF | I10: INR | J10: 9210300223943516 - Axis Bank Ltd. CC Tronica - GCF | K10: INR | L10: 32300 | M10: 1 | N10: 32300 | O10: 32300 | P10: 1 | Q10: 32300 | R10: Approved | S10: Initiated | T10: NEFT/RTGS | U10: Customer | V10: Chacha Tau Chap | W10: Chacha Tau Chap | X10: 0 | Y10: 0 | Z10: AXIS BANK 921030023943516 - GZB | AD10: -38902 | AE10: Receivable | AF10: -38902 | AG10: Bank | AH10: -52039112 | AI10: 32300 | AJ10: 32300 | AK10: 32300 | AL10: 32300 | AM10: 0 | AN10: 0 | AO10: 32300 | AP10: 0 | AS10: 0 | AU10: 0 | AV10: 0 | AW10: G.C. Foods Pvt. Ltd.Ghaziabad - Uttar Pradesh-Billing | AX10: 09AACCG2244H1ZS | AY10: 07-Delhi | AZ10: Chacha Tau Chap-Billing | BA10: 07DCJPA3280A1Z5 | BB10: Registered Regular | BC10: N/A | BD10: 45862 | BG10: Ghaziabad | BI10: Cancelled | BJ10: 1 | BK10: Pay In Advance | BL10: INR Thirty Two Thousand, Three Hundred only. | BM10: No | BN10: GCF Letterhead | BP10: AXIS BANK | BQ10: 921030023943516 | BS10: INR Thirty Two Thousand, Three Hundred only. | BU10: Chacha Tau Chap
A11: PAY/G/23-24/0882 | B11: PAY/G/23-24/0882-1 | C11: =VLOOKUP(A11,'Old Status'!B:C,2,0) -> Cancelled | D11: PAY/G/23-24/.#### | E11: Pay | F11: 45860 | G11: G. C. Foods Pvt. Ltd. | H11: 923020053773708 - Axis Bank - Bihar - GCF | I11: INR | J11: Creditors - GCF | K11: INR | L11: 750000 | M11: 1 | N11: 750000 | O11: 750000 | P11: 1 | Q11: 750000 | R11: Approved | S11: Initiated | T11: NEFT/RTGS | U11: Employee | V11: Rajesh Kumar Chaudhry (M) | W11: Rajesh Kumar Chaudhry (M) | X11: 0 | Y11: 0 | Z11: AXIS BANK 923020053773708 - BIHAR | AD11: 230000 | AE11: Bank | AF11: 570.1 | AG11: Payable | AH11: 230000 | AI11: 750000 | AJ11: 750000 | AK11: 750000 | AL11: 750000 | AM11: 0 | AN11: 0 | AO11: 750000 | AP11: 0 | AS11: 0 | AU11: 0 | AV11: 0 | AW11: GC Foods Muzaffarpur-Billing | AX11: 10AACCG2244H1Z9 | BC11: N/A | BD11: 45860 | BG11: Muzaffarpur | BI11: Cancelled | BJ11: 0 | BK11: Amount INR 750000 to Rajesh Kumar Chaudhry (M) Transaction reference no N/A dated 2025-07-22 | BL11: INR Seven Lakh, Fifty Thousand only. | BM11: No | BN11: GCF Letterhead | BP11: AXIS BANK | BQ11: 923020053773708 | BS11: INR Seven Lakh, Fifty Thousand only. | BU11: Rajesh Kumar Chaudhry (M)
A12: PAY/M/25-26/0911 | B12: PAY/M/25-26/0911-1 | C12: =VLOOKUP(A12,'Old Status'!B:C,2,0) -> Cancelled | D12: PAY/G/23-24/.#### | E12: Receive | F12: 45861 | G12: G. C. Foods Pvt. Ltd. | H12: Debtors - GCF | I12: INR | J12: 923020053773708 - Axis Bank - Bihar - GCF | K12: INR | L12: 1000000 | M12: 1 | N12: 1000000 | O12: 1000000 | P12: 1 | Q12: 1000000 | R12: Approved | S12: Initiated | T12: NEFT/RTGS | U12: Customer | V12: G.C.Wilmar Private Limited | W12: GC Wilmar Private Limited | X12: 0 | Y12: 0 | Z12: AXIS BANK 923020053773708 - BIHAR | AB12: G.C.Wilmar Private Limited-G.C.Wilmar Private Limited | AD12: -2863732.7 | AE12: Receivable | AF12: -2863732.7 | AG12: Bank | AH12: 570.1 | AI12: 1000000 | AJ12: 1000000 | AK12: 1000000 | AL12: 1000000 | AM12: 0 | AN12: 0 | AO12: 1000000 | AP12: 0 | AS12: 0 | AU12: 0 | AV12: 0 | AW12: GC Foods Muzaffarpur-Billing | AX12: 10AACCG2244H1Z9 | AY12: 10-Bihar | AZ12: G.C.Wilmar Private Limited-Billing | BA12: 10AHOPS6771R1ZF | BB12: Registered Regular | BC12: N/A | BD12: 45861 | BG12: Muzaffarpur | BI12: Cancelled | BJ12: 0 | BK12: Amount INR 1000000 received from G.C.Wilmar Private Limited Transaction reference no N/A dated 2025-07-23 | BL12: INR Ten Lakh only. | BM12: No | BN12: GCF Letterhead | BP12: AXIS BANK | BQ12: 923020053773708 | BS12: INR Ten Lakh only. | BU12: G.C.Wilmar Private Limited
A13: PAY/G/23-24/0881 | B13: PAY/G/23-24/0881-1 | C13: =VLOOKUP(A13,'Old Status'!B:C,2,0) -> Cancelled | D13: PAY/G/23-24/.#### | E13: Pay | F13: 45859 | G13: G. C. Foods Pvt. Ltd. | H13: 9210300223943516 - Axis Bank Ltd. CC Tronica - GCF | I13: INR | J13: Creditors - GCF | K13: INR | L13: 21000 | M13: 1 | N13: 21000 | O13: 21000 | P13: 1 | Q13: 21000 | R13: Approved | S13: Initiated | T13: NEFT/RTGS | U13: Supplier | V13: G.C.WILMAR Private Limited | W13: G.C.WILMAR Private Limited | X13: 0 | Y13: 0 | Z13: AXIS BANK 921030023943516 - GZB | AD13: -630600 | AE13: Bank | AF13: -51845742 | AG13: Payable | AH13: 68580934 | AI13: 21000 | AJ13: 21000 | AK13: 21000 | AL13: 21000 | AM13: 0 | AN13: 0 | AO13: 21000 | AP13: 0 | AS13: 0 | AU13: 0 | AV13: 0 | AW13: GC Foods Muzaffarpur-Billing | AX13: 10AACCG2244H1Z9 | BC13: N/A | BD13: 45859 | BG13: Muzaffarpur | BI13: Cancelled | BJ13: 0 | BK13: Amount INR 21000 to G.C.WILMAR Private Limited Transaction reference no N/A dated 2025-07-21 | BL13: INR Twenty One Thousand only. | BM13: No | BN13: GCF Letterhead | BP13: AXIS BANK | BQ13: 921030023943516 | BS13: INR Twenty One Thousand only. | BU13: G.C.WILMAR Private Limited
A14: PAY/N/25-26/0572 | B14: PAY/N/25-26/0572-1 | C14: =VLOOKUP(A14,'Old Status'!B:C,2,0) -> Cancelled | D14: PAY/G/23-24/.#### | E14: Pay | F14: 45861 | G14: G. C. Foods Pvt. Ltd. | H14: 921030030087786 - Axis Bank Ltd. CC Noida - GCF | I14: INR | J14: Creditors - GCF | K14: INR | L14: 20000 | M14: 1 | N14: 20000 | O14: 20000 | P14: 1 | Q14: 20000 | R14: Approved | S14: Initiated | T14: NEFT/RTGS | U14: Supplier | V14: Frontier Automobiles Private Limited | W14: Frontier Automobiles Private Limited | X14: 0 | Y14: 0 | Z14: AXIS BANK 921030030087786 - NOIDA | AD14: 444943 | AE14: Bank | AF14: -4854404.6 | AG14: Payable | AH14: 444943 | AI14: 20000 | AJ14: 20000 | AK14: 20000 | AL14: 20000 | AM14: 0 | AN14: 0 | AO14: 20000 | AP14: 0 | AS14: 0 | AU14: 0 | AV14: 0 | AW14: G.C. Foods Pvt. Ltd. Noida - Uttar Pradesh (Shipping) | AX14: 09AACCG2244H1ZS | BC14: N/A | BD14: 45861 | BG14: Noida | BI14: Cancelled | BJ14: 0 | BK14: Amount INR 20000 to Frontier Automobiles Private Limited Transaction reference no N/A dated 2025-07-23 | BL14: INR Twenty Thousand only. | BM14: No | BN14: GCF Letterhead | BP14: AXIS BANK | BQ14: 921030030087786 | BS14: INR Twenty Thousand only. | BU14: Frontier Automobiles Private Limited
A15: PAY/G/25-26/1391 | B15: PAY/G/25-26/1391-1 | C15: =VLOOKUP(A15,'Old Status'!B:C,2,0) -> Cancelled | D15: PAY/G/23-24/.#### | E15: Receive | F15: 45856 | G15: G. C. Foods Pvt. Ltd. | H15: Debtors - GCF | I15: INR | J15: 9210300223943516 - Axis Bank Ltd. CC Tronica - GCF | K15: INR | L15: 145000 | M15: 1 | N15: 145000 | O15: 145000 | P15: 1 | Q15: 145000 | R15: Approved | S15: Initiated | T15: NEFT/RTGS | U15: Customer | V15: M/S Puja Enterprises | W15: M/S Puja Enterprises | X15: 0 | Y15: 0 | Z15: AXIS BANK 921030023943516 - GZB | AD15: 41223 | AE15: Receivable | AF15: 41223 | AG15: Bank | AH15: -52328248 | AI15: 145000 | AJ15: 145000 | AK15: 145000 | AL15: 145000 | AM15: 0 | AN15: 0 | AO15: 145000 | AP15: 0 | AS15: 0 | AU15: 0 | AV15: 0 | AW15: G.C. Foods Pvt. Ltd.Ghaziabad - Uttar Pradesh-Billing | AX15: 09AACCG2244H1ZS | AY15: 07-Delhi | AZ15: M/S Puja Enterprises-Billing | BA15: 07BRPPJ6469M1ZV | BB15: Registered Regular | BC15: N/A | BD15: 45858 | BG15: Ghaziabad | BI15: Cancelled | BJ15: 0 | BK15: Amount INR 145000 received from M/S Puja Enterprises Transaction reference no N/A dated 2025-07-20 | BL15: INR One Lakh, Forty Five Thousand only. | BM15: No | BP15: AXIS BANK | BQ15: 921030023943516 | BS15: INR One Lakh, Forty Five Thousand only. | BU15: M/S Puja Enterprises
A16: PAY/G/25-26/1379 | B16: PAY/G/25-26/1379-1 | C16: =VLOOKUP(A16,'Old Status'!B:C,2,0) -> Cancelled | D16: PAY/G/23-24/.#### | E16: Receive | F16: 45857 | G16: G. C. Foods Pvt. Ltd. | H16: Debtors - GCF | I16: INR | J16: 9210300223943516 - Axis Bank Ltd. CC Tronica - GCF | K16: INR | L16: 10000 | M16: 1 | N16: 10000 | O16: 10000 | P16: 1 | Q16: 10000 | R16: Approved | S16: Initiated | T16: NEFT/RTGS | U16: Customer | V16: J.K. Traders | W16: J.K. Traders | X16: 0 | Y16: 0 | Z16: AXIS BANK 921030023943516 - GZB | AD16: -34641 | AE16: Receivable | AF16: -34641 | AG16: Bank | AH16: -51738887 | AI16: 10000 | AJ16: 10000 | AK16: 10000 | AL16: 10000 | AM16: 0 | AN16: 0 | AO16: 10000 | AP16: 0 | AS16: 0 | AU16: 0 | AV16: 0 | AW16: G.C. Foods Pvt. Ltd.Ghaziabad - Uttar Pradesh-Billing | AX16: 09AACCG2244H1ZS | AY16: 07-Delhi | AZ16: J.K. Traders-Billing | BB16: Unregistered | BC16: N/A | BD16: 45857 | BG16: Ghaziabad | BI16: Cancelled | BJ16: 0 | BK16: Amount INR 10000 received from J.K. Traders Transaction reference no N/A dated 2025-07-19 | BL16: INR Ten Thousand only. | BM16: No | BP16: AXIS BANK | BQ16: 921030023943516 | BS16: INR Ten Thousand only. | BU16: J.K. Traders
A17: PAY/N/25-26/0554 | B17: PAY/N/25-26/0554-1 | C17: =VLOOKUP(A17,'Old Status'!B:C,2,0) -> Cancelled | D17: PAY/G/23-24/.#### | E17: Receive | F17: 45849 | G17: G. C. Foods Pvt. Ltd. | H17: Debtors - GCF | I17: INR | J17: 921030030087786 - Axis Bank Ltd. CC Noida - GCF | K17: INR | L17: 339140 | M17: 1 | N17: 339140 | O17: 339140 | P17: 1 | Q17: 339140 | R17: Approved | S17: Initiated | T17: NEFT/RTGS | U17: Customer | V17: E-powertech | W17: E-powertech | X17: 0 | Y17: 0 | Z17: AXIS BANK 921030030087786 - NOIDA | AD17: 0 | AE17: Receivable | AF17: -16957861 | AG17: Bank | AH17: -4861280.3 | AI17: 339140 | AJ17: 339140 | AK17: 339140 | AL17: 339140 | AM17: 0 | AN17: 0 | AO17: 339140 | AP17: 0 | AS17: 0 | AU17: 0 | AV17: 0 | AW17: G.C. Foods Pvt. Ltd. Noida - Uttar Pradesh (Shipping) | AX17: 09AACCG2244H1ZS | AY17: 10-Bihar | BB17: Unregistered | BC17: N/A | BD17: 45849 | BG17: Noida | BI17: Cancelled | BJ17: 0 | BK17: Amount INR 339140 received from E-powertech Transaction reference no N/A dated 2025-07-11 | BL17: INR Three Lakh, Thirty Nine Thousand, One Hundred And Forty only. | BM17: No | BP17: AXIS BANK | BQ17: 921030030087786 | BS17: INR Three Lakh, Thirty Nine Thousand, One Hundred And Forty only. | BU17: E-powertech
A18: PAY/M/25-26/0862 | B18: PAY/M/25-26/0862-1 | C18: =VLOOKUP(A18,'Old Status'!B:C,2,0) -> Cancelled | D18: PAY/G/23-24/.#### | E18: Pay | F18: 45769 | G18: G. C. Foods Pvt. Ltd. | H18: 921030030087773 - Axis Bank Ltd. CC Bihar - GCF | I18: INR | J18: Creditors - GCF | K18: INR | L18: 48000 | M18: 1 | N18: 48000 | O18: 48000 | P18: 1 | Q18: 48000 | R18: Approved | S18: Initiated | T18: NEFT/RTGS | U18: Employee | V18: Shashi Kant Bhalla (M) | W18: Shashi Kant Bhalla (M) | X18: 0 | Y18: 0 | AD18: 0 | AE18: Bank | AF18: -19973354 | AG18: Payable | AH18: -5936117.7 | AI18: 48000 | AJ18: 48000 | AK18: 48000 | AL18: 48000 | AM18: 0 | AN18: 0 | AO18: 48000 | AP18: 0 | AS18: 0 | AU18: 0 | AV18: 0 | AW18: GC Foods Muzaffarpur-Billing | AX18: 10AACCG2244H1Z9 | BC18: N/A | BD18: 45769 | BG18: Muzaffarpur | BI18: Cancelled | BJ18: 0 | BK18: Amount INR 48000 to Shashi Kant Bhalla (M) Transaction reference no N/A dated 2025-04-22 | BL18: INR Forty Eight Thousand only. | BM18: No | BS18: INR Forty Eight Thousand only. | BU18: Shashi Kant Bhalla (M)
A19: PAY/M/25-26/0844-2 | B19: PAY/M/25-26/0844-2-1 | C19: =VLOOKUP(A19,'Old Status'!B:C,2,0) -> Cancelled | D19: PAY/G/23-24/.#### | E19: Receive | F19: 45855 | G19: G. C. Foods Pvt. Ltd. | H19: Debtors - GCF | I19: INR | J19: 921030030087773 - Axis Bank Ltd. CC Bihar - GCF | K19: INR | L19: 119892 | M19: 1 | N19: 119892 | O19: 119892 | P19: 1 | Q19: 119892 | R19: Approved | S19: Initiated | T19: NEFT/RTGS | U19: Customer | V19: Jay Mata TranportPan.No.AHUPT5943Q | W19: Jay Mata TranportPan.No.AHUPT5943Q | X19: 0 | Y19: 0 | Z19: AXIS BANK 921030030087773 - BIHAR | AD19: 0 | AE19: Receivable | AF19: -16202970 | AG19: Bank | AH19: -19646286 | AI19: 119892 | AJ19: 119892 | AK19: 119892 | AL19: 119892 | AM19: 0 | AN19: 0 | AO19: 119892 | AP19: 0 | AS19: 0 | AU19: 0 | AV19: 0 | AW19: GC Foods Muzaffarpur-Billing | AX19: 10AACCG2244H1Z9 | AY19: 10-Bihar | BB19: Unregistered | BC19: N/A | BD19: 45855 | BG19: Muzaffarpur | BI19: Cancelled | BJ19: 0 | BK19: Amount INR 119892 received from Jay Mata TranportPan.No.AHUPT5943Q Transaction reference no N/A dated 2025-07-17 | BL19: INR One Lakh, Nineteen Thousand, Eight Hundred And Ninety Two only. | BM19: No | BP19: AXIS BANK | BQ19: 921030030087773 | BS19: INR One Lakh, Nineteen Thousand, Eight Hundred And Ninety Two only. | BU19: Jay Mata TranportPan.No.AHUPT5943Q
A20: PAY/M/25-26/0844-1 | B20: PAY/M/25-26/0844-2 | C20: =VLOOKUP(A20,'Old Status'!B:C,2,0) -> Cancelled | D20: PAY/G/23-24/.#### | E20: Receive | F20: 45855 | G20: G. C. Foods Pvt. Ltd. | H20: Debtors - GCF | I20: INR | J20: 9210300223943516 - Axis Bank Ltd. CC Tronica - GCF | K20: INR | L20: 119892 | M20: 1 | N20: 119892 | O20: 119892 | P20: 1 | Q20: 119892 | R20: Approved | S20: Initiated | T20: NEFT/RTGS | U20: Customer | V20: Jay Mata TranportPan.No.AHUPT5943Q | W20: Jay Mata TranportPan.No.AHUPT5943Q | X20: 0 | Y20: 0 | Z20: AXIS BANK 921030030087773 - BIHAR | AD20: 0 | AE20: Receivable | AF20: -16202970 | AG20: Bank | AH20: -54154327 | AI20: 119892 | AJ20: 119892 | AK20: 119892 | AL20: 119892 | AM20: 0 | AN20: 0 | AO20: 119892 | AP20: 0 | AS20: 0 | AU20: 0 | AV20: 0 | AW20: GC Foods Muzaffarpur-Billing | AX20: 10AACCG2244H1Z9 | AY20: 10-Bihar | BB20: Unregistered | BC20: N/A | BD20: 45855 | BG20: Muzaffarpur | BI20: Cancelled | BJ20: 0 | BK20: Amount INR 119892 received from Jay Mata TranportPan.No.AHUPT5943Q Transaction reference no N/A dated 2025-07-17 | BL20: INR One Lakh, Nineteen Thousand, Eight Hundred And Ninety Two only. | BM20: No | BP20: AXIS BANK | BQ20: 921030030087773 | BS20: INR One Lakh, Nineteen Thousand, Eight Hundred And Ninety Two only. | BU20: Jay Mata TranportPan.No.AHUPT5943Q
A21: PAY/M/25-26/0844 | B21: PAY/M/25-26/0844-1 | C21: =VLOOKUP(A21,'Old Status'!B:C,2,0) -> Cancelled | D21: PAY/G/23-24/.#### | E21: Receive | F21: 45856 | G21: G. C. Foods Pvt. Ltd. | H21: Debtors - GCF | I21: INR | J21: 921030030087773 - Axis Bank Ltd. CC Bihar - GCF | K21: INR | L21: 119892 | M21: 1 | N21: 119892 | O21: 119892 | P21: 1 | Q21: 119892 | R21: Approved | S21: Initiated | U21: Customer | V21: Jay Mata TranportPan.No.AHUPT5943Q | W21: Jay Mata TranportPan.No.AHUPT5943Q | X21: 0 | Y21: 0 | Z21: AXIS BANK 921030030087773 - BIHAR | AD21: 0 | AE21: Receivable | AF21: -16202970 | AG21: Bank | AH21: -18873949 | AI21: 119892 | AJ21: 119892 | AK21: 119892 | AL21: 119892 | AM21: 0 | AN21: 0 | AO21: 119892 | AP21: 0 | AS21: 0 | AU21: 0 | AV21: 0 | AW21: GC Foods Muzaffarpur-Billing | AX21: 10AACCG2244H1Z9 | AY21: 10-Bihar | BB21: Unregistered | BC21: N/A | BD21: 45855 | BG21: Muzaffarpur | BI21: Cancelled | BJ21: 0 | BK21: Amount INR 119892 received from Jay Mata TranportPan.No.AHUPT5943Q Transaction reference no N/A dated 2025-07-17 | BL21: INR One Lakh, Nineteen Thousand, Eight Hundred And Ninety Two only. | BM21: No | BP21: AXIS BANK | BQ21: 921030030087773 | BS21: INR One Lakh, Nineteen Thousand, Eight Hundred And Ninety Two only. | BU21: Jay Mata TranportPan.No.AHUPT5943Q
A22: PAY/G/25-26/1360 | B22: PAY/G/25-26/1360-1 | C22: =VLOOKUP(A22,'Old Status'!B:C,2,0) -> Cancelled | D22: PAY/G/23-24/.#### | E22: Pay | F22: 45855 | G22: G. C. Foods Pvt. Ltd. | H22: 9210300223943516 - Axis Bank Ltd. CC Tronica - GCF | I22: INR | J22: Creditors - GCF | K22: INR | L22: 27080 | M22: 1 | N22: 27080 | O22: 27080 | P22: 1 | Q22: 27080 | R22: Approved | S22: Initiated | T22: NEFT/RTGS | U22: Supplier | V22: Mahaadev Traders | W22: Mahaadev Traders | X22: 0 | Y22: 0 | Z22: AXIS BANK 921030023943516 - GZB | AD22: -1655649.8 | AE22: Bank | AF22: -52588746 | AG22: Payable | AH22: -1655649.8 | AI22: 27080 | AJ22: 27080 | AK22: 27080 | AL22: 27080 | AM22: 0 | AN22: 0 | AO22: 27080 | AP22: 0 | AS22: 0 | AU22: 0 | AV22: 0 | AW22: G.C. Foods Pvt. Ltd.Ghaziabad - Uttar Pradesh-Billing | AX22: 09AACCG2244H1ZS | BC22: N/A | BD22: 45855 | BG22: Ghaziabad | BI22: Cancelled | BJ22: 0 | BK22: Amount INR 27080 to Mahaadev Traders Transaction reference no N/A dated 2025-07-17 | BL22: INR Twenty Seven Thousand And Eighty only. | BM22: No | BP22: AXIS BANK | BQ22: 921030023943516 | BS22: INR Twenty Seven Thousand And Eighty only. | BU22: Mahaadev Traders
A23: PAY/G/25-26/1355 | B23: PAY/G/25-26/1355-1 | C23: =VLOOKUP(A23,'Old Status'!B:C,2,0) -> Cancelled | D23: PAY/G/23-24/.#### | E23: Pay | F23: 45855 | G23: G. C. Foods Pvt. Ltd. | H23: 9210300223943516 - Axis Bank Ltd. CC Tronica - GCF | I23: INR | J23: Creditors - GCF | K23: INR | L23: 1328158 | M23: 1 | N23: 1328158 | O23: 1328158 | P23: 1 | Q23: 1328158 | R23: Approved | S23: Initiated | T23: NEFT/RTGS | U23: Supplier | V23: Mahaadev Traders | W23: Mahaadev Traders | X23: 0 | Y23: 0 | Z23: AXIS BANK 921030023943516 - GZB | AD23: -2983807.8 | AE23: Bank | AF23: -53318128 | AG23: Payable | AH23: -2983807.8 | AI23: 1328158 | AJ23: 1328158 | AK23: 1328158 | AL23: 1328158 | AM23: 0 | AN23: 0 | AO23: 1328158 | AP23: 0 | AS23: 0 | AU23: 0 | AV23: 0 | AW23: G.C. Foods Pvt. Ltd.Ghaziabad - Uttar Pradesh-Billing | AX23: 09AACCG2244H1ZS | BC23: N/A | BD23: 45855 | BG23: Ghaziabad | BI23: Cancelled | BJ23: 0 | BK23: Amount INR 1328158 to Mahaadev Traders Transaction reference no N/A dated 2025-07-17 | BL23: INR Thirteen Lakh, Twenty Eight Thousand, One Hundred And Fifty Eight only. | BM23: No | BP23: AXIS BANK | BQ23: 921030023943516 | BS23: INR Thirteen Lakh, Twenty Eight Thousand, One Hundred And Fifty Eight only. | BU23: Mahaadev Traders
A24: PAY/M/25-26/0826 | B24: PAY/M/25-26/0826-1 | C24: =VLOOKUP(A24,'Old Status'!B:C,2,0) -> Cancelled | D24: PAY/G/23-24/.#### | E24: Pay | F24: 45850 | G24: G. C. Foods Pvt. Ltd. | H24: 921030030087773 - Axis Bank Ltd. CC Bihar - GCF | I24: INR | J24: Creditors - GCF | K24: INR | L24: 38709 | M24: 1 | N24: 38709 | O24: 38709 | P24: 1 | Q24: 38709 | R24: Approved | S24: Initiated | T24: NEFT/RTGS | U24: Supplier | V24: GC foods Pvt Ltd (T) | W24: GC foods Pvt Ltd (T) | X24: 0 | Y24: 0 | Z24: AXIS BANK 921030030087773 - BIHAR | AD24: 42792485 | AE24: Bank | AF24: -19738705 | AG24: Payable | AH24: 42792485 | AI24: 38709 | AJ24: 38709 | AK24: 38709 | AL24: 38709 | AM24: 0 | AN24: 0 | AO24: 38709 | AP24: 0 | AS24: 0 | AU24: 0 | AV24: 0 | AW24: GC Foods Muzaffarpur-Billing | AX24: 10AACCG2244H1Z9 | BC24: N/A | BD24: 45850 | BG24: Muzaffarpur | BI24: Cancelled | BJ24: 0 | BK24: Amount INR 38709 to GC foods Pvt Ltd (T) Transaction reference no N/A dated 2025-07-12 | BL24: INR Thirty Eight Thousand, Seven Hundred And Nine only. | BM24: No | BP24: AXIS BANK | BQ24: 921030030087773 | BS24: INR Thirty Eight Thousand, Seven Hundred And Nine only. | BU24: GC foods Pvt Ltd (T)
A25: PAY/N/25-26/0522 | B25: PAY/N/25-26/0522-1 | C25: =VLOOKUP(A25,'Old Status'!B:C,2,0) -> Cancelled | D25: PAY/G/23-24/.#### | E25: Receive | F25: 45846 | G25: G. C. Foods Pvt. Ltd. | H25: Debtors - GCF | I25: INR | J25: 923020017959018 - Axis Bank - NOIDA - GCF | K25: INR | L25: 1771.89 | M25: 1 | N25: 1771.89 | O25: 1771.89 | P25: 1 | Q25: 1771.89 | R25: Approved | S25: Initiated | T25: NEFT/RTGS | U25: Customer | V25: DTDC EXPRESS (Courier) | W25: DTDC EXPRESS (Courier) | X25: 0 | Y25: 0 | Z25: AXIS BANK 923020017959018 -NOIDA | AB25: Amrit Varsha-DTDC EXPRESS SERVICE | AD25: 4125.22 | AE25: Receivable | AF25: 4125.22 | AG25: Bank | AH25: 24288.68 | AI25: 1771.89 | AJ25: 1771.89 | AK25: 1771.89 | AL25: 1771.89 | AM25: 0 | AN25: 0 | AO25: 1771.89 | AP25: 0 | AS25: 0 | AU25: 0 | AV25: 0 | AW25: G.C. Foods Pvt. Ltd. Noida - Uttar Pradesh (Shipping) | AX25: 09AACCG2244H1ZS | AY25: 27-Maharashtra | AZ25: DTDC EXPRESS SERVICE-Billing-18 | BB25: Unregistered | BC25: N/A | BD25: 45846 | BG25: Noida | BI25: Cancelled | BJ25: 0 | BK25: Amount INR 1771.89 received from DTDC EXPRESS (Courier) Transaction reference no N/A dated 2025-07-08 | BL25: INR One Thousand, Seven Hundred And Seventy One and Eighty Nine Paisa only. | BM25: No | BP25: AXIS BANK | BQ25: 923020017959018 | BS25: INR One Thousand, Seven Hundred And Seventy One and Eighty Nine Paisa only. | BU25: DTDC EXPRESS (Courier)
A26: PAY/M/25-26/0769-1 | B26: PAY/M/25-26/0769-2 | C26: =VLOOKUP(A26,'Old Status'!B:C,2,0) -> Cancelled | D26: PAY/G/23-24/.#### | E26: Pay | F26: 45845 | G26: G. C. Foods Pvt. Ltd. | H26: 921030030087773 - Axis Bank Ltd. CC Bihar - GCF | I26: INR | J26: Creditors - GCF | K26: INR | L26: 30600 | M26: 1 | N26: 30600 | O26: 30600 | P26: 1 | Q26: 30600 | R26: Approved | S26: Initiated | T26: NEFT/RTGS | U26: Supplier | V26: Jogendra jee, Patna | W26: Jogendra jee, Patna | X26: 0 | Y26: 0 | Z26: AXIS BANK 921030030087773 - BIHAR | AD26: -30000 | AE26: Bank | AF26: -18051699 | AG26: Payable | AH26: -30000 | AI26: 30600 | AJ26: 30600 | AK26: 30600 | AL26: 30600 | AM26: 0 | AN26: 0 | AO26: 30600 | AP26: 0 | AS26: 0 | AU26: 0 | AV26: 0 | AW26: GC Foods Muzaffarpur-Billing | AX26: 10AACCG2244H1Z9 | BC26: N/A | BD26: 45845 | BG26: Muzaffarpur | BI26: Cancelled | BJ26: 0 | BK26: Amount INR 30600 to Jogendra jee, Patna Transaction reference no N/A dated 2025-07-07 | BL26: INR Thirty Thousand, Six Hundred only. | BM26: No | BP26: AXIS BANK | BQ26: 921030030087773 | BS26: INR Thirty Thousand, Six Hundred only. | BU26: Jogendra jee, Patna
A27: PAY/N/25-26/0513 | B27: PAY/N/25-26/0513-1 | C27: =VLOOKUP(A27,'Old Status'!B:C,2,0) -> Cancelled | D27: PAY/G/23-24/.#### | E27: Pay | F27: 45848 | G27: G. C. Foods Pvt. Ltd. | H27: 921030030087786 - Axis Bank Ltd. CC Noida - GCF | I27: INR | J27: Creditors - GCF | K27: INR | L27: 339140 | M27: 1 | N27: 339140 | O27: 339140 | P27: 1 | Q27: 339140 | R27: Approved | S27: Initiated | T27: NEFT/RTGS | U27: Supplier | V27: E Powertech | W27: E Power Technologies | X27: 0 | Y27: 0 | Z27: AXIS BANK 921030030087786 - NOIDA | AD27: 772380 | AE27: Bank | AF27: -4857980.3 | AG27: Payable | AH27: 772380 | AI27: 339140 | AJ27: 339140 | AK27: 339140 | AL27: 339140 | AM27: 0 | AN27: 0 | AO27: 339140 | AP27: 0 | AS27: 0 | AU27: 0 | AV27: 0 | AW27: G.C. Foods Pvt. Ltd. Noida - Uttar Pradesh (Shipping) | AX27: 09AACCG2244H1ZS | BC27: N/A | BD27: 45848 | BG27: Noida | BI27: Cancelled | BJ27: 0 | BK27: Amount INR 339140 to E Power Technologies Transaction reference no N/A dated 2025-07-10 | BL27: INR Three Lakh, Thirty Nine Thousand, One Hundred And Forty only. | BM27: No | BP27: AXIS BANK | BQ27: 921030030087786 | BS27: INR Three Lakh, Thirty Nine Thousand, One Hundred And Forty only. | BU27: E Power Technologies
A28: PAY/N/25-26/0505 | B28: PAY/N/25-26/0505-1 | C28: =VLOOKUP(A28,'Old Status'!B:C,2,0) -> Cancelled | D28: PAY/G/23-24/.#### | E28: Pay | F28: 45847 | G28: G. C. Foods Pvt. Ltd. | H28: 921030030087786 - Axis Bank Ltd. CC Noida - GCF | I28: INR | J28: Creditors - GCF | K28: INR | L28: 6333 | M28: 1 | N28: 6333 | O28: 6333 | P28: 1 | Q28: 6333 | R28: Approved | S28: Initiated | T28: NEFT/RTGS | U28: Employee | V28: Ankit Kumar - Staff Noida | W28: Ankit Kumar - Staff Noida | X28: 0 | Y28: 0 | AD28: 0 | AE28: Bank | AF28: -4914951.3 | AG28: Payable | AH28: 68176968 | AI28: 6333 | AJ28: 6333 | AK28: 6333 | AL28: 6333 | AM28: 0 | AN28: 0 | AO28: 6333 | AP28: 0 | AS28: 0 | AU28: 0 | AV28: 0 | AW28: G.C. Foods Pvt. Ltd. Noida - Uttar Pradesh (Shipping) | AX28: 09AACCG2244H1ZS | BC28: N/A | BD28: 45847 | BG28: Noida | BI28: Cancelled | BJ28: 0 | BK28: Amount INR 6333 to Ankit Kumar - Staff Noida Transaction reference no N/A dated 2025-07-09 | BL28: INR Six Thousand, Three Hundred And Thirty Three only. | BM28: No | BS28: INR Six Thousand, Three Hundred And Thirty Three only. | BU28: Ankit Kumar - Staff Noida
A29: PAY/N/25-26/0478 | B29: PAY/N/25-26/0478-1 | C29: =VLOOKUP(A29,'Old Status'!B:C,2,0) -> Cancelled | D29: PAY/G/23-24/.#### | E29: Pay | F29: 45846 | G29: G. C. Foods Pvt. Ltd. | H29: 921030030087786 - Axis Bank Ltd. CC Noida - GCF | I29: INR | J29: Creditors - GCF | K29: INR | L29: 31500 | M29: 1 | N29: 31500 | O29: 31500 | P29: 1 | Q29: 31500 | R29: Approved | S29: Initiated | T29: NEFT/RTGS | U29: Supplier | V29: GC foods Pvt Ltd Bihar | W29: GC foods Pvt Ltd Bihar | X29: 0 | Y29: 0 | Z29: AXIS BANK 921030030087786 - NOIDA | AD29: 5195000 | AE29: Bank | AF29: -4896731.3 | AG29: Payable | AH29: 5195000 | AI29: 31500 | AJ29: 31500 | AK29: 31500 | AL29: 31500 | AM29: 0 | AN29: 0 | AO29: 31500 | AP29: 0 | AS29: 0 | AU29: 0 | AV29: 0 | AW29: G.C. Foods Pvt. Ltd. Noida - Uttar Pradesh (Shipping) | AX29: 09AACCG2244H1ZS | BC29: N/A | BD29: 45846 | BG29: Noida | BI29: Cancelled | BJ29: 0 | BK29: Amount INR 31500 to GC foods Pvt Ltd Bihar Transaction reference no N/A dated 2025-07-08 | BL29: INR Thirty One Thousand, Five Hundred only. | BM29: No | BP29: AXIS BANK | BQ29: 921030030087786 | BS29: INR Thirty One Thousand, Five Hundred only. | BU29: GC foods Pvt Ltd Bihar
A30: PAY/N/25-26/0462 | B30: PAY/N/25-26/0462-1 | C30: =VLOOKUP(A30,'Old Status'!B:C,2,0) -> Cancelled | D30: PAY/G/23-24/.#### | E30: Pay | F30: 45845 | G30: G. C. Foods Pvt. Ltd. | H30: 9210300223943516 - Axis Bank Ltd. CC Tronica - GCF | I30: INR | J30: Creditors - GCF | K30: INR | L30: 3300 | M30: 1 | N30: 3300 | O30: 3300 | P30: 1 | Q30: 3300 | R30: Approved | S30: Initiated | T30: NEFT/RTGS | U30: Employee | V30: Kanhiya Lal Sales - NCR | W30: Kanhiya Lal Sales - NCR | X30: 0 | Y30: 0 | AD30: 10875 | AE30: Bank | AF30: -53173281 | AG30: Payable | AH30: 10875 | AI30: 3300 | AJ30: 3300 | AK30: 3300 | AL30: 3300 | AM30: 0 | AN30: 0 | AO30: 3300 | AP30: 0 | AS30: 0 | AU30: 0 | AV30: 0 | AW30: G.C. Foods Pvt. Ltd. Noida - Uttar Pradesh (Shipping) | AX30: 09AACCG2244H1ZS | BC30: N/A | BD30: 45845 | BG30: Noida | BI30: Cancelled | BJ30: 0 | BK30: Amount INR 3300 to Kanhiya Lal Sales - NCR Transaction reference no N/A dated 2025-07-07 | BL30: INR Three Thousand, Three Hundred only. | BM30: No | BS30: INR Three Thousand, Three Hundred only. | BU30: Kanhiya Lal Sales - NCR
A31: PAY/N/25-26/0455-1 | B31: PAY/N/25-26/0455-2 | C31: =VLOOKUP(A31,'Old Status'!B:C,2,0) -> Cancelled | D31: PAY/G/23-24/.#### | E31: Pay | F31: 45843 | G31: G. C. Foods Pvt. Ltd. | H31: 921030030087786 - Axis Bank Ltd. CC Noida - GCF | I31: INR | J31: Creditors - GCF | K31: INR | L31: 34043 | M31: 1 | N31: 34043 | O31: 34043 | P31: 1 | Q31: 34043 | R31: Approved | S31: Initiated | T31: NEFT/RTGS | U31: Supplier | V31: Galaxy Sivtek Private Limited | W31: Galaxy Sivtek Private Limited | X31: 0 | Y31: 0 | Z31: AXIS BANK 921030030087786 - NOIDA | AD31: 0 | AE31: Bank | AF31: -5133173.3 | AG31: Payable | AH31: 61551320 | AI31: 34043 | AJ31: 34043 | AK31: 34043 | AL31: 34043 | AM31: 0 | AN31: 0 | AO31: 34043 | AP31: 0 | AS31: 0 | AU31: 0 | AV31: 0 | AW31: G.C. Foods Pvt. Ltd. Noida - Uttar Pradesh (Shipping) | AX31: 09AACCG2244H1ZS | BC31: N/A | BD31: 45843 | BG31: Noida | BI31: Cancelled | BJ31: 0 | BK31: Amount INR 34043 to Galaxy Sivtek Private Limited Transaction reference no N/A dated 2025-07-05 | BL31: INR Thirty Four Thousand And Forty Three only. | BM31: No | BP31: AXIS BANK | BQ31: 921030030087786 | BS31: INR Thirty Four Thousand And Forty Three only. | BU31: Galaxy Sivtek Private Limited
A32: PAY/N/25-26/0456 | B32: PAY/N/25-26/0456-1 | C32: =VLOOKUP(A32,'Old Status'!B:C,2,0) -> Cancelled | D32: PAY/G/23-24/.#### | E32: Pay | F32: 45842 | G32: G. C. Foods Pvt. Ltd. | H32: 921030030087786 - Axis Bank Ltd. CC Noida - GCF | I32: INR | J32: Creditors - GCF | K32: INR | L32: 9038 | M32: 1 | N32: 9038 | O32: 9038 | P32: 1 | Q32: 9038 | R32: Approved | S32: Initiated | T32: NEFT/RTGS | U32: Supplier | V32: Gogia Chemical Industries (P) Ltd | W32: Gogia Chemical Industries (P) Ltd | X32: 0 | Y32: 0 | Z32: AXIS BANK 921030030087786 - NOIDA | AD32: -9038 | AE32: Bank | AF32: -5167216.3 | AG32: Payable | AH32: -9038 | AI32: 9038 | AJ32: 9038 | AK32: 9038 | AL32: 9038 | AM32: 0 | AN32: 0 | AO32: 9038 | AP32: 0 | AS32: 0 | AU32: 0 | AV32: 0 | AW32: G.C. Foods Pvt. Ltd. Noida - Uttar Pradesh (Shipping) | AX32: 09AACCG2244H1ZS | BC32: N/A | BD32: 45842 | BG32: Noida | BI32: Cancelled | BJ32: 0 | BK32: Amount INR 9038 to Gogia Chemical Industries (P) Ltd Transaction reference no N/A dated 2025-07-04 | BL32: INR Nine Thousand And Thirty Eight only. | BM32: No | BP32: AXIS BANK | BQ32: 921030030087786 | BS32: INR Nine Thousand And Thirty Eight only. | BU32: Gogia Chemical Industries (P) Ltd
A33: PAY/N/25-26/0455 | B33: PAY/N/25-26/0455-1 | C33: =VLOOKUP(A33,'Old Status'!B:C,2,0) -> Cancelled | D33: PAY/G/23-24/.#### | E33: Pay | F33: 45842 | G33: G. C. Foods Pvt. Ltd. | H33: 921030030087786 - Axis Bank Ltd. CC Noida - GCF | I33: INR | J33: Creditors - GCF | K33: INR | L33: 34043 | M33: 1 | N33: 34043 | O33: 34043 | P33: 1 | Q33: 34043 | R33: Approved | S33: Initiated | T33: NEFT/RTGS | U33: Supplier | V33: Galaxy Sivtek Private Limited | W33: Galaxy Sivtek Private Limited | X33: 0 | Y33: 0 | Z33: AXIS BANK 921030030087786 - NOIDA | AD33: 0 | AE33: Bank | AF33: -5133173.3 | AG33: Payable | AH33: 61551320 | AI33: 34043 | AJ33: 34043 | AK33: 34043 | AL33: 34043 | AM33: 0 | AN33: 0 | AO33: 34043 | AP33: 0 | AS33: 0 | AU33: 0 | AV33: 0 | AW33: G.C. Foods Pvt. Ltd. Noida - Uttar Pradesh (Shipping) | AX33: 09AACCG2244H1ZS | BC33: N/A | BD33: 45842 | BG33: Noida | BI33: Cancelled | BJ33: 0 | BK33: Amount INR 34043 to Galaxy Sivtek Private Limited Transaction reference no N/A dated 2025-07-04 | BL33: INR Thirty Four Thousand And Forty Three only. | BM33: No | BP33: AXIS BANK | BQ33: 921030030087786 | BS33: INR Thirty Four Thousand And Forty Three only. | BU33: Galaxy Sivtek Private Limited
A34: PAY/N/25-26/0454 | B34: PAY/N/25-26/0454-1 | C34: =VLOOKUP(A34,'Old Status'!B:C,2,0) -> Cancelled | D34: PAY/G/23-24/.#### | E34: Pay | F34: 45842 | G34: G. C. Foods Pvt. Ltd. | H34: 921030030087786 - Axis Bank Ltd. CC Noida - GCF | I34: INR | J34: Creditors - GCF | K34: INR | L34: 130956 | M34: 1 | N34: 130956 | O34: 130956 | P34: 1 | Q34: 130956 | R34: Approved | S34: Initiated | T34: NEFT/RTGS | U34: Supplier | V34: Daulat Ram Rakesh Kumar | W34: Daulat Ram Rakesh Kumar | X34: 0 | Y34: 0 | Z34: AXIS BANK 921030030087786 - NOIDA | AD34: -160697.45 | AE34: Bank | AF34: -5002217.3 | AG34: Payable | AH34: -160697.45 | AI34: 130956 | AJ34: 130956 | AK34: 130956 | AL34: 130956 | AM34: 0 | AN34: 0 | AO34: 130956 | AP34: 0 | AS34: 0 | AU34: 0 | AV34: 0 | AW34: G.C. Foods Pvt. Ltd. Noida - Uttar Pradesh (Shipping) | AX34: 09AACCG2244H1ZS | BC34: N/A | BD34: 45842 | BG34: Noida | BI34: Cancelled | BJ34: 0 | BK34: Amount INR 130956 to Daulat Ram Rakesh Kumar Transaction reference no N/A dated 2025-07-04 | BL34: INR One Lakh, Thirty Thousand, Nine Hundred And Fifty Six only. | BM34: No | BP34: AXIS BANK | BQ34: 921030030087786 | BS34: INR One Lakh, Thirty Thousand, Nine Hundred And Fifty Six only. | BU34: Daulat Ram Rakesh Kumar
A35: PAY/N/25-26/0453 | B35: PAY/N/25-26/0453-1 | C35: =VLOOKUP(A35,'Old Status'!B:C,2,0) -> Cancelled | D35: PAY/G/23-24/.#### | E35: Pay | F35: 45842 | G35: G. C. Foods Pvt. Ltd. | H35: 921030030087786 - Axis Bank Ltd. CC Noida - GCF | I35: INR | J35: Creditors - GCF | K35: INR | L35: 34250 | M35: 1 | N35: 34250 | O35: 34250 | P35: 1 | Q35: 34250 | R35: Approved | S35: Initiated | T35: NEFT/RTGS | U35: Supplier | V35: Bajrang Traders | W35: Bajrang Traders | X35: 0 | Y35: 0 | Z35: AXIS BANK 921030030087786 - NOIDA | AD35: -66628 | AE35: Bank | AF35: -4967967.3 | AG35: Payable | AH35: -66628 | AI35: 34250 | AJ35: 34250 | AK35: 34250 | AL35: 34250 | AM35: 0 | AN35: 0 | AO35: 34250 | AP35: 0 | AS35: 0 | AU35: 0 | AV35: 0 | AW35: G.C. Foods Pvt. Ltd. Noida - Uttar Pradesh (Shipping) | AX35: 09AACCG2244H1ZS | BC35: N/A | BD35: 45842 | BG35: Noida | BI35: Cancelled | BJ35: 0 | BK35: Amount INR 34250 to Bajrang Traders Transaction reference no N/A dated 2025-07-04 | BL35: INR Thirty Four Thousand, Two Hundred And Fifty only. | BM35: No | BP35: AXIS BANK | BQ35: 921030030087786 | BS35: INR Thirty Four Thousand, Two Hundred And Fifty only. | BU35: Bajrang Traders
A36: PAY/N/25-26/0452 | B36: PAY/N/25-26/0452-1 | C36: =VLOOKUP(A36,'Old Status'!B:C,2,0) -> Cancelled | D36: PAY/G/23-24/.#### | E36: Pay | F36: 45842 | G36: G. C. Foods Pvt. Ltd. | H36: 921030030087786 - Axis Bank Ltd. CC Noida - GCF | I36: INR | J36: Creditors - GCF | K36: INR | L36: 1858.5 | M36: 1 | N36: 1858.5 | O36: 1858.5 | P36: 1 | Q36: 1858.5 | R36: Approved | S36: Initiated | T36: NEFT/RTGS | U36: Supplier | V36: AG Enviro Infra Projects Pvt Ltd. | W36: AG Enviro Infra Projects Pvt Ltd. | X36: 0 | Y36: 0 | Z36: AXIS BANK 921030030087786 - NOIDA | AD36: 0 | AE36: Bank | AF36: -4966108.8 | AG36: Payable | AH36: 61392923 | AI36: 1858.5 | AJ36: 1858.5 | AK36: 1858.5 | AL36: 1858.5 | AM36: 0 | AN36: 0 | AO36: 1858.5 | AP36: 0 | AS36: 0 | AU36: 0 | AV36: 0 | AW36: G.C. Foods Pvt. Ltd. Noida - Uttar Pradesh (Shipping) | AX36: 09AACCG2244H1ZS | BC36: N/A | BD36: 45842 | BG36: Noida | BI36: Cancelled | BJ36: 0 | BK36: Amount INR 1858.5 to AG Enviro Infra Projects Pvt Ltd. Transaction reference no N/A dated 2025-07-04 | BL36: INR One Thousand, Eight Hundred And Fifty Eight and Fifty Paisa only. | BM36: No | BP36: AXIS BANK | BQ36: 921030030087786 | BS36: INR One Thousand, Eight Hundred And Fifty Eight and Fifty Paisa only. | BU36: AG Enviro Infra Projects Pvt Ltd.
A37: PAY/N/25-26/0451 | B37: PAY/N/25-26/0451-1 | C37: =VLOOKUP(A37,'Old Status'!B:C,2,0) -> Cancelled | D37: PAY/G/23-24/.#### | E37: Pay | F37: 45842 | G37: G. C. Foods Pvt. Ltd. | H37: 921030030087786 - Axis Bank Ltd. CC Noida - GCF | I37: INR | J37: Creditors - GCF | K37: INR | L37: 9137.63 | M37: 1 | N37: 9137.63 | O37: 9137.63 | P37: 1 | Q37: 9137.63 | R37: Approved | S37: Initiated | T37: NEFT/RTGS | U37: Supplier | V37: DTDC Express Limited - Billing | W37: DTDC Express Limited | X37: 0 | Y37: 0 | Z37: AXIS BANK 921030030087786 - NOIDA | AD37: 16376.93 | AE37: Bank | AF37: -4956971.2 | AG37: Payable | AH37: 16376.93 | AI37: 9137.63 | AJ37: 9137.63 | AK37: 9137.63 | AL37: 9137.63 | AM37: 0 | AN37: 0 | AO37: 9137.63 | AP37: 0 | AS37: 0 | AU37: 0 | AV37: 0 | AW37: G.C. Foods Pvt. Ltd. Noida - Uttar Pradesh (Shipping) | AX37: 09AACCG2244H1ZS | BC37: N/A | BD37: 45842 | BG37: Noida | BI37: Cancelled | BJ37: 0 | BK37: Amount INR 9137.63 to DTDC Express Limited Transaction reference no N/A dated 2025-07-04 | BL37: INR Nine Thousand, One Hundred And Thirty Seven and Sixty Three Paisa only. | BM37: No | BP37: AXIS BANK | BQ37: 921030030087786 | BS37: INR Nine Thousand, One Hundred And Thirty Seven and Sixty Three Paisa only. | BU37: DTDC Express Limited
A38: PAY/N/25-26/0450 | B38: PAY/N/25-26/0450-1 | C38: =VLOOKUP(A38,'Old Status'!B:C,2,0) -> Cancelled | D38: PAY/G/23-24/.#### | E38: Pay | F38: 45842 | G38: G. C. Foods Pvt. Ltd. | H38: 921030030087786 - Axis Bank Ltd. CC Noida - GCF | I38: INR | J38: Creditors - GCF | K38: INR | L38: 27720 | M38: 1 | N38: 27720 | O38: 27720 | P38: 1 | Q38: 27720 | R38: Approved | S38: Initiated | T38: NEFT/RTGS | U38: Supplier | V38: Royal Securitas | W38: Royal Securitas | X38: 0 | Y38: 0 | Z38: AXIS BANK 921030030087786 - NOIDA | AD38: 27720 | AE38: Bank | AF38: -4929251.2 | AG38: Payable | AH38: 27720 | AI38: 27720 | AJ38: 27720 | AK38: 27720 | AL38: 27720 | AM38: 0 | AN38: 0 | AO38: 27720 | AP38: 0 | AS38: 0 | AU38: 0 | AV38: 0 | AW38: G.C. Foods Pvt. Ltd. Noida - Uttar Pradesh (Shipping) | AX38: 09AACCG2244H1ZS | BC38: N/A | BD38: 45842 | BG38: Noida | BI38: Cancelled | BJ38: 0 | BK38: Amount INR 27720 to Royal Securitas Transaction reference no N/A dated 2025-07-04 | BL38: INR Twenty Seven Thousand, Seven Hundred And Twenty only. | BM38: No | BP38: AXIS BANK | BQ38: 921030030087786 | BS38: INR Twenty Seven Thousand, Seven Hundred And Twenty only. | BU38: Royal Securitas
A39: PAY/G/25-26/1311 | B39: PAY/G/25-26/1311-1 | C39: =VLOOKUP(A39,'Old Status'!B:C,2,0) -> Cancelled | D39: PAY/G/23-24/.#### | E39: Pay | F39: 45850 | G39: G. C. Foods Pvt. Ltd. | H39: 9210300223943516 - Axis Bank Ltd. CC Tronica - GCF | I39: INR | J39: Creditors - GCF | K39: INR | L39: 45639 | M39: 1 | N39: 45639 | O39: 45639 | P39: 1 | Q39: 45639 | R39: Approved | S39: Initiated | T39: NEFT/RTGS | U39: Supplier | V39: GC foods Pvt Ltd Bihar | W39: GC foods Pvt Ltd Bihar | X39: 0 | Y39: 0 | Z39: AXIS BANK 921030023943516 - GZB | AD39: 5195000 | AE39: Bank | AF39: -53344451 | AG39: Payable | AH39: 5195000 | AI39: 45639 | AJ39: 45639 | AK39: 45639 | AL39: 45639 | AM39: 0 | AN39: 0 | AO39: 45639 | AP39: 0 | AS39: 0 | AU39: 0 | AV39: 0 | AW39: G.C. Foods Pvt. Ltd.Ghaziabad - Uttar Pradesh-Billing | AX39: 09AACCG2244H1ZS | BC39: N/A | BD39: 45850 | BG39: Ghaziabad | BI39: Cancelled | BJ39: 0 | BK39: Amount INR 45639 to GC foods Pvt Ltd Bihar Transaction reference no N/A dated 2025-07-12 | BL39: INR Forty Five Thousand, Six Hundred And Thirty Nine only. | BM39: No | BP39: AXIS BANK | BQ39: 921030023943516 | BS39: INR Forty Five Thousand, Six Hundred And Thirty Nine only. | BU39: GC foods Pvt Ltd Bihar
A40: PAY/G/25-26/1253 | B40: PAY/G/25-26/1253-1 | C40: =VLOOKUP(A40,'Old Status'!B:C,2,0) -> Cancelled | D40: PAY/G/23-24/.#### | E40: Pay | F40: 45848 | G40: G. C. Foods Pvt. Ltd. | H40: 9210300223943516 - Axis Bank Ltd. CC Tronica - GCF | I40: INR | J40: Creditors - GCF | K40: INR | L40: 620465.46 | M40: 1 | N40: 620465.46 | O40: 620465.46 | P40: 1 | Q40: 620465.46 | R40: Approved | S40: Initiated | T40: NEFT/RTGS | U40: Supplier | V40: Mahaadev Traders | W40: Mahaadev Traders | X40: 0 | Y40: 0 | Z40: AXIS BANK 921030023943516 - GZB | AD40: 576960.12 | AE40: Bank | AF40: -53513900 | AG40: Payable | AH40: 576960.12 | AI40: 620465.46 | AJ40: 620465.46 | AK40: 620465.46 | AL40: 620465.46 | AM40: 0 | AN40: 0 | AO40: 620465.46 | AP40: 0 | AS40: 0 | AU40: 0 | AV40: 0 | AW40: G.C. Foods Pvt. Ltd.Ghaziabad - Uttar Pradesh-Billing | AX40: 09AACCG2244H1ZS | BC40: N/A | BD40: 45848 | BG40: Ghaziabad | BI40: Cancelled | BJ40: 0 | BK40: Amount INR 620465.46 to Mahaadev Traders Transaction reference no N/A dated 2025-07-10 | BL40: INR Six Lakh, Twenty Thousand, Four Hundred And Sixty Five and Forty Six Paisa only. | BM40: No | BP40: AXIS BANK | BQ40: 921030023943516 | BS40: INR Six Lakh, Twenty Thousand, Four Hundred And Sixty Five and Forty Six Paisa only. | BU40: Mahaadev Traders
A41: PAY/N/25-26/0448 | B41: PAY/N/25-26/0448-1 | C41: =VLOOKUP(A41,'Old Status'!B:C,2,0) -> Cancelled | D41: PAY/G/23-24/.#### | E41: Receive | F41: 45848 | G41: G. C. Foods Pvt. Ltd. | H41: Debtors - GCF | I41: INR | J41: 9210300223943516 - Axis Bank Ltd. CC Tronica - GCF | K41: INR | L41: 1000000 | M41: 1 | N41: 1000000 | O41: 1000000 | P41: 1 | Q41: 1000000 | R41: Approved | S41: Initiated | T41: NEFT/RTGS | U41: Customer | V41: Sanjay Trading Company | W41: Sanjay Trading Company | X41: 0 | Y41: 0 | Z41: AXIS BANK 921030023943516 - GZB | AD41: 821394.34 | AE41: Receivable | AF41: 821394.34 | AG41: Bank | AH41: -52648582 | AI41: 1000000 | AJ41: 1000000 | AK41: 1000000 | AL41: 1000000 | AM41: 0 | AN41: 0 | AO41: 1000000 | AP41: 0 | AS41: 0 | AU41: 0 | AV41: 0 | AW41: G.C. Foods Pvt. Ltd. Noida - Uttar Pradesh (Shipping) | AX41: 09AACCG2244H1ZS | AY41: 10-Bihar | AZ41: Sanjay Trading Company-Billing | BA41: 10AUUPK5490N2ZZ | BB41: Registered Regular | BC41: N/A | BD41: 45848 | BG41: Noida | BI41: Cancelled | BJ41: 0 | BK41: Amount INR 1000000 received from Sanjay Trading Company Transaction reference no N/A dated 2025-07-10 | BL41: INR Ten Lakh only. | BM41: No | BP41: AXIS BANK | BQ41: 921030023943516 | BS41: INR Ten Lakh only. | BU41: Sanjay Trading Company
A42: PAY/G/25-26/1240-1 | B42: PAY/G/25-26/1240-2 | C42: =VLOOKUP(A42,'Old Status'!B:C,2,0) -> Cancelled | D42: PAY/G/23-24/.#### | E42: Receive | F42: 45847 | G42: G. C. Foods Pvt. Ltd. | H42: Debtors - GCF | I42: INR | J42: 9210300223943516 - Axis Bank Ltd. CC Tronica - GCF | K42: INR | L42: 522375 | M42: 1 | N42: 522375 | O42: 522375 | P42: 1 | Q42: 522375 | R42: Approved | S42: Initiated | U42: Customer | V42: Naveen Trading Company | W42: Naveen Trading Company | X42: 0 | Y42: 0 | Z42: AXIS BANK 921030023943516 - GZB | AD42: 0 | AE42: Receivable | AF42: -39369616 | AG42: Bank | AH42: -52164419 | AI42: 522375 | AJ42: 522375 | AK42: 522375 | AL42: 522375 | AM42: 0 | AN42: 0 | AO42: 522375 | AP42: 0 | AS42: 0 | AU42: 0 | AV42: 0 | AW42: G.C. Foods Pvt. Ltd.Ghaziabad - Uttar Pradesh-Billing | AX42: 09AACCG2244H1ZS | AY42: 08-Rajasthan | BA42: 08ACHPS6047E1ZF | BB42: Registered Regular | BC42: N/A | BD42: 45847 | BG42: Ghaziabad | BI42: Cancelled | BJ42: 0 | BK42: Amount INR 522375 received from Naveen Trading Company Transaction reference no N/A dated 2025-07-09 | BL42: INR Five Lakh, Twenty Two Thousand, Three Hundred And Seventy Five only. | BM42: No | BP42: AXIS BANK | BQ42: 921030023943516 | BS42: INR Five Lakh, Twenty Two Thousand, Three Hundred And Seventy Five only. | BU42: Naveen Trading Company
A43: PAY/G/25-26/1240 | B43: PAY/G/25-26/1240-1 | C43: =VLOOKUP(A43,'Old Status'!B:C,2,0) -> Cancelled | D43: PAY/G/23-24/.#### | E43: Receive | F43: 45817 | G43: G. C. Foods Pvt. Ltd. | H43: Debtors - GCF | I43: INR | J43: 9210300223943516 - Axis Bank Ltd. CC Tronica - GCF | K43: INR | L43: 522375 | M43: 1 | N43: 522375 | O43: 522375 | P43: 1 | Q43: 522375 | R43: Approved | S43: Initiated | U43: Customer | V43: Naveen Trading Company | W43: Naveen Trading Company | X43: 0 | Y43: 0 | Z43: AXIS BANK 921030023943516 - GZB | AD43: 0 | AE43: Receivable | AF43: -39369616 | AG43: Bank | AH43: -52164419 | AI43: 522375 | AJ43: 522375 | AK43: 522375 | AL43: 522375 | AM43: 0 | AN43: 0 | AO43: 522375 | AP43: 0 | AS43: 0 | AU43: 0 | AV43: 0 | AW43: G.C. Foods Pvt. Ltd.Ghaziabad - Uttar Pradesh-Billing | AX43: 09AACCG2244H1ZS | AY43: 08-Rajasthan | BA43: 08ACHPS6047E1ZF | BB43: Registered Regular | BC43: N/A | BD43: 45847 | BG43: Ghaziabad | BI43: Cancelled | BJ43: 0 | BK43: Amount INR 522375 received from Naveen Trading Company Transaction reference no N/A dated 2025-07-09 | BL43: INR Five Lakh, Twenty Two Thousand, Three Hundred And Seventy Five only. | BM43: No | BP43: AXIS BANK | BQ43: 921030023943516 | BS43: INR Five Lakh, Twenty Two Thousand, Three Hundred And Seventy Five only. | BU43: Naveen Trading Company
A44: PAY/M/25-26/0769 | B44: PAY/M/25-26/0769-1 | C44: =VLOOKUP(A44,'Old Status'!B:C,2,0) -> Cancelled | D44: PAY/G/23-24/.#### | E44: Pay | F44: 45845 | G44: G. C. Foods Pvt. Ltd. | H44: 921030030087773 - Axis Bank Ltd. CC Bihar - GCF | I44: INR | J44: Creditors - GCF | K44: INR | L44: 30600 | M44: 1 | N44: 30600 | O44: 30600 | P44: 1 | Q44: 30600 | R44: Approved | S44: Initiated | T44: NEFT/RTGS | U44: Supplier | V44: Jogi Jee Patna | W44: Jogi Jee Patna | X44: 0 | Y44: 0 | Z44: AXIS BANK 921030030087773 - BIHAR | AD44: 0 | AE44: Bank | AF44: -18051699 | AG44: Payable | AH44: 68336946 | AI44: 30600 | AJ44: 30600 | AK44: 30600 | AL44: 30600 | AM44: 0 | AN44: 0 | AO44: 30600 | AP44: 0 | AS44: 0 | AU44: 0 | AV44: 0 | AW44: GC Foods Muzaffarpur-Billing | AX44: 10AACCG2244H1Z9 | BC44: N/A | BD44: 45845 | BG44: Muzaffarpur | BI44: Cancelled | BJ44: 0 | BK44: Amount INR 30600 to Jogi Jee Patna Transaction reference no N/A dated 2025-07-07 | BL44: INR Thirty Thousand, Six Hundred only. | BM44: No | BP44: AXIS BANK | BQ44: 921030030087773 | BS44: INR Thirty Thousand, Six Hundred only. | BU44: Jogi Jee Patna
A45: PAY/G/25-26/1222 | B45: PAY/G/25-26/1222-1 | C45: =VLOOKUP(A45,'Old Status'!B:C,2,0) -> Cancelled | D45: PAY/G/23-24/.#### | E45: Receive | F45: 45845 | G45: G. C. Foods Pvt. Ltd. | H45: Debtors - GCF | I45: INR | J45: 921030030087773 - Axis Bank Ltd. CC Bihar - GCF | K45: INR | L45: 51215 | M45: 1 | N45: 51215 | O45: 51215 | P45: 1 | Q45: 51215 | R45: Approved | S45: Initiated | T45: NEFT/RTGS | U45: Customer | V45: M/s Govind Kirana ,Sevaipati | W45: Govind Kirana, Sevaipati | X45: 0 | Y45: 0 | Z45: AXIS BANK 921030030087773 - BIHAR | AB45: M/s Govind Kirana ,Sevaipati-M/s Govind Kirana ,Sevaipati | AD45: -51217 | AE45: Receivable | AF45: -51217 | AG45: Bank | AH45: -18819204 | AI45: 51215 | AJ45: 51215 | AK45: 51215 | AL45: 51215 | AM45: 0 | AN45: 0 | AO45: 51215 | AP45: 0 | AS45: 0 | AU45: 0 | AV45: 0 | AW45: GC Foods Muzaffarpur-Billing | AX45: 10AACCG2244H1Z9 | AY45: 10-Bihar | AZ45: M/s Govind Kirana ,Sevaipati-Billing | BA45: 10COKPK3572F1Z6 | BB45: Registered Regular | BC45: N/A | BD45: 45845 | BG45: Muzaffarpur | BI45: Cancelled | BJ45: 0 | BK45: Amount INR 51215 received from M/s Govind Kirana ,Sevaipati Transaction reference no N/A dated 2025-07-07 | BL45: INR Fifty One Thousand, Two Hundred And Fifteen only. | BM45: No | BP45: AXIS BANK | BQ45: 921030030087773 | BS45: INR Fifty One Thousand, Two Hundred And Fifteen only. | BU45: M/s Govind Kirana ,Sevaipati
A46: PAY/M/25-26/0756 | B46: PAY/M/25-26/0756-1 | C46: =VLOOKUP(A46,'Old Status'!B:C,2,0) -> Cancelled | D46: PAY/G/23-24/.#### | E46: Receive | F46: 45843 | G46: G. C. Foods Pvt. Ltd. | H46: Debtors - GCF | I46: INR | J46: 921030030087773 - Axis Bank Ltd. CC Bihar - GCF | K46: INR | L46: 500000 | M46: 1 | N46: 500000 | O46: 500000 | P46: 1 | Q46: 500000 | R46: Approved | S46: Initiated | T46: NEFT/RTGS | U46: Customer | V46: G.C.Wilmar Private Limited | W46: GC Wilmar Private Limited | X46: 0 | Y46: 0 | Z46: AXIS BANK 921030030087773 - BIHAR | AB46: G.C.Wilmar Private Limited-G.C.Wilmar Private Limited | AD46: -27318300 | AE46: Receivable | AF46: -27318300 | AG46: Bank | AH46: -19160701 | AI46: 500000 | AJ46: 500000 | AK46: 500000 | AL46: 500000 | AM46: 0 | AN46: 0 | AO46: 500000 | AP46: 0 | AS46: 0 | AU46: 0 | AV46: 0 | AW46: GC Foods Muzaffarpur-Billing | AX46: 10AACCG2244H1Z9 | AY46: 10-Bihar | AZ46: G.C.Wilmar Private Limited-Billing | BA46: 10AAICG5386J1ZH | BB46: Registered Regular | BC46: N/A | BD46: 45843 | BG46: Muzaffarpur | BI46: Cancelled | BJ46: 0 | BK46: Amount INR 500000 received from G.C.Wilmar Private Limited Transaction reference no N/A dated 2025-07-05 | BL46: INR Five Lakh only. | BM46: No | BP46: AXIS BANK | BQ46: 921030030087773 | BS46: INR Five Lakh only. | BU46: G.C.Wilmar Private Limited
A47: PAY/M/25-26/0746 | B47: PAY/M/25-26/0746-1 | C47: =VLOOKUP(A47,'Old Status'!B:C,2,0) -> Cancelled | D47: PAY/G/23-24/.#### | E47: Receive | F47: 45842 | G47: G. C. Foods Pvt. Ltd. | H47: Debtors - GCF | I47: INR | J47: 923020053773708 - Axis Bank - Bihar - GCF | K47: INR | L47: 50000 | M47: 1 | N47: 50000 | O47: 50000 | P47: 1 | Q47: 50000 | R47: Approved | S47: Initiated | T47: NEFT/RTGS | U47: Customer | V47: G.C.Wilmar Private Limited | W47: GC Wilmar Private Limited | X47: 0 | Y47: 0 | Z47: AXIS BANK 923020053773708 - BIHAR | AB47: G.C.Wilmar Private Limited-G.C.Wilmar Private Limited | AD47: -31295776 | AE47: Receivable | AF47: -31295776 | AG47: Bank | AH47: 606.45 | AI47: 50000 | AJ47: 50000 | AK47: 50000 | AL47: 50000 | AM47: 0 | AN47: 0 | AO47: 50000 | AP47: 0 | AS47: 0 | AU47: 0 | AV47: 0 | AW47: GC Foods Muzaffarpur-Billing | AX47: 10AACCG2244H1Z9 | AY47: 10-Bihar | AZ47: G.C.Wilmar Private Limited-Billing | BA47: 10AAICG5386J1ZH | BB47: Registered Regular | BC47: N/A | BD47: 45842 | BG47: Muzaffarpur | BI47: Cancelled | BJ47: 0 | BK47: Amount INR 50000 received from G.C.Wilmar Private Limited Transaction reference no N/A dated 2025-07-04 | BL47: INR Fifty Thousand only. | BM47: No | BP47: AXIS BANK | BQ47: 923020053773708 | BS47: INR Fifty Thousand only. | BU47: G.C.Wilmar Private Limited
A48: PAY/G/25-26/1185 | B48: PAY/G/25-26/1185-1 | C48: =VLOOKUP(A48,'Old Status'!B:C,2,0) -> Cancelled | D48: PAY/G/23-24/.#### | E48: Pay | F48: 45842 | G48: G. C. Foods Pvt. Ltd. | H48: 9210300223943516 - Axis Bank Ltd. CC Tronica - GCF | I48: INR | J48: Creditors - GCF | K48: INR | L48: 30000 | M48: 1 | N48: 30000 | O48: 30000 | P48: 1 | Q48: 30000 | R48: Approved | S48: Initiated | T48: NEFT/RTGS | U48: Supplier | V48: Suspense A/c | W48: Suspense A/c | X48: 0 | Y48: 0 | Z48: AXIS BANK 921030023943516 - GZB | AD48: 0 | AE48: Bank | AF48: -52189519 | AG48: Payable | AH48: 68175945 | AI48: 30000 | AJ48: 30000 | AK48: 30000 | AL48: 30000 | AM48: 0 | AN48: 0 | AO48: 30000 | AP48: 0 | AS48: 0 | AU48: 0 | AV48: 0 | AW48: G.C. Foods Pvt. Ltd.Ghaziabad - Uttar Pradesh-Billing | AX48: 09AACCG2244H1ZS | BC48: N/A | BD48: 45842 | BG48: Ghaziabad | BI48: Cancelled | BJ48: 0 | BK48: Amount INR 30000 to Suspense A/c Transaction reference no N/A dated 2025-07-04 | BL48: INR Thirty Thousand only. | BM48: No | BP48: AXIS BANK | BQ48: 921030023943516 | BS48: INR Thirty Thousand only. | BU48: Suspense A/c
A49: PAY/M/25-26/0727 | B49: PAY/M/25-26/0727-1 | C49: =VLOOKUP(A49,'Old Status'!B:C,2,0) -> Cancelled | D49: PAY/G/23-24/.#### | E49: Receive | F49: 45841 | G49: G. C. Foods Pvt. Ltd. | H49: Debtors - GCF | I49: INR | J49: 9210300223943516 - Axis Bank Ltd. CC Tronica - GCF | K49: INR | L49: 50841 | M49: 1 | N49: 50841 | O49: 50841 | P49: 1 | Q49: 50841 | R49: Approved | S49: Initiated | T49: NEFT/RTGS | U49: Customer | V49: Ansh Trading Madhubani | W49: Ansh Trading Madhubani | X49: 0 | Y49: 0 | Z49: AXIS BANK 921030030087773 - BIHAR | AB49: Ans Trading Madhubani-Ans Trading Madhubani | AD49: -383250 | AE49: Receivable | AF49: -383250 | AG49: Bank | AH49: -52907658 | AI49: 50841 | AJ49: 50841 | AK49: 50841 | AL49: 50841 | AM49: 0 | AN49: 0 | AO49: 50841 | AP49: 0 | AS49: 0 | AU49: 0 | AV49: 0 | AW49: GC Foods Muzaffarpur-Billing | AX49: 10AACCG2244H1Z9 | AY49: 10-Bihar | AZ49: Ans Trading Madhubani-Billing | BA49: 10DNWPP5708L1ZF | BB49: Registered Regular | BC49: N/A | BD49: 45841 | BG49: Muzaffarpur | BI49: Cancelled | BJ49: 0 | BK49: Amount INR 50841 received from Ansh Trading Madhubani Transaction reference no N/A dated 2025-07-03 | BL49: INR Fifty Thousand, Eight Hundred And Forty One only. | BM49: No | BP49: AXIS BANK | BQ49: 921030030087773 | BS49: INR Fifty Thousand, Eight Hundred And Forty One only. | BU49: Ansh Trading Madhubani
A50: PAY/G/25-26/1178 | B50: PAY/G/25-26/1178-1 | C50: =VLOOKUP(A50,'Old Status'!B:C,2,0) -> Cancelled | D50: PAY/G/23-24/.#### | E50: Receive | F50: 45841 | G50: G. C. Foods Pvt. Ltd. | H50: Debtors - GCF | I50: INR | J50: 9210300223943516 - Axis Bank Ltd. CC Tronica - GCF | K50: INR | L50: 83295 | M50: 1 | N50: 83295 | O50: 83295 | P50: 1 | Q50: 83295 | R50: Approved | S50: Initiated | T50: NEFT/RTGS | U50: Customer | V50: RRR Traders | W50: RRR Traders | X50: 0 | Y50: 0 | Z50: AXIS BANK 921030023943516 - GZB | AD50: 3315 | AE50: Receivable | AF50: 3315 | AG50: Bank | AH50: -52900399 | AI50: 83295 | AJ50: 83295 | AK50: 83295 | AL50: 83295 | AM50: 0 | AN50: 0 | AO50: 83295 | AP50: 0 | AS50: 0 | AU50: 0 | AV50: 0 | AW50: G.C. Foods Pvt. Ltd.Ghaziabad - Uttar Pradesh-Billing | AX50: 09AACCG2244H1ZS | AY50: 09-Uttar Pradesh | AZ50: RRR Traders-Billing | BA50: 09ABEFR8587N1Z4 | BB50: Registered Regular | BC50: N/A | BD50: 45841 | BG50: Ghaziabad | BI50: Cancelled | BJ50: 0 | BK50: Amount INR 83295 received from RRR Traders Transaction reference no N/A dated 2025-07-03 | BL50: INR Eighty Three Thousand, Two Hundred And Ninety Five only. | BM50: No | BP50: AXIS BANK | BQ50: 921030023943516 | BS50: INR Eighty Three Thousand, Two Hundred And Ninety Five only. | BU50: RRR Traders
