Workbook

Sheet Purchase Invoice Raw
A1: Amended From | B1: ID | C1: Series | D1: Supplier | E1: Date | F1: Branch | G1: Credit To | H1: Title | I1: Supplier Name | J1: e-Waybill No. | K1: Tax Id | L1: Company | M1: Posting Time | N1: Edit Posting Date and Time | O1: Due Date | P1: Purchase Order Type | Q1: Is Paid | R1: Is Return (Debit Note) | S1: Return Against Purchase Invoice | T1: Update Outstanding for Self | U1: Update Billed Amount in Purchase Order | V1: Update Billed Amount in Purchase Receipt | W1: Apply Tax Withholding Amount | X1: Is Reverse Charge | Y1: Tax Withholding Category | Z1: Supplier Invoice No | AA1: Supplier Invoice Date | AB1: Cost Center | AC1: Project | AD1: Currency | AE1: Exchange Rate | AF1: Use Transaction Date Exchange Rate | AG1: Price List | AH1: Price List Currency | AI1: Price List Exchange Rate | AJ1: Ignore Pricing Rule | AK1: Scan Barcode | AL1: Update Stock | AM1: Set Accepted Warehouse | AN1: Set From Warehouse | AO1: Is Subcontracted | AP1: Rejected Warehouse | AQ1: Supplier Warehouse | AR1: Total Quantity | AS1: Total Net Weight | AT1: Total (Company Currency) | AU1: Net Total (Company Currency) | AV1: Total | AW1: Net Total | AX1: Tax Withholding Net Total | AY1: Base Tax Withholding Net Total | AZ1: Tax Category | BA1: Purchase Taxes and Charges Template | BB1: Shipping Rule | BC1: Incoterm | BD1: Named Place | BE1: Taxes and Charges Added (Company Currency) | BF1: Taxes and Charges Deducted (Company Currency) | BG1: Total Taxes and Charges (Company Currency) | BH1: Taxes and Charges Added | BI1: Taxes and Charges Deducted | BJ1: Total Taxes and Charges | BK1: Grand Total (Company Currency) | BL1: Rounding Adjustment (Company Currency) | BM1: Rounded Total (Company Currency) | BN1: In Words (Company Currency) | BO1: Grand Total | BP1: Rounding Adjustment | BQ1: Use Company Default Round Off Cost Center | BR1: Rounded Total | BS1: In Words | BT1: Total Advance | BU1: Outstanding Amount | BV1: Disable Rounded Total | BW1: Apply Additional Discount On | BX1: Additional Discount Amount (Company Currency) | BY1: Additional Discount Percentage | BZ1: Additional Discount Amount | CA1: Taxes and Charges Calculation | CB1: Mode of Payment | CC1: Paid Amount (Company Currency) | CD1: Clearance Date | CE1: Cash/Bank Account | CF1: Paid Amount | CG1: Set Advances and Allocate (FIFO) | CH1: Only Include Allocated Payments | CI1: Write Off Amount | CJ1: Write Off Amount (Company Currency) | CK1: Write Off Account | CL1: Write Off Cost Center | CM1: Select Supplier Address | CN1: Address | CO1: Supplier GSTIN | CP1: GST Category | CQ1: Contact Person | CR1: Contact | CS1: Mobile No | CT1: Contact Email | CU1: Select Dispatch Address | CV1: Dispatch Address | CW1: Select Shipping Address | CX1: Shipping Address | CY1: Select Billing Address | CZ1: Billing Address | DA1: Company GSTIN | DB1: Place of Supply | DC1: Payment Terms Template | DD1: Ignore Default Payment Terms Template | DE1: Terms | DF1: Terms and Conditions | DG1: Per Received | DH1: Party Account Currency | DI1: Is Opening Entry | DJ1: Against Expense Account | DK1: Unrealized Profit / Loss Account | DL1: Subscription | DM1: Auto Repeat | DN1: From Date | DO1: To Date | DP1: Letter Head | DQ1: Group same items | DR1: Print Heading | DS1: Print Language | DT1: Transporter | DU1: GST Transporter ID | DV1: Driver | DW1: Transport Receipt No | DX1: Vehicle No | DY1: Distance (in km) | DZ1: Transporter Name | EA1: Mode of Transport | EB1: Driver Name | EC1: Transport Receipt Date | ED1: GST Vehicle Type | EE1: ITC Classification | EF1: Reason for Ineligibility | EG1: Reconciliation Status | EH1: Hold Invoice | EI1: Release Date | EJ1: Reason For Putting On Hold | EK1: Is Internal Supplier | EL1: Represents Company | EM1: Supplier Group | EN1: Inter Company Invoice Reference | EO1: Is Old Subcontracting Flow | EP1: Remarks | EQ1: ID (Items) | ER1: Accepted Qty (Items) | ES1: Accepted Qty in Stock UOM (Items) | ET1: Amount (Items) | EU1: Amount (Company Currency) (Items) | EV1: Item Name (Items) | EW1: Rate (Items) | EX1: Rate (Company Currency) (Items) | EY1: UOM (Items) | EZ1: UOM Conversion Factor (Items) | FA1: Accepted Warehouse (Items) | FB1: Allow Zero Valuation Rate (Items) | FC1: Apply TDS (Items) | FD1: Asset Category (Items) | FE1: Asset Location (Items) | FF1: Batch No (Items) | FG1: BOM (Items) | FH1: Brand (Items) | FI1: CESS Amount (Items) | FJ1: CESS Non Advol Amount (Items) | FK1: CESS Non Advol Rate (Items) | FL1: CESS Rate (Items) | FM1: CGST Amount (Items) | FN1: CGST Rate (Items) | FO1: Cost Center (Items) | FP1: Deferred Expense Account (Items) | FQ1: Description (Items) | FR1: Discount Amount (Items) | FS1: Discount on Price List Rate (%) (Items) | FT1: Distributed Discount Amount (Items) | FU1: Enable Deferred Expense (Items) | FV1: Expense Head (Items) | FW1: From Warehouse (Items) | FX1: GST Treatment (Items) | FY1: HSN/SAC (Items) | FZ1: IGST Amount (Items) | GA1: IGST Rate (Items) | GB1: Image (Items) | GC1: Include Exploded Items (Items) | GD1: Is Fixed Asset (Items) | GE1: Is Free Item (Items) | GF1: Is Ineligible for Input Tax Credit (Items) | GG1: Item (Items) | GH1: Item Group (Items) | GI1: Item Tax Amount Included in Value (Items) | GJ1: Item Tax Rate (Items) | GK1: Item Tax Template (Items) | GL1: Landed Cost Voucher Amount (Items) | GM1: Manufacturer (Items) | GN1: Manufacturer Part Number (Items) | GO1: Margin Rate or Amount (Items) | GP1: Margin Type (Items) | GQ1: Material Request (Items) | GR1: Material Request Item (Items) | GS1: Net Amount (Items) | GT1: Net Amount (Company Currency) (Items) | GU1: Net Rate (Items) | GV1: Net Rate (Company Currency) (Items) | GW1: Page Break (Items) | GX1: Pending BOE Qty (Items) | GY1: Price List Rate (Items) | GZ1: Price List Rate (Company Currency) (Items) | HA1: Pricing Rules (Items) | HB1: Product Bundle (Items) | HC1: Project (Items) | HD1: Purchase Invoice Item (Items) | HE1: Purchase Order (Items) | HF1: Purchase Order Item (Items) | HG1: Purchase Receipt (Items) | HH1: Purchase Receipt Detail (Items) | HI1: Quality Inspection (Items) | HJ1: Rate of Stock UOM (Items) | HK1: Rate With Margin (Items) | HL1: Rate With Margin (Company Currency) (Items) | HM1: Raw Materials Supplied Cost (Items) | HN1: Received Qty (Items) | HO1: Rejected Branch (Items) | HP1: Rejected Qty (Items) | HQ1: Rejected Serial and Batch Bundle (Items) | HR1: Rejected Serial No (Items) | HS1: Rejected Warehouse (Items) | HT1: Sales Incoming Rate (Items) | HU1: Sales Invoice Item (Items) | HV1: Serial and Batch Bundle (Items) | HW1: Serial No (Items) | HX1: Service End Date (Items) | HY1: Service Start Date (Items) | HZ1: Service Stop Date (Items) | IA1: SGST Amount (Items) | IB1: SGST Rate (Items) | IC1: Source Branch (Items) | ID1: Stock UOM (Items) | IE1: Target Branch (Items) | IF1: Taxable Value (Items) | IG1: Total Weight (Items) | IH1: Use Serial No / Batch Fields (Items) | II1: Valuation Rate (Items) | IJ1: Weight Per Unit (Items) | IK1: Weight UOM (Items) | IL1: WIP Composite Asset (Items) | IM1: ID (Purchase Taxes and Charges) | IN1: Account Currency (Purchase Taxes and Charges) | IO1: Account Head (Purchase Taxes and Charges) | IP1: Add or Deduct (Purchase Taxes and Charges) | IQ1: Amount (Purchase Taxes and Charges) | IR1: Amount (Company Currency) (Purchase Taxes and Charges) | IS1: Branch (Purchase Taxes and Charges) | IT1: Consider Tax or Charge for (Purchase Taxes and Charges) | IU1: Considered In Paid Amount (Purchase Taxes and Charges) | IV1: Cost Center (Purchase Taxes and Charges) | IW1: Description (Purchase Taxes and Charges) | IX1: GST Tax Type (Purchase Taxes and Charges) | IY1: Is Tax Withholding Account (Purchase Taxes and Charges) | IZ1: Is this Tax included in Basic Rate? (Purchase Taxes and Charges) | JA1: Item Wise Tax Detail (Purchase Taxes and Charges) | JB1: Reference Row # (Purchase Taxes and Charges) | JC1: Tax Amount After Discount Amount (Purchase Taxes and Charges) | JD1: taxes.base_tax_amount_after_discount_amount | JE1: Tax Rate (Purchase Taxes and Charges) | JF1: Total (Purchase Taxes and Charges) | JG1: Total (Company Currency) (Purchase Taxes and Charges) | JH1: Type (Purchase Taxes and Charges) | JI1: ID (Tax Withheld Vouchers) | JJ1: Taxable Amount (Tax Withheld Vouchers) | JK1: Voucher Name (Tax Withheld Vouchers) | JL1: Voucher Type (Tax Withheld Vouchers) | JM1: ID (Pricing Rule Detail) | JN1: Child Docname (Pricing Rule Detail) | JO1: Item Code (Pricing Rule Detail) | JP1: Margin Type (Pricing Rule Detail) | JQ1: Pricing Rule (Pricing Rule Detail) | JR1: Rate or Discount (Pricing Rule Detail) | JS1: Rule Applied (Pricing Rule Detail) | JT1: ID (Supplied Items) | JU1: Amount (Supplied Items) | JV1: Available Qty For Consumption (Supplied Items) | JW1: Batch No (Supplied Items) | JX1: BOM Detail No (Supplied Items) | JY1: Branch (Supplied Items) | JZ1: Conversion Factor (Supplied Items) | KA1: Current Stock (Supplied Items) | KB1: Description (Supplied Items) | KC1: Item Code (Supplied Items) | KD1: Item Name (Supplied Items) | KE1: Purchase Order (Supplied Items) | KF1: Qty to Be Consumed (Supplied Items) | KG1: Rate (Supplied Items) | KH1: Raw Material Item Code (Supplied Items) | KI1: Reference Name (Supplied Items) | KJ1: Serial No (Supplied Items) | KK1: Stock Uom (Supplied Items) | KL1: ID (Advances) | KM1: Advance Amount (Advances) | KN1: Allocated Amount (Advances) | KO1: Difference Posting Date (Advances) | KP1: Exchange Gain/Loss (Advances) | KQ1: Reference Exchange Rate (Advances) | KR1: Reference Name (Advances) | KS1: Reference Row (Advances) | KT1: Reference Type (Advances) | KU1: Remarks (Advances) | KV1: ID (Advance Tax) | KW1: Account Head (Advance Tax) | KX1: Allocated Amount (Advance Tax) | KY1: Reference Detail (Advance Tax) | KZ1: Reference Name (Advance Tax) | LA1: Reference Type (Advance Tax) | LB1: ID (Payment Schedule) | LC1: Description (Payment Schedule) | LD1: Discount (Payment Schedule) | LE1: Discount Date (Payment Schedule) | LF1: Discount Type (Payment Schedule) | LG1: Discounted Amount (Payment Schedule) | LH1: Due Date (Payment Schedule) | LI1: Invoice Portion (Payment Schedule) | LJ1: Mode of Payment (Payment Schedule) | LK1: Outstanding (Payment Schedule) | LL1: Outstanding (Company Currency) (Payment Schedule) | LM1: Paid Amount (Payment Schedule) | LN1: Paid Amount (Company Currency) (Payment Schedule) | LO1: Payment Amount (Payment Schedule) | LP1: Payment Amount (Company Currency) (Payment Schedule) | LQ1: Payment Term (Payment Schedule)
A2: PI/G/25-26/0202 | B2: PI/G/25-26/0202-1 | C2: PINV-.YY.- | D2: Freight Outward Non TDS | E2: 45759 | F2: Ghaziabad | G2: Creditors - GCF | H2: Freight Outward Non TDS | I2: Freight Outward Non TDS | L2: G. C. Foods Pvt. Ltd. | M2: 0.63431713 | N2: 1 | O2: 45759 | Q2: 0 | R2: 0 | T2: 1 | U2: 0 | V2: 1 | W2: 0 | X2: 1 | AD2: INR | AE2: 1 | AF2: 1 | AG2: Standard Buying | AH2: INR | AI2: 1 | AJ2: 0 | AL2: 0 | AO2: 0 | AR2: 1 | AS2: 0 | AT2: 40000 | AU2: 40000 | AV2: 40000 | AW2: 40000 | AX2: 40000 | AY2: 40000 | BA2: Input GST RCM In-state - GCF | BE2: 2000 | BF2: 2000 | BG2: 0 | BH2: 2000 | BI2: 2000 | BJ2: 0 | BK2: 40000 | BL2: 0 | BM2: 0 | BN2: INR Forty Thousand only. | BO2: 40000 | BP2: 0 | BQ2: 0 | BR2: 0 | BS2: INR Forty Thousand only. | BT2: 0 | BU2: 40000 | BV2: 1 | BW2: Grand Total | BX2: 0 | BY2: 0 | BZ2: 0 | CA2: | HSN/SAC | Taxable Amount | Input Tax CGST @ 9.0 | Input Tax SGST @ 9.0 | Input Tax CGST RCM @ 9.0 | Input Tax SGST RCM @ 9.0 | | --- | --- | --- | --- | --- | --- | | 996511 | ₹ 40,000.00 | (2.5%) ₹ 1,000.00 | (2.5%) ₹ 1,000.00 | (2.5%) ₹ 1,000.00 | (2.5%) ₹ 1,000.00 | | CC2: 0 | CF2: 0 | CG2: 0 | CH2: 0 | CI2: 0 | CJ2: 0 | CP2: Unregistered | CW2: G.C. Foods Pvt. Ltd.Ghaziabad - Uttar Pradesh-Billing | CX2: C-4, Sector A-2, , Tronica city Indl. Area, LoniGhaziabad, Uttar Pradesh, State Code: 09, Pincode: 201103, India, Phone: 9350041990, GSTIN: 09AACCG2244H1ZS, | CY2: G.C. Foods Pvt. Ltd.Ghaziabad - Uttar Pradesh-Billing | CZ2: C-4, Sector A-2, , Tronica city Indl. Area, LoniGhaziabad, Uttar Pradesh, State Code: 09, Pincode: 201103, India, Phone: 9350041990, GSTIN: 09AACCG2244H1ZS, | DA2: 09AACCG2244H1ZS | DB2: 09-Uttar Pradesh | DD2: 0 | DG2: 0 | DH2: INR | DI2: No | DJ2: Freight Outward - GCF | DP2: GCF Letterhead | DQ2: 0 | DS2: en | DY2: 0 | EA2: Road | EC2: 45869 | ED2: Regular | EE2: ITC on Reverse Charge | EG2: Not Applicable | EH2: 0 | EK2: 0 | EM2: Creditors (Transport) | EO2: 0 | EP2: No Remarks | ER2: 1 | ES2: 1 | ET2: 40000 | EU2: 40000 | EV2: Freight Outward - GCF | EW2: 40000 | EX2: 40000 | EY2: Unit | EZ2: 1 | FB2: 0 | FC2: 1 | FI2: 0 | FJ2: 0 | FK2: 0 | FL2: 0 | FM2: 1000 | FN2: 2.5 | FO2: Main - GCF | FQ2: Freight Outward | FR2: 0 | FS2: 0 | FT2: 0 | FU2: 0 | FV2: Freight Outward - GCF | FX2: Taxable | FY2: 996511 | FZ2: 0 | GA2: 0 | GC2: 0 | GD2: 0 | GE2: 0 | GF2: 0 | GG2: Freight Outward - GCF | GH2: Services | GI2: 0 | GJ2: {"Output Tax SGST - GCF": 2.5, "Output Tax CGST - GCF": 2.5, "Output Tax IGST - GCF": 5.0, "Input Tax SGST - GCF": 2.5, "Input Tax CGST - GCF": 2.5, "Input Tax IGST - GCF": 5.0, "Input Tax SGST RCM - GCF": 2.5, "Input Tax CGST RCM - GCF": 2.5, "Input Tax IGST RCM - GCF": 5.0} | GK2: GST 5% - GCF | GL2: 0 | GO2: 0 | GS2: 40000 | GT2: 40000 | GU2: 40000 | GV2: 40000 | GW2: 0 | GX2: 1 | GY2: 0 | GZ2: 0 | HJ2: 40000 | HK2: 0 | HL2: 0 | HM2: 0 | HN2: 0 | HP2: 0 | HT2: 0 | IA2: 1000 | IB2: 2.5 | ID2: Unit | IE2: Ghaziabad | IF2: 40000 | IG2: 0 | IH2: 0 | II2: 0 | IJ2: 0 | IN2: INR | IO2: Input Tax CGST - GCF | IP2: Add | IQ2: 1000 | IR2: 1000 | IT2: Total | IU2: 0 | IV2: Main - GCF | IW2: Input Tax CGST @ 9.0 | IX2: cgst | IY2: 0 | IZ2: 0 | JA2: {"Freight Outward - GCF":[2.5,1000.0]} | JC2: 1000 | JD2: 1000 | JE2: 0 | JF2: 41000 | JG2: 41000 | JH2: On Net Total | LD2: 0 | LG2: 0 | LH2: 45759 | LI2: 100 | LK2: 40000 | LL2: 40000 | LM2: 0 | LN2: 0 | LO2: 40000 | LP2: 40000
IN3: INR | IO3: Input Tax SGST - GCF | IP3: Add | IQ3: 1000 | IR3: 1000 | IT3: Total | IU3: 0 | IV3: Main - GCF | IW3: Input Tax SGST @ 9.0 | IX3: sgst | IY3: 0 | IZ3: 0 | JA3: {"Freight Outward - GCF":[2.5,1000.0]} | JC3: 1000 | JD3: 1000 | JE3: 0 | JF3: 42000 | JG3: 42000 | JH3: On Net Total
IN4: INR | IO4: Input Tax CGST RCM - GCF | IP4: Deduct | IQ4: 1000 | IR4: 1000 | IT4: Total | IU4: 0 | IV4: Main - GCF | IW4: Input Tax CGST RCM @ 9.0 | IX4: cgst_rcm | IY4: 0 | IZ4: 0 | JA4: {"Freight Outward - GCF":[2.5,1000.0]} | JC4: 1000 | JD4: 1000 | JE4: 0 | JF4: 41000 | JG4: 41000 | JH4: On Net Total
IN5: INR | IO5: Input Tax SGST RCM - GCF | IP5: Deduct | IQ5: 1000 | IR5: 1000 | IT5: Total | IU5: 0 | IV5: Main - GCF | IW5: Input Tax SGST RCM @ 9.0 | IX5: sgst_rcm | IY5: 0 | IZ5: 0 | JA5: {"Freight Outward - GCF":[2.5,1000.0]} | JC5: 1000 | JD5: 1000 | JE5: 0 | JF5: 40000 | JG5: 40000 | JH5: On Net Total
A6: PI/G/25-26/0201 | B6: PI/G/25-26/0201-1 | C6: PINV-.YY.- | D6: Freight Outward Non TDS | E6: 45749 | F6: Ghaziabad | G6: Creditors - GCF | H6: Freight Outward Non TDS | I6: Freight Outward Non TDS | L6: G. C. Foods Pvt. Ltd. | M6: 0.63162037 | N6: 1 | O6: 45749 | Q6: 0 | R6: 0 | T6: 1 | U6: 0 | V6: 1 | W6: 0 | X6: 1 | AD6: INR | AE6: 1 | AF6: 1 | AG6: Standard Buying | AH6: INR | AI6: 1 | AJ6: 0 | AL6: 0 | AO6: 0 | AR6: 1 | AS6: 0 | AT6: 50000 | AU6: 50000 | AV6: 50000 | AW6: 50000 | AX6: 50000 | AY6: 50000 | BA6: Input GST RCM In-state - GCF | BE6: 2500 | BF6: 2500 | BG6: 0 | BH6: 2500 | BI6: 2500 | BJ6: 0 | BK6: 50000 | BL6: 0 | BM6: 0 | BN6: INR Fifty Thousand only. | BO6: 50000 | BP6: 0 | BQ6: 0 | BR6: 0 | BS6: INR Fifty Thousand only. | BT6: 0 | BU6: 50000 | BV6: 1 | BW6: Grand Total | BX6: 0 | BY6: 0 | BZ6: 0 | CA6: | HSN/SAC | Taxable Amount | Input Tax CGST @ 9.0 | Input Tax SGST @ 9.0 | Input Tax CGST RCM @ 9.0 | Input Tax SGST RCM @ 9.0 | | --- | --- | --- | --- | --- | --- | | 996511 | ₹ 50,000.00 | (2.5%) ₹ 1,250.00 | (2.5%) ₹ 1,250.00 | (2.5%) ₹ 1,250.00 | (2.5%) ₹ 1,250.00 | | CC6: 0 | CF6: 0 | CG6: 0 | CH6: 0 | CI6: 0 | CJ6: 0 | CP6: Unregistered | CW6: G.C. Foods Pvt. Ltd.Ghaziabad - Uttar Pradesh-Billing | CX6: C-4, Sector A-2, , Tronica city Indl. Area, LoniGhaziabad, Uttar Pradesh, State Code: 09, Pincode: 201103, India, Phone: 9350041990, GSTIN: 09AACCG2244H1ZS, | CY6: G.C. Foods Pvt. Ltd.Ghaziabad - Uttar Pradesh-Billing | CZ6: C-4, Sector A-2, , Tronica city Indl. Area, LoniGhaziabad, Uttar Pradesh, State Code: 09, Pincode: 201103, India, Phone: 9350041990, GSTIN: 09AACCG2244H1ZS, | DA6: 09AACCG2244H1ZS | DB6: 09-Uttar Pradesh | DD6: 0 | DG6: 0 | DH6: INR | DI6: No | DJ6: Freight Outward - GCF | DP6: GCF Letterhead | DQ6: 0 | DS6: en | DY6: 0 | EA6: Road | EC6: 45869 | ED6: Regular | EE6: ITC on Reverse Charge | EG6: Not Applicable | EH6: 0 | EK6: 0 | EM6: Creditors (Transport) | EO6: 0 | EP6: No Remarks | ER6: 1 | ES6: 1 | ET6: 50000 | EU6: 50000 | EV6: Freight Outward - GCF | EW6: 50000 | EX6: 50000 | EY6: Unit | EZ6: 1 | FB6: 0 | FC6: 1 | FI6: 0 | FJ6: 0 | FK6: 0 | FL6: 0 | FM6: 1250 | FN6: 2.5 | FO6: Main - GCF | FQ6: Freight Outward | FR6: 0 | FS6: 0 | FT6: 0 | FU6: 0 | FV6: Freight Outward - GCF | FX6: Taxable | FY6: 996511 | FZ6: 0 | GA6: 0 | GC6: 0 | GD6: 0 | GE6: 0 | GF6: 0 | GG6: Freight Outward - GCF | GH6: Services | GI6: 0 | GJ6: {"Output Tax SGST - GCF": 2.5, "Output Tax CGST - GCF": 2.5, "Output Tax IGST - GCF": 5.0, "Input Tax SGST - GCF": 2.5, "Input Tax CGST - GCF": 2.5, "Input Tax IGST - GCF": 5.0, "Input Tax SGST RCM - GCF": 2.5, "Input Tax CGST RCM - GCF": 2.5, "Input Tax IGST RCM - GCF": 5.0} | GK6: GST 5% - GCF | GL6: 0 | GO6: 0 | GS6: 50000 | GT6: 50000 | GU6: 50000 | GV6: 50000 | GW6: 0 | GX6: 1 | GY6: 0 | GZ6: 0 | HJ6: 50000 | HK6: 0 | HL6: 0 | HM6: 0 | HN6: 0 | HP6: 0 | HT6: 0 | IA6: 1250 | IB6: 2.5 | ID6: Unit | IE6: Ghaziabad | IF6: 50000 | IG6: 0 | IH6: 0 | II6: 0 | IJ6: 0 | IN6: INR | IO6: Input Tax CGST - GCF | IP6: Add | IQ6: 1250 | IR6: 1250 | IT6: Total | IU6: 0 | IV6: Main - GCF | IW6: Input Tax CGST @ 9.0 | IX6: cgst | IY6: 0 | IZ6: 0 | JA6: {"Freight Outward - GCF":[2.5,1250.0]} | JC6: 1250 | JD6: 1250 | JE6: 0 | JF6: 51250 | JG6: 51250 | JH6: On Net Total | LD6: 0 | LG6: 0 | LH6: 45749 | LI6: 100 | LK6: 50000 | LL6: 50000 | LM6: 0 | LN6: 0 | LO6: 50000 | LP6: 50000
IN7: INR | IO7: Input Tax SGST - GCF | IP7: Add | IQ7: 1250 | IR7: 1250 | IT7: Total | IU7: 0 | IV7: Main - GCF | IW7: Input Tax SGST @ 9.0 | IX7: sgst | IY7: 0 | IZ7: 0 | JA7: {"Freight Outward - GCF":[2.5,1250.0]} | JC7: 1250 | JD7: 1250 | JE7: 0 | JF7: 52500 | JG7: 52500 | JH7: On Net Total
IN8: INR | IO8: Input Tax CGST RCM - GCF | IP8: Deduct | IQ8: 1250 | IR8: 1250 | IT8: Total | IU8: 0 | IV8: Main - GCF | IW8: Input Tax CGST RCM @ 9.0 | IX8: cgst_rcm | IY8: 0 | IZ8: 0 | JA8: {"Freight Outward - GCF":[2.5,1250.0]} | JC8: 1250 | JD8: 1250 | JE8: 0 | JF8: 51250 | JG8: 51250 | JH8: On Net Total
IN9: INR | IO9: Input Tax SGST RCM - GCF | IP9: Deduct | IQ9: 1250 | IR9: 1250 | IT9: Total | IU9: 0 | IV9: Main - GCF | IW9: Input Tax SGST RCM @ 9.0 | IX9: sgst_rcm | IY9: 0 | IZ9: 0 | JA9: {"Freight Outward - GCF":[2.5,1250.0]} | JC9: 1250 | JD9: 1250 | JE9: 0 | JF9: 50000 | JG9: 50000 | JH9: On Net Total
A10: PI/G/25-26/0200 | B10: PI/G/25-26/0200-1 | C10: PINV-.YY.- | D10: Freight Outward Non TDS | E10: 45749 | F10: Ghaziabad | G10: Creditors - GCF | H10: Freight Outward Non TDS | I10: Freight Outward Non TDS | L10: G. C. Foods Pvt. Ltd. | M10: 0.61439815 | N10: 1 | O10: 45749 | Q10: 0 | R10: 0 | T10: 1 | U10: 0 | V10: 1 | W10: 0 | X10: 1 | AD10: INR | AE10: 1 | AF10: 1 | AG10: Standard Buying | AH10: INR | AI10: 1 | AJ10: 0 | AL10: 0 | AO10: 0 | AR10: 1 | AS10: 0 | AT10: 40000 | AU10: 40000 | AV10: 40000 | AW10: 40000 | AX10: 40000 | AY10: 40000 | BA10: Input GST RCM In-state - GCF | BE10: 2000 | BF10: 2000 | BG10: 0 | BH10: 2000 | BI10: 2000 | BJ10: 0 | BK10: 40000 | BL10: 0 | BM10: 0 | BN10: INR Forty Thousand only. | BO10: 40000 | BP10: 0 | BQ10: 0 | BR10: 0 | BS10: INR Forty Thousand only. | BT10: 0 | BU10: 40000 | BV10: 1 | BW10: Grand Total | BX10: 0 | BY10: 0 | BZ10: 0 | CA10: | HSN/SAC | Taxable Amount | Input Tax CGST @ 9.0 | Input Tax SGST @ 9.0 | Input Tax CGST RCM @ 9.0 | Input Tax SGST RCM @ 9.0 | | --- | --- | --- | --- | --- | --- | | 996511 | ₹ 40,000.00 | (2.5%) ₹ 1,000.00 | (2.5%) ₹ 1,000.00 | (2.5%) ₹ 1,000.00 | (2.5%) ₹ 1,000.00 | | CC10: 0 | CF10: 0 | CG10: 0 | CH10: 0 | CI10: 0 | CJ10: 0 | CP10: Unregistered | CW10: G.C. Foods Pvt. Ltd.Ghaziabad - Uttar Pradesh-Billing | CX10: C-4, Sector A-2, , Tronica city Indl. Area, LoniGhaziabad, Uttar Pradesh, State Code: 09, Pincode: 201103, India, Phone: 9350041990, GSTIN: 09AACCG2244H1ZS, | CY10: G.C. Foods Pvt. Ltd.Ghaziabad - Uttar Pradesh-Billing | CZ10: C-4, Sector A-2, , Tronica city Indl. Area, LoniGhaziabad, Uttar Pradesh, State Code: 09, Pincode: 201103, India, Phone: 9350041990, GSTIN: 09AACCG2244H1ZS, | DA10: 09AACCG2244H1ZS | DB10: 09-Uttar Pradesh | DD10: 0 | DG10: 0 | DH10: INR | DI10: No | DJ10: Freight Outward - GCF | DP10: GCF Letterhead | DQ10: 0 | DS10: en | DY10: 0 | EA10: Road | EC10: 45869 | ED10: Regular | EE10: ITC on Reverse Charge | EG10: Not Applicable | EH10: 0 | EK10: 0 | EM10: Creditors (Transport) | EO10: 0 | EP10: No Remarks | ER10: 1 | ES10: 1 | ET10: 40000 | EU10: 40000 | EV10: Freight Outward - GCF | EW10: 40000 | EX10: 40000 | EY10: Unit | EZ10: 1 | FB10: 0 | FC10: 1 | FI10: 0 | FJ10: 0 | FK10: 0 | FL10: 0 | FM10: 1000 | FN10: 2.5 | FO10: Main - GCF | FQ10: Freight Outward | FR10: 0 | FS10: 0 | FT10: 0 | FU10: 0 | FV10: Freight Outward - GCF | FX10: Taxable | FY10: 996511 | FZ10: 0 | GA10: 0 | GC10: 0 | GD10: 0 | GE10: 0 | GF10: 0 | GG10: Freight Outward - GCF | GH10: Services | GI10: 0 | GJ10: {"Output Tax SGST - GCF": 2.5, "Output Tax CGST - GCF": 2.5, "Output Tax IGST - GCF": 5.0, "Input Tax SGST - GCF": 2.5, "Input Tax CGST - GCF": 2.5, "Input Tax IGST - GCF": 5.0, "Input Tax SGST RCM - GCF": 2.5, "Input Tax CGST RCM - GCF": 2.5, "Input Tax IGST RCM - GCF": 5.0} | GK10: GST 5% - GCF | GL10: 0 | GO10: 0 | GS10: 40000 | GT10: 40000 | GU10: 40000 | GV10: 40000 | GW10: 0 | GX10: 1 | GY10: 0 | GZ10: 0 | HJ10: 40000 | HK10: 0 | HL10: 0 | HM10: 0 | HN10: 0 | HP10: 0 | HT10: 0 | IA10: 1000 | IB10: 2.5 | ID10: Unit | IE10: Ghaziabad | IF10: 40000 | IG10: 0 | IH10: 0 | II10: 0 | IJ10: 0 | IN10: INR | IO10: Input Tax CGST - GCF | IP10: Add | IQ10: 1000 | IR10: 1000 | IT10: Total | IU10: 0 | IV10: Main - GCF | IW10: Input Tax CGST @ 9.0 | IX10: cgst | IY10: 0 | IZ10: 0 | JA10: {"Freight Outward - GCF":[2.5,1000.0]} | JC10: 1000 | JD10: 1000 | JE10: 0 | JF10: 41000 | JG10: 41000 | JH10: On Net Total | LD10: 0 | LG10: 0 | LH10: 45749 | LI10: 100 | LK10: 40000 | LL10: 40000 | LM10: 0 | LN10: 0 | LO10: 40000 | LP10: 40000
IN11: INR | IO11: Input Tax SGST - GCF | IP11: Add | IQ11: 1000 | IR11: 1000 | IT11: Total | IU11: 0 | IV11: Main - GCF | IW11: Input Tax SGST @ 9.0 | IX11: sgst | IY11: 0 | IZ11: 0 | JA11: {"Freight Outward - GCF":[2.5,1000.0]} | JC11: 1000 | JD11: 1000 | JE11: 0 | JF11: 42000 | JG11: 42000 | JH11: On Net Total
IN12: INR | IO12: Input Tax CGST RCM - GCF | IP12: Deduct | IQ12: 1000 | IR12: 1000 | IT12: Total | IU12: 0 | IV12: Main - GCF | IW12: Input Tax CGST RCM @ 9.0 | IX12: cgst_rcm | IY12: 0 | IZ12: 0 | JA12: {"Freight Outward - GCF":[2.5,1000.0]} | JC12: 1000 | JD12: 1000 | JE12: 0 | JF12: 41000 | JG12: 41000 | JH12: On Net Total
IN13: INR | IO13: Input Tax SGST RCM - GCF | IP13: Deduct | IQ13: 1000 | IR13: 1000 | IT13: Total | IU13: 0 | IV13: Main - GCF | IW13: Input Tax SGST RCM @ 9.0 | IX13: sgst_rcm | IY13: 0 | IZ13: 0 | JA13: {"Freight Outward - GCF":[2.5,1000.0]} | JC13: 1000 | JD13: 1000 | JE13: 0 | JF13: 40000 | JG13: 40000 | JH13: On Net Total
A14: PI/M/25-26/0139 | B14: PI/M/25-26/0139-1 | C14: PINV-.YY.- | D14: Freight Outward Non TDS | E14: 45749 | F14: Muzaffarpur | G14: Creditors - GCF | H14: Freight Outward Non TDS | I14: Freight Outward Non TDS | L14: G. C. Foods Pvt. Ltd. | M14: 0.58376157 | N14: 1 | O14: 45749 | Q14: 0 | R14: 0 | T14: 1 | U14: 0 | V14: 1 | W14: 0 | X14: 1 | AD14: INR | AE14: 1 | AF14: 1 | AG14: Standard Buying | AH14: INR | AI14: 1 | AJ14: 0 | AL14: 0 | AO14: 0 | AR14: 1 | AS14: 0 | AT14: 2100 | AU14: 2100 | AV14: 2100 | AW14: 2100 | AX14: 2100 | AY14: 2100 | BA14: Input GST RCM In-state - GCF | BE14: 105 | BF14: 105 | BG14: 0 | BH14: 105 | BI14: 105 | BJ14: 0 | BK14: 2100 | BL14: 0 | BM14: 0 | BN14: INR Two Thousand, One Hundred only. | BO14: 2100 | BP14: 0 | BQ14: 0 | BR14: 0 | BS14: INR Two Thousand, One Hundred only. | BT14: 0 | BU14: 2100 | BV14: 1 | BW14: Grand Total | BX14: 0 | BY14: 0 | BZ14: 0 | CA14: | HSN/SAC | Taxable Amount | Input Tax CGST @ 9.0 | Input Tax SGST @ 9.0 | Input Tax CGST RCM @ 9.0 | Input Tax SGST RCM @ 9.0 | | --- | --- | --- | --- | --- | --- | | 996511 | ₹ 2,100.00 | (2.5%) ₹ 52.50 | (2.5%) ₹ 52.50 | (2.5%) ₹ 52.50 | (2.5%) ₹ 52.50 | | CC14: 0 | CF14: 0 | CG14: 0 | CH14: 0 | CI14: 0 | CJ14: 0 | CP14: Unregistered | CW14: GC Foods Muzaffarpur-Billing | CX14: A-03 and A-04, Bela Industrial Estate, Muzaffarpur, Bihar, State Code: 10, Pincode: 842005, India, GSTIN: 10AACCG2244H1Z9, | CY14: GC Foods Muzaffarpur-Billing | CZ14: A-03 and A-04, Bela Industrial Estate, Muzaffarpur, Bihar, State Code: 10, Pincode: 842005, India, GSTIN: 10AACCG2244H1Z9, | DA14: 10AACCG2244H1Z9 | DB14: 10-Bihar | DD14: 0 | DG14: 0 | DH14: INR | DI14: No | DJ14: Freight Outward - GCF | DP14: GCF Letterhead | DQ14: 0 | DS14: en | DY14: 0 | EA14: Road | EC14: 45869 | ED14: Regular | EE14: ITC on Reverse Charge | EG14: Not Applicable | EH14: 0 | EK14: 0 | EM14: Creditors (Transport) | EO14: 0 | EP14: No Remarks | ER14: 1 | ES14: 1 | ET14: 2100 | EU14: 2100 | EV14: Freight Outward - GCF | EW14: 2100 | EX14: 2100 | EY14: Unit | EZ14: 1 | FB14: 0 | FC14: 1 | FI14: 0 | FJ14: 0 | FK14: 0 | FL14: 0 | FM14: 52.5 | FN14: 2.5 | FO14: Main - GCF | FQ14: Freight Outward | FR14: 0 | FS14: 0 | FT14: 0 | FU14: 0 | FV14: Freight Outward - GCF | FX14: Taxable | FY14: 996511 | FZ14: 0 | GA14: 0 | GC14: 0 | GD14: 0 | GE14: 0 | GF14: 0 | GG14: Freight Outward - GCF | GH14: Services | GI14: 0 | GJ14: {"Output Tax SGST - GCF": 2.5, "Output Tax CGST - GCF": 2.5, "Output Tax IGST - GCF": 5.0, "Input Tax SGST - GCF": 2.5, "Input Tax CGST - GCF": 2.5, "Input Tax IGST - GCF": 5.0, "Input Tax SGST RCM - GCF": 2.5, "Input Tax CGST RCM - GCF": 2.5, "Input Tax IGST RCM - GCF": 5.0} | GK14: GST 5% - GCF | GL14: 0 | GO14: 0 | GS14: 2100 | GT14: 2100 | GU14: 2100 | GV14: 2100 | GW14: 0 | GX14: 1 | GY14: 0 | GZ14: 0 | HJ14: 2100 | HK14: 0 | HL14: 0 | HM14: 0 | HN14: 0 | HP14: 0 | HT14: 0 | IA14: 52.5 | IB14: 2.5 | ID14: Unit | IE14: Muzaffarpur | IF14: 2100 | IG14: 0 | IH14: 0 | II14: 0 | IJ14: 0 | IN14: INR | IO14: Input Tax CGST - GCF | IP14: Add | IQ14: 52.5 | IR14: 52.5 | IT14: Total | IU14: 0 | IV14: Main - GCF | IW14: Input Tax CGST @ 9.0 | IX14: cgst | IY14: 0 | IZ14: 0 | JA14: {"Freight Outward - GCF":[2.5,52.5]} | JC14: 52.5 | JD14: 52.5 | JE14: 0 | JF14: 2152.5 | JG14: 2152.5 | JH14: On Net Total | LD14: 0 | LG14: 0 | LH14: 45749 | LI14: 100 | LK14: 2100 | LL14: 2100 | LM14: 0 | LN14: 0 | LO14: 2100 | LP14: 2100
IN15: INR | IO15: Input Tax SGST - GCF | IP15: Add | IQ15: 52.5 | IR15: 52.5 | IT15: Total | IU15: 0 | IV15: Main - GCF | IW15: Input Tax SGST @ 9.0 | IX15: sgst | IY15: 0 | IZ15: 0 | JA15: {"Freight Outward - GCF":[2.5,52.5]} | JC15: 52.5 | JD15: 52.5 | JE15: 0 | JF15: 2205 | JG15: 2205 | JH15: On Net Total
IN16: INR | IO16: Input Tax CGST RCM - GCF | IP16: Deduct | IQ16: 52.5 | IR16: 52.5 | IT16: Total | IU16: 0 | IV16: Main - GCF | IW16: Input Tax CGST RCM @ 9.0 | IX16: cgst_rcm | IY16: 0 | IZ16: 0 | JA16: {"Freight Outward - GCF":[2.5,52.5]} | JC16: 52.5 | JD16: 52.5 | JE16: 0 | JF16: 2152.5 | JG16: 2152.5 | JH16: On Net Total
IN17: INR | IO17: Input Tax SGST RCM - GCF | IP17: Deduct | IQ17: 52.5 | IR17: 52.5 | IT17: Total | IU17: 0 | IV17: Main - GCF | IW17: Input Tax SGST RCM @ 9.0 | IX17: sgst_rcm | IY17: 0 | IZ17: 0 | JA17: {"Freight Outward - GCF":[2.5,52.5]} | JC17: 52.5 | JD17: 52.5 | JE17: 0 | JF17: 2100 | JG17: 2100 | JH17: On Net Total
A18: PI/M/25-26/0138 | B18: PI/M/25-26/0138-1 | C18: PINV-.YY.- | D18: Freight Outward Non TDS | E18: 45749 | F18: Muzaffarpur | G18: Creditors - GCF | H18: Freight Outward Non TDS | I18: Freight Outward Non TDS | L18: G. C. Foods Pvt. Ltd. | M18: 0.58346065 | N18: 1 | O18: 45749 | Q18: 0 | R18: 0 | T18: 1 | U18: 0 | V18: 1 | W18: 0 | X18: 1 | AD18: INR | AE18: 1 | AF18: 1 | AG18: Standard Buying | AH18: INR | AI18: 1 | AJ18: 0 | AL18: 0 | AO18: 0 | AR18: 1 | AS18: 0 | AT18: 1500 | AU18: 1500 | AV18: 1500 | AW18: 1500 | AX18: 1500 | AY18: 1500 | BA18: Input GST RCM In-state - GCF | BE18: 75 | BF18: 75 | BG18: 0 | BH18: 75 | BI18: 75 | BJ18: 0 | BK18: 1500 | BL18: 0 | BM18: 0 | BN18: INR One Thousand, Five Hundred only. | BO18: 1500 | BP18: 0 | BQ18: 0 | BR18: 0 | BS18: INR One Thousand, Five Hundred only. | BT18: 0 | BU18: 1500 | BV18: 1 | BW18: Grand Total | BX18: 0 | BY18: 0 | BZ18: 0 | CA18: | HSN/SAC | Taxable Amount | Input Tax CGST @ 9.0 | Input Tax SGST @ 9.0 | Input Tax CGST RCM @ 9.0 | Input Tax SGST RCM @ 9.0 | | --- | --- | --- | --- | --- | --- | | 996511 | ₹ 1,500.00 | (2.5%) ₹ 37.50 | (2.5%) ₹ 37.50 | (2.5%) ₹ 37.50 | (2.5%) ₹ 37.50 | | CC18: 0 | CF18: 0 | CG18: 0 | CH18: 0 | CI18: 0 | CJ18: 0 | CP18: Unregistered | CW18: GC Foods Muzaffarpur-Billing | CX18: A-03 and A-04, Bela Industrial Estate, Muzaffarpur, Bihar, State Code: 10, Pincode: 842005, India, GSTIN: 10AACCG2244H1Z9, | CY18: GC Foods Muzaffarpur-Billing | CZ18: A-03 and A-04, Bela Industrial Estate, Muzaffarpur, Bihar, State Code: 10, Pincode: 842005, India, GSTIN: 10AACCG2244H1Z9, | DA18: 10AACCG2244H1Z9 | DB18: 10-Bihar | DD18: 0 | DG18: 0 | DH18: INR | DI18: No | DJ18: Freight Outward - GCF | DP18: GCF Letterhead | DQ18: 0 | DS18: en | DY18: 0 | EA18: Road | EC18: 45869 | ED18: Regular | EE18: ITC on Reverse Charge | EG18: Not Applicable | EH18: 0 | EK18: 0 | EM18: Creditors (Transport) | EO18: 0 | EP18: No Remarks | ER18: 1 | ES18: 1 | ET18: 1500 | EU18: 1500 | EV18: Freight Outward - GCF | EW18: 1500 | EX18: 1500 | EY18: Unit | EZ18: 1 | FB18: 0 | FC18: 1 | FI18: 0 | FJ18: 0 | FK18: 0 | FL18: 0 | FM18: 37.5 | FN18: 2.5 | FO18: Main - GCF | FQ18: Freight Outward | FR18: 0 | FS18: 0 | FT18: 0 | FU18: 0 | FV18: Freight Outward - GCF | FX18: Taxable | FY18: 996511 | FZ18: 0 | GA18: 0 | GC18: 0 | GD18: 0 | GE18: 0 | GF18: 0 | GG18: Freight Outward - GCF | GH18: Services | GI18: 0 | GJ18: {"Output Tax SGST - GCF": 2.5, "Output Tax CGST - GCF": 2.5, "Output Tax IGST - GCF": 5.0, "Input Tax SGST - GCF": 2.5, "Input Tax CGST - GCF": 2.5, "Input Tax IGST - GCF": 5.0, "Input Tax SGST RCM - GCF": 2.5, "Input Tax CGST RCM - GCF": 2.5, "Input Tax IGST RCM - GCF": 5.0} | GK18: GST 5% - GCF | GL18: 0 | GO18: 0 | GS18: 1500 | GT18: 1500 | GU18: 1500 | GV18: 1500 | GW18: 0 | GX18: 1 | GY18: 0 | GZ18: 0 | HJ18: 1500 | HK18: 0 | HL18: 0 | HM18: 0 | HN18: 0 | HP18: 0 | HT18: 0 | IA18: 37.5 | IB18: 2.5 | ID18: Unit | IE18: Muzaffarpur | IF18: 1500 | IG18: 0 | IH18: 0 | II18: 0 | IJ18: 0 | IN18: INR | IO18: Input Tax CGST - GCF | IP18: Add | IQ18: 37.5 | IR18: 37.5 | IT18: Total | IU18: 0 | IV18: Main - GCF | IW18: Input Tax CGST @ 9.0 | IX18: cgst | IY18: 0 | IZ18: 0 | JA18: {"Freight Outward - GCF":[2.5,37.5]} | JC18: 37.5 | JD18: 37.5 | JE18: 0 | JF18: 1537.5 | JG18: 1537.5 | JH18: On Net Total | LD18: 0 | LG18: 0 | LH18: 45749 | LI18: 100 | LK18: 1500 | LL18: 1500 | LM18: 0 | LN18: 0 | LO18: 1500 | LP18: 1500
IN19: INR | IO19: Input Tax SGST - GCF | IP19: Add | IQ19: 37.5 | IR19: 37.5 | IT19: Total | IU19: 0 | IV19: Main - GCF | IW19: Input Tax SGST @ 9.0 | IX19: sgst | IY19: 0 | IZ19: 0 | JA19: {"Freight Outward - GCF":[2.5,37.5]} | JC19: 37.5 | JD19: 37.5 | JE19: 0 | JF19: 1575 | JG19: 1575 | JH19: On Net Total
IN20: INR | IO20: Input Tax CGST RCM - GCF | IP20: Deduct | IQ20: 37.5 | IR20: 37.5 | IT20: Total | IU20: 0 | IV20: Main - GCF | IW20: Input Tax CGST RCM @ 9.0 | IX20: cgst_rcm | IY20: 0 | IZ20: 0 | JA20: {"Freight Outward - GCF":[2.5,37.5]} | JC20: 37.5 | JD20: 37.5 | JE20: 0 | JF20: 1537.5 | JG20: 1537.5 | JH20: On Net Total
IN21: INR | IO21: Input Tax SGST RCM - GCF | IP21: Deduct | IQ21: 37.5 | IR21: 37.5 | IT21: Total | IU21: 0 | IV21: Main - GCF | IW21: Input Tax SGST RCM @ 9.0 | IX21: sgst_rcm | IY21: 0 | IZ21: 0 | JA21: {"Freight Outward - GCF":[2.5,37.5]} | JC21: 37.5 | JD21: 37.5 | JE21: 0 | JF21: 1500 | JG21: 1500 | JH21: On Net Total
A22: PI/M/25-26/0137 | B22: PI/M/25-26/0137-1 | C22: PINV-.YY.- | D22: Freight Outward Non TDS | E22: 45749 | F22: Muzaffarpur | G22: Creditors - GCF | H22: Freight Outward Non TDS | I22: Freight Outward Non TDS | L22: G. C. Foods Pvt. Ltd. | M22: 0.5794213 | N22: 1 | O22: 45749 | Q22: 0 | R22: 0 | T22: 1 | U22: 0 | V22: 1 | W22: 0 | X22: 1 | AD22: INR | AE22: 1 | AF22: 1 | AG22: Standard Buying | AH22: INR | AI22: 1 | AJ22: 0 | AL22: 0 | AO22: 0 | AR22: 1 | AS22: 0 | AT22: 600 | AU22: 600 | AV22: 600 | AW22: 600 | AX22: 600 | AY22: 600 | BA22: Input GST RCM In-state - GCF | BE22: 30 | BF22: 30 | BG22: 0 | BH22: 30 | BI22: 30 | BJ22: 0 | BK22: 600 | BL22: 0 | BM22: 0 | BN22: INR Six Hundred only. | BO22: 600 | BP22: 0 | BQ22: 0 | BR22: 0 | BS22: INR Six Hundred only. | BT22: 0 | BU22: 600 | BV22: 1 | BW22: Grand Total | BX22: 0 | BY22: 0 | BZ22: 0 | CA22: | HSN/SAC | Taxable Amount | Input Tax CGST @ 9.0 | Input Tax SGST @ 9.0 | Input Tax CGST RCM @ 9.0 | Input Tax SGST RCM @ 9.0 | | --- | --- | --- | --- | --- | --- | | 996511 | ₹ 600.00 | (2.5%) ₹ 15.00 | (2.5%) ₹ 15.00 | (2.5%) ₹ 15.00 | (2.5%) ₹ 15.00 | | CC22: 0 | CF22: 0 | CG22: 0 | CH22: 0 | CI22: 0 | CJ22: 0 | CP22: Unregistered | CW22: GC Foods Muzaffarpur-Billing | CX22: A-03 and A-04, Bela Industrial Estate, Muzaffarpur, Bihar, State Code: 10, Pincode: 842005, India, GSTIN: 10AACCG2244H1Z9, | CY22: GC Foods Muzaffarpur-Billing | CZ22: A-03 and A-04, Bela Industrial Estate, Muzaffarpur, Bihar, State Code: 10, Pincode: 842005, India, GSTIN: 10AACCG2244H1Z9, | DA22: 10AACCG2244H1Z9 | DB22: 10-Bihar | DD22: 0 | DG22: 0 | DH22: INR | DI22: No | DJ22: Freight Outward - GCF | DP22: GCF Letterhead | DQ22: 0 | DS22: en | DY22: 0 | EA22: Road | EC22: 45869 | ED22: Regular | EE22: ITC on Reverse Charge | EG22: Not Applicable | EH22: 0 | EK22: 0 | EM22: Creditors (Transport) | EO22: 0 | EP22: No Remarks | ER22: 1 | ES22: 1 | ET22: 600 | EU22: 600 | EV22: Freight Outward - GCF | EW22: 600 | EX22: 600 | EY22: Unit | EZ22: 1 | FB22: 0 | FC22: 1 | FI22: 0 | FJ22: 0 | FK22: 0 | FL22: 0 | FM22: 15 | FN22: 2.5 | FO22: Main - GCF | FQ22: Freight Outward | FR22: 0 | FS22: 0 | FT22: 0 | FU22: 0 | FV22: Freight Outward - GCF | FX22: Taxable | FY22: 996511 | FZ22: 0 | GA22: 0 | GC22: 0 | GD22: 0 | GE22: 0 | GF22: 0 | GG22: Freight Outward - GCF | GH22: Services | GI22: 0 | GJ22: {"Output Tax SGST - GCF": 2.5, "Output Tax CGST - GCF": 2.5, "Output Tax IGST - GCF": 5.0, "Input Tax SGST - GCF": 2.5, "Input Tax CGST - GCF": 2.5, "Input Tax IGST - GCF": 5.0, "Input Tax SGST RCM - GCF": 2.5, "Input Tax CGST RCM - GCF": 2.5, "Input Tax IGST RCM - GCF": 5.0} | GK22: GST 5% - GCF | GL22: 0 | GO22: 0 | GS22: 600 | GT22: 600 | GU22: 600 | GV22: 600 | GW22: 0 | GX22: 1 | GY22: 0 | GZ22: 0 | HJ22: 600 | HK22: 0 | HL22: 0 | HM22: 0 | HN22: 0 | HP22: 0 | HT22: 0 | IA22: 15 | IB22: 2.5 | ID22: Unit | IE22: Muzaffarpur | IF22: 600 | IG22: 0 | IH22: 0 | II22: 0 | IJ22: 0 | IN22: INR | IO22: Input Tax CGST - GCF | IP22: Add | IQ22: 15 | IR22: 15 | IT22: Total | IU22: 0 | IV22: Main - GCF | IW22: Input Tax CGST @ 9.0 | IX22: cgst | IY22: 0 | IZ22: 0 | JA22: {"Freight Outward - GCF":[2.5,15.0]} | JC22: 15 | JD22: 15 | JE22: 0 | JF22: 615 | JG22: 615 | JH22: On Net Total | LD22: 0 | LG22: 0 | LH22: 45749 | LI22: 100 | LK22: 600 | LL22: 600 | LM22: 0 | LN22: 0 | LO22: 600 | LP22: 600
IN23: INR | IO23: Input Tax SGST - GCF | IP23: Add | IQ23: 15 | IR23: 15 | IT23: Total | IU23: 0 | IV23: Main - GCF | IW23: Input Tax SGST @ 9.0 | IX23: sgst | IY23: 0 | IZ23: 0 | JA23: {"Freight Outward - GCF":[2.5,15.0]} | JC23: 15 | JD23: 15 | JE23: 0 | JF23: 630 | JG23: 630 | JH23: On Net Total
IN24: INR | IO24: Input Tax CGST RCM - GCF | IP24: Deduct | IQ24: 15 | IR24: 15 | IT24: Total | IU24: 0 | IV24: Main - GCF | IW24: Input Tax CGST RCM @ 9.0 | IX24: cgst_rcm | IY24: 0 | IZ24: 0 | JA24: {"Freight Outward - GCF":[2.5,15.0]} | JC24: 15 | JD24: 15 | JE24: 0 | JF24: 615 | JG24: 615 | JH24: On Net Total
IN25: INR | IO25: Input Tax SGST RCM - GCF | IP25: Deduct | IQ25: 15 | IR25: 15 | IT25: Total | IU25: 0 | IV25: Main - GCF | IW25: Input Tax SGST RCM @ 9.0 | IX25: sgst_rcm | IY25: 0 | IZ25: 0 | JA25: {"Freight Outward - GCF":[2.5,15.0]} | JC25: 15 | JD25: 15 | JE25: 0 | JF25: 600 | JG25: 600 | JH25: On Net Total
A26: PI/M/25-26/0136 | B26: PI/M/25-26/0136-1 | C26: PINV-.YY.- | D26: Freight Outward Non TDS | E26: 45749 | F26: Muzaffarpur | G26: Creditors - GCF | H26: Freight Outward Non TDS | I26: Freight Outward Non TDS | L26: G. C. Foods Pvt. Ltd. | M26: 0.57923611 | N26: 1 | O26: 45749 | Q26: 0 | R26: 0 | T26: 1 | U26: 0 | V26: 1 | W26: 0 | X26: 1 | AD26: INR | AE26: 1 | AF26: 1 | AG26: Standard Buying | AH26: INR | AI26: 1 | AJ26: 0 | AL26: 0 | AO26: 0 | AR26: 1 | AS26: 0 | AT26: 600 | AU26: 600 | AV26: 600 | AW26: 600 | AX26: 600 | AY26: 600 | BA26: Input GST RCM In-state - GCF | BE26: 30 | BF26: 30 | BG26: 0 | BH26: 30 | BI26: 30 | BJ26: 0 | BK26: 600 | BL26: 0 | BM26: 0 | BN26: INR Six Hundred only. | BO26: 600 | BP26: 0 | BQ26: 0 | BR26: 0 | BS26: INR Six Hundred only. | BT26: 0 | BU26: 600 | BV26: 1 | BW26: Grand Total | BX26: 0 | BY26: 0 | BZ26: 0 | CA26: | HSN/SAC | Taxable Amount | Input Tax CGST @ 9.0 | Input Tax SGST @ 9.0 | Input Tax CGST RCM @ 9.0 | Input Tax SGST RCM @ 9.0 | | --- | --- | --- | --- | --- | --- | | 996511 | ₹ 600.00 | (2.5%) ₹ 15.00 | (2.5%) ₹ 15.00 | (2.5%) ₹ 15.00 | (2.5%) ₹ 15.00 | | CC26: 0 | CF26: 0 | CG26: 0 | CH26: 0 | CI26: 0 | CJ26: 0 | CP26: Unregistered | CW26: GC Foods Muzaffarpur-Billing | CX26: A-03 and A-04, Bela Industrial Estate, Muzaffarpur, Bihar, State Code: 10, Pincode: 842005, India, GSTIN: 10AACCG2244H1Z9, | CY26: GC Foods Muzaffarpur-Billing | CZ26: A-03 and A-04, Bela Industrial Estate, Muzaffarpur, Bihar, State Code: 10, Pincode: 842005, India, GSTIN: 10AACCG2244H1Z9, | DA26: 10AACCG2244H1Z9 | DB26: 10-Bihar | DD26: 0 | DG26: 0 | DH26: INR | DI26: No | DJ26: Freight Outward - GCF | DP26: GCF Letterhead | DQ26: 0 | DS26: en | DY26: 0 | EA26: Road | EC26: 45869 | ED26: Regular | EE26: ITC on Reverse Charge | EG26: Not Applicable | EH26: 0 | EK26: 0 | EM26: Creditors (Transport) | EO26: 0 | EP26: No Remarks | ER26: 1 | ES26: 1 | ET26: 600 | EU26: 600 | EV26: Freight Outward - GCF | EW26: 600 | EX26: 600 | EY26: Unit | EZ26: 1 | FB26: 0 | FC26: 1 | FI26: 0 | FJ26: 0 | FK26: 0 | FL26: 0 | FM26: 15 | FN26: 2.5 | FO26: Main - GCF | FQ26: Freight Outward | FR26: 0 | FS26: 0 | FT26: 0 | FU26: 0 | FV26: Freight Outward - GCF | FX26: Taxable | FY26: 996511 | FZ26: 0 | GA26: 0 | GC26: 0 | GD26: 0 | GE26: 0 | GF26: 0 | GG26: Freight Outward - GCF | GH26: Services | GI26: 0 | GJ26: {"Output Tax SGST - GCF": 2.5, "Output Tax CGST - GCF": 2.5, "Output Tax IGST - GCF": 5.0, "Input Tax SGST - GCF": 2.5, "Input Tax CGST - GCF": 2.5, "Input Tax IGST - GCF": 5.0, "Input Tax SGST RCM - GCF": 2.5, "Input Tax CGST RCM - GCF": 2.5, "Input Tax IGST RCM - GCF": 5.0} | GK26: GST 5% - GCF | GL26: 0 | GO26: 0 | GS26: 600 | GT26: 600 | GU26: 600 | GV26: 600 | GW26: 0 | GX26: 1 | GY26: 0 | GZ26: 0 | HJ26: 600 | HK26: 0 | HL26: 0 | HM26: 0 | HN26: 0 | HP26: 0 | HT26: 0 | IA26: 15 | IB26: 2.5 | ID26: Unit | IE26: Muzaffarpur | IF26: 600 | IG26: 0 | IH26: 0 | II26: 0 | IJ26: 0 | IN26: INR | IO26: Input Tax CGST - GCF | IP26: Add | IQ26: 15 | IR26: 15 | IT26: Total | IU26: 0 | IV26: Main - GCF | IW26: Input Tax CGST @ 9.0 | IX26: cgst | IY26: 0 | IZ26: 0 | JA26: {"Freight Outward - GCF":[2.5,15.0]} | JC26: 15 | JD26: 15 | JE26: 0 | JF26: 615 | JG26: 615 | JH26: On Net Total | LD26: 0 | LG26: 0 | LH26: 45749 | LI26: 100 | LK26: 600 | LL26: 600 | LM26: 0 | LN26: 0 | LO26: 600 | LP26: 600
IN27: INR | IO27: Input Tax SGST - GCF | IP27: Add | IQ27: 15 | IR27: 15 | IT27: Total | IU27: 0 | IV27: Main - GCF | IW27: Input Tax SGST @ 9.0 | IX27: sgst | IY27: 0 | IZ27: 0 | JA27: {"Freight Outward - GCF":[2.5,15.0]} | JC27: 15 | JD27: 15 | JE27: 0 | JF27: 630 | JG27: 630 | JH27: On Net Total
IN28: INR | IO28: Input Tax CGST RCM - GCF | IP28: Deduct | IQ28: 15 | IR28: 15 | IT28: Total | IU28: 0 | IV28: Main - GCF | IW28: Input Tax CGST RCM @ 9.0 | IX28: cgst_rcm | IY28: 0 | IZ28: 0 | JA28: {"Freight Outward - GCF":[2.5,15.0]} | JC28: 15 | JD28: 15 | JE28: 0 | JF28: 615 | JG28: 615 | JH28: On Net Total
IN29: INR | IO29: Input Tax SGST RCM - GCF | IP29: Deduct | IQ29: 15 | IR29: 15 | IT29: Total | IU29: 0 | IV29: Main - GCF | IW29: Input Tax SGST RCM @ 9.0 | IX29: sgst_rcm | IY29: 0 | IZ29: 0 | JA29: {"Freight Outward - GCF":[2.5,15.0]} | JC29: 15 | JD29: 15 | JE29: 0 | JF29: 600 | JG29: 600 | JH29: On Net Total
A30: PI/M/25-26/0135 | B30: PI/M/25-26/0135-1 | C30: PINV-.YY.- | D30: Freight Outward Non TDS | E30: 45749 | F30: Muzaffarpur | G30: Creditors - GCF | H30: Freight Outward Non TDS | I30: Freight Outward Non TDS | L30: G. C. Foods Pvt. Ltd. | M30: 0.5730787 | N30: 1 | O30: 45749 | Q30: 0 | R30: 0 | T30: 1 | U30: 0 | V30: 1 | W30: 0 | X30: 1 | AD30: INR | AE30: 1 | AF30: 1 | AG30: Standard Buying | AH30: INR | AI30: 1 | AJ30: 0 | AL30: 0 | AO30: 0 | AR30: 1 | AS30: 0 | AT30: 600 | AU30: 600 | AV30: 600 | AW30: 600 | AX30: 600 | AY30: 600 | BA30: Input GST RCM In-state - GCF | BE30: 30 | BF30: 30 | BG30: 0 | BH30: 30 | BI30: 30 | BJ30: 0 | BK30: 600 | BL30: 0 | BM30: 0 | BN30: INR Six Hundred only. | BO30: 600 | BP30: 0 | BQ30: 0 | BR30: 0 | BS30: INR Six Hundred only. | BT30: 0 | BU30: 600 | BV30: 1 | BW30: Grand Total | BX30: 0 | BY30: 0 | BZ30: 0 | CA30: | HSN/SAC | Taxable Amount | Input Tax CGST @ 9.0 | Input Tax SGST @ 9.0 | Input Tax CGST RCM @ 9.0 | Input Tax SGST RCM @ 9.0 | | --- | --- | --- | --- | --- | --- | | 996511 | ₹ 600.00 | (2.5%) ₹ 15.00 | (2.5%) ₹ 15.00 | (2.5%) ₹ 15.00 | (2.5%) ₹ 15.00 | | CC30: 0 | CF30: 0 | CG30: 0 | CH30: 0 | CI30: 0 | CJ30: 0 | CP30: Unregistered | CW30: GC Foods Muzaffarpur-Billing | CX30: A-03 and A-04, Bela Industrial Estate, Muzaffarpur, Bihar, State Code: 10, Pincode: 842005, India, GSTIN: 10AACCG2244H1Z9, | CY30: GC Foods Muzaffarpur-Billing | CZ30: A-03 and A-04, Bela Industrial Estate, Muzaffarpur, Bihar, State Code: 10, Pincode: 842005, India, GSTIN: 10AACCG2244H1Z9, | DA30: 10AACCG2244H1Z9 | DB30: 10-Bihar | DD30: 0 | DG30: 0 | DH30: INR | DI30: No | DJ30: Freight Outward - GCF | DP30: GCF Letterhead | DQ30: 0 | DS30: en | DY30: 0 | EA30: Road | EC30: 45869 | ED30: Regular | EE30: ITC on Reverse Charge | EG30: Not Applicable | EH30: 0 | EK30: 0 | EM30: Creditors (Transport) | EO30: 0 | EP30: No Remarks | ER30: 1 | ES30: 1 | ET30: 600 | EU30: 600 | EV30: Freight Outward - GCF | EW30: 600 | EX30: 600 | EY30: Unit | EZ30: 1 | FB30: 0 | FC30: 1 | FI30: 0 | FJ30: 0 | FK30: 0 | FL30: 0 | FM30: 15 | FN30: 2.5 | FO30: Main - GCF | FQ30: Freight Outward | FR30: 0 | FS30: 0 | FT30: 0 | FU30: 0 | FV30: Freight Outward - GCF | FX30: Taxable | FY30: 996511 | FZ30: 0 | GA30: 0 | GC30: 0 | GD30: 0 | GE30: 0 | GF30: 0 | GG30: Freight Outward - GCF | GH30: Services | GI30: 0 | GJ30: {"Output Tax SGST - GCF": 2.5, "Output Tax CGST - GCF": 2.5, "Output Tax IGST - GCF": 5.0, "Input Tax SGST - GCF": 2.5, "Input Tax CGST - GCF": 2.5, "Input Tax IGST - GCF": 5.0, "Input Tax SGST RCM - GCF": 2.5, "Input Tax CGST RCM - GCF": 2.5, "Input Tax IGST RCM - GCF": 5.0} | GK30: GST 5% - GCF | GL30: 0 | GO30: 0 | GS30: 600 | GT30: 600 | GU30: 600 | GV30: 600 | GW30: 0 | GX30: 1 | GY30: 0 | GZ30: 0 | HJ30: 600 | HK30: 0 | HL30: 0 | HM30: 0 | HN30: 0 | HP30: 0 | HT30: 0 | IA30: 15 | IB30: 2.5 | ID30: Unit | IE30: Muzaffarpur | IF30: 600 | IG30: 0 | IH30: 0 | II30: 0 | IJ30: 0 | IN30: INR | IO30: Input Tax CGST - GCF | IP30: Add | IQ30: 15 | IR30: 15 | IT30: Total | IU30: 0 | IV30: Main - GCF | IW30: Input Tax CGST @ 9.0 | IX30: cgst | IY30: 0 | IZ30: 0 | JA30: {"Freight Outward - GCF":[2.5,15.0]} | JC30: 15 | JD30: 15 | JE30: 0 | JF30: 615 | JG30: 615 | JH30: On Net Total | LD30: 0 | LG30: 0 | LH30: 45749 | LI30: 100 | LK30: 600 | LL30: 600 | LM30: 0 | LN30: 0 | LO30: 600 | LP30: 600
IN31: INR | IO31: Input Tax SGST - GCF | IP31: Add | IQ31: 15 | IR31: 15 | IT31: Total | IU31: 0 | IV31: Main - GCF | IW31: Input Tax SGST @ 9.0 | IX31: sgst | IY31: 0 | IZ31: 0 | JA31: {"Freight Outward - GCF":[2.5,15.0]} | JC31: 15 | JD31: 15 | JE31: 0 | JF31: 630 | JG31: 630 | JH31: On Net Total
IN32: INR | IO32: Input Tax CGST RCM - GCF | IP32: Deduct | IQ32: 15 | IR32: 15 | IT32: Total | IU32: 0 | IV32: Main - GCF | IW32: Input Tax CGST RCM @ 9.0 | IX32: cgst_rcm | IY32: 0 | IZ32: 0 | JA32: {"Freight Outward - GCF":[2.5,15.0]} | JC32: 15 | JD32: 15 | JE32: 0 | JF32: 615 | JG32: 615 | JH32: On Net Total
IN33: INR | IO33: Input Tax SGST RCM - GCF | IP33: Deduct | IQ33: 15 | IR33: 15 | IT33: Total | IU33: 0 | IV33: Main - GCF | IW33: Input Tax SGST RCM @ 9.0 | IX33: sgst_rcm | IY33: 0 | IZ33: 0 | JA33: {"Freight Outward - GCF":[2.5,15.0]} | JC33: 15 | JD33: 15 | JE33: 0 | JF33: 600 | JG33: 600 | JH33: On Net Total
A34: PI/M/25-26/0132 | B34: PI/M/25-26/0132-1 | C34: PINV-.YY.- | D34: Jogi Jee Patna | E34: 45866 | F34: Muzaffarpur | G34: Creditors - GCF | H34: Jogi Jee Patna | I34: Jogi Jee Patna | L34: G. C. Foods Pvt. Ltd. | M34: 0.61065559 | N34: 1 | O34: 45866 | Q34: 0 | R34: 0 | T34: 1 | U34: 0 | V34: 1 | W34: 0 | X34: 0 | AA34: 45866 | AD34: INR | AE34: 1 | AF34: 1 | AG34: Standard Buying | AH34: INR | AI34: 1 | AJ34: 0 | AL34: 0 | AM34: Store Mujaffarpur - GCF | AO34: 0 | AR34: 4740 | AS34: 0 | AT34: 26544 | AU34: 26544 | AV34: 26544 | AW34: 26544 | AX34: 26544 | AY34: 26544 | BE34: 6 | BF34: 0 | BG34: 6 | BH34: 6 | BI34: 0 | BJ34: 6 | BK34: 26550 | BL34: 0 | BM34: 0 | BN34: INR Twenty Six Thousand, Five Hundred And Fifty only. | BO34: 26550 | BP34: 0 | BQ34: 0 | BR34: 0 | BS34: INR Twenty Six Thousand, Five Hundred And Fifty only. | BT34: 0 | BU34: 26550 | BV34: 1 | BW34: Grand Total | BX34: 0 | BY34: 0 | BZ34: 0 | CA34: | HSN/SAC | Taxable Amount | Rounded Off | | --- | --- | --- | | 08055000 | ₹ 26,544.00 | ₹ 6.00 | | CC34: 0 | CF34: 0 | CG34: 0 | CH34: 0 | CI34: 0 | CJ34: 0 | CP34: Unregistered | CW34: GC Foods Muzaffarpur-Billing | CX34: A-03 and A-04, Bela Industrial Estate, Muzaffarpur, Bihar, State Code: 10, Pincode: 842005, India, GSTIN: 10AACCG2244H1Z9, | CY34: GC Foods Muzaffarpur-Billing | CZ34: A-03 and A-04, Bela Industrial Estate, Muzaffarpur, Bihar, State Code: 10, Pincode: 842005, India, GSTIN: 10AACCG2244H1Z9, | DA34: 10AACCG2244H1Z9 | DB34: 10-Bihar | DD34: 0 | DF34: Lemon 4740 Kg (118 Bag ) as per Ingate Voucher No.1133 | DG34: 100 | DH34: INR | DI34: No | DJ34: Stock Received But Not Billed - GCF | DP34: GCF Letterhead | DQ34: 0 | DS34: en | DY34: 0 | EA34: Road | EC34: 45867 | ED34: Regular | EE34: All Other ITC | EG34: Not Applicable | EH34: 0 | EK34: 0 | EO34: 0 | EP34: No Remarks | ER34: 4740 | ES34: 4740 | ET34: 26544 | EU34: 26544 | EV34: Lemon | EW34: 5.6 | EX34: 5.6 | EY34: KGS | EZ34: 1 | FA34: Store Mujaffarpur - GCF | FB34: 0 | FC34: 1 | FI34: 0 | FJ34: 0 | FK34: 0 | FL34: 0 | FM34: 0 | FN34: 0 | FO34: Main - GCF | FQ34: Lemon | FR34: 14.4 | FS34: 72 | FT34: 0 | FU34: 0 | FV34: Stock Received But Not Billed - GCF | FX34: Nil-Rated | FY34: 08055000 | FZ34: 0 | GA34: 0 | GC34: 0 | GD34: 0 | GE34: 0 | GF34: 0 | GG34: Lemon | GH34: Spices and Seasoning - RM | GI34: 0 | GJ34: {} | GL34: 0 | GO34: 0 | GS34: 26544 | GT34: 26544 | GU34: 5.6 | GV34: 5.6 | GW34: 0 | GX34: 4740 | GY34: 20 | GZ34: 20 | HG34: PR/M/25-26/0128 | HH34: 779ntpsl6o | HJ34: 5.6 | HK34: 0 | HL34: 0 | HM34: 0 | HN34: 4740 | HP34: 0 | HT34: 0 | IA34: 0 | IB34: 0 | ID34: KGS | IE34: Muzaffarpur | IF34: 26550 | IG34: 0 | IH34: 0 | II34: 5.6 | IJ34: 0 | IN34: INR | IO34: Rounded Off - GCF | IP34: Add | IQ34: 6 | IR34: 6 | IT34: Total | IU34: 0 | IV34: Main - GCF | IW34: Rounded Off | IY34: 0 | IZ34: 0 | JA34: {"Lemon":[0.0,6.0]} | JC34: 6 | JD34: 6 | JE34: 0 | JF34: 26550 | JG34: 26550 | JH34: Actual | LD34: 0 | LF34: Percentage | LG34: 0 | LH34: 45866 | LI34: 100 | LK34: 26550 | LL34: 26550 | LM34: 0 | LN34: 0 | LO34: 26550 | LP34: 26550
A35: PI/N/25-26/0042 | B35: PI/N/25-26/0042-1 | C35: PINV-.YY.- | D35: Bajrang Traders | E35: 45860 | F35: Noida | G35: Creditors - GCF | H35: Bajrang Traders | I35: Bajrang Traders | L35: G. C. Foods Pvt. Ltd. | M35: 0.6595488 | N35: 1 | O35: 45860 | Q35: 0 | R35: 0 | T35: 1 | U35: 0 | V35: 1 | W35: 0 | X35: 0 | Z35: TAX/25-26/75 | AA35: 45860 | AD35: INR | AE35: 1 | AF35: 1 | AG35: Standard Buying | AH35: INR | AI35: 1 | AJ35: 0 | AL35: 0 | AM35: Stores Noida - GCF | AO35: 0 | AR35: 26 | AS35: 0 | AT35: 38060 | AU35: 38060 | AV35: 38060 | AW35: 38060 | AX35: 38060 | AY35: 38060 | BA35: Input GST In-state - GCF | BE35: 0 | BF35: 0 | BG35: 0 | BH35: 0 | BI35: 0 | BJ35: 0 | BK35: 38060 | BL35: 0 | BM35: 0 | BN35: INR Thirty Eight Thousand And Sixty only. | BO35: 38060 | BP35: 0 | BQ35: 0 | BR35: 0 | BS35: INR Thirty Eight Thousand And Sixty only. | BT35: 0 | BU35: 38060 | BV35: 1 | BW35: Grand Total | BX35: 0 | BY35: 0 | BZ35: 0 | CA35: | HSN/SAC | Taxable Amount | Input Tax CGST @ 9.0 | Input Tax SGST @ 9.0 | | --- | --- | --- | --- | | 11010000 | ₹ 36,610.00 | (0.0%) ₹ 0.00 | (0.0%) ₹ 0.00 | | 110100 | ₹ 1,450.00 | (0.0%) ₹ 0.00 | (0.0%) ₹ 0.00 | | CC35: 0 | CF35: 0 | CG35: 0 | CH35: 0 | CI35: 0 | CJ35: 0 | CM35: Bajrang Traders-Billing | CN35: Ghaza Road, BangelNoida, Uttar Pradesh, State Code: 09, Pincode: 201304, India, GSTIN: 09BGHPB1865L1Z6, | CO35: 09BGHPB1865L1Z6 | CP35: Registered Regular | CU35: Bajrang Traders-Billing | CV35: Ghaza Road, BangelNoida, Uttar Pradesh, State Code: 09, Pincode: 201304, India, GSTIN: 09BGHPB1865L1Z6, | CW35: G.C. Foods Pvt. Ltd. Noida - Uttar Pradesh (Shipping) | CX35: B-64, Sector-80,, Noida, Gautam Buddha Nagar, Noida, Uttar Pradesh, State Code: 09, Pincode: 201305, India, Phone: 9958003759, GSTIN: 09AACCG2244H1ZS, | CY35: G.C. Foods Pvt. Ltd. Noida - Uttar Pradesh (Shipping) | CZ35: B-64, Sector-80,, Noida, Gautam Buddha Nagar, Noida, Uttar Pradesh, State Code: 09, Pincode: 201305, India, Phone: 9958003759, GSTIN: 09AACCG2244H1ZS, | DA35: 09AACCG2244H1ZS | DB35: 09-Uttar Pradesh | DD35: 0 | DF35: Ingate No.166 , Date - 22.07.2025 | DG35: 100 | DH35: INR | DI35: No | DJ35: Stock Received But Not Billed - GCF | DP35: GCF Letterhead | DQ35: 0 | DS35: en | DY35: 0 | EA35: Road | EC35: 45864 | ED35: Regular | EE35: All Other ITC | EG35: Unreconciled | EH35: 0 | EK35: 0 | EM35: Creditors - Raw Material | EO35: 0 | EP35: Against Supplier Invoice TAX/25-26/75 dated 22-07-2025 | ER35: 18 | ES35: 792 | ET35: 25200 | EU35: 25200 | EV35: Maida Normal | EW35: 1400 | EX35: 1400 | EY35: BAG | EZ35: 44 | FA35: Stores Noida - GCF | FB35: 0 | FC35: 1 | FI35: 0 | FJ35: 0 | FK35: 0 | FL35: 0 | FM35: 0 | FN35: 0 | FO35: Main - GCF | FQ35: Maida | FR35: -70 | FS35: 0 | FT35: 0 | FU35: 0 | FV35: Stock Received But Not Billed - GCF | FX35: Exempted | FY35: 11010000 | FZ35: 0 | GA35: 0 | GC35: 0 | GD35: 0 | GE35: 0 | GF35: 0 | GG35: Maida | GH35: Cookies - RM | GI35: 0 | GJ35: {"Input Tax CGST - GCF": 0.0, "Input Tax SGST - GCF": 0.0, "Input Tax IGST - GCF": 0.0, "Output Tax CGST - GCF": 0.0, "Output Tax SGST - GCF": 0.0, "Output Tax IGST - GCF": 0.0, "Input Tax CGST RCM - GCF": 0.0, "Input Tax SGST RCM - GCF": 0.0, "Input Tax IGST RCM - GCF": 0.0} | GK35: Exempted - GCF | GL35: 0 | GO35: 70 | GP35: Amount | GS35: 25200 | GT35: 25200 | GU35: 1400 | GV35: 1400 | GW35: 0 | GX35: 18 | GY35: 1330 | GZ35: 1330 | HE35: PO/N/25-26/0032 | HF35: 4c44spgpm0 | HG35: PR/N/25-26/0082 | HH35: 9cr4p32clf | HJ35: 31.82 | HK35: 0 | HL35: 0 | HM35: 0 | HN35: 18 | HP35: 0 | HT35: 0 | IA35: 0 | IB35: 0 | ID35: KGS | IE35: Noida | IF35: 25200 | IG35: 0 | IH35: 0 | II35: 31.818182 | IJ35: 0 | IN35: INR | IO35: Input Tax CGST - GCF | IP35: Add | IQ35: 0 | IR35: 0 | IT35: Total | IU35: 0 | IV35: Main - GCF | IW35: Input Tax CGST @ 9.0 | IX35: cgst | IY35: 0 | IZ35: 0 | JA35: {"Maida":[0.0,0.0],"Maida Patent":[0.0,0.0],"Suji":[0.0,0.0]} | JC35: 0 | JD35: 0 | JE35: 0 | JF35: 38060 | JG35: 38060 | JH35: On Net Total | LD35: 0 | LF35: Percentage | LG35: 0 | LH35: 45860 | LI35: 100 | LK35: 38060 | LL35: 38060 | LM35: 0 | LN35: 0 | LO35: 38060 | LP35: 38060
ER36: 7 | ES36: 350 | ET36: 11410 | EU36: 11410 | EV36: Maida Patent | EW36: 1630 | EX36: 1630 | EY36: BAG | EZ36: 50 | FA36: Stores Noida - GCF | FB36: 0 | FC36: 1 | FI36: 0 | FJ36: 0 | FK36: 0 | FL36: 0 | FM36: 0 | FN36: 0 | FO36: Main - GCF | FQ36: Maida Rusk | FR36: -80 | FS36: 0 | FT36: 0 | FU36: 0 | FV36: Stock Received But Not Billed - GCF | FX36: Exempted | FY36: 11010000 | FZ36: 0 | GA36: 0 | GC36: 0 | GD36: 0 | GE36: 0 | GF36: 0 | GG36: Maida Patent | GH36: Cookies - RM | GI36: 0 | GJ36: {"Input Tax CGST - GCF": 0.0, "Input Tax SGST - GCF": 0.0, "Input Tax IGST - GCF": 0.0, "Output Tax CGST - GCF": 0.0, "Output Tax SGST - GCF": 0.0, "Output Tax IGST - GCF": 0.0, "Input Tax CGST RCM - GCF": 0.0, "Input Tax SGST RCM - GCF": 0.0, "Input Tax IGST RCM - GCF": 0.0} | GK36: Exempted - GCF | GL36: 0 | GO36: 80 | GP36: Amount | GS36: 11410 | GT36: 11410 | GU36: 1630 | GV36: 1630 | GW36: 0 | GX36: 7 | GY36: 1550 | GZ36: 1550 | HE36: PO/N/25-26/0032 | HF36: 4c44qpbdp6 | HG36: PR/N/25-26/0082 | HH36: 9cr4ljj2tr | HJ36: 32.6 | HK36: 0 | HL36: 0 | HM36: 0 | HN36: 7 | HP36: 0 | HT36: 0 | IA36: 0 | IB36: 0 | ID36: KGS | IE36: Noida | IF36: 11410 | IG36: 0 | IH36: 0 | II36: 32.6 | IJ36: 0 | IN36: INR | IO36: Input Tax SGST - GCF | IP36: Add | IQ36: 0 | IR36: 0 | IT36: Total | IU36: 0 | IV36: Main - GCF | IW36: Input Tax SGST @ 9.0 | IX36: sgst | IY36: 0 | IZ36: 0 | JA36: {"Maida":[0.0,0.0],"Maida Patent":[0.0,0.0],"Suji":[0.0,0.0]} | JC36: 0 | JD36: 0 | JE36: 0 | JF36: 38060 | JG36: 38060 | JH36: On Net Total
ER37: 1 | ES37: 44 | ET37: 1450 | EU37: 1450 | EV37: Suji | EW37: 1450 | EX37: 1450 | EY37: BAG | EZ37: 44 | FA37: Stores Noida - GCF | FB37: 0 | FC37: 1 | FI37: 0 | FJ37: 0 | FK37: 0 | FL37: 0 | FM37: 0 | FN37: 0 | FO37: Main - GCF | FQ37: Suji | FR37: -70 | FS37: 0 | FT37: 0 | FU37: 0 | FV37: Stock Received But Not Billed - GCF | FX37: Exempted | FY37: 110100 | FZ37: 0 | GA37: 0 | GC37: 0 | GD37: 0 | GE37: 0 | GF37: 0 | GG37: Suji | GH37: Cookies - RM | GI37: 0 | GJ37: {"Input Tax CGST - GCF": 0.0, "Input Tax SGST - GCF": 0.0, "Input Tax IGST - GCF": 0.0, "Output Tax CGST - GCF": 0.0, "Output Tax SGST - GCF": 0.0, "Output Tax IGST - GCF": 0.0, "Input Tax CGST RCM - GCF": 0.0, "Input Tax SGST RCM - GCF": 0.0, "Input Tax IGST RCM - GCF": 0.0} | GK37: Exempted - GCF | GL37: 0 | GO37: 70 | GP37: Amount | GS37: 1450 | GT37: 1450 | GU37: 1450 | GV37: 1450 | GW37: 0 | GX37: 1 | GY37: 1380 | GZ37: 1380 | HE37: PO/N/25-26/0032 | HF37: 4c4468q1v4 | HG37: PR/N/25-26/0082 | HH37: 9cr4bp1p7s | HJ37: 32.95 | HK37: 0 | HL37: 0 | HM37: 0 | HN37: 1 | HP37: 0 | HT37: 0 | IA37: 0 | IB37: 0 | ID37: KGS | IE37: Noida | IF37: 1450 | IG37: 0 | IH37: 0 | II37: 32.954545 | IJ37: 0
A38: PI/N/25-26/0034-1 | B38: PI/N/25-26/0034-1-1 | C38: PINV-.YY.- | D38: Om Mithila Industries | E38: 45850 | F38: Noida | G38: Creditors - GCF | H38: Om Mithila Industries | I38: Om Mithila Industries | L38: G. C. Foods Pvt. Ltd. | M38: 0 | N38: 1 | O38: 45850 | Q38: 0 | R38: 0 | T38: 1 | U38: 0 | V38: 1 | W38: 0 | X38: 0 | Z38: 497/25-26 | AA38: 45850 | AD38: INR | AE38: 1 | AF38: 1 | AG38: Standard Selling Delhi | AH38: INR | AI38: 1 | AJ38: 0 | AL38: 0 | AM38: Stores Noida - GCF | AO38: 0 | AR38: 1520 | AS38: 0 | AT38: 29640 | AU38: 29640 | AV38: 29640 | AW38: 29640 | AX38: 29640 | AY38: 29640 | BA38: Input GST In-state - GCF | BE38: 3557 | BF38: 0 | BG38: 3557 | BH38: 3557 | BI38: 0 | BJ38: 3557 | BK38: 33197 | BL38: 0 | BM38: 0 | BN38: INR Thirty Three Thousand, One Hundred And Ninety Seven only. | BO38: 33197 | BP38: 0 | BQ38: 0 | BR38: 0 | BS38: INR Thirty Three Thousand, One Hundred And Ninety Seven only. | BT38: 0 | BU38: 33197 | BV38: 1 | BW38: Grand Total | BX38: 0 | BY38: 0 | BZ38: 0 | CA38: | HSN/SAC | Taxable Amount | Input Tax CGST @ 9.0 | Input Tax SGST @ 9.0 | Rounded Off | | --- | --- | --- | --- | --- | | 48191010 | ₹ 29,640.00 | (6.0%) ₹ 1,778.40 | (6.0%) ₹ 1,778.40 | ₹ 0.20 | | CC38: 0 | CF38: 0 | CG38: 0 | CH38: 0 | CI38: 0 | CJ38: 0 | CM38: Om Mithila Industries-Billing | CN38: A-109 V Sec - 80 Noida, G.B NagarNoida, Uttar Pradesh, State Code: 09, Pincode: 201305, India, GSTIN: 09AOYPS4034E1ZG, | CO38: 09AOYPS4034E1ZG | CP38: Registered Regular | CU38: Om Mithila Industries-Billing | CV38: A-109 V Sec - 80 Noida, G.B NagarNoida, Uttar Pradesh, State Code: 09, Pincode: 201305, India, GSTIN: 09AOYPS4034E1ZG, | CW38: G.C. Foods Pvt. Ltd. Noida - Uttar Pradesh (Shipping) | CX38: B-64, Sector-80,, Noida, Gautam Buddha Nagar, Noida, Uttar Pradesh, State Code: 09, Pincode: 201305, India, Phone: 9958003759, GSTIN: 09AACCG2244H1ZS, | CY38: G.C. Foods Pvt. Ltd. Noida - Uttar Pradesh (Shipping) | CZ38: B-64, Sector-80,, Noida, Gautam Buddha Nagar, Noida, Uttar Pradesh, State Code: 09, Pincode: 201305, India, Phone: 9958003759, GSTIN: 09AACCG2244H1ZS, | DA38: 09AACCG2244H1ZS | DB38: 09-Uttar Pradesh | DD38: 0 | DF38: Ingate No-137, Invoice Bo 497/25-26, Invoice date-12/7/25, Ingate Date -12/7/25 | DG38: 100 | DH38: INR | DI38: No | DJ38: Stock Received But Not Billed - GCF | DP38: GCF Letterhead | DQ38: 0 | DS38: en | DY38: 0 | EA38: Road | EC38: 45859 | ED38: Regular | EE38: All Other ITC | EG38: Unreconciled | EH38: 0 | EK38: 0 | EM38: Creditors - Raw Material | EO38: 0 | EP38: Against Supplier Invoice 497/25-26 dated 12-07-2025 | ER38: 1520 | ES38: 1520 | ET38: 29640 | EU38: 29640 | EV38: Carton - Suji Rusk 65g | EW38: 19.5 | EX38: 19.5 | EY38: PCS | EZ38: 1 | FA38: Stores Noida - GCF | FB38: 0 | FC38: 1 | FI38: 0 | FJ38: 0 | FK38: 0 | FL38: 0 | FM38: 1778.4 | FN38: 6 | FO38: Main - GCF | FQ38: Carton Box - Suji Rusk 65 Gm | FR38: 0 | FS38: 0 | FT38: 0 | FU38: 0 | FV38: Stock Received But Not Billed - GCF | FX38: Taxable | FY38: 48191010 | FZ38: 0 | GA38: 0 | GC38: 0 | GD38: 0 | GE38: 0 | GF38: 0 | GG38: Carton - Suji Rusk 65g | GH38: Cookies - PM | GI38: 0 | GJ38: {"Output Tax SGST - GCF": 6.0, "Output Tax CGST - GCF": 6.0, "Output Tax IGST - GCF": 12.0, "Input Tax SGST - GCF": 6.0, "Input Tax CGST - GCF": 6.0, "Input Tax IGST - GCF": 12.0, "Input Tax SGST RCM - GCF": 6.0, "Input Tax CGST RCM - GCF": 6.0, "Input Tax IGST RCM - GCF": 12.0} | GK38: GST 12% - GCF | GL38: 0 | GO38: 0 | GS38: 29640 | GT38: 29640 | GU38: 19.5 | GV38: 19.5 | GW38: 0 | GX38: 1520 | GY38: 19.5 | GZ38: 19.5 | HG38: PR/N/25-26/0074 | HH38: 8rmo4ojobu | HJ38: 19.5 | HK38: 0 | HL38: 0 | HM38: 0 | HN38: 1520 | HP38: 0 | HT38: 0 | IA38: 1778.4 | IB38: 6 | ID38: PCS | IE38: Noida | IF38: 29640 | IG38: 0 | IH38: 0 | II38: 19.5 | IJ38: 0 | IN38: INR | IO38: Input Tax CGST - GCF | IP38: Add | IQ38: 1778.4 | IR38: 1778.4 | IT38: Total | IU38: 0 | IV38: Main - GCF | IW38: Input Tax CGST @ 9.0 | IX38: cgst | IY38: 0 | IZ38: 0 | JA38: {"Carton - Suji Rusk 65g":[6.0,1778.4]} | JC38: 1778.4 | JD38: 1778.4 | JE38: 0 | JF38: 31418.4 | JG38: 31418.4 | JH38: On Net Total | LD38: 0 | LF38: Percentage | LG38: 0 | LH38: 45850 | LI38: 100 | LK38: 33197 | LL38: 33197 | LM38: 0 | LN38: 0 | LO38: 33197 | LP38: 33197
IN39: INR | IO39: Input Tax SGST - GCF | IP39: Add | IQ39: 1778.4 | IR39: 1778.4 | IT39: Total | IU39: 0 | IV39: Main - GCF | IW39: Input Tax SGST @ 9.0 | IX39: sgst | IY39: 0 | IZ39: 0 | JA39: {"Carton - Suji Rusk 65g":[6.0,1778.4]} | JC39: 1778.4 | JD39: 1778.4 | JE39: 0 | JF39: 33196.8 | JG39: 33196.8 | JH39: On Net Total
IN40: INR | IO40: Rounded Off - GCF | IP40: Add | IQ40: 0.2 | IR40: 0.2 | IT40: Total | IU40: 0 | IV40: Main - GCF | IW40: Rounded Off | IY40: 0 | IZ40: 0 | JA40: {"Carton - Suji Rusk 65g":[0.0,0.2]} | JC40: 0.2 | JD40: 0.2 | JE40: 0 | JF40: 33197 | JG40: 33197 | JH40: Actual
A41: PI/M/25-26/0131 | B41: PI/M/25-26/0131-1 | C41: PINV-.YY.- | D41: Dev Shri Road Line | E41: 45862 | F41: Muzaffarpur | G41: Creditors - GCF | H41: Dev Shri Road Line | I41: Dev Shri Road Line | L41: G. C. Foods Pvt. Ltd. | M41: 0.49857778 | N41: 1 | O41: 45862 | Q41: 0 | R41: 0 | T41: 1 | U41: 0 | V41: 1 | W41: 0 | X41: 1 | Z41: GPL25/07878 | AA41: 45857 | AD41: INR | AE41: 1 | AF41: 1 | AG41: Standard Buying | AH41: INR | AI41: 1 | AJ41: 0 | AL41: 0 | AM41: Store Mujaffarpur - GCF | AO41: 0 | AR41: 1 | AS41: 0 | AT41: 126728 | AU41: 126728 | AV41: 126728 | AW41: 126728 | AX41: 126728 | AY41: 126728 | BA41: Input GST RCM Out-state - GCF | BE41: 6336.4 | BF41: 6336.4 | BG41: 0 | BH41: 6336.4 | BI41: 6336.4 | BJ41: 0 | BK41: 126728 | BL41: 0 | BM41: 0 | BN41: INR One Lakh, Twenty Six Thousand, Seven Hundred And Twenty Eight only. | BO41: 126728 | BP41: 0 | BQ41: 0 | BR41: 0 | BS41: INR One Lakh, Twenty Six Thousand, Seven Hundred And Twenty Eight only. | BT41: 0 | BU41: 126728 | BV41: 1 | BW41: Grand Total | BX41: 0 | BY41: 0 | BZ41: 0 | CA41: | HSN/SAC | Taxable Amount | Input Tax IGST @ 18.0 | Input Tax IGST RCM @ 18.0 | | --- | --- | --- | --- | | 996511 | ₹ 1,26,728.00 | (5.0%) ₹ 6,336.40 | (5.0%) ₹ 6,336.40 | | CC41: 0 | CF41: 0 | CG41: 0 | CH41: 0 | CI41: 0 | CJ41: 0 | CM41: Dev Shri Road Line-Billing | CN41: 05, Ghas, Tonk, Rajasthan, State Code: 08, Pincode: 304001, India, | CP41: Unregistered | CW41: GC Foods Muzaffarpur-Billing | CX41: A-03 and A-04, Bela Industrial Estate, Muzaffarpur, Bihar, State Code: 10, Pincode: 842005, India, GSTIN: 10AACCG2244H1Z9, | CY41: GC Foods Muzaffarpur-Billing | CZ41: A-03 and A-04, Bela Industrial Estate, Muzaffarpur, Bihar, State Code: 10, Pincode: 842005, India, GSTIN: 10AACCG2244H1Z9, | DA41: 10AACCG2244H1Z9 | DB41: 10-Bihar | DD41: 0 | DG41: 100 | DH41: INR | DI41: No | DJ41: Stock Received But Not Billed - GCF | DP41: GCF Letterhead | DQ41: 0 | DS41: en | DY41: 0 | EA41: Road | EC41: 45864 | ED41: Regular | EE41: ITC on Reverse Charge | EG41: Not Applicable | EH41: 0 | EK41: 0 | EM41: Creditors (Transport) | EO41: 0 | EP41: Against Supplier Invoice GPL25/07878 dated 19-07-2025 | ER41: 1 | ES41: 1 | ET41: 126728 | EU41: 126728 | EV41: Transportation Charges (Interstate) | EW41: 126728 | EX41: 126728 | EY41: Nos | EZ41: 1 | FA41: Store Mujaffarpur - GCF | FB41: 0 | FC41: 1 | FI41: 0 | FJ41: 0 | FK41: 0 | FL41: 0 | FM41: 0 | FN41: 0 | FO41: Main - GCF | FQ41: Transportation Charges (Interstate) | FR41: 6648 | FS41: 4.984 | FT41: 0 | FU41: 0 | FV41: Stock Received But Not Billed - GCF | FX41: Taxable | FY41: 996511 | FZ41: 6336.4 | GA41: 5 | GC41: 0 | GD41: 0 | GE41: 0 | GF41: 0 | GG41: Transportation Charges (Interstate) | GH41: Services | GI41: 0 | GJ41: {"Output Tax SGST - GCF": 2.5, "Output Tax CGST - GCF": 2.5, "Output Tax IGST - GCF": 5.0, "Input Tax SGST - GCF": 2.5, "Input Tax CGST - GCF": 2.5, "Input Tax IGST - GCF": 5.0, "Input Tax SGST RCM - GCF": 2.5, "Input Tax CGST RCM - GCF": 2.5, "Input Tax IGST RCM - GCF": 5.0} | GK41: GST 5% - GCF | GL41: 0 | GO41: 0 | GS41: 126728 | GT41: 126728 | GU41: 126728 | GV41: 126728 | GW41: 0 | GX41: 1 | GY41: 133376 | GZ41: 133376 | HG41: PR/M/25-26/0127 | HH41: 95e4rda5i1 | HJ41: 126728 | HK41: 0 | HL41: 0 | HM41: 0 | HN41: 1 | HP41: 0 | HT41: 0 | IA41: 0 | IB41: 0 | ID41: Nos | IE41: Muzaffarpur | IF41: 126728 | IG41: 0 | IH41: 0 | II41: 126728 | IJ41: 0 | IN41: INR | IO41: Input Tax IGST - GCF | IP41: Add | IQ41: 6336.4 | IR41: 6336.4 | IT41: Total | IU41: 0 | IV41: Main - GCF | IW41: Input Tax IGST @ 18.0 | IX41: igst | IY41: 0 | IZ41: 0 | JA41: {"Transportation Charges (Interstate)":[5.0,6336.4]} | JC41: 6336.4 | JD41: 6336.4 | JE41: 0 | JF41: 133064.4 | JG41: 133064.4 | JH41: On Net Total | LD41: 0 | LF41: Percentage | LG41: 0 | LH41: 45862 | LI41: 100 | LK41: 126728 | LL41: 126728 | LM41: 0 | LN41: 0 | LO41: 126728 | LP41: 126728
IN42: INR | IO42: Input Tax IGST RCM - GCF | IP42: Deduct | IQ42: 6336.4 | IR42: 6336.4 | IT42: Total | IU42: 0 | IV42: Main - GCF | IW42: Input Tax IGST RCM @ 18.0 | IX42: igst_rcm | IY42: 0 | IZ42: 0 | JA42: {"Transportation Charges (Interstate)":[5.0,6336.4]} | JC42: 6336.4 | JD42: 6336.4 | JE42: 0 | JF42: 126728 | JG42: 126728 | JH42: On Net Total
A43: PI/M/25-26/0130 | B43: PI/M/25-26/0130-1 | C43: PINV-.YY.- | D43: Goyal Proteins Limited | E43: 45862 | F43: Muzaffarpur | G43: Creditors - GCF | H43: Goyal Proteins Limited | I43: Goyal Proteins Limited | L43: G. C. Foods Pvt. Ltd. | M43: 0.4868881 | N43: 1 | O43: 45862 | Q43: 0 | R43: 0 | T43: 1 | U43: 0 | V43: 1 | W43: 1 | X43: 0 | Y43: TDS ON PURCHASE - 194Q | Z43: GPL25/07878 | AA43: 45862 | AD43: INR | AE43: 1 | AF43: 1 | AG43: Standard Buying | AH43: INR | AI43: 1 | AJ43: 0 | AL43: 0 | AM43: Store Mujaffarpur - GCF | AO43: 0 | AR43: 41.88 | AS43: 0 | AT43: 1538527 | AU43: 1538527 | AV43: 1538527 | AW43: 1538527 | AX43: 1538527 | AY43: 1538527 | BA43: Input GST Out-state - GCF | BE43: 76926.53 | BF43: 1538.53 | BG43: 75388 | BH43: 76926.53 | BI43: 1538.53 | BJ43: 75388 | BK43: 1613915 | BL43: 0 | BM43: 0 | BN43: INR Sixteen Lakh, Thirteen Thousand, Nine Hundred And Fifteen only. | BO43: 1613915 | BP43: 0 | BQ43: 0 | BR43: 0 | BS43: INR Sixteen Lakh, Thirteen Thousand, Nine Hundred And Fifteen only. | BT43: 0 | BU43: 1613915 | BV43: 1 | BW43: Grand Total | BX43: 0 | BY43: 0 | BZ43: 0 | CA43: | HSN/SAC | Taxable Amount | Input Tax IGST @ 18.0 | TDS ON PURCHASE - 194Q | Rounded Off | | --- | --- | --- | --- | --- | | 23040030 | ₹ 15,37,720.00 | (5.0%) ₹ 76,886.00 | ₹ 1,537.72 | ₹ 0.18 | | 997133 | ₹ 807.00 | (5.0%) ₹ 40.35 | ₹ 0.81 | (0.0%) ₹ 0.00 | | CC43: 0 | CF43: 0 | CG43: 0 | CH43: 0 | CI43: 0 | CJ43: 0 | CM43: Goyal Proteins Limited-Billing | CN43: Kasar NH,52 , Kota, Rajasthan, State Code: 08, Pincode: 325003, India, GSTIN: 08AABCG3707A1Z7, | CO43: 08AABCG3707A1Z7 | CP43: Registered Regular | CW43: GC Foods Muzaffarpur-Billing | CX43: A-03 and A-04, Bela Industrial Estate, Muzaffarpur, Bihar, State Code: 10, Pincode: 842005, India, GSTIN: 10AACCG2244H1Z9, | CY43: GC Foods Muzaffarpur-Billing | CZ43: A-03 and A-04, Bela Industrial Estate, Muzaffarpur, Bihar, State Code: 10, Pincode: 842005, India, GSTIN: 10AACCG2244H1Z9, | DA43: 10AACCG2244H1Z9 | DB43: 10-Bihar | DD43: 0 | DG43: 100 | DH43: INR | DI43: No | DJ43: Stock Received But Not Billed - GCF,Cost of Goods Sold - GCF | DP43: GCF Letterhead | DQ43: 0 | DS43: en | DY43: 0 | EA43: Road | EC43: 45862 | ED43: Regular | EE43: All Other ITC | EG43: Unreconciled | EH43: 0 | EK43: 0 | EM43: Creditors - Soya | EO43: 0 | EP43: Against Supplier Invoice GPL25/07878 dated 24-07-2025 | ER43: 9.44 | ES43: 9440 | ET43: 358720 | EU43: 358720 | EV43: Soya Grit | EW43: 38000 | EX43: 38000 | EY43: Ton | EZ43: 1000 | FA43: Store Mujaffarpur - GCF | FB43: 0 | FC43: 1 | FI43: 0 | FJ43: 0 | FK43: 0 | FL43: 0 | FM43: 0 | FN43: 0 | FO43: Main - GCF | FQ43: Soyagrit | FR43: 0 | FS43: 0 | FT43: 0 | FU43: 0 | FV43: Stock Received But Not Billed - GCF | FX43: Taxable | FY43: 23040030 | FZ43: 17936 | GA43: 5 | GC43: 0 | GD43: 0 | GE43: 0 | GF43: 0 | GG43: Soya Grit | GH43: Raw Material | GI43: 0 | GJ43: {"Output Tax SGST - GCF": 2.5, "Output Tax CGST - GCF": 2.5, "Output Tax IGST - GCF": 5.0, "Input Tax SGST - GCF": 2.5, "Input Tax CGST - GCF": 2.5, "Input Tax IGST - GCF": 5.0, "Input Tax SGST RCM - GCF": 2.5, "Input Tax CGST RCM - GCF": 2.5, "Input Tax IGST RCM - GCF": 5.0} | GK43: GST 5% - GCF | GL43: 0 | GO43: 0 | GS43: 358720 | GT43: 358720 | GU43: 38000 | GV43: 38000 | GW43: 0 | GX43: 9.44 | GY43: 38000 | GZ43: 38000 | HG43: PR/M/25-26/0124 | HH43: a9okcdf656 | HJ43: 38 | HK43: 0 | HL43: 0 | HM43: 0 | HN43: 9.44 | HP43: 0 | HT43: 0 | IA43: 0 | IB43: 0 | ID43: KGS | IE43: Muzaffarpur | IF43: 358720 | IG43: 0 | IH43: 0 | II43: 38 | IJ43: 0 | IN43: INR | IO43: Input Tax IGST - GCF | IP43: Add | IQ43: 76926.35 | IR43: 76926.35 | IT43: Total | IU43: 0 | IV43: Main - GCF | IW43: Input Tax IGST @ 18.0 | IX43: igst | IY43: 0 | IZ43: 0 | JA43: {"Soya Grit":[5.0,76886.0],"Insurance Charges On Purchase":[5.0,40.35]} | JC43: 76926.35 | JD43: 76926.35 | JE43: 0 | JF43: 1615453.4 | JG43: 1615453.4 | JH43: On Net Total | LD43: 0 | LF43: Percentage | LG43: 0 | LH43: 45862 | LI43: 100 | LK43: 1613915 | LL43: 1613915 | LM43: 0 | LN43: 0 | LO43: 1613915 | LP43: 1613915
ER44: 31.44 | ES44: 31440 | ET44: 1179000 | EU44: 1179000 | EV44: Soya Grit | EW44: 37500 | EX44: 37500 | EY44: Ton | EZ44: 1000 | FA44: Store Mujaffarpur - GCF | FB44: 0 | FC44: 1 | FI44: 0 | FJ44: 0 | FK44: 0 | FL44: 0 | FM44: 0 | FN44: 0 | FO44: Main - GCF | FQ44: Soyagrit | FR44: 0 | FS44: 0 | FT44: 0 | FU44: 0 | FV44: Stock Received But Not Billed - GCF | FX44: Taxable | FY44: 23040030 | FZ44: 58950 | GA44: 5 | GC44: 0 | GD44: 0 | GE44: 0 | GF44: 0 | GG44: Soya Grit | GH44: Raw Material | GI44: 0 | GJ44: {"Output Tax SGST - GCF": 2.5, "Output Tax CGST - GCF": 2.5, "Output Tax IGST - GCF": 5.0, "Input Tax SGST - GCF": 2.5, "Input Tax CGST - GCF": 2.5, "Input Tax IGST - GCF": 5.0, "Input Tax SGST RCM - GCF": 2.5, "Input Tax CGST RCM - GCF": 2.5, "Input Tax IGST RCM - GCF": 5.0} | GK44: GST 5% - GCF | GL44: 0 | GO44: 0 | GS44: 1179000 | GT44: 1179000 | GU44: 37500 | GV44: 37500 | GW44: 0 | GX44: 31.44 | GY44: 37500 | GZ44: 37500 | HG44: PR/M/25-26/0124 | HH44: a9okbi6ceh | HJ44: 37.5 | HK44: 0 | HL44: 0 | HM44: 0 | HN44: 31.44 | HP44: 0 | HT44: 0 | IA44: 0 | IB44: 0 | ID44: KGS | IE44: Muzaffarpur | IF44: 1179000 | IG44: 0 | IH44: 0 | II44: 37.5 | IJ44: 0 | IN44: INR | IO44: TDS Payable - GCF | IP44: Deduct | IQ44: 1538.53 | IR44: 1538.53 | IT44: Total | IU44: 0 | IV44: Main - GCF | IW44: TDS ON PURCHASE - 194Q | IY44: 1 | IZ44: 0 | JA44: {"Soya Grit":[0.0,1537.72],"Insurance Charges On Purchase":[0.0,0.81]} | JC44: 1538.53 | JD44: 1538.53 | JE44: 0 | JF44: 1613914.8 | JG44: 1613914.8 | JH44: Actual
ER45: 1 | ES45: 1 | ET45: 807 | EU45: 807 | EV45: Insurance Charges On Purchase | EW45: 807 | EX45: 807 | EY45: Nos | EZ45: 1 | FA45: Store Mujaffarpur - GCF | FB45: 0 | FC45: 1 | FI45: 0 | FJ45: 0 | FK45: 0 | FL45: 0 | FM45: 0 | FN45: 0 | FO45: Main - GCF | FQ45: Insurance Charges On Purchase | FR45: 0 | FS45: 0 | FT45: 0 | FU45: 0 | FV45: Cost of Goods Sold - GCF | FX45: Taxable | FY45: 997133 | FZ45: 40.35 | GA45: 5 | GC45: 0 | GD45: 0 | GE45: 0 | GF45: 0 | GG45: Insurance Charges On Purchase | GH45: Services | GI45: 0 | GJ45: {"Output Tax SGST - GCF": 2.5, "Output Tax CGST - GCF": 2.5, "Output Tax IGST - GCF": 5.0, "Input Tax SGST - GCF": 2.5, "Input Tax CGST - GCF": 2.5, "Input Tax IGST - GCF": 5.0, "Input Tax SGST RCM - GCF": 2.5, "Input Tax CGST RCM - GCF": 2.5, "Input Tax IGST RCM - GCF": 5.0} | GK45: GST 5% - GCF | GL45: 0 | GO45: 0 | GS45: 807 | GT45: 807 | GU45: 807 | GV45: 807 | GW45: 0 | GX45: 1 | GY45: 807 | GZ45: 807 | HG45: PR/M/25-26/0124 | HH45: a9oke7e7r9 | HJ45: 807 | HK45: 0 | HL45: 0 | HM45: 0 | HN45: 1 | HP45: 0 | HT45: 0 | IA45: 0 | IB45: 0 | ID45: Nos | IF45: 807 | IG45: 0 | IH45: 0 | II45: 0 | IJ45: 0 | IN45: INR | IO45: Rounded Off - GCF | IP45: Add | IQ45: 0.18 | IR45: 0.18 | IT45: Total | IU45: 0 | IV45: Main - GCF | IW45: Rounded Off | IY45: 0 | IZ45: 0 | JA45: {"Soya Grit":[0.0,0.18],"Insurance Charges On Purchase":[0.0,0.0]} | JC45: 0.18 | JD45: 0.18 | JE45: 0 | JF45: 1613915 | JG45: 1613915 | JH45: Actual
A46: PI/M/25-26/0127 | B46: PI/M/25-26/0127-1 | C46: PINV-.YY.- | D46: Jaibalajee Polypark Private Limited | E46: 45860 | F46: Muzaffarpur | G46: Creditors - GCF | H46: Jaibalajee Polypark Private Limited | I46: Jaibalajee Polypark Private Limited | L46: G. C. Foods Pvt. Ltd. | M46: 0.62946834 | N46: 1 | O46: 45860 | Q46: 0 | R46: 0 | T46: 1 | U46: 0 | V46: 1 | W46: 0 | X46: 0 | Z46: JBP/25-26/1245 | AA46: 45860 | AD46: INR | AE46: 1 | AF46: 1 | AG46: Standard Buying | AH46: INR | AI46: 1 | AJ46: 0 | AL46: 0 | AM46: Store Mujaffarpur - GCF | AO46: 0 | AR46: 1800 | AS46: 0 | AT46: 27000 | AU46: 27000 | AV46: 27000 | AW46: 27000 | AX46: 27000 | AY46: 27000 | BA46: Input GST In-state - GCF | BE46: 4860 | BF46: 0 | BG46: 4860 | BH46: 4860 | BI46: 0 | BJ46: 4860 | BK46: 31860 | BL46: 0 | BM46: 0 | BN46: INR Thirty One Thousand, Eight Hundred And Sixty only. | BO46: 31860 | BP46: 0 | BQ46: 0 | BR46: 0 | BS46: INR Thirty One Thousand, Eight Hundred And Sixty only. | BT46: 0 | BU46: 31860 | BV46: 1 | BW46: Grand Total | BX46: 0 | BY46: 0 | BZ46: 0 | CA46: | HSN/SAC | Taxable Amount | Input Tax CGST @ 9.0 | Input Tax SGST @ 9.0 | | --- | --- | --- | --- | | 392329 | ₹ 27,000.00 | (9.0%) ₹ 2,430.00 | (9.0%) ₹ 2,430.00 | | CC46: 0 | CF46: 0 | CG46: 0 | CH46: 0 | CI46: 0 | CJ46: 0 | CM46: Jaibalajee Polypark Private Limited-Billing | CN46: C/O Jaibalajee Polypark PVT Ltd., Near Shahi Chowk Jasholi, Motipur, MuzaffarpurMuzaffarpur, Bihar, State Code: 10, Pincode: 843111, India, GSTIN: 10AAFCJ0866R1ZA, | CO46: 10AAFCJ0866R1ZA | CP46: Registered Regular | CW46: GC Foods Muzaffarpur-Billing | CX46: A-03 and A-04, Bela Industrial Estate, Muzaffarpur, Bihar, State Code: 10, Pincode: 842005, India, GSTIN: 10AACCG2244H1Z9, | CY46: GC Foods Muzaffarpur-Billing | CZ46: A-03 and A-04, Bela Industrial Estate, Muzaffarpur, Bihar, State Code: 10, Pincode: 842005, India, GSTIN: 10AACCG2244H1Z9, | DA46: 10AACCG2244H1Z9 | DB46: 10-Bihar | DD46: 0 | DG46: 100 | DH46: INR | DI46: No | DJ46: Stock Received But Not Billed - GCF | DP46: GCF Letterhead | DQ46: 0 | DS46: en | DY46: 0 | EA46: Road | EC46: 45863 | ED46: Regular | EE46: All Other ITC | EG46: Unreconciled | EH46: 0 | EK46: 0 | EO46: 0 | EP46: Against Supplier Invoice JBP/25-26/1245 dated 22-07-2025 | ER46: 1800 | ES46: 1800 | ET46: 27000 | EU46: 27000 | EV46: Soyabari Bag | EW46: 15 | EX46: 15 | EY46: PCS | EZ46: 1 | FA46: Store Mujaffarpur - GCF | FB46: 0 | FC46: 1 | FI46: 0 | FJ46: 0 | FK46: 0 | FL46: 0 | FM46: 2430 | FN46: 9 | FO46: Main - GCF | FQ46: soyabari Bag | FR46: 0 | FS46: 0 | FT46: 0 | FU46: 0 | FV46: Stock Received But Not Billed - GCF | FX46: Taxable | FY46: 392329 | FZ46: 0 | GA46: 0 | GC46: 0 | GD46: 0 | GE46: 0 | GF46: 0 | GG46: Soyabari Bag | GH46: Packing Material - PM | GI46: 0 | GJ46: {"Output Tax SGST - GCF": 9.0, "Output Tax CGST - GCF": 9.0, "Output Tax IGST - GCF": 18.0, "Input Tax SGST - GCF": 9.0, "Input Tax CGST - GCF": 9.0, "Input Tax IGST - GCF": 18.0, "Input Tax SGST RCM - GCF": 9.0, "Input Tax CGST RCM - GCF": 9.0, "Input Tax IGST RCM - GCF": 18.0} | GK46: GST 18% - GCF | GL46: 0 | GO46: 0 | GS46: 27000 | GT46: 27000 | GU46: 15 | GV46: 15 | GW46: 0 | GX46: 1800 | GY46: 0 | GZ46: 0 | HG46: PR/M/25-26/0126 | HH46: c865abqjee | HJ46: 15 | HK46: 0 | HL46: 0 | HM46: 0 | HN46: 1800 | HP46: 0 | HT46: 0 | IA46: 2430 | IB46: 9 | ID46: PCS | IE46: Muzaffarpur | IF46: 27000 | IG46: 0 | IH46: 0 | II46: 15 | IJ46: 0 | IN46: INR | IO46: Input Tax CGST - GCF | IP46: Add | IQ46: 2430 | IR46: 2430 | IT46: Total | IU46: 0 | IV46: Main - GCF | IW46: Input Tax CGST @ 9.0 | IX46: cgst | IY46: 0 | IZ46: 0 | JA46: {"Soyabari Bag":[9.0,2430.0]} | JC46: 2430 | JD46: 2430 | JE46: 0 | JF46: 29430 | JG46: 29430 | JH46: On Net Total | LD46: 0 | LF46: Percentage | LG46: 0 | LH46: 45860 | LI46: 100 | LK46: 31860 | LL46: 31860 | LM46: 0 | LN46: 0 | LO46: 31860 | LP46: 31860
IN47: INR | IO47: Input Tax SGST - GCF | IP47: Add | IQ47: 2430 | IR47: 2430 | IT47: Total | IU47: 0 | IV47: Main - GCF | IW47: Input Tax SGST @ 9.0 | IX47: sgst | IY47: 0 | IZ47: 0 | JA47: {"Soyabari Bag":[9.0,2430.0]} | JC47: 2430 | JD47: 2430 | JE47: 0 | JF47: 31860 | JG47: 31860 | JH47: On Net Total
A48: PI/M/25-26/0126 | B48: PI/M/25-26/0126-1 | C48: PINV-.YY.- | D48: Jaibalajee Polypark Private Limited | E48: 45861 | F48: Muzaffarpur | G48: Creditors - GCF | H48: Jaibalajee Polypark Private Limited | I48: Jaibalajee Polypark Private Limited | L48: G. C. Foods Pvt. Ltd. | M48: 0.62417644 | N48: 1 | O48: 45861 | Q48: 0 | R48: 0 | T48: 1 | U48: 0 | V48: 1 | W48: 0 | X48: 0 | Z48: JBP/25-26/1288 | AA48: 45861 | AD48: INR | AE48: 1 | AF48: 1 | AG48: Standard Buying | AH48: INR | AI48: 1 | AJ48: 0 | AL48: 0 | AM48: Store Mujaffarpur - GCF | AO48: 0 | AR48: 5100 | AS48: 0 | AT48: 116800 | AU48: 116800 | AV48: 116800 | AW48: 116800 | AX48: 116800 | AY48: 116800 | BA48: Input GST In-state - GCF | BE48: 21024 | BF48: 0 | BG48: 21024 | BH48: 21024 | BI48: 0 | BJ48: 21024 | BK48: 137824 | BL48: 0 | BM48: 0 | BN48: INR One Lakh, Thirty Seven Thousand, Eight Hundred And Twenty Four only. | BO48: 137824 | BP48: 0 | BQ48: 0 | BR48: 0 | BS48: INR One Lakh, Thirty Seven Thousand, Eight Hundred And Twenty Four only. | BT48: 0 | BU48: 137824 | BV48: 1 | BW48: Grand Total | BX48: 0 | BY48: 0 | BZ48: 0 | CA48: | HSN/SAC | Taxable Amount | Input Tax CGST @ 9.0 | Input Tax SGST @ 9.0 | | --- | --- | --- | --- | | 392329 | ₹ 1,16,800.00 | (9.0%) ₹ 10,512.00 | (9.0%) ₹ 10,512.00 | | CC48: 0 | CF48: 0 | CG48: 0 | CH48: 0 | CI48: 0 | CJ48: 0 | CM48: Jaibalajee Polypark Private Limited-Billing | CN48: C/O Jaibalajee Polypark PVT Ltd., Near Shahi Chowk Jasholi, Motipur, MuzaffarpurMuzaffarpur, Bihar, State Code: 10, Pincode: 843111, India, GSTIN: 10AAFCJ0866R1ZA, | CO48: 10AAFCJ0866R1ZA | CP48: Registered Regular | CW48: GC Foods Muzaffarpur-Billing | CX48: A-03 and A-04, Bela Industrial Estate, Muzaffarpur, Bihar, State Code: 10, Pincode: 842005, India, GSTIN: 10AACCG2244H1Z9, | CY48: GC Foods Muzaffarpur-Billing | CZ48: A-03 and A-04, Bela Industrial Estate, Muzaffarpur, Bihar, State Code: 10, Pincode: 842005, India, GSTIN: 10AACCG2244H1Z9, | DA48: 10AACCG2244H1Z9 | DB48: 10-Bihar | DD48: 0 | DG48: 100 | DH48: INR | DI48: No | DJ48: Stock Received But Not Billed - GCF | DP48: GCF Letterhead | DQ48: 0 | DS48: en | DY48: 0 | EA48: Road | EC48: 45863 | ED48: Regular | EE48: All Other ITC | EG48: Unreconciled | EH48: 0 | EK48: 0 | EO48: 0 | EP48: Against Supplier Invoice JBP/25-26/1288 dated 23-07-2025 | ER48: 3100 | ES48: 3100 | ET48: 86800 | EU48: 86800 | EV48: Soyabari Bag | EW48: 28 | EX48: 28 | EY48: PCS | EZ48: 1 | FA48: Store Mujaffarpur - GCF | FB48: 0 | FC48: 1 | FI48: 0 | FJ48: 0 | FK48: 0 | FL48: 0 | FM48: 7812 | FN48: 9 | FO48: Main - GCF | FQ48: soyabari Bag | FR48: 9 | FS48: 24.324 | FT48: 0 | FU48: 0 | FV48: Stock Received But Not Billed - GCF | FX48: Taxable | FY48: 392329 | FZ48: 0 | GA48: 0 | GC48: 0 | GD48: 0 | GE48: 0 | GF48: 0 | GG48: Soyabari Bag | GH48: Packing Material - PM | GI48: 0 | GJ48: {"Output Tax SGST - GCF": 9.0, "Output Tax CGST - GCF": 9.0, "Output Tax IGST - GCF": 18.0, "Input Tax SGST - GCF": 9.0, "Input Tax CGST - GCF": 9.0, "Input Tax IGST - GCF": 18.0, "Input Tax SGST RCM - GCF": 9.0, "Input Tax CGST RCM - GCF": 9.0, "Input Tax IGST RCM - GCF": 18.0} | GK48: GST 18% - GCF | GL48: 0 | GO48: 0 | GS48: 86800 | GT48: 86800 | GU48: 28 | GV48: 28 | GW48: 0 | GX48: 3100 | GY48: 37 | GZ48: 37 | HG48: PR/M/25-26/0125 | HH48: 33jh44jill | HJ48: 28 | HK48: 0 | HL48: 0 | HM48: 0 | HN48: 3100 | HP48: 0 | HT48: 0 | IA48: 7812 | IB48: 9 | ID48: PCS | IE48: Muzaffarpur | IF48: 86800 | IG48: 0 | IH48: 0 | II48: 28 | IJ48: 0 | IN48: INR | IO48: Input Tax CGST - GCF | IP48: Add | IQ48: 10512 | IR48: 10512 | IT48: Total | IU48: 0 | IV48: Main - GCF | IW48: Input Tax CGST @ 9.0 | IX48: cgst | IY48: 0 | IZ48: 0 | JA48: {"Soyabari Bag":[9.0,10512.0]} | JC48: 10512 | JD48: 10512 | JE48: 0 | JF48: 127312 | JG48: 127312 | JH48: On Net Total | LD48: 0 | LF48: Percentage | LG48: 0 | LH48: 45861 | LI48: 100 | LK48: 137824 | LL48: 137824 | LM48: 0 | LN48: 0 | LO48: 137824 | LP48: 137824
ER49: 2000 | ES49: 2000 | ET49: 30000 | EU49: 30000 | EV49: Soyabari Bag | EW49: 15 | EX49: 15 | EY49: PCS | EZ49: 1 | FA49: Store Mujaffarpur - GCF | FB49: 0 | FC49: 1 | FI49: 0 | FJ49: 0 | FK49: 0 | FL49: 0 | FM49: 2700 | FN49: 9 | FO49: Main - GCF | FQ49: soyabari Bag | FR49: 22 | FS49: 59.459 | FT49: 0 | FU49: 0 | FV49: Stock Received But Not Billed - GCF | FX49: Taxable | FY49: 392329 | FZ49: 0 | GA49: 0 | GC49: 0 | GD49: 0 | GE49: 0 | GF49: 0 | GG49: Soyabari Bag | GH49: Packing Material - PM | GI49: 0 | GJ49: {"Output Tax SGST - GCF": 9.0, "Output Tax CGST - GCF": 9.0, "Output Tax IGST - GCF": 18.0, "Input Tax SGST - GCF": 9.0, "Input Tax CGST - GCF": 9.0, "Input Tax IGST - GCF": 18.0, "Input Tax SGST RCM - GCF": 9.0, "Input Tax CGST RCM - GCF": 9.0, "Input Tax IGST RCM - GCF": 18.0} | GK49: GST 18% - GCF | GL49: 0 | GO49: 0 | GS49: 30000 | GT49: 30000 | GU49: 15 | GV49: 15 | GW49: 0 | GX49: 2000 | GY49: 37 | GZ49: 37 | HG49: PR/M/25-26/0125 | HH49: 33jh7vjnil | HJ49: 15 | HK49: 0 | HL49: 0 | HM49: 0 | HN49: 2000 | HP49: 0 | HT49: 0 | IA49: 2700 | IB49: 9 | ID49: PCS | IE49: Muzaffarpur | IF49: 30000 | IG49: 0 | IH49: 0 | II49: 15 | IJ49: 0 | IN49: INR | IO49: Input Tax SGST - GCF | IP49: Add | IQ49: 10512 | IR49: 10512 | IT49: Total | IU49: 0 | IV49: Main - GCF | IW49: Input Tax SGST @ 9.0 | IX49: sgst | IY49: 0 | IZ49: 0 | JA49: {"Soyabari Bag":[9.0,10512.0]} | JC49: 10512 | JD49: 10512 | JE49: 0 | JF49: 137824 | JG49: 137824 | JH49: On Net Total
A50: PI/G/25-26/0196 | B50: PI/G/25-26/0196-1 | C50: PINV-.YY.- | D50: Om Sai Ram Traders | E50: 45862 | F50: Ghaziabad | G50: Creditors - GCF | H50: Om Sai Ram Traders | I50: Om Sai Ram Traders | L50: G. C. Foods Pvt. Ltd. | M50: 0.75389113 | N50: 0 | O50: 45862 | Q50: 0 | R50: 0 | T50: 1 | U50: 0 | V50: 1 | W50: 0 | X50: 0 | Z50: 123 | AA50: 45862 | AD50: INR | AE50: 1 | AF50: 1 | AG50: Standard Buying | AH50: INR | AI50: 1 | AJ50: 0 | AL50: 0 | AM50: Store Ghaziabad - GCF | AO50: 1 | AQ50: Stores Noida - GCF | AR50: 1 | AS50: 0 | AT50: 10 | AU50: 10 | AV50: 10 | AW50: 10 | AX50: 10 | AY50: 10 | BE50: 0 | BF50: 0 | BG50: 0 | BH50: 0 | BI50: 0 | BJ50: 0 | BK50: 10 | BL50: 0 | BM50: 0 | BN50: INR Ten only. | BO50: 10 | BP50: 0 | BQ50: 0 | BR50: 0 | BS50: INR Ten only. | BT50: 0 | BU50: 10 | BV50: 1 | BW50: Grand Total | BX50: 0 | BY50: 0 | BZ50: 0 | CC50: 0 | CF50: 0 | CG50: 0 | CH50: 0 | CI50: 0 | CJ50: 0 | CM50: Om Sai Ram Traders-Billing | CN50: House No. 183, Khasra No. 13/18, Ground Floor, Swaroop NagarNorth West Delhi, Delhi, State Code: 07, Pincode: 110042, India, GSTIN: 07AMYPK9910F1ZJ, | CO50: 07AMYPK9910F1ZJ | CP50: Registered Regular | CW50: G.C. Foods Pvt. Ltd.Ghaziabad - Uttar Pradesh-Billing | CX50: C-4, Sector A-2, , Tronica city Indl. Area, LoniGhaziabad, Uttar Pradesh, State Code: 09, Pincode: 201103, India, Phone: 9350041990, GSTIN: 09AACCG2244H1ZS, | CY50: G.C. Foods Pvt. Ltd.Ghaziabad - Uttar Pradesh-Billing | CZ50: C-4, Sector A-2, , Tronica city Indl. Area, LoniGhaziabad, Uttar Pradesh, State Code: 09, Pincode: 201103, India, Phone: 9350041990, GSTIN: 09AACCG2244H1ZS, | DA50: 09AACCG2244H1ZS | DB50: 09-Uttar Pradesh | DD50: 0 | DG50: 100 | DH50: INR | DI50: No | DJ50: Cost of Goods Sold - GCF | DP50: GCF Letterhead | DQ50: 0 | DS50: en | DY50: 0 | EA50: Road | EC50: 45862 | ED50: Regular | EE50: All Other ITC | EG50: Unreconciled | EH50: 0 | EK50: 0 | EM50: Creditors - Raw Material | EO50: 0 | EP50: Against Supplier Invoice 123 dated 24-07-2025 | ER50: 1 | ES50: 1 | ET50: 10 | EU50: 10 | EV50: Job Work Test | EW50: 10 | EX50: 10 | EY50: Nos | EZ50: 1 | FA50: Store Ghaziabad - GCF | FB50: 0 | FC50: 1 | FI50: 0 | FJ50: 0 | FK50: 0 | FL50: 0 | FM50: 0 | FN50: 0 | FO50: Main - GCF | FQ50: Job Work Test | FR50: 0 | FS50: 0 | FT50: 0 | FU50: 0 | FV50: Cost of Goods Sold - GCF | FX50: Nil-Rated | FY50: 071320 | FZ50: 0 | GA50: 0 | GC50: 0 | GD50: 0 | GE50: 0 | GF50: 0 | GG50: Job Work Test | GH50: Services | GI50: 0 | GJ50: {} | GL50: 0 | GO50: 0 | GS50: 10 | GT50: 10 | GU50: 10 | GV50: 10 | GW50: 0 | GX50: 1 | GY50: 10 | GZ50: 10 | HE50: PO/G/25-26/0141-1 | HF50: 73n8onqqns | HG50: PR/G/25-26/0209 | HH50: 158dlpmf0p | HJ50: 10 | HK50: 0 | HL50: 0 | HM50: 0 | HN50: 1 | HP50: 0 | HT50: 0 | IA50: 0 | IB50: 0 | ID50: Nos | IE50: Ghaziabad | IF50: 10 | IG50: 0 | IH50: 0 | II50: 0 | IJ50: 0 | LD50: 0 | LF50: Percentage | LG50: 0 | LH50: 45862 | LI50: 100 | LK50: 10 | LL50: 10 | LM50: 0 | LN50: 0 | LO50: 10 | LP50: 10
A51: PI/N/25-26/0039 | B51: PI/N/25-26/0039-1 | C51: PINV-.YY.- | D51: Unique Pack Tech | E51: 45754 | F51: Noida | G51: Creditors - GCF | H51: Unique Pack Tech | I51: Unique Pack Tech | L51: G. C. Foods Pvt. Ltd. | M51: 0.7260445 | N51: 1 | O51: 45754 | Q51: 0 | R51: 0 | T51: 1 | U51: 0 | V51: 1 | W51: 0 | X51: 0 | Z51: U/25-26/0032 | AA51: 45754 | AD51: INR | AE51: 1 | AF51: 1 | AG51: Standard Selling Delhi | AH51: INR | AI51: 1 | AJ51: 0 | AL51: 0 | AM51: Stores Noida - GCF | AO51: 0 | AR51: 319.76 | AS51: 0 | AT51: 69068.16 | AU51: 69068.16 | AV51: 69068.16 | AW51: 69068.16 | AX51: 69068.16 | AY51: 69068.16 | BA51: Input GST In-state - GCF | BE51: 12431.84 | BF51: 0 | BG51: 12431.84 | BH51: 12431.84 | BI51: 0 | BJ51: 12431.84 | BK51: 81500 | BL51: 0 | BM51: 0 | BN51: INR Eighty One Thousand, Five Hundred only. | BO51: 81500 | BP51: 0 | BQ51: 0 | BR51: 0 | BS51: INR Eighty One Thousand, Five Hundred only. | BT51: 0 | BU51: 81500 | BV51: 1 | BW51: Grand Total | BX51: 0 | BY51: 0 | BZ51: 0 | CA51: | HSN/SAC | Taxable Amount | Input Tax CGST @ 9.0 | Input Tax SGST @ 9.0 | Rounded Off | | --- | --- | --- | --- | --- | | 392190 | ₹ 69,068.16 | (9.0%) ₹ 6,216.13 | (9.0%) ₹ 6,216.13 | ₹ -0.42 | | CC51: 0 | CF51: 0 | CG51: 0 | CH51: 0 | CI51: 0 | CJ51: 0 | CM51: Unique Pack Tech-Billing | CN51: B-12, 1st Floor, Sector-57, Noida, Up, Noida, Uttar Pradesh, State Code: 09, Pincode: 201301, India, Phone: 9350836603, GSTIN: 09AJDPP7545D1Z2, | CO51: 09AJDPP7545D1Z2 | CP51: Registered Regular | CW51: G.C. Foods Pvt. Ltd. Noida - Uttar Pradesh (Shipping) | CX51: B-64, Sector-80,, Noida, Gautam Buddha Nagar, Noida, Uttar Pradesh, State Code: 09, Pincode: 201305, India, Phone: 9958003759, GSTIN: 09AACCG2244H1ZS, | CY51: G.C. Foods Pvt. Ltd. Noida - Uttar Pradesh (Shipping) | CZ51: B-64, Sector-80,, Noida, Gautam Buddha Nagar, Noida, Uttar Pradesh, State Code: 09, Pincode: 201305, India, Phone: 9958003759, GSTIN: 09AACCG2244H1ZS, | DA51: 09AACCG2244H1ZS | DB51: 09-Uttar Pradesh | DD51: 0 | DF51: Printed Peanut Cookies Leminate \* 16 Role = 319.170kg @216 + Tax , Against Bill No. U/25-26/0032 , Ingate Receipt No. 009 , Ingate Date - 07.04.2025 | DG51: 100 | DH51: INR | DI51: No | DJ51: Stock Received But Not Billed - GCF | DP51: GCF Letterhead | DQ51: 0 | DS51: en | DY51: 0 | EA51: Road | EC51: 45862 | ED51: Regular | EE51: All Other ITC | EG51: Unreconciled | EH51: 0 | EK51: 0 | EM51: Creditors - Raw Material | EO51: 0 | EP51: Against Supplier Invoice U/25-26/0032 dated 07-04-2025 | ER51: 319.76 | ES51: 319.76 | ET51: 69068.16 | EU51: 69068.16 | EV51: Laminate Peanut Cookies 200g | EW51: 216 | EX51: 216 | EY51: KGS | EZ51: 1 | FA51: Stores Noida - GCF | FB51: 0 | FC51: 1 | FI51: 0 | FJ51: 0 | FK51: 0 | FL51: 0 | FM51: 6216.13 | FN51: 9 | FO51: Main - GCF | FQ51: Leminate Peanut Cookies 400 Gm | FR51: 0 | FS51: 0 | FT51: 0 | FU51: 0 | FV51: Stock Received But Not Billed - GCF | FX51: Taxable | FY51: 392190 | FZ51: 0 | GA51: 0 | GC51: 0 | GD51: 0 | GE51: 0 | GF51: 0 | GG51: Laminate Peanut Cookies 200g | GH51: Cookies - PM | GI51: 0 | GJ51: {"Output Tax SGST - GCF": 9.0, "Output Tax CGST - GCF": 9.0, "Output Tax IGST - GCF": 18.0, "Input Tax SGST - GCF": 9.0, "Input Tax CGST - GCF": 9.0, "Input Tax IGST - GCF": 18.0, "Input Tax SGST RCM - GCF": 9.0, "Input Tax CGST RCM - GCF": 9.0, "Input Tax IGST RCM - GCF": 18.0} | GK51: GST 18% - GCF | GL51: 0 | GO51: 0 | GS51: 69068.16 | GT51: 69068.16 | GU51: 216 | GV51: 216 | GW51: 0 | GX51: 319.76 | GY51: 216 | GZ51: 216 | HG51: PR/N/25-26/0079 | HH51: bdhqh3cg4n | HJ51: 216 | HK51: 0 | HL51: 0 | HM51: 0 | HN51: 319.76 | HP51: 0 | HT51: 0 | IA51: 6216.13 | IB51: 9 | ID51: KGS | IE51: Noida | IF51: 69068.16 | IG51: 0 | IH51: 0 | II51: 216 | IJ51: 0 | IN51: INR | IO51: Input Tax CGST - GCF | IP51: Add | IQ51: 6216.13 | IR51: 6216.13 | IT51: Total | IU51: 0 | IV51: Main - GCF | IW51: Input Tax CGST @ 9.0 | IX51: cgst | IY51: 0 | IZ51: 0 | JA51: {"Laminate Peanut Cookies 200g":[9.0,6216.13]} | JC51: 6216.13 | JD51: 6216.13 | JE51: 0 | JF51: 75284.29 | JG51: 75284.29 | JH51: On Net Total | LD51: 0 | LF51: Percentage | LG51: 0 | LH51: 45754 | LI51: 100 | LK51: 81500 | LL51: 81500 | LM51: 0 | LN51: 0 | LO51: 81500 | LP51: 81500
IN52: INR | IO52: Input Tax SGST - GCF | IP52: Add | IQ52: 6216.13 | IR52: 6216.13 | IT52: Total | IU52: 0 | IV52: Main - GCF | IW52: Input Tax SGST @ 9.0 | IX52: sgst | IY52: 0 | IZ52: 0 | JA52: {"Laminate Peanut Cookies 200g":[9.0,6216.13]} | JC52: 6216.13 | JD52: 6216.13 | JE52: 0 | JF52: 81500.42 | JG52: 81500.42 | JH52: On Net Total
IN53: INR | IO53: Rounded Off - GCF | IP53: Add | IQ53: -0.42 | IR53: -0.42 | IT53: Total | IU53: 0 | IV53: Main - GCF | IW53: Rounded Off | IY53: 0 | IZ53: 0 | JA53: {"Laminate Peanut Cookies 200g":[0.0,-0.42]} | JC53: -0.42 | JD53: -0.42 | JE53: 0 | JF53: 81500 | JG53: 81500 | JH53: Actual
A54: PI/N/25-26/0037 | B54: PI/N/25-26/0037-1 | C54: PINV-.YY.- | D54: Suryansh Enterprises | E54: 45849 | F54: Noida | G54: Creditors - GCF | H54: Suryansh Enterprises | I54: Suryansh Enterprises | L54: G. C. Foods Pvt. Ltd. | M54: 0.70201396 | N54: 1 | O54: 45849 | Q54: 0 | R54: 0 | T54: 1 | U54: 0 | V54: 1 | W54: 0 | X54: 0 | Z54: GST/25-26/642 | AA54: 45849 | AD54: INR | AE54: 1 | AF54: 1 | AG54: Standard Buying | AH54: INR | AI54: 1 | AJ54: 0 | AL54: 0 | AM54: Stores Noida - GCF | AO54: 0 | AR54: 165 | AS54: 0 | AT54: 24200.55 | AU54: 24200.55 | AV54: 24200.55 | AW54: 24200.55 | AX54: 24200.55 | AY54: 24200.55 | BA54: Input GST In-state - GCF | BE54: 1209.45 | BF54: 0 | BG54: 1209.45 | BH54: 1209.45 | BI54: 0 | BJ54: 1209.45 | BK54: 25410 | BL54: 0 | BM54: 0 | BN54: INR Twenty Five Thousand, Four Hundred And Ten only. | BO54: 25410 | BP54: 0 | BQ54: 0 | BR54: 0 | BS54: INR Twenty Five Thousand, Four Hundred And Ten only. | BT54: 0 | BU54: 25410 | BV54: 1 | BW54: Grand Total | BX54: 0 | BY54: 0 | BZ54: 0 | CA54: | HSN/SAC | Taxable Amount | Input Tax CGST @ 9.0 | Input Tax SGST @ 9.0 | Rounded Off | | --- | --- | --- | --- | --- | | 15119020 | ₹ 22,000.50 | (2.5%) ₹ 550.01 | (2.5%) ₹ 550.01 | ₹ -0.52 | | 15179090 | ₹ 2,200.05 | (2.5%) ₹ 55.00 | (2.5%) ₹ 55.00 | ₹ -0.05 | | CC54: 0 | CF54: 0 | CG54: 0 | CH54: 0 | CI54: 0 | CJ54: 0 | CM54: Suryansh Enterprises-Billing-1 | CN54: RC-216, Gali No-14, Pragati Vihar Khora Colony, Ghaziabad , Uttar PradeshGhaziabad, Uttar Pradesh, State Code: 09, Pincode: 201309, India, GSTIN: 09AAJPD9813B1ZW, | CO54: 09AAJPD9813B1ZW | CP54: Registered Regular | CW54: G.C. Foods Pvt. Ltd. Noida - Uttar Pradesh (Shipping) | CX54: B-64, Sector-80,, Noida, Gautam Buddha Nagar, Noida, Uttar Pradesh, State Code: 09, Pincode: 201305, India, Phone: 9958003759, GSTIN: 09AACCG2244H1ZS, | CY54: G.C. Foods Pvt. Ltd. Noida - Uttar Pradesh (Shipping) | CZ54: B-64, Sector-80,, Noida, Gautam Buddha Nagar, Noida, Uttar Pradesh, State Code: 09, Pincode: 201305, India, Phone: 9958003759, GSTIN: 09AACCG2244H1ZS, | DA54: 09AACCG2244H1ZS | DB54: 09-Uttar Pradesh | DD54: 0 | DG54: 100 | DH54: INR | DI54: No | DJ54: Stock Received But Not Billed - GCF | DP54: GCF Letterhead | DQ54: 0 | DS54: en | DY54: 0 | EA54: Road | EC54: 45862 | ED54: Regular | EE54: All Other ITC | EG54: Unreconciled | EH54: 0 | EK54: 0 | EM54: Creditors - Raw Material | EO54: 0 | EP54: Against Supplier Invoice GST/25-26/642 dated 11-07-2025 | ER54: 150 | ES54: 150 | ET54: 22000.5 | EU54: 22000.5 | EV54: Vanaspati Ghee | EW54: 146.67 | EX54: 146.67 | EY54: KGS | EZ54: 1 | FA54: Stores Noida - GCF | FB54: 0 | FC54: 1 | FI54: 0 | FJ54: 0 | FK54: 0 | FL54: 0 | FM54: 550.01 | FN54: 2.5 | FO54: Main - GCF | FQ54: Vanaspati Ghee | FR54: 3.33 | FS54: 2.22 | FT54: 0 | FU54: 0 | FV54: Stock Received But Not Billed - GCF | FX54: Taxable | FY54: 15119020 | FZ54: 0 | GA54: 0 | GC54: 0 | GD54: 0 | GE54: 0 | GF54: 0 | GG54: Vanaspati Ghee | GH54: Cookies - RM | GI54: 0 | GJ54: {"Output Tax SGST - GCF": 2.5, "Output Tax CGST - GCF": 2.5, "Output Tax IGST - GCF": 5.0, "Input Tax SGST - GCF": 2.5, "Input Tax CGST - GCF": 2.5, "Input Tax IGST - GCF": 5.0, "Input Tax SGST RCM - GCF": 2.5, "Input Tax CGST RCM - GCF": 2.5, "Input Tax IGST RCM - GCF": 5.0} | GK54: GST 5% - GCF | GL54: 0 | GO54: 0 | GS54: 22000.5 | GT54: 22000.5 | GU54: 146.67 | GV54: 146.67 | GW54: 0 | GX54: 150 | GY54: 150 | GZ54: 150 | HE54: PO/N/25-26/0028 | HF54: 5oobbjktri | HG54: PR/N/25-26/0077 | HH54: cpgiticfhv | HJ54: 146.67 | HK54: 0 | HL54: 0 | HM54: 0 | HN54: 150 | HP54: 0 | HT54: 0 | IA54: 550.01 | IB54: 2.5 | ID54: KGS | IE54: Noida | IF54: 22000.5 | IG54: 0 | IH54: 0 | II54: 146.67 | IJ54: 0 | IN54: INR | IO54: Input Tax CGST - GCF | IP54: Add | IQ54: 605.01 | IR54: 605.01 | IT54: Total | IU54: 0 | IV54: Main - GCF | IW54: Input Tax CGST @ 9.0 | IX54: cgst | IY54: 0 | IZ54: 0 | JA54: {"Vanaspati Ghee":[2.5,550.01],"PRA LOTUS JAR":[2.5,55.0]} | JC54: 605.01 | JD54: 605.01 | JE54: 0 | JF54: 24805.56 | JG54: 24805.56 | JH54: On Net Total | LD54: 0 | LF54: Percentage | LG54: 0 | LH54: 45849 | LI54: 100 | LK54: 25410 | LL54: 25410 | LM54: 0 | LN54: 0 | LO54: 25410 | LP54: 25410
ER55: 15 | ES55: 15 | ET55: 2200.05 | EU55: 2200.05 | EV55: PRA LOTUS JAR | EW55: 146.67 | EX55: 146.67 | EY55: KGS | EZ55: 1 | FA55: Stores Noida - GCF | FB55: 0 | FC55: 1 | FI55: 0 | FJ55: 0 | FK55: 0 | FL55: 0 | FM55: 55 | FN55: 2.5 | FO55: Main - GCF | FQ55: PRA LOTUS JAR | FR55: 0 | FS55: 0 | FT55: 0 | FU55: 0 | FV55: Stock Received But Not Billed - GCF | FX55: Taxable | FY55: 15179090 | FZ55: 0 | GA55: 0 | GC55: 0 | GD55: 0 | GE55: 0 | GF55: 0 | GG55: PRA LOTUS JAR | GH55: Raw Material | GI55: 0 | GJ55: {"Output Tax SGST - GCF": 2.5, "Output Tax CGST - GCF": 2.5, "Output Tax IGST - GCF": 5.0, "Input Tax SGST - GCF": 2.5, "Input Tax CGST - GCF": 2.5, "Input Tax IGST - GCF": 5.0, "Input Tax SGST RCM - GCF": 2.5, "Input Tax CGST RCM - GCF": 2.5, "Input Tax IGST RCM - GCF": 5.0} | GK55: GST 5% - GCF | GL55: 0 | GO55: 0 | GS55: 2200.05 | GT55: 2200.05 | GU55: 146.67 | GV55: 146.67 | GW55: 0 | GX55: 15 | GY55: 0 | GZ55: 0 | HE55: PO/N/25-26/0028 | HF55: 5oobs43rib | HG55: PR/N/25-26/0077 | HH55: cpgi06qv2l | HJ55: 146.67 | HK55: 0 | HL55: 0 | HM55: 0 | HN55: 15 | HP55: 0 | HT55: 0 | IA55: 55 | IB55: 2.5 | ID55: KGS | IE55: Noida | IF55: 2200.05 | IG55: 0 | IH55: 0 | II55: 146.67 | IJ55: 0 | IN55: INR | IO55: Input Tax SGST - GCF | IP55: Add | IQ55: 605.01 | IR55: 605.01 | IT55: Total | IU55: 0 | IV55: Main - GCF | IW55: Input Tax SGST @ 9.0 | IX55: sgst | IY55: 0 | IZ55: 0 | JA55: {"Vanaspati Ghee":[2.5,550.01],"PRA LOTUS JAR":[2.5,55.0]} | JC55: 605.01 | JD55: 605.01 | JE55: 0 | JF55: 25410.57 | JG55: 25410.57 | JH55: On Net Total
IN56: INR | IO56: Rounded Off - GCF | IP56: Add | IQ56: -0.57 | IR56: -0.57 | IT56: Total | IU56: 0 | IV56: Main - GCF | IW56: Rounded Off | IY56: 0 | IZ56: 0 | JA56: {"Vanaspati Ghee":[0.0,-0.52],"PRA LOTUS JAR":[0.0,-0.05]} | JC56: -0.57 | JD56: -0.57 | JE56: 0 | JF56: 25410 | JG56: 25410 | JH56: Actual
A57: PI/N/25-26/0036 | B57: PI/N/25-26/0036-1 | C57: PINV-.YY.- | D57: Shiv Shakti Traders | E57: 45857 | F57: Noida | G57: Creditors - GCF | H57: Shiv Shakti Traders | I57: Shiv Shakti Traders | L57: G. C. Foods Pvt. Ltd. | M57: 0.64208214 | N57: 1 | O57: 45857 | Q57: 0 | R57: 0 | T57: 1 | U57: 0 | V57: 1 | W57: 0 | X57: 0 | Z57: 2058 | AA57: 45846 | AD57: INR | AE57: 1 | AF57: 1 | AG57: Standard Selling Delhi | AH57: INR | AI57: 1 | AJ57: 0 | AL57: 0 | AM57: Stores Noida - GCF | AO57: 0 | AR57: 46 | AS57: 0 | AT57: 7205.04 | AU57: 7205.04 | AV57: 7205.04 | AW57: 7205.04 | AX57: 7205.04 | AY57: 7205.04 | BA57: Input GST In-state - GCF | BE57: 1194.96 | BF57: 0 | BG57: 1194.96 | BH57: 1194.96 | BI57: 0 | BJ57: 1194.96 | BK57: 8400 | BL57: 0 | BM57: 0 | BN57: INR Eight Thousand, Four Hundred only. | BO57: 8400 | BP57: 0 | BQ57: 0 | BR57: 0 | BS57: INR Eight Thousand, Four Hundred only. | BT57: 0 | BU57: 8400 | BV57: 1 | BW57: Grand Total | BX57: 0 | BY57: 0 | BZ57: 0 | CA57: | HSN/SAC | Taxable Amount | Input Tax CGST @ 9.0 | Input Tax SGST @ 9.0 | Rounded Off | | --- | --- | --- | --- | --- | | 21021020 | ₹ 1,696.40 | (6.0%) ₹ 101.78 | (6.0%) ₹ 101.78 | ₹ -0.04 | | 18062000 | ₹ 5,084.80 | (9.0%) ₹ 457.63 | (9.0%) ₹ 457.63 | ₹ -0.11 | | 17029040 | ₹ 423.84 | (9.0%) ₹ 38.15 | (9.0%) ₹ 38.15 | ₹ -0.01 | | CC57: 0 | CF57: 0 | CG57: 0 | CH57: 0 | CI57: 0 | CJ57: 0 | CM57: Shiv Shakti Traders-Billing | CN57: Plot No. 08, South Side, G.T. Road,, Behind Arya Farm HouseGhaziabad, Uttar Pradesh, State Code: 09, Pincode: 201001, India, GSTIN: 09AJSPP8533G1ZJ, | CO57: 09AJSPP8533G1ZJ | CP57: Registered Regular | CU57: Shiv Shakti Traders-Billing | CV57: Plot No. 08, South Side, G.T. Road,, Behind Arya Farm HouseGhaziabad, Uttar Pradesh, State Code: 09, Pincode: 201001, India, GSTIN: 09AJSPP8533G1ZJ, | CW57: G.C. Foods Pvt. Ltd. Noida - Uttar Pradesh (Shipping) | CX57: B-64, Sector-80,, Noida, Gautam Buddha Nagar, Noida, Uttar Pradesh, State Code: 09, Pincode: 201305, India, Phone: 9958003759, GSTIN: 09AACCG2244H1ZS, | CY57: G.C. Foods Pvt. Ltd. Noida - Uttar Pradesh (Shipping) | CZ57: B-64, Sector-80,, Noida, Gautam Buddha Nagar, Noida, Uttar Pradesh, State Code: 09, Pincode: 201305, India, Phone: 9958003759, GSTIN: 09AACCG2244H1ZS, | DA57: 09AACCG2244H1ZS | DB57: 09-Uttar Pradesh | DD57: 0 | DF57: Ingate Receipt No. 160 | DG57: 100 | DH57: INR | DI57: No | DJ57: Stock Received But Not Billed - GCF | DP57: GCF Letterhead | DQ57: 0 | DS57: en | DY57: 0 | EA57: Road | EC57: 45862 | ED57: Regular | EE57: All Other ITC | EG57: Unreconciled | EH57: 0 | EK57: 0 | EM57: Creditors - Raw Material | EO57: 0 | EP57: Against Supplier Invoice 2058 dated 08-07-2025 | ER57: 20 | ES57: 20 | ET57: 1696.4 | EU57: 1696.4 | EV57: Fresh Yeast | EW57: 84.82 | EX57: 84.82 | EY57: KGS | EZ57: 1 | FA57: Stores Noida - GCF | FB57: 0 | FC57: 1 | FI57: 0 | FJ57: 0 | FK57: 0 | FL57: 0 | FM57: 101.78 | FN57: 6 | FO57: Main - GCF | FQ57: Fresh Yeast | FR57: 0 | FS57: 0 | FT57: 0 | FU57: 0 | FV57: Stock Received But Not Billed - GCF | FX57: Taxable | FY57: 21021020 | FZ57: 0 | GA57: 0 | GC57: 0 | GD57: 0 | GE57: 0 | GF57: 0 | GG57: Fresh Yeast | GH57: Cookies - RM | GI57: 0 | GJ57: {"Output Tax SGST - GCF": 6.0, "Output Tax CGST - GCF": 6.0, "Output Tax IGST - GCF": 12.0, "Input Tax SGST - GCF": 6.0, "Input Tax CGST - GCF": 6.0, "Input Tax IGST - GCF": 12.0, "Input Tax SGST RCM - GCF": 6.0, "Input Tax CGST RCM - GCF": 6.0, "Input Tax IGST RCM - GCF": 12.0} | GK57: GST 12% - GCF | GL57: 0 | GO57: 0 | GS57: 1696.4 | GT57: 1696.4 | GU57: 84.82 | GV57: 84.82 | GW57: 0 | GX57: 20 | GY57: 84.82 | GZ57: 84.82 | HG57: PR/N/25-26/0076 | HH57: b6fn0jtioj | HJ57: 84.82 | HK57: 0 | HL57: 0 | HM57: 0 | HN57: 20 | HP57: 0 | HT57: 0 | IA57: 101.78 | IB57: 6 | ID57: KGS | IE57: Noida | IF57: 1696.4 | IG57: 0 | IH57: 0 | II57: 84.82 | IJ57: 0 | IN57: INR | IO57: Input Tax CGST - GCF | IP57: Add | IQ57: 597.56 | IR57: 597.56 | IT57: Total | IU57: 0 | IV57: Main - GCF | IW57: Input Tax CGST @ 9.0 | IX57: cgst | IY57: 0 | IZ57: 0 | JA57: {"Fresh Yeast":[6.0,101.78],"Choco Chips Dark":[9.0,457.63],"Colour - Caramel":[9.0,38.15]} | JC57: 597.56 | JD57: 597.56 | JE57: 0 | JF57: 7802.6 | JG57: 7802.6 | JH57: On Net Total | LD57: 0 | LF57: Percentage | LG57: 0 | LH57: 45857 | LI57: 100 | LK57: 8400 | LL57: 8400 | LM57: 0 | LN57: 0 | LO57: 8400 | LP57: 8400
ER58: 20 | ES58: 20 | ET58: 5084.8 | EU58: 5084.8 | EV58: Choco Chip Dark | EW58: 254.24 | EX58: 254.24 | EY58: KGS | EZ58: 1 | FA58: Stores Noida - GCF | FB58: 0 | FC58: 1 | FI58: 0 | FJ58: 0 | FK58: 0 | FL58: 0 | FM58: 457.63 | FN58: 9 | FO58: Main - GCF | FQ58: Choco Chips Dark | FR58: 0 | FS58: 0 | FT58: 0 | FU58: 0 | FV58: Stock Received But Not Billed - GCF | FX58: Taxable | FY58: 18062000 | FZ58: 0 | GA58: 0 | GC58: 0 | GD58: 0 | GE58: 0 | GF58: 0 | GG58: Choco Chips Dark | GH58: Cookies - RM | GI58: 0 | GJ58: {"Output Tax SGST - GCF": 9.0, "Output Tax CGST - GCF": 9.0, "Output Tax IGST - GCF": 18.0, "Input Tax SGST - GCF": 9.0, "Input Tax CGST - GCF": 9.0, "Input Tax IGST - GCF": 18.0, "Input Tax SGST RCM - GCF": 9.0, "Input Tax CGST RCM - GCF": 9.0, "Input Tax IGST RCM - GCF": 18.0} | GK58: GST 18% - GCF | GL58: 0 | GO58: 0 | GS58: 5084.8 | GT58: 5084.8 | GU58: 254.24 | GV58: 254.24 | GW58: 0 | GX58: 20 | GY58: 254.24 | GZ58: 254.24 | HG58: PR/N/25-26/0076 | HH58: b6fno9s74k | HJ58: 254.24 | HK58: 0 | HL58: 0 | HM58: 0 | HN58: 20 | HP58: 0 | HT58: 0 | IA58: 457.63 | IB58: 9 | ID58: KGS | IE58: Noida | IF58: 5084.8 | IG58: 0 | IH58: 0 | II58: 254.24 | IJ58: 0 | IN58: INR | IO58: Input Tax SGST - GCF | IP58: Add | IQ58: 597.56 | IR58: 597.56 | IT58: Total | IU58: 0 | IV58: Main - GCF | IW58: Input Tax SGST @ 9.0 | IX58: sgst | IY58: 0 | IZ58: 0 | JA58: {"Fresh Yeast":[6.0,101.78],"Choco Chips Dark":[9.0,457.63],"Colour - Caramel":[9.0,38.15]} | JC58: 597.56 | JD58: 597.56 | JE58: 0 | JF58: 8400.16 | JG58: 8400.16 | JH58: On Net Total
ER59: 6 | ES59: 6 | ET59: 423.84 | EU59: 423.84 | EV59: Colour - Caramel | EW59: 70.64 | EX59: 70.64 | EY59: KGS | EZ59: 1 | FA59: Stores Noida - GCF | FB59: 0 | FC59: 1 | FI59: 0 | FJ59: 0 | FK59: 0 | FL59: 0 | FM59: 38.14 | FN59: 9 | FO59: Main - GCF | FQ59: Colour - Caramel | FR59: 0 | FS59: 0 | FT59: 0 | FU59: 0 | FV59: Stock Received But Not Billed - GCF | FX59: Taxable | FY59: 17029040 | FZ59: 0 | GA59: 0 | GC59: 0 | GD59: 0 | GE59: 0 | GF59: 0 | GG59: Colour - Caramel | GH59: Cookies - RM | GI59: 0 | GJ59: {"Output Tax SGST - GCF": 9.0, "Output Tax CGST - GCF": 9.0, "Output Tax IGST - GCF": 18.0, "Input Tax SGST - GCF": 9.0, "Input Tax CGST - GCF": 9.0, "Input Tax IGST - GCF": 18.0, "Input Tax SGST RCM - GCF": 9.0, "Input Tax CGST RCM - GCF": 9.0, "Input Tax IGST RCM - GCF": 18.0} | GK59: GST 18% - GCF | GL59: 0 | GO59: 0 | GS59: 423.84 | GT59: 423.84 | GU59: 70.64 | GV59: 70.64 | GW59: 0 | GX59: 6 | GY59: 70.64 | GZ59: 70.64 | HG59: PR/N/25-26/0076 | HH59: b6fnmdqpst | HJ59: 70.64 | HK59: 0 | HL59: 0 | HM59: 0 | HN59: 6 | HP59: 0 | HT59: 0 | IA59: 38.14 | IB59: 9 | ID59: KGS | IE59: Noida | IF59: 423.84 | IG59: 0 | IH59: 0 | II59: 70.64 | IJ59: 0 | IN59: INR | IO59: Rounded Off - GCF | IP59: Add | IQ59: -0.16 | IR59: -0.16 | IT59: Total | IU59: 0 | IV59: Main - GCF | IW59: Rounded Off | IY59: 0 | IZ59: 0 | JA59: {"Fresh Yeast":[0.0,-0.04],"Choco Chips Dark":[0.0,-0.11],"Colour - Caramel":[0.0,-0.01]} | JC59: -0.16 | JD59: -0.16 | JE59: 0 | JF59: 8400 | JG59: 8400 | JH59: Actual
A60: PI/M/25-26/0125 | B60: PI/M/25-26/0125-1 | C60: PINV-.YY.- | D60: Mohan Fabrics | E60: 45843 | F60: Muzaffarpur | G60: Creditors - GCF | H60: Mohan Fabrics | I60: Mohan Fabrics | L60: G. C. Foods Pvt. Ltd. | M60: 0.58232852 | N60: 1 | O60: 45843 | Q60: 0 | R60: 0 | T60: 1 | U60: 0 | V60: 1 | W60: 0 | X60: 0 | Z60: MF/25-26/027 | AA60: 45840 | AD60: INR | AE60: 1 | AF60: 1 | AG60: Standard Buying | AH60: INR | AI60: 1 | AJ60: 0 | AL60: 0 | AM60: Store Mujaffarpur - GCF | AO60: 0 | AR60: 3845 | AS60: 0 | AT60: 142265 | AU60: 142265 | AV60: 142265 | AW60: 142265 | AX60: 142265 | AY60: 142265 | BA60: Input GST Out-state - GCF | BE60: 25608 | BF60: 0 | BG60: 25608 | BH60: 25608 | BI60: 0 | BJ60: 25608 | BK60: 167873 | BL60: 0 | BM60: 0 | BN60: INR One Lakh, Sixty Seven Thousand, Eight Hundred And Seventy Three only. | BO60: 167873 | BP60: 0 | BQ60: 0 | BR60: 0 | BS60: INR One Lakh, Sixty Seven Thousand, Eight Hundred And Seventy Three only. | BT60: 0 | BU60: 167873 | BV60: 1 | BW60: Grand Total | BX60: 0 | BY60: 0 | BZ60: 0 | CA60: | HSN/SAC | Taxable Amount | Input Tax IGST @ 18.0 | Rounded Off | | --- | --- | --- | --- | | 392329 | ₹ 1,42,265.00 | (18.0%) ₹ 25,607.70 | ₹ 0.30 | | CC60: 0 | CF60: 0 | CG60: 0 | CH60: 0 | CI60: 0 | CJ60: 0 | CM60: Mohan Fabrics-Billing | CN60: 101-A, Khasra No.615/3, Main Road, Main Road Sabhapur Extention, North East DelhiDelhi, Delhi, State Code: 07, Pincode: 110094, India, GSTIN: 07AARPA0163H1ZY, | CO60: 07AARPA0163H1ZY | CP60: Registered Regular | CW60: GC Foods Muzaffarpur-Billing | CX60: A-03 and A-04, Bela Industrial Estate, Muzaffarpur, Bihar, State Code: 10, Pincode: 842005, India, GSTIN: 10AACCG2244H1Z9, | CY60: GC Foods Muzaffarpur-Billing | CZ60: A-03 and A-04, Bela Industrial Estate, Muzaffarpur, Bihar, State Code: 10, Pincode: 842005, India, GSTIN: 10AACCG2244H1Z9, | DA60: 10AACCG2244H1Z9 | DB60: 10-Bihar | DD60: 0 | DG60: 100 | DH60: INR | DI60: No | DJ60: Stock Received But Not Billed - GCF | DP60: GCF Letterhead | DQ60: 0 | DS60: en | DY60: 0 | EA60: Road | EC60: 45861 | ED60: Regular | EE60: All Other ITC | EG60: Unreconciled | EH60: 0 | EK60: 0 | EM60: Creditors - Raw Material | EO60: 0 | EP60: Against Supplier Invoice MF/25-26/027 dated 02-07-2025 | ER60: 3845 | ES60: 3845 | ET60: 142265 | EU60: 142265 | EV60: Soyabari Bag | EW60: 37 | EX60: 37 | EY60: PCS | EZ60: 1 | FA60: Store Mujaffarpur - GCF | FB60: 0 | FC60: 1 | FI60: 0 | FJ60: 0 | FK60: 0 | FL60: 0 | FM60: 0 | FN60: 0 | FO60: Main - GCF | FQ60: soyabari Bag | FR60: 0 | FS60: 0 | FT60: 0 | FU60: 0 | FV60: Stock Received But Not Billed - GCF | FX60: Taxable | FY60: 392329 | FZ60: 25607.7 | GA60: 18 | GC60: 0 | GD60: 0 | GE60: 0 | GF60: 0 | GG60: Soyabari Bag | GH60: Packing Material - PM | GI60: 0 | GJ60: {"Output Tax SGST - GCF": 9.0, "Output Tax CGST - GCF": 9.0, "Output Tax IGST - GCF": 18.0, "Input Tax SGST - GCF": 9.0, "Input Tax CGST - GCF": 9.0, "Input Tax IGST - GCF": 18.0, "Input Tax SGST RCM - GCF": 9.0, "Input Tax CGST RCM - GCF": 9.0, "Input Tax IGST RCM - GCF": 18.0} | GK60: GST 18% - GCF | GL60: 0 | GO60: 0 | GS60: 142265 | GT60: 142265 | GU60: 37 | GV60: 37 | GW60: 0 | GX60: 3845 | GY60: 0 | GZ60: 0 | HG60: PR/M/25-26/0123 | HH60: f8tdgu7hgu | HJ60: 37 | HK60: 0 | HL60: 0 | HM60: 0 | HN60: 3845 | HP60: 0 | HT60: 0 | IA60: 0 | IB60: 0 | ID60: PCS | IE60: Muzaffarpur | IF60: 142265 | IG60: 0 | IH60: 0 | II60: 37 | IJ60: 0 | IN60: INR | IO60: Input Tax IGST - GCF | IP60: Add | IQ60: 25607.7 | IR60: 25607.7 | IT60: Total | IU60: 0 | IV60: Main - GCF | IW60: Input Tax IGST @ 18.0 | IX60: igst | IY60: 0 | IZ60: 0 | JA60: {"Soyabari Bag":[18.0,25607.7]} | JC60: 25607.7 | JD60: 25607.7 | JE60: 0 | JF60: 167872.7 | JG60: 167872.7 | JH60: On Net Total | LD60: 0 | LF60: Percentage | LG60: 0 | LH60: 45843 | LI60: 100 | LK60: 167873 | LL60: 167873 | LM60: 0 | LN60: 0 | LO60: 167873 | LP60: 167873
IN61: INR | IO61: Rounded Off - GCF | IP61: Add | IQ61: 0.3 | IR61: 0.3 | IT61: Total | IU61: 0 | IV61: Main - GCF | IW61: Rounded Off | IY61: 0 | IZ61: 0 | JA61: {"Soyabari Bag":[0.0,0.3]} | JC61: 0.3 | JD61: 0.3 | JE61: 0 | JF61: 167873 | JG61: 167873 | JH61: Actual
A62: PI/M/25-26/0124 | B62: PI/M/25-26/0124-1 | C62: PINV-.YY.- | D62: Goyal Proteins Limited | E62: 45853 | F62: Muzaffarpur | G62: Creditors - GCF | H62: Goyal Proteins Limited | I62: Goyal Proteins Limited | L62: G. C. Foods Pvt. Ltd. | M62: 0.54691703 | N62: 1 | O62: 45853 | Q62: 0 | R62: 0 | T62: 1 | U62: 0 | V62: 1 | W62: 0 | X62: 0 | Z62: GPL25/07297 | AA62: 45849 | AD62: INR | AE62: 1 | AF62: 1 | AG62: Standard Buying | AH62: INR | AI62: 1 | AJ62: 0 | AL62: 0 | AM62: Store Mujaffarpur - GCF | AO62: 0 | AR62: 41871 | AS62: 0 | AT62: 1578478.3 | AU62: 1578478.3 | AV62: 1578478.3 | AW62: 1578478.3 | AX62: 1578478.3 | AY62: 1578478.3 | BA62: Input GST Out-state - GCF | BE62: 78923.74 | BF62: 0 | BG62: 78923.74 | BH62: 78923.74 | BI62: 0 | BJ62: 78923.74 | BK62: 1657402 | BL62: 0 | BM62: 0 | BN62: INR Sixteen Lakh, Fifty Seven Thousand, Four Hundred And Two only. | BO62: 1657402 | BP62: 0 | BQ62: 0 | BR62: 0 | BS62: INR Sixteen Lakh, Fifty Seven Thousand, Four Hundred And Two only. | BT62: 0 | BU62: 1657402 | BV62: 1 | BW62: Grand Total | BX62: 0 | BY62: 0 | BZ62: 0 | CA62: | HSN/SAC | Taxable Amount | Input Tax IGST @ 18.0 | Rounded Off | | --- | --- | --- | --- | | 23040030 | ₹ 15,77,650.00 | (5.0%) ₹ 78,882.50 | ₹ -0.17 | | 997133 | ₹ 828.26 | (5.0%) ₹ 41.41 | (0.0%) ₹ 0.00 | | CC62: 0 | CF62: 0 | CG62: 0 | CH62: 0 | CI62: 0 | CJ62: 0 | CM62: Goyal Proteins Limited-Billing | CN62: Kasar NH,52 , Kota, Rajasthan, State Code: 08, Pincode: 325003, India, GSTIN: 08AABCG3707A1Z7, | CO62: 08AABCG3707A1Z7 | CP62: Registered Regular | CW62: GC Foods Muzaffarpur-Billing | CX62: A-03 and A-04, Bela Industrial Estate, Muzaffarpur, Bihar, State Code: 10, Pincode: 842005, India, GSTIN: 10AACCG2244H1Z9, | CY62: GC Foods Muzaffarpur-Billing | CZ62: A-03 and A-04, Bela Industrial Estate, Muzaffarpur, Bihar, State Code: 10, Pincode: 842005, India, GSTIN: 10AACCG2244H1Z9, | DA62: 10AACCG2244H1Z9 | DB62: 10-Bihar | DD62: 0 | DG62: 100 | DH62: INR | DI62: No | DJ62: Stock Received But Not Billed - GCF,Cost of Goods Sold - GCF | DQ62: 0 | DS62: en | DY62: 0 | EA62: Road | EC62: 45860 | ED62: Regular | EE62: All Other ITC | EG62: Unreconciled | EH62: 0 | EK62: 0 | EM62: Creditors - Soya | EO62: 0 | EP62: Against Supplier Invoice GPL25/07297 dated 11-07-2025 | ER62: 32930 | ES62: 32930 | ET62: 1251340 | EU62: 1251340 | EV62: Soya Grit | EW62: 38 | EX62: 38 | EY62: KGS | EZ62: 1 | FA62: Store Mujaffarpur - GCF | FB62: 0 | FC62: 1 | FI62: 0 | FJ62: 0 | FK62: 0 | FL62: 0 | FM62: 0 | FN62: 0 | FO62: Main - GCF | FQ62: Soyagrit | FR62: 1 | FS62: 2.564 | FT62: 0 | FU62: 0 | FV62: Stock Received But Not Billed - GCF | FX62: Taxable | FY62: 23040030 | FZ62: 62567 | GA62: 5 | GC62: 0 | GD62: 0 | GE62: 0 | GF62: 0 | GG62: Soya Grit | GH62: Raw Material | GI62: 0 | GJ62: {"Output Tax SGST - GCF": 2.5, "Output Tax CGST - GCF": 2.5, "Output Tax IGST - GCF": 5.0, "Input Tax SGST - GCF": 2.5, "Input Tax CGST - GCF": 2.5, "Input Tax IGST - GCF": 5.0, "Input Tax SGST RCM - GCF": 2.5, "Input Tax CGST RCM - GCF": 2.5, "Input Tax IGST RCM - GCF": 5.0} | GK62: GST 5% - GCF | GL62: 0 | GO62: 0 | GS62: 1251340 | GT62: 1251340 | GU62: 38 | GV62: 38 | GW62: 0 | GX62: 32930 | GY62: 39 | GZ62: 39 | HE62: PO/M/25-26/0092 | HF62: 1trgc1vrfi | HG62: PR/M/25-26/0122 | HH62: 4v7spuju7h | HJ62: 38 | HK62: 0 | HL62: 0 | HM62: 0 | HN62: 32930 | HP62: 0 | HT62: 0 | IA62: 0 | IB62: 0 | ID62: KGS | IE62: Muzaffarpur | IF62: 1251340 | IG62: 0 | IH62: 0 | II62: 38 | IJ62: 0 | IN62: INR | IO62: Input Tax IGST - GCF | IP62: Add | IQ62: 78923.91 | IR62: 78923.91 | IT62: Total | IU62: 0 | IV62: Main - GCF | IW62: Input Tax IGST @ 18.0 | IX62: igst | IY62: 0 | IZ62: 0 | JA62: {"Soya Grit":[5.0,78882.5],"Insurance Charges On Purchase":[5.0,41.41]} | JC62: 78923.91 | JD62: 78923.91 | JE62: 0 | JF62: 1657402.2 | JG62: 1657402.2 | JH62: On Net Total | LD62: 0 | LF62: Percentage | LG62: 0 | LH62: 45853 | LI62: 100 | LK62: 1657402 | LL62: 1657402 | LM62: 0 | LN62: 0 | LO62: 1657402 | LP62: 1657402
ER63: 8940 | ES63: 8940 | ET63: 326310 | EU63: 326310 | EV63: Soya Grit | EW63: 36.5 | EX63: 36.5 | EY63: KGS | EZ63: 1 | FA63: Store Mujaffarpur - GCF | FB63: 0 | FC63: 1 | FI63: 0 | FJ63: 0 | FK63: 0 | FL63: 0 | FM63: 0 | FN63: 0 | FO63: Main - GCF | FQ63: Soyagrit | FR63: 2.5 | FS63: 6.41 | FT63: 0 | FU63: 0 | FV63: Stock Received But Not Billed - GCF | FX63: Taxable | FY63: 23040030 | FZ63: 16315.5 | GA63: 5 | GC63: 0 | GD63: 0 | GE63: 0 | GF63: 0 | GG63: Soya Grit | GH63: Raw Material | GI63: 0 | GJ63: {"Output Tax SGST - GCF": 2.5, "Output Tax CGST - GCF": 2.5, "Output Tax IGST - GCF": 5.0, "Input Tax SGST - GCF": 2.5, "Input Tax CGST - GCF": 2.5, "Input Tax IGST - GCF": 5.0, "Input Tax SGST RCM - GCF": 2.5, "Input Tax CGST RCM - GCF": 2.5, "Input Tax IGST RCM - GCF": 5.0} | GK63: GST 5% - GCF | GL63: 0 | GO63: 0 | GS63: 326310 | GT63: 326310 | GU63: 36.5 | GV63: 36.5 | GW63: 0 | GX63: 8940 | GY63: 39 | GZ63: 39 | HE63: PO/M/25-26/0092 | HF63: 1trg1tcvt1 | HG63: PR/M/25-26/0122 | HH63: 4v7s90fdti | HJ63: 36.5 | HK63: 0 | HL63: 0 | HM63: 0 | HN63: 8940 | HP63: 0 | HT63: 0 | IA63: 0 | IB63: 0 | ID63: KGS | IE63: Muzaffarpur | IF63: 326310 | IG63: 0 | IH63: 0 | II63: 36.5 | IJ63: 0 | IN63: INR | IO63: Rounded Off - GCF | IP63: Add | IQ63: -0.17 | IR63: -0.17 | IT63: Total | IU63: 0 | IV63: Main - GCF | IW63: Rounded Off | IY63: 0 | IZ63: 0 | JA63: {"Soya Grit":[0.0,-0.17],"Insurance Charges On Purchase":[0.0,0.0]} | JC63: -0.17 | JD63: -0.17 | JE63: 0 | JF63: 1657402 | JG63: 1657402 | JH63: Actual
ER64: 1 | ES64: 1 | ET64: 828.26 | EU64: 828.26 | EV64: Insurance Charges On Purchase | EW64: 828.26 | EX64: 828.26 | EY64: Nos | EZ64: 1 | FA64: Store Mujaffarpur - GCF | FB64: 0 | FC64: 1 | FI64: 0 | FJ64: 0 | FK64: 0 | FL64: 0 | FM64: 0 | FN64: 0 | FO64: Main - GCF | FQ64: Insurance Charges On Purchase | FR64: -33.26 | FS64: 0 | FT64: 0 | FU64: 0 | FV64: Cost of Goods Sold - GCF | FX64: Taxable | FY64: 997133 | FZ64: 41.41 | GA64: 5 | GC64: 0 | GD64: 0 | GE64: 0 | GF64: 0 | GG64: Insurance Charges On Purchase | GH64: Services | GI64: 0 | GJ64: {"Output Tax SGST - GCF": 2.5, "Output Tax CGST - GCF": 2.5, "Output Tax IGST - GCF": 5.0, "Input Tax SGST - GCF": 2.5, "Input Tax CGST - GCF": 2.5, "Input Tax IGST - GCF": 5.0, "Input Tax SGST RCM - GCF": 2.5, "Input Tax CGST RCM - GCF": 2.5, "Input Tax IGST RCM - GCF": 5.0} | GK64: GST 5% - GCF | GL64: 0 | GO64: 33.26 | GP64: Amount | GS64: 828.26 | GT64: 828.26 | GU64: 828.26 | GV64: 828.26 | GW64: 0 | GX64: 1 | GY64: 795 | GZ64: 795 | HE64: PO/M/25-26/0092 | HF64: 7uqs1dn7cs | HG64: PR/M/25-26/0122 | HH64: 4v7s8237vk | HJ64: 828.26 | HK64: 0 | HL64: 0 | HM64: 0 | HN64: 1 | HP64: 0 | HT64: 0 | IA64: 0 | IB64: 0 | ID64: Nos | IE64: Muzaffarpur | IF64: 828.26 | IG64: 0 | IH64: 0 | II64: 0 | IJ64: 0
A65: PI/M/25-26/0122 | B65: PI/M/25-26/0122-1 | C65: PINV-.YY.- | D65: Goyal Proteins Limited | E65: 45858 | F65: Muzaffarpur | G65: Creditors - GCF | H65: Goyal Proteins Limited | I65: Goyal Proteins Limited | L65: G. C. Foods Pvt. Ltd. | M65: 0.74498093 | N65: 1 | O65: 45858 | Q65: 0 | R65: 0 | T65: 1 | U65: 0 | V65: 1 | W65: 0 | X65: 0 | Z65: GPL25/07623 | AA65: 45854 | AD65: INR | AE65: 1 | AF65: 1 | AG65: Standard Buying | AH65: INR | AI65: 1 | AJ65: 0 | AL65: 0 | AM65: Store Mujaffarpur - GCF | AO65: 0 | AR65: 41631 | AS65: 0 | AT65: 1583186.3 | AU65: 1583186.3 | AV65: 1583186.3 | AW65: 1583186.3 | AX65: 1583186.3 | AY65: 1583186.3 | BA65: Input GST Out-state - GCF | BE65: 78722.7 | BF65: 0 | BG65: 78722.7 | BH65: 78722.7 | BI65: 0 | BJ65: 78722.7 | BK65: 1661909 | BL65: 0 | BM65: 0 | BN65: INR Sixteen Lakh, Sixty One Thousand, Nine Hundred And Nine only. | BO65: 1661909 | BP65: 0 | BQ65: 0 | BR65: 0 | BS65: INR Sixteen Lakh, Sixty One Thousand, Nine Hundred And Nine only. | BT65: 0 | BU65: 1661909 | BV65: 1 | BW65: Grand Total | BX65: 0 | BY65: 0 | BZ65: 0 | CA65: | HSN/SAC | Taxable Amount | Input Tax IGST @ 18.0 | Rounded Off | | --- | --- | --- | --- | | 23040030 | ₹ 15,82,356.30 | (5.0%) ₹ 79,117.82 | ₹ -436.39 | | 997133 | ₹ 830.00 | (5.0%) ₹ 41.50 | ₹ -0.23 | | CC65: 0 | CF65: 0 | CG65: 0 | CH65: 0 | CI65: 0 | CJ65: 0 | CM65: Goyal Proteins Limited-Billing | CN65: Kasar NH,52 , Kota, Rajasthan, State Code: 08, Pincode: 325003, India, GSTIN: 08AABCG3707A1Z7, | CO65: 08AABCG3707A1Z7 | CP65: Registered Regular | CW65: GC Foods Muzaffarpur-Billing | CX65: A-03 and A-04, Bela Industrial Estate, Muzaffarpur, Bihar, State Code: 10, Pincode: 842005, India, GSTIN: 10AACCG2244H1Z9, | CY65: GC Foods Muzaffarpur-Billing | CZ65: A-03 and A-04, Bela Industrial Estate, Muzaffarpur, Bihar, State Code: 10, Pincode: 842005, India, GSTIN: 10AACCG2244H1Z9, | DA65: 10AACCG2244H1Z9 | DB65: 10-Bihar | DD65: 0 | DG65: 100 | DH65: INR | DI65: No | DJ65: Stock Received But Not Billed - GCF,Cost of Goods Sold - GCF | DQ65: 0 | DS65: en | DY65: 0 | EA65: Road | EC65: 45859 | ED65: Regular | EE65: All Other ITC | EG65: Unreconciled | EH65: 0 | EK65: 0 | EM65: Creditors - Soya | EO65: 0 | EP65: Against Supplier Invoice GPL25/07623 dated 16-07-2025 | ER65: 41630 | ES65: 41630 | ET65: 1582356.3 | EU65: 1582356.3 | EV65: Soya Grit | EW65: 38.01 | EX65: 38.01 | EY65: KGS | EZ65: 1 | FA65: Store Mujaffarpur - GCF | FB65: 0 | FC65: 1 | FI65: 0 | FJ65: 0 | FK65: 0 | FL65: 0 | FM65: 0 | FN65: 0 | FO65: Main - GCF | FQ65: Soyagrit | FR65: 0.99 | FS65: 2.538 | FT65: 0 | FU65: 0 | FV65: Stock Received But Not Billed - GCF | FX65: Taxable | FY65: 23040030 | FZ65: 79117.82 | GA65: 5 | GC65: 0 | GD65: 0 | GE65: 0 | GF65: 0 | GG65: Soya Grit | GH65: Raw Material | GI65: 0 | GJ65: {"Output Tax SGST - GCF": 2.5, "Output Tax CGST - GCF": 2.5, "Output Tax IGST - GCF": 5.0, "Input Tax SGST - GCF": 2.5, "Input Tax CGST - GCF": 2.5, "Input Tax IGST - GCF": 5.0, "Input Tax SGST RCM - GCF": 2.5, "Input Tax CGST RCM - GCF": 2.5, "Input Tax IGST RCM - GCF": 5.0} | GK65: GST 5% - GCF | GL65: 0 | GO65: 0 | GS65: 1582356.3 | GT65: 1582356.3 | GU65: 38.01 | GV65: 38.01 | GW65: 0 | GX65: 41630 | GY65: 39 | GZ65: 39 | HE65: PO/M/25-26/0091 | HF65: 8q4vobnmca | HG65: PR/M/25-26/0121 | HH65: 6qjt0tbm2a | HJ65: 38.01 | HK65: 0 | HL65: 0 | HM65: 0 | HN65: 41630 | HP65: 0 | HT65: 0 | IA65: 0 | IB65: 0 | ID65: KGS | IE65: Muzaffarpur | IF65: 1582356.3 | IG65: 0 | IH65: 0 | II65: 38.01 | IJ65: 0 | IN65: INR | IO65: Input Tax IGST - GCF | IP65: Add | IQ65: 79159.32 | IR65: 79159.32 | IT65: Total | IU65: 0 | IV65: Main - GCF | IW65: Input Tax IGST @ 18.0 | IX65: igst | IY65: 0 | IZ65: 0 | JA65: {"Soya Grit":[5.0,79117.82],"Insurance Charges On Purchase":[5.0,41.5]} | JC65: 79159.32 | JD65: 79159.32 | JE65: 0 | JF65: 1662345.6 | JG65: 1662345.6 | JH65: On Net Total | LD65: 0 | LF65: Percentage | LG65: 0 | LH65: 45858 | LI65: 100 | LK65: 1661909 | LL65: 1661909 | LM65: 0 | LN65: 0 | LO65: 1661909 | LP65: 1661909
ER66: 1 | ES66: 1 | ET66: 830 | EU66: 830 | EV66: Insurance Charges On Purchase | EW66: 830 | EX66: 830 | EY66: Nos | EZ66: 1 | FA66: Store Mujaffarpur - GCF | FB66: 0 | FC66: 1 | FI66: 0 | FJ66: 0 | FK66: 0 | FL66: 0 | FM66: 0 | FN66: 0 | FO66: Main - GCF | FQ66: Insurance Charges On Purchase | FR66: -35 | FS66: 0 | FT66: 0 | FU66: 0 | FV66: Cost of Goods Sold - GCF | FX66: Taxable | FY66: 997133 | FZ66: 41.505 | GA66: 5 | GC66: 0 | GD66: 0 | GE66: 0 | GF66: 0 | GG66: Insurance Charges On Purchase | GH66: Services | GI66: 0 | GJ66: {"Output Tax SGST - GCF": 2.5, "Output Tax CGST - GCF": 2.5, "Output Tax IGST - GCF": 5.0, "Input Tax SGST - GCF": 2.5, "Input Tax CGST - GCF": 2.5, "Input Tax IGST - GCF": 5.0, "Input Tax SGST RCM - GCF": 2.5, "Input Tax CGST RCM - GCF": 2.5, "Input Tax IGST RCM - GCF": 5.0} | GK66: GST 5% - GCF | GL66: 0 | GO66: 35 | GP66: Amount | GS66: 830 | GT66: 830 | GU66: 830 | GV66: 830 | GW66: 0 | GX66: 1 | GY66: 795 | GZ66: 795 | HE66: PO/M/25-26/0091 | HF66: 8q4v4ub5hb | HG66: PR/M/25-26/0121 | HH66: 6qjt206kch | HJ66: 830 | HK66: 0 | HL66: 0 | HM66: 0 | HN66: 1 | HP66: 0 | HT66: 0 | IA66: 0 | IB66: 0 | ID66: Nos | IE66: Muzaffarpur | IF66: 830 | IG66: 0 | IH66: 0 | II66: 0 | IJ66: 0 | IN66: INR | IO66: Rounded Off - GCF | IP66: Add | IQ66: -436.62 | IR66: -436.62 | IT66: Total | IU66: 0 | IV66: Main - GCF | IW66: Rounded Off | IY66: 0 | IZ66: 0 | JA66: {"Soya Grit":[0.0,-436.39],"Insurance Charges On Purchase":[0.0,-0.23]} | JC66: -436.62 | JD66: -436.62 | JE66: 0 | JF66: 1661909 | JG66: 1661909 | JH66: Actual
A67: PI/M/25-26/0121 | B67: PI/M/25-26/0121-1 | C67: PINV-.YY.- | D67: GC foods Pvt Ltd (T) | E67: 45857 | F67: Muzaffarpur | G67: Creditors - GCF | H67: GC foods Pvt Ltd (T) | I67: GC foods Pvt Ltd (T) | L67: G. C. Foods Pvt. Ltd. | M67: 0.57038573 | N67: 1 | O67: 45857 | Q67: 0 | R67: 0 | T67: 1 | U67: 0 | V67: 1 | W67: 0 | X67: 0 | Z67: GCF/T-489/25-26 | AA67: 45853 | AD67: INR | AE67: 1 | AF67: 1 | AG67: Standard Buying | AH67: INR | AI67: 1 | AJ67: 0 | AL67: 0 | AM67: Store Mujaffarpur - GCF | AO67: 0 | AR67: 28480 | AS67: 0 | AT67: 3203412 | AU67: 3203412 | AV67: 3203412 | AW67: 3203412 | AX67: 3203412 | AY67: 3203412 | BA67: Input GST Out-state - GCF | BE67: 160171 | BF67: 0 | BG67: 160171 | BH67: 160171 | BI67: 0 | BJ67: 160171 | BK67: 3363583 | BL67: 0 | BM67: 0 | BN67: INR Thirty Three Lakh, Sixty Three Thousand, Five Hundred And Eighty Three only. | BO67: 3363583 | BP67: 0 | BQ67: 0 | BR67: 0 | BS67: INR Thirty Three Lakh, Sixty Three Thousand, Five Hundred And Eighty Three only. | BT67: 0 | BU67: 3363583 | BV67: 1 | BW67: Grand Total | BX67: 0 | BY67: 0 | BZ67: 0 | CA67: | HSN/SAC | Taxable Amount | Input Tax IGST @ 18.0 | Rounded Off | | --- | --- | --- | --- | | 11061000 | ₹ 32,03,412.00 | (5.0%) ₹ 1,60,170.60 | ₹ 0.40 | | CC67: 0 | CF67: 0 | CG67: 0 | CH67: 0 | CI67: 0 | CJ67: 0 | CM67: G.C.foods Pvt Ltd-Billing | CN67: C-4,sector-a-2, Tronica City Industrial Area, LoniGhaziabad, Uttar Pradesh, State Code: 09, Pincode: 201102, India, GSTIN: 09AACCG2244H1ZS, | CO67: 09AACCG2244H1ZS | CP67: Registered Regular | CW67: GC Foods Muzaffarpur-Billing | CX67: A-03 and A-04, Bela Industrial Estate, Muzaffarpur, Bihar, State Code: 10, Pincode: 842005, India, GSTIN: 10AACCG2244H1Z9, | CY67: GC Foods Muzaffarpur-Billing | CZ67: A-03 and A-04, Bela Industrial Estate, Muzaffarpur, Bihar, State Code: 10, Pincode: 842005, India, GSTIN: 10AACCG2244H1Z9, | DA67: 10AACCG2244H1Z9 | DB67: 10-Bihar | DD67: 0 | DG67: 100 | DH67: INR | DI67: No | DJ67: Stock Received But Not Billed - GCF | DQ67: 0 | DS67: en | DY67: 0 | EA67: Road | EC67: 45859 | ED67: Regular | EE67: All Other ITC | EG67: Unreconciled | EH67: 0 | EK67: 0 | EM67: Creditors - Others | EO67: 0 | EP67: Against Supplier Invoice GCF/T-489/25-26 dated 15-07-2025 | ER67: 18480 | ES67: 18480 | ET67: 2067912 | EU67: 2067912 | EV67: Anoop Sattu 500g (40 Kg) | EW67: 111.9 | EX67: 111.9 | EY67: KGS | EZ67: 1 | FA67: Store Mujaffarpur - GCF | FB67: 0 | FC67: 1 | FI67: 0 | FJ67: 0 | FK67: 0 | FL67: 0 | FM67: 0 | FN67: 0 | FO67: Main - GCF | FQ67: Anoop Sattu - 500 g (20 Kg) | FR67: 3.4 | FS67: 2.949 | FT67: 0 | FU67: 0 | FV67: Stock Received But Not Billed - GCF | FX67: Taxable | FY67: 11061000 | FZ67: 103395.6 | GA67: 5 | GC67: 0 | GD67: 0 | GE67: 0 | GF67: 0 | GG67: Anoop Sattu 500g (40 Kg) | GH67: Sattu and Chana - FG | GI67: 0 | GJ67: {"Output Tax SGST - GCF": 2.5, "Output Tax CGST - GCF": 2.5, "Output Tax IGST - GCF": 5.0, "Input Tax SGST - GCF": 2.5, "Input Tax CGST - GCF": 2.5, "Input Tax IGST - GCF": 5.0, "Input Tax SGST RCM - GCF": 2.5, "Input Tax CGST RCM - GCF": 2.5, "Input Tax IGST RCM - GCF": 5.0} | GK67: GST 5% - GCF | GL67: 0 | GO67: 0 | GS67: 2067912 | GT67: 2067912 | GU67: 111.9 | GV67: 111.9 | GW67: 0 | GX67: 18480 | GY67: 115.3 | GZ67: 115.3 | HG67: PR/M/25-26/0120 | HH67: f7a1m3p94i | HJ67: 111.9 | HK67: 0 | HL67: 0 | HM67: 0 | HN67: 18480 | HP67: 0 | HT67: 0 | IA67: 0 | IB67: 0 | ID67: KGS | IE67: Muzaffarpur | IF67: 2067912 | IG67: 0 | IH67: 0 | II67: 111.9 | IJ67: 0 | IN67: INR | IO67: Input Tax IGST - GCF | IP67: Add | IQ67: 160170.6 | IR67: 160170.6 | IT67: Total | IU67: 0 | IV67: Main - GCF | IW67: Input Tax IGST @ 18.0 | IX67: igst | IY67: 0 | IZ67: 0 | JA67: {"Anoop Sattu 500g (40 Kg)":[5.0,103395.6],"Anoop Sattu 200g (40kg)":[5.0,56775.0]} | JC67: 160170.6 | JD67: 160170.6 | JE67: 0 | JF67: 3363582.6 | JG67: 3363582.6 | JH67: On Net Total | LD67: 0 | LF67: Percentage | LG67: 0 | LH67: 45857 | LI67: 100 | LK67: 3363583 | LL67: 3363583 | LM67: 0 | LN67: 0 | LO67: 3363583 | LP67: 3363583
ER68: 10000 | ES68: 10000 | ET68: 1135500 | EU68: 1135500 | EV68: Anoop Sattu 200g (40kg) | EW68: 113.55 | EX68: 113.55 | EY68: KGS | EZ68: 1 | FA68: Store Mujaffarpur - GCF | FB68: 0 | FC68: 1 | FI68: 0 | FJ68: 0 | FK68: 0 | FL68: 0 | FM68: 0 | FN68: 0 | FO68: Main - GCF | FQ68: Anoop Sattu - 200 g (20 Kg) | FR68: 3.45 | FS68: 2.949 | FT68: 0 | FU68: 0 | FV68: Stock Received But Not Billed - GCF | FX68: Taxable | FY68: 11061000 | FZ68: 56775 | GA68: 5 | GC68: 0 | GD68: 0 | GE68: 0 | GF68: 0 | GG68: Anoop Sattu 200g (40kg) | GH68: Sattu and Chana - FG | GI68: 0 | GJ68: {"Output Tax SGST - GCF": 2.5, "Output Tax CGST - GCF": 2.5, "Output Tax IGST - GCF": 5.0, "Input Tax SGST - GCF": 2.5, "Input Tax CGST - GCF": 2.5, "Input Tax IGST - GCF": 5.0, "Input Tax SGST RCM - GCF": 2.5, "Input Tax CGST RCM - GCF": 2.5, "Input Tax IGST RCM - GCF": 5.0} | GK68: GST 5% - GCF | GL68: 0 | GO68: 0 | GS68: 1135500 | GT68: 1135500 | GU68: 113.55 | GV68: 113.55 | GW68: 0 | GX68: 10000 | GY68: 117 | GZ68: 117 | HG68: PR/M/25-26/0120 | HH68: f7a1qargad | HJ68: 113.55 | HK68: 0 | HL68: 0 | HM68: 0 | HN68: 10000 | HP68: 0 | HT68: 0 | IA68: 0 | IB68: 0 | ID68: KGS | IE68: Muzaffarpur | IF68: 1135500 | IG68: 0 | IH68: 0 | II68: 113.55 | IJ68: 0 | IN68: INR | IO68: Rounded Off - GCF | IP68: Add | IQ68: 0.4 | IR68: 0.4 | IT68: Total | IU68: 0 | IV68: Main - GCF | IW68: Rounded Off | IY68: 0 | IZ68: 0 | JA68: {"Anoop Sattu 500g (40 Kg)":[0.0,0.26],"Anoop Sattu 200g (40kg)":[0.0,0.14]} | JC68: 0.4 | JD68: 0.4 | JE68: 0 | JF68: 3363583 | JG68: 3363583 | JH68: Actual
A69: PI/N/25-26/0035 | B69: PI/N/25-26/0035-1 | C69: PINV-.YY.- | D69: Om Mithila Industries | E69: 45854 | F69: Noida | G69: Creditors - GCF | H69: Om Mithila Industries | I69: Om Mithila Industries | L69: G. C. Foods Pvt. Ltd. | M69: 0.48241475 | N69: 1 | O69: 45854 | Q69: 0 | R69: 0 | T69: 1 | U69: 0 | V69: 1 | W69: 0 | X69: 0 | Z69: 516/25-26 | AA69: 45850 | AD69: INR | AE69: 1 | AF69: 1 | AG69: Standard Selling Delhi | AH69: INR | AI69: 1 | AJ69: 0 | AL69: 0 | AM69: Stores Noida - GCF | AO69: 0 | AR69: 1488 | AS69: 0 | AT69: 26784 | AU69: 26784 | AV69: 26784 | AW69: 26784 | AX69: 26784 | AY69: 26784 | BA69: Input GST In-state - GCF | BE69: 3214 | BF69: 0 | BG69: 3214 | BH69: 3214 | BI69: 0 | BJ69: 3214 | BK69: 29998 | BL69: 0 | BM69: 0 | BN69: INR Twenty Nine Thousand, Nine Hundred And Ninety Eight only. | BO69: 29998 | BP69: 0 | BQ69: 0 | BR69: 0 | BS69: INR Twenty Nine Thousand, Nine Hundred And Ninety Eight only. | BT69: 0 | BU69: 29998 | BV69: 1 | BW69: Grand Total | BX69: 0 | BY69: 0 | BZ69: 0 | CA69: | HSN/SAC | Taxable Amount | Input Tax CGST @ 9.0 | Input Tax SGST @ 9.0 | Rounded Off | | --- | --- | --- | --- | --- | | 481910 | ₹ 26,784.00 | (6.0%) ₹ 1,607.04 | (6.0%) ₹ 1,607.04 | ₹ -0.08 | | CC69: 0 | CF69: 0 | CG69: 0 | CH69: 0 | CI69: 0 | CJ69: 0 | CM69: Om Mithila Industries-Billing | CN69: A-109 V Sec - 80 Noida, G.B NagarNoida, Uttar Pradesh, State Code: 09, Pincode: 201305, India, GSTIN: 09AOYPS4034E1ZG, | CO69: 09AOYPS4034E1ZG | CP69: Registered Regular | CU69: Om Mithila Industries-Billing | CV69: A-109 V Sec - 80 Noida, G.B NagarNoida, Uttar Pradesh, State Code: 09, Pincode: 201305, India, GSTIN: 09AOYPS4034E1ZG, | CW69: G.C. Foods Pvt. Ltd. Noida - Uttar Pradesh (Shipping) | CX69: B-64, Sector-80,, Noida, Gautam Buddha Nagar, Noida, Uttar Pradesh, State Code: 09, Pincode: 201305, India, Phone: 9958003759, GSTIN: 09AACCG2244H1ZS, | CY69: G.C. Foods Pvt. Ltd. Noida - Uttar Pradesh (Shipping) | CZ69: B-64, Sector-80,, Noida, Gautam Buddha Nagar, Noida, Uttar Pradesh, State Code: 09, Pincode: 201305, India, Phone: 9958003759, GSTIN: 09AACCG2244H1ZS, | DA69: 09AACCG2244H1ZS | DB69: 09-Uttar Pradesh | DD69: 0 | DF69: Being Purchase 3 PLY Box ( Corrugated) 1488 pcs @18/-+12% GST, Invoice No-516/25-26, Invoice Date-16/7/25, INgate No-145< INgate Date -16/7/25 | DG69: 100 | DH69: INR | DI69: No | DJ69: Stock Received But Not Billed - GCF | DP69: GCF Letterhead | DQ69: 0 | DS69: en | DY69: 0 | EA69: Road | EC69: 45859 | ED69: Regular | EE69: All Other ITC | EG69: Unreconciled | EH69: 0 | EK69: 0 | EM69: Creditors - Raw Material | EO69: 0 | EP69: Against Supplier Invoice 516/25-26 dated 12-07-2025 | ER69: 1488 | ES69: 1488 | ET69: 26784 | EU69: 26784 | EV69: Carton - Cookies 300g | EW69: 18 | EX69: 18 | EY69: PCS | EZ69: 1 | FA69: Stores Noida - GCF | FB69: 0 | FC69: 1 | FI69: 0 | FJ69: 0 | FK69: 0 | FL69: 0 | FM69: 1607.04 | FN69: 6 | FO69: Main - GCF | FQ69: Carton - Cookies 300 g | FR69: 0 | FS69: 0 | FT69: 0 | FU69: 0 | FV69: Stock Received But Not Billed - GCF | FX69: Taxable | FY69: 481910 | FZ69: 0 | GA69: 0 | GC69: 0 | GD69: 0 | GE69: 0 | GF69: 0 | GG69: Carton - Cookies 300g | GH69: Cookies - PM | GI69: 0 | GJ69: {"Output Tax SGST - GCF": 6.0, "Output Tax CGST - GCF": 6.0, "Output Tax IGST - GCF": 12.0, "Input Tax SGST - GCF": 6.0, "Input Tax CGST - GCF": 6.0, "Input Tax IGST - GCF": 12.0, "Input Tax SGST RCM - GCF": 6.0, "Input Tax CGST RCM - GCF": 6.0, "Input Tax IGST RCM - GCF": 12.0} | GK69: GST 12% - GCF | GL69: 0 | GO69: 0 | GS69: 26784 | GT69: 26784 | GU69: 18 | GV69: 18 | GW69: 0 | GX69: 1488 | GY69: 18 | GZ69: 18 | HG69: PR/N/25-26/0075 | HH69: 7ss6m5mjep | HJ69: 18 | HK69: 0 | HL69: 0 | HM69: 0 | HN69: 1488 | HP69: 0 | HT69: 0 | IA69: 1607.04 | IB69: 6 | ID69: PCS | IE69: Noida | IF69: 26784 | IG69: 0 | IH69: 0 | II69: 18 | IJ69: 0 | IN69: INR | IO69: Input Tax CGST - GCF | IP69: Add | IQ69: 1607.04 | IR69: 1607.04 | IT69: Total | IU69: 0 | IV69: Main - GCF | IW69: Input Tax CGST @ 9.0 | IX69: cgst | IY69: 0 | IZ69: 0 | JA69: {"Carton - Cookies 300g":[6.0,1607.04]} | JC69: 1607.04 | JD69: 1607.04 | JE69: 0 | JF69: 28391.04 | JG69: 28391.04 | JH69: On Net Total | LD69: 0 | LF69: Percentage | LG69: 0 | LH69: 45854 | LI69: 100 | LK69: 29998 | LL69: 29998 | LM69: 0 | LN69: 0 | LO69: 29998 | LP69: 29998
IN70: INR | IO70: Input Tax SGST - GCF | IP70: Add | IQ70: 1607.04 | IR70: 1607.04 | IT70: Total | IU70: 0 | IV70: Main - GCF | IW70: Input Tax SGST @ 9.0 | IX70: sgst | IY70: 0 | IZ70: 0 | JA70: {"Carton - Cookies 300g":[6.0,1607.04]} | JC70: 1607.04 | JD70: 1607.04 | JE70: 0 | JF70: 29998.08 | JG70: 29998.08 | JH70: On Net Total
IN71: INR | IO71: Rounded Off - GCF | IP71: Add | IQ71: -0.08 | IR71: -0.08 | IT71: Total | IU71: 0 | IV71: Main - GCF | IW71: Rounded Off | IY71: 0 | IZ71: 0 | JA71: {"Carton - Cookies 300g":[0.0,-0.08]} | JC71: -0.08 | JD71: -0.08 | JE71: 0 | JF71: 29998 | JG71: 29998 | JH71: Actual
A72: PI/N/25-26/0034 | B72: PI/N/25-26/0034-1 | C72: PINV-.YY.- | D72: Om Mithila Industries | E72: 45859 | F72: Noida | G72: Creditors - GCF | H72: Om Mithila Industries | I72: Om Mithila Industries | L72: G. C. Foods Pvt. Ltd. | M72: 0 | N72: 1 | O72: 45859 | Q72: 0 | R72: 0 | T72: 1 | U72: 0 | V72: 1 | W72: 0 | X72: 0 | Z72: 497/25-26 | AA72: 45850 | AD72: INR | AE72: 1 | AF72: 1 | AG72: Standard Selling Delhi | AH72: INR | AI72: 1 | AJ72: 0 | AL72: 0 | AM72: Stores Noida - GCF | AO72: 0 | AR72: 1520 | AS72: 0 | AT72: 29640 | AU72: 29640 | AV72: 29640 | AW72: 29640 | AX72: 29640 | AY72: 29640 | BA72: Input GST In-state - GCF | BE72: 3557 | BF72: 0 | BG72: 3557 | BH72: 3557 | BI72: 0 | BJ72: 3557 | BK72: 33197 | BL72: 0 | BM72: 0 | BN72: INR Thirty Three Thousand, One Hundred And Ninety Seven only. | BO72: 33197 | BP72: 0 | BQ72: 0 | BR72: 0 | BS72: INR Thirty Three Thousand, One Hundred And Ninety Seven only. | BT72: 0 | BU72: 33197 | BV72: 1 | BW72: Grand Total | BX72: 0 | BY72: 0 | BZ72: 0 | CA72: | HSN/SAC | Taxable Amount | Input Tax CGST @ 9.0 | Input Tax SGST @ 9.0 | Rounded Off | | --- | --- | --- | --- | --- | | 48191010 | ₹ 29,640.00 | (6.0%) ₹ 1,778.40 | (6.0%) ₹ 1,778.40 | ₹ 0.20 | | CC72: 0 | CF72: 0 | CG72: 0 | CH72: 0 | CI72: 0 | CJ72: 0 | CM72: Om Mithila Industries-Billing | CN72: A-109 V Sec - 80 Noida, G.B NagarNoida, Uttar Pradesh, State Code: 09, Pincode: 201305, India, GSTIN: 09AOYPS4034E1ZG, | CO72: 09AOYPS4034E1ZG | CP72: Registered Regular | CU72: Om Mithila Industries-Billing | CV72: A-109 V Sec - 80 Noida, G.B NagarNoida, Uttar Pradesh, State Code: 09, Pincode: 201305, India, GSTIN: 09AOYPS4034E1ZG, | CW72: G.C. Foods Pvt. Ltd. Noida - Uttar Pradesh (Shipping) | CX72: B-64, Sector-80,, Noida, Gautam Buddha Nagar, Noida, Uttar Pradesh, State Code: 09, Pincode: 201305, India, Phone: 9958003759, GSTIN: 09AACCG2244H1ZS, | CY72: G.C. Foods Pvt. Ltd. Noida - Uttar Pradesh (Shipping) | CZ72: B-64, Sector-80,, Noida, Gautam Buddha Nagar, Noida, Uttar Pradesh, State Code: 09, Pincode: 201305, India, Phone: 9958003759, GSTIN: 09AACCG2244H1ZS, | DA72: 09AACCG2244H1ZS | DB72: 09-Uttar Pradesh | DD72: 0 | DF72: Ingate No-137, Invoice Bo 497/25-26, Invoice date-12/7/25, Ingate Date -12/7/25 | DG72: 100 | DH72: INR | DI72: No | DJ72: Stock Received But Not Billed - GCF | DP72: GCF Letterhead | DQ72: 0 | DS72: en | DY72: 0 | EA72: Road | EC72: 45859 | ED72: Regular | EE72: All Other ITC | EG72: Unreconciled | EH72: 0 | EK72: 0 | EM72: Creditors - Raw Material | EO72: 0 | EP72: Against Supplier Invoice 497/25-26 dated 12-07-2025 | ER72: 1520 | ES72: 1520 | ET72: 29640 | EU72: 29640 | EV72: Carton - Suji Rusk 65g | EW72: 19.5 | EX72: 19.5 | EY72: PCS | EZ72: 1 | FA72: Stores Noida - GCF | FB72: 0 | FC72: 1 | FI72: 0 | FJ72: 0 | FK72: 0 | FL72: 0 | FM72: 1778.4 | FN72: 6 | FO72: Main - GCF | FQ72: Carton Box - Suji Rusk 65 Gm | FR72: 0 | FS72: 0 | FT72: 0 | FU72: 0 | FV72: Stock Received But Not Billed - GCF | FX72: Taxable | FY72: 48191010 | FZ72: 0 | GA72: 0 | GC72: 0 | GD72: 0 | GE72: 0 | GF72: 0 | GG72: Carton - Suji Rusk 65g | GH72: Cookies - PM | GI72: 0 | GJ72: {"Output Tax SGST - GCF": 6.0, "Output Tax CGST - GCF": 6.0, "Output Tax IGST - GCF": 12.0, "Input Tax SGST - GCF": 6.0, "Input Tax CGST - GCF": 6.0, "Input Tax IGST - GCF": 12.0, "Input Tax SGST RCM - GCF": 6.0, "Input Tax CGST RCM - GCF": 6.0, "Input Tax IGST RCM - GCF": 12.0} | GK72: GST 12% - GCF | GL72: 0 | GO72: 0 | GS72: 29640 | GT72: 29640 | GU72: 19.5 | GV72: 19.5 | GW72: 0 | GX72: 1520 | GY72: 19.5 | GZ72: 19.5 | HG72: PR/N/25-26/0074 | HH72: 8rmo4ojobu | HJ72: 19.5 | HK72: 0 | HL72: 0 | HM72: 0 | HN72: 1520 | HP72: 0 | HT72: 0 | IA72: 1778.4 | IB72: 6 | ID72: PCS | IE72: Noida | IF72: 29640 | IG72: 0 | IH72: 0 | II72: 19.5 | IJ72: 0 | IN72: INR | IO72: Input Tax CGST - GCF | IP72: Add | IQ72: 1778.4 | IR72: 1778.4 | IT72: Total | IU72: 0 | IV72: Main - GCF | IW72: Input Tax CGST @ 9.0 | IX72: cgst | IY72: 0 | IZ72: 0 | JA72: {"Carton - Suji Rusk 65g":[6.0,1778.4]} | JC72: 1778.4 | JD72: 1778.4 | JE72: 0 | JF72: 31418.4 | JG72: 31418.4 | JH72: On Net Total | LD72: 0 | LF72: Percentage | LG72: 0 | LH72: 45859 | LI72: 100 | LK72: 33197 | LL72: 33197 | LM72: 0 | LN72: 0 | LO72: 33197 | LP72: 33197
IN73: INR | IO73: Input Tax SGST - GCF | IP73: Add | IQ73: 1778.4 | IR73: 1778.4 | IT73: Total | IU73: 0 | IV73: Main - GCF | IW73: Input Tax SGST @ 9.0 | IX73: sgst | IY73: 0 | IZ73: 0 | JA73: {"Carton - Suji Rusk 65g":[6.0,1778.4]} | JC73: 1778.4 | JD73: 1778.4 | JE73: 0 | JF73: 33196.8 | JG73: 33196.8 | JH73: On Net Total
IN74: INR | IO74: Rounded Off - GCF | IP74: Add | IQ74: 0.2 | IR74: 0.2 | IT74: Total | IU74: 0 | IV74: Main - GCF | IW74: Rounded Off | IY74: 0 | IZ74: 0 | JA74: {"Carton - Suji Rusk 65g":[0.0,0.2]} | JC74: 0.2 | JD74: 0.2 | JE74: 0 | JF74: 33197 | JG74: 33197 | JH74: Actual
A75: PI/G/25-26/0194 | B75: PI/G/25-26/0194-1 | C75: PINV-.YY.- | D75: Daulat Ram Rakesh Kumar | E75: 45853 | F75: Ghaziabad | G75: Creditors - GCF | H75: Daulat Ram Rakesh Kumar | I75: Daulat Ram Rakesh Kumar | L75: G. C. Foods Pvt. Ltd. | M75: 0.37858796 | N75: 1 | O75: 45853 | Q75: 0 | R75: 0 | T75: 1 | U75: 0 | V75: 1 | W75: 1 | X75: 0 | Y75: TDS ON PURCHASE - 194Q | Z75: GST/25-26/140 | AA75: 45853 | AD75: INR | AE75: 1 | AF75: 1 | AG75: Standard Selling Delhi | AH75: INR | AI75: 1 | AJ75: 0 | AL75: 0 | AM75: Store Ghaziabad - GCF | AO75: 0 | AR75: 830.9 | AS75: 0 | AT75: 312620 | AU75: 312620 | AV75: 312620 | AW75: 312620 | AX75: 312620 | AY75: 312620 | BE75: 16180.62 | BF75: 312.62 | BG75: 15868 | BH75: 16180.62 | BI75: 312.62 | BJ75: 15868 | BK75: 328488 | BL75: 0 | BM75: 0 | BN75: INR Three Lakh, Twenty Eight Thousand, Four Hundred And Eighty Eight only. | BO75: 328488 | BP75: 0 | BQ75: 0 | BR75: 0 | BS75: INR Three Lakh, Twenty Eight Thousand, Four Hundred And Eighty Eight only. | BT75: 0 | BU75: 328488 | BV75: 1 | BW75: Grand Total | BX75: 0 | BY75: 0 | BZ75: 0 | CA75: | HSN/SAC | Taxable Amount | Input Tax IGST | Labour charges | TDS ON PURCHASE - 194Q | Rounded Off | | --- | --- | --- | --- | --- | --- | | 09096139 | ₹ 20,815.00 | (5.0%) ₹ 1,040.75 | ₹ 36.62 | ₹ 20.82 | ₹ -0.03 | | 09041120 | ₹ 37,164.00 | (5.0%) ₹ 1,858.20 | ₹ 65.38 | ₹ 37.16 | ₹ -0.05 | | 09083110 | ₹ 1,26,000.00 | (5.0%) ₹ 6,300.00 | ₹ 221.67 | ₹ 126.00 | ₹ -0.15 | | 282710 | ₹ 21,250.00 | (5.0%) ₹ 1,062.50 | ₹ 37.39 | ₹ 21.25 | ₹ -0.03 | | 04021010 | ₹ 75,000.00 | (5.0%) ₹ 3,750.00 | ₹ 131.95 | ₹ 75.00 | ₹ -0.09 | | 08013210 | ₹ 32,000.00 | (5.0%) ₹ 1,600.00 | ₹ 56.30 | ₹ 32.00 | ₹ -0.04 | | 23040030 | ₹ 391.00 | (5.0%) ₹ 19.55 | ₹ 0.69 | ₹ 0.39 | (0.0%) ₹ 0.00 | | CC75: 0 | CF75: 0 | CG75: 0 | CH75: 0 | CI75: 0 | CJ75: 0 | CM75: Daulat Ram Rakesh Kumar-Billing | CN75: 6232, Kucha Shiv Mandir, Gali Batashan, Khari BaoliNorth Delhi, Delhi, State Code: 07, Pincode: 110006, India, GSTIN: 07AAJPK0095L1ZG, | CO75: 07AAJPK0095L1ZG | CP75: Registered Regular | CU75: Daulat Ram Rakesh Kumar-Billing | CV75: 6232, Kucha Shiv Mandir, Gali Batashan, Khari BaoliNorth Delhi, Delhi, State Code: 07, Pincode: 110006, India, GSTIN: 07AAJPK0095L1ZG, | CW75: G.C. Foods Pvt. Ltd.Ghaziabad - Uttar Pradesh-Billing | CX75: C-4, Sector A-2, , Tronica city Indl. Area, LoniGhaziabad, Uttar Pradesh, State Code: 09, Pincode: 201103, India, Phone: 9350041990, GSTIN: 09AACCG2244H1ZS, | CY75: G.C. Foods Pvt. Ltd.Ghaziabad - Uttar Pradesh-Billing | CZ75: C-4, Sector A-2, , Tronica city Indl. Area, LoniGhaziabad, Uttar Pradesh, State Code: 09, Pincode: 201103, India, Phone: 9350041990, GSTIN: 09AACCG2244H1ZS, | DA75: 09AACCG2244H1ZS | DB75: 09-Uttar Pradesh | DD75: 0 | DF75: Ingate Vch no. 361 Date : 15-07-2025 | DG75: 100 | DH75: INR | DI75: No | DJ75: Stock Received But Not Billed - GCF,Cost of Goods Sold - GCF | DQ75: 0 | DS75: en | DY75: 0 | EA75: Road | EC75: 45853 | ED75: Regular | EE75: All Other ITC | EG75: Unreconciled | EH75: 0 | EK75: 0 | EM75: Creditors - Raw Material | EO75: 0 | EP75: Against Supplier Invoice GST/25-26/140 dated 15-07-2025 | ER75: 181 | ES75: 181 | ET75: 20815 | EU75: 20815 | EV75: Saunf / Sonf | EW75: 115 | EX75: 115 | EY75: KGS | EZ75: 1 | FA75: Store Ghaziabad - GCF | FB75: 0 | FC75: 1 | FI75: 0 | FJ75: 0 | FK75: 0 | FL75: 0 | FM75: 0 | FN75: 0 | FO75: Main - GCF | FQ75: Saunf | FR75: 0 | FS75: 0 | FT75: 0 | FU75: 0 | FV75: Stock Received But Not Billed - GCF | FX75: Taxable | FY75: 09096139 | FZ75: 1040.75 | GA75: 5 | GC75: 0 | GD75: 0 | GE75: 0 | GF75: 0 | GG75: Saunf / Sonf | GH75: Spices and Seasoning - RM | GI75: 0 | GJ75: {"Output Tax SGST - GCF": 2.5, "Output Tax CGST - GCF": 2.5, "Output Tax IGST - GCF": 5.0, "Input Tax SGST - GCF": 2.5, "Input Tax CGST - GCF": 2.5, "Input Tax IGST - GCF": 5.0, "Input Tax SGST RCM - GCF": 2.5, "Input Tax CGST RCM - GCF": 2.5, "Input Tax IGST RCM - GCF": 5.0} | GK75: GST 5% - GCF | GL75: 0 | GO75: 0 | GS75: 20815 | GT75: 20815 | GU75: 115 | GV75: 115 | GW75: 0 | GX75: 181 | GY75: 115 | GZ75: 115 | HG75: PR/G/25-26/0203 | HH75: acrgqkg565 | HJ75: 115 | HK75: 0 | HL75: 0 | HM75: 0 | HN75: 181 | HP75: 0 | HT75: 0 | IA75: 0 | IB75: 0 | ID75: KGS | IE75: Ghaziabad | IF75: 20815 | IG75: 0 | IH75: 0 | II75: 115 | IJ75: 0 | IN75: INR | IO75: Input Tax IGST - GCF | IP75: Add | IQ75: 15631 | IR75: 15631 | IT75: Total | IU75: 0 | IV75: Main - GCF | IW75: Input Tax IGST | IX75: igst | IY75: 0 | IZ75: 0 | JA75: {"Saunf / Sonf":[5.0,1040.75],"Laung / Clove":[5.0,1858.2],"Chhoti Elachi":[5.0,6300.0],"Nausadar":[5.0,1062.5],"Milk Powder":[5.0,3750.0],"Cashew / Kaju":[5.0,1600.0],"BARDANA ON PURCHASE":[5.0,19.55]} | JC75: 15631 | JD75: 15631 | JE75: 18 | JF75: 328251 | JG75: 328251 | JH75: On Net Total | LD75: 0 | LF75: Percentage | LG75: 0 | LH75: 45853 | LI75: 100 | LK75: 328488 | LL75: 328488 | LM75: 0 | LN75: 0 | LO75: 328488 | LP75: 328488
ER76: 48.9 | ES76: 48.9 | ET76: 37164 | EU76: 37164 | EV76: Laung / Clove | EW76: 760 | EX76: 760 | EY76: KGS | EZ76: 1 | FA76: Store Ghaziabad - GCF | FB76: 0 | FC76: 1 | FI76: 0 | FJ76: 0 | FK76: 0 | FL76: 0 | FM76: 0 | FN76: 0 | FO76: Main - GCF | FQ76: Laung | FR76: 0 | FS76: 0 | FT76: 0 | FU76: 0 | FV76: Stock Received But Not Billed - GCF | FX76: Taxable | FY76: 09041120 | FZ76: 1858.2 | GA76: 5 | GC76: 0 | GD76: 0 | GE76: 0 | GF76: 0 | GG76: Laung / Clove | GH76: Spices and Seasoning - RM | GI76: 0 | GJ76: {"Output Tax SGST - GCF": 2.5, "Output Tax CGST - GCF": 2.5, "Output Tax IGST - GCF": 5.0, "Input Tax SGST - GCF": 2.5, "Input Tax CGST - GCF": 2.5, "Input Tax IGST - GCF": 5.0, "Input Tax SGST RCM - GCF": 2.5, "Input Tax CGST RCM - GCF": 2.5, "Input Tax IGST RCM - GCF": 5.0} | GK76: GST 5% - GCF | GL76: 0 | GO76: 0 | GS76: 37164 | GT76: 37164 | GU76: 760 | GV76: 760 | GW76: 0 | GX76: 48.9 | GY76: 760 | GZ76: 760 | HG76: PR/G/25-26/0203 | HH76: acrgd5hl6k | HJ76: 760 | HK76: 0 | HL76: 0 | HM76: 0 | HN76: 48.9 | HP76: 0 | HT76: 0 | IA76: 0 | IB76: 0 | ID76: KGS | IE76: Ghaziabad | IF76: 37164 | IG76: 0 | IH76: 0 | II76: 760 | IJ76: 0 | IN76: INR | IO76: Labour charges - GCF | IP76: Add | IQ76: 550 | IR76: 550 | IT76: Total | IU76: 0 | IV76: Main - GCF | IW76: Labour charges | IY76: 0 | IZ76: 0 | JA76: {"Saunf / Sonf":[0.0,36.62],"Laung / Clove":[0.0,65.38],"Chhoti Elachi":[0.0,221.67],"Nausadar":[0.0,37.39],"Milk Powder":[0.0,131.95],"Cashew / Kaju":[0.0,56.3],"BARDANA ON PURCHASE":[0.0,0.69]} | JC76: 550 | JD76: 550 | JE76: 0 | JF76: 328801 | JG76: 328801 | JH76: Actual
ER77: 60 | ES77: 60 | ET77: 126000 | EU77: 126000 | EV77: Chhoti Elaichi / Green Cardamom | EW77: 2100 | EX77: 2100 | EY77: KGS | EZ77: 1 | FA77: Store Ghaziabad - GCF | FB77: 0 | FC77: 1 | FI77: 0 | FJ77: 0 | FK77: 0 | FL77: 0 | FM77: 0 | FN77: 0 | FO77: Main - GCF | FQ77: Chhoti Elachi | FR77: 0 | FS77: 0 | FT77: 0 | FU77: 0 | FV77: Stock Received But Not Billed - GCF | FX77: Taxable | FY77: 09083110 | FZ77: 6300 | GA77: 5 | GC77: 0 | GD77: 0 | GE77: 0 | GF77: 0 | GG77: Chhoti Elachi | GH77: Spices and Seasoning - RM | GI77: 0 | GJ77: {"Output Tax SGST - GCF": 2.5, "Output Tax CGST - GCF": 2.5, "Output Tax IGST - GCF": 5.0, "Input Tax SGST - GCF": 2.5, "Input Tax CGST - GCF": 2.5, "Input Tax IGST - GCF": 5.0, "Input Tax SGST RCM - GCF": 2.5, "Input Tax CGST RCM - GCF": 2.5, "Input Tax IGST RCM - GCF": 5.0} | GK77: GST 5% - GCF | GL77: 0 | GO77: 0 | GS77: 126000 | GT77: 126000 | GU77: 2100 | GV77: 2100 | GW77: 0 | GX77: 60 | GY77: 0 | GZ77: 0 | HG77: PR/G/25-26/0203 | HH77: acrg6onp58 | HJ77: 2100 | HK77: 0 | HL77: 0 | HM77: 0 | HN77: 60 | HP77: 0 | HT77: 0 | IA77: 0 | IB77: 0 | ID77: KGS | IE77: Ghaziabad | IF77: 126000 | IG77: 0 | IH77: 0 | II77: 2100 | IJ77: 0 | IN77: INR | IO77: TDS Payable - GCF | IP77: Deduct | IQ77: 312.62 | IR77: 312.62 | IT77: Total | IU77: 0 | IV77: Main - GCF | IW77: TDS ON PURCHASE - 194Q | IY77: 1 | IZ77: 0 | JA77: {"Saunf / Sonf":[0.0,20.82],"Laung / Clove":[0.0,37.16],"Chhoti Elachi":[0.0,126.0],"Nausadar":[0.0,21.25],"Milk Powder":[0.0,75.0],"Cashew / Kaju":[0.0,32.0],"BARDANA ON PURCHASE":[0.0,0.39]} | JC77: 312.62 | JD77: 312.62 | JE77: 0 | JF77: 328488.38 | JG77: 328488.38 | JH77: Actual
ER78: 250 | ES78: 250 | ET78: 21250 | EU78: 21250 | EV78: Nausadar | EW78: 85 | EX78: 85 | EY78: KGS | EZ78: 1 | FA78: Store Ghaziabad - GCF | FB78: 0 | FC78: 1 | FI78: 0 | FJ78: 0 | FK78: 0 | FL78: 0 | FM78: 0 | FN78: 0 | FO78: Main - GCF | FQ78: Nausadar | FR78: 0 | FS78: 0 | FT78: 0 | FU78: 0 | FV78: Stock Received But Not Billed - GCF | FX78: Taxable | FY78: 282710 | FZ78: 1062.5 | GA78: 5 | GC78: 0 | GD78: 0 | GE78: 0 | GF78: 0 | GG78: Nausadar | GH78: Spices and Seasoning - RM | GI78: 0 | GJ78: {"Output Tax SGST - GCF": 2.5, "Output Tax CGST - GCF": 2.5, "Output Tax IGST - GCF": 5.0, "Input Tax SGST - GCF": 2.5, "Input Tax CGST - GCF": 2.5, "Input Tax IGST - GCF": 5.0, "Input Tax SGST RCM - GCF": 2.5, "Input Tax CGST RCM - GCF": 2.5, "Input Tax IGST RCM - GCF": 5.0} | GK78: GST 5% - GCF | GL78: 0 | GO78: 0 | GS78: 21250 | GT78: 21250 | GU78: 85 | GV78: 85 | GW78: 0 | GX78: 250 | GY78: 85 | GZ78: 85 | HG78: PR/G/25-26/0203 | HH78: acrghmtvel | HJ78: 85 | HK78: 0 | HL78: 0 | HM78: 0 | HN78: 250 | HP78: 0 | HT78: 0 | IA78: 0 | IB78: 0 | ID78: KGS | IE78: Ghaziabad | IF78: 21250 | IG78: 0 | IH78: 0 | II78: 85 | IJ78: 0 | IN78: INR | IO78: Rounded Off - GCF | IP78: Add | IQ78: -0.38 | IR78: -0.38 | IT78: Total | IU78: 0 | IV78: Main - GCF | IW78: Rounded Off | IY78: 0 | IZ78: 0 | JA78: {"Saunf / Sonf":[0.0,-0.03],"Laung / Clove":[0.0,-0.05],"Chhoti Elachi":[0.0,-0.15],"Nausadar":[0.0,-0.03],"Milk Powder":[0.0,-0.09],"Cashew / Kaju":[0.0,-0.04],"BARDANA ON PURCHASE":[0.0,0.0]} | JC78: -0.38 | JD78: -0.38 | JE78: 0 | JF78: 328488 | JG78: 328488 | JH78: Actual
ER79: 250 | ES79: 250 | ET79: 75000 | EU79: 75000 | EV79: Milk Powder | EW79: 300 | EX79: 300 | EY79: KGS | EZ79: 1 | FA79: Store Ghaziabad - GCF | FB79: 0 | FC79: 1 | FI79: 0 | FJ79: 0 | FK79: 0 | FL79: 0 | FM79: 0 | FN79: 0 | FO79: Main - GCF | FQ79: MIlk Powder | FR79: 20 | FS79: 6.25 | FT79: 0 | FU79: 0 | FV79: Stock Received But Not Billed - GCF | FX79: Taxable | FY79: 04021010 | FZ79: 3750 | GA79: 5 | GC79: 0 | GD79: 0 | GE79: 0 | GF79: 0 | GG79: Milk Powder | GH79: Cookies - RM | GI79: 0 | GJ79: {"Output Tax SGST - GCF": 2.5, "Output Tax CGST - GCF": 2.5, "Output Tax IGST - GCF": 5.0, "Input Tax SGST - GCF": 2.5, "Input Tax CGST - GCF": 2.5, "Input Tax IGST - GCF": 5.0, "Input Tax SGST RCM - GCF": 2.5, "Input Tax CGST RCM - GCF": 2.5, "Input Tax IGST RCM - GCF": 5.0} | GK79: GST 5% - GCF | GL79: 0 | GO79: 0 | GS79: 75000 | GT79: 75000 | GU79: 300 | GV79: 300 | GW79: 0 | GX79: 250 | GY79: 320 | GZ79: 320 | HG79: PR/G/25-26/0203 | HH79: acrg1kb8dl | HJ79: 300 | HK79: 0 | HL79: 0 | HM79: 0 | HN79: 250 | HP79: 0 | HT79: 0 | IA79: 0 | IB79: 0 | ID79: KGS | IE79: Ghaziabad | IF79: 75000 | IG79: 0 | IH79: 0 | II79: 300 | IJ79: 0
ER80: 40 | ES80: 40 | ET80: 32000 | EU80: 32000 | EV80: Cashew / Kaju | EW80: 800 | EX80: 800 | EY80: KGS | EZ80: 1 | FA80: Store Ghaziabad - GCF | FB80: 0 | FC80: 1 | FI80: 0 | FJ80: 0 | FK80: 0 | FL80: 0 | FM80: 0 | FN80: 0 | FO80: Main - GCF | FQ80: Cashew / Kaju | FR80: 60 | FS80: 6.977 | FT80: 0 | FU80: 0 | FV80: Stock Received But Not Billed - GCF | FX80: Taxable | FY80: 08013210 | FZ80: 1600 | GA80: 5 | GC80: 0 | GD80: 0 | GE80: 0 | GF80: 0 | GG80: Cashew / Kaju | GH80: Cookies - RM | GI80: 0 | GJ80: {"Output Tax SGST - GCF": 2.5, "Output Tax CGST - GCF": 2.5, "Output Tax IGST - GCF": 5.0, "Input Tax SGST - GCF": 2.5, "Input Tax CGST - GCF": 2.5, "Input Tax IGST - GCF": 5.0, "Input Tax SGST RCM - GCF": 2.5, "Input Tax CGST RCM - GCF": 2.5, "Input Tax IGST RCM - GCF": 5.0} | GK80: GST 5% - GCF | GL80: 0 | GO80: 0 | GS80: 32000 | GT80: 32000 | GU80: 800 | GV80: 800 | GW80: 0 | GX80: 40 | GY80: 860 | GZ80: 860 | HG80: PR/G/25-26/0203 | HH80: acrgrge8np | HJ80: 800 | HK80: 0 | HL80: 0 | HM80: 0 | HN80: 40 | HP80: 0 | HT80: 0 | IA80: 0 | IB80: 0 | ID80: KGS | IE80: Ghaziabad | IF80: 32000 | IG80: 0 | IH80: 0 | II80: 800 | IJ80: 0
ER81: 1 | ES81: 1 | ET81: 391 | EU81: 391 | EV81: BARDANA ON PURCHASE | EW81: 391 | EX81: 391 | EY81: Nos | EZ81: 1 | FA81: Store Ghaziabad - GCF | FB81: 0 | FC81: 1 | FI81: 0 | FJ81: 0 | FK81: 0 | FL81: 0 | FM81: 0 | FN81: 0 | FO81: Main - GCF | FQ81: BARDANA ON PURCHASE | FR81: 49 | FS81: 11.136 | FT81: 0 | FU81: 0 | FV81: Cost of Goods Sold - GCF | FX81: Taxable | FY81: 23040030 | FZ81: 19.55 | GA81: 5 | GC81: 0 | GD81: 0 | GE81: 0 | GF81: 0 | GG81: BARDANA ON PURCHASE | GH81: Charges Taxable | GI81: 0 | GJ81: {"Output Tax SGST - GCF": 2.5, "Output Tax CGST - GCF": 2.5, "Output Tax IGST - GCF": 5.0, "Input Tax SGST - GCF": 2.5, "Input Tax CGST - GCF": 2.5, "Input Tax IGST - GCF": 5.0, "Input Tax SGST RCM - GCF": 2.5, "Input Tax CGST RCM - GCF": 2.5, "Input Tax IGST RCM - GCF": 5.0} | GK81: GST 5% - GCF | GL81: 0 | GO81: 0 | GS81: 391 | GT81: 391 | GU81: 391 | GV81: 391 | GW81: 0 | GX81: 1 | GY81: 440 | GZ81: 440 | HG81: PR/G/25-26/0203 | HH81: cemj4sm5vu | HJ81: 391 | HK81: 0 | HL81: 0 | HM81: 0 | HN81: 1 | HP81: 0 | HT81: 0 | IA81: 0 | IB81: 0 | ID81: Nos | IE81: Ghaziabad | IF81: 391 | IG81: 0 | IH81: 0 | II81: 0 | IJ81: 0
A82: PI/G/25-26/0193 | B82: PI/G/25-26/0193-1 | C82: PINV-.YY.- | D82: Nimsa Enterprises | E82: 45835 | F82: Ghaziabad | G82: Creditors - GCF | H82: Nimsa Enterprises | I82: Nimsa Enterprises | L82: G. C. Foods Pvt. Ltd. | M82: 0.74007858 | N82: 1 | O82: 45835 | Q82: 0 | R82: 0 | T82: 1 | U82: 0 | V82: 1 | W82: 0 | X82: 0 | Z82: NE/25-26/065 | AA82: 45835 | AD82: INR | AE82: 1 | AF82: 1 | AG82: Standard Buying | AH82: INR | AI82: 1 | AJ82: 0 | AL82: 0 | AM82: Store Ghaziabad - GCF | AO82: 0 | AR82: 5 | AS82: 0 | AT82: 65000 | AU82: 65000 | AV82: 65000 | AW82: 65000 | AX82: 65000 | AY82: 65000 | BA82: Input GST In-state - GCF | BE82: 11700 | BF82: 0 | BG82: 11700 | BH82: 11700 | BI82: 0 | BJ82: 11700 | BK82: 76700 | BL82: 0 | BM82: 0 | BN82: INR Seventy Six Thousand, Seven Hundred only. | BO82: 76700 | BP82: 0 | BQ82: 0 | BR82: 0 | BS82: INR Seventy Six Thousand, Seven Hundred only. | BT82: 0 | BU82: 76700 | BV82: 1 | BW82: Grand Total | BX82: 0 | BY82: 0 | BZ82: 0 | CA82: | HSN/SAC | Taxable Amount | Input Tax CGST @ 9.0 | Input Tax SGST @ 9.0 | | --- | --- | --- | --- | | 84271000 | ₹ 65,000.00 | (9.0%) ₹ 5,850.00 | (9.0%) ₹ 5,850.00 | | CC82: 0 | CF82: 0 | CG82: 0 | CH82: 0 | CI82: 0 | CJ82: 0 | CO82: 09CHMPN4083P1ZE | CP82: Registered Regular | CW82: G.C. Foods Pvt. Ltd.Ghaziabad - Uttar Pradesh-Billing | CX82: C-4, Sector A-2, , Tronica city Indl. Area, LoniGhaziabad, Uttar Pradesh, State Code: 09, Pincode: 201103, India, Phone: 9350041990, GSTIN: 09AACCG2244H1ZS, | CY82: G.C. Foods Pvt. Ltd.Ghaziabad - Uttar Pradesh-Billing | CZ82: C-4, Sector A-2, , Tronica city Indl. Area, LoniGhaziabad, Uttar Pradesh, State Code: 09, Pincode: 201103, India, Phone: 9350041990, GSTIN: 09AACCG2244H1ZS, | DA82: 09AACCG2244H1ZS | DB82: 09-Uttar Pradesh | DD82: 0 | DG82: 100 | DH82: INR | DI82: No | DJ82: Stock Received But Not Billed - GCF | DP82: GCF Letterhead | DQ82: 0 | DS82: en | DY82: 0 | EA82: Road | EC82: 45850 | ED82: Regular | EE82: All Other ITC | EG82: Unreconciled | EH82: 0 | EK82: 0 | EO82: 0 | EP82: Against Supplier Invoice NE/25-26/065 dated 27-06-2025 | ER82: 5 | ES82: 5 | ET82: 65000 | EU82: 65000 | EV82: Hand Pallet Truck - 550 MM | EW82: 13000 | EX82: 13000 | EY82: Nos | EZ82: 1 | FA82: Store Ghaziabad - GCF | FB82: 0 | FC82: 1 | FI82: 0 | FJ82: 0 | FK82: 0 | FL82: 0 | FM82: 5850 | FN82: 9 | FO82: Main - GCF | FQ82: Hand Pallet Truck - 550 MM | FR82: 0 | FS82: 0 | FT82: 0 | FU82: 0 | FV82: Stock Received But Not Billed - GCF | FX82: Taxable | FY82: 84271000 | FZ82: 0 | GA82: 0 | GC82: 0 | GD82: 0 | GE82: 0 | GF82: 0 | GG82: Hand Pallet Truck - 550 MM | GH82: Primary | GI82: 0 | GJ82: {"Output Tax SGST - GCF": 9.0, "Output Tax CGST - GCF": 9.0, "Output Tax IGST - GCF": 18.0, "Input Tax SGST - GCF": 9.0, "Input Tax CGST - GCF": 9.0, "Input Tax IGST - GCF": 18.0, "Input Tax SGST RCM - GCF": 9.0, "Input Tax CGST RCM - GCF": 9.0, "Input Tax IGST RCM - GCF": 18.0} | GK82: GST 18% - GCF | GL82: 0 | GO82: 0 | GS82: 65000 | GT82: 65000 | GU82: 13000 | GV82: 13000 | GW82: 0 | GX82: 5 | GY82: 13000 | GZ82: 13000 | HE82: PO/G/25-26/0140 | HF82: 0oltrpl5f1 | HG82: PR/G/25-26/0181 | HH82: 9paaj6jrrs | HJ82: 13000 | HK82: 0 | HL82: 0 | HM82: 0 | HN82: 5 | HP82: 0 | HT82: 0 | IA82: 5850 | IB82: 9 | ID82: Nos | IE82: Ghaziabad | IF82: 65000 | IG82: 0 | IH82: 0 | II82: 13000 | IJ82: 0 | IN82: INR | IO82: Input Tax CGST - GCF | IP82: Add | IQ82: 5850 | IR82: 5850 | IT82: Total | IU82: 0 | IV82: Main - GCF | IW82: Input Tax CGST @ 9.0 | IX82: cgst | IY82: 0 | IZ82: 0 | JA82: {"Hand Pallet Truck - 550 MM":[9.0,5850.0]} | JC82: 5850 | JD82: 5850 | JE82: 0 | JF82: 70850 | JG82: 70850 | JH82: On Net Total | LD82: 0 | LF82: Percentage | LG82: 0 | LH82: 45835 | LI82: 100 | LK82: 76700 | LL82: 76700 | LM82: 0 | LN82: 0 | LO82: 76700 | LP82: 76700
IN83: INR | IO83: Input Tax SGST - GCF | IP83: Add | IQ83: 5850 | IR83: 5850 | IT83: Total | IU83: 0 | IV83: Main - GCF | IW83: Input Tax SGST @ 9.0 | IX83: sgst | IY83: 0 | IZ83: 0 | JA83: {"Hand Pallet Truck - 550 MM":[9.0,5850.0]} | JC83: 5850 | JD83: 5850 | JE83: 0 | JF83: 76700 | JG83: 76700 | JH83: On Net Total
A84: PI/G/25-26/0192 | B84: PI/G/25-26/0192-1 | C84: PINV-.YY.- | D84: Woxan Packaging Solutions Pvt Ltd | E84: 45828 | F84: Ghaziabad | G84: Creditors - GCF | H84: Woxan Packaging Solutions Pvt Ltd | I84: Woxan Packaging Solutions Pvt Ltd | L84: G. C. Foods Pvt. Ltd. | M84: 0.7286195 | N84: 1 | O84: 45828 | Q84: 0 | R84: 0 | T84: 1 | U84: 0 | V84: 1 | W84: 0 | X84: 0 | Z84: 2025-26/84 | AA84: 45828 | AD84: INR | AE84: 1 | AF84: 1 | AG84: Standard Buying | AH84: INR | AI84: 1 | AJ84: 0 | AL84: 0 | AM84: Store Ghaziabad - GCF | AO84: 0 | AR84: 1 | AS84: 0 | AT84: 33000 | AU84: 33000 | AV84: 33000 | AW84: 33000 | AX84: 33000 | AY84: 33000 | BA84: Input GST In-state - GCF | BE84: 5940 | BF84: 0 | BG84: 5940 | BH84: 5940 | BI84: 0 | BJ84: 5940 | BK84: 38940 | BL84: 0 | BM84: 0 | BN84: INR Thirty Eight Thousand, Nine Hundred And Forty only. | BO84: 38940 | BP84: 0 | BQ84: 0 | BR84: 0 | BS84: INR Thirty Eight Thousand, Nine Hundred And Forty only. | BT84: 0 | BU84: 38940 | BV84: 1 | BW84: Grand Total | BX84: 0 | BY84: 0 | BZ84: 0 | CA84: | HSN/SAC | Taxable Amount | Input Tax CGST @ 9.0 | Input Tax SGST @ 9.0 | | --- | --- | --- | --- | | 84381010 | ₹ 33,000.00 | (9.0%) ₹ 2,970.00 | (9.0%) ₹ 2,970.00 | | CC84: 0 | CF84: 0 | CG84: 0 | CH84: 0 | CI84: 0 | CJ84: 0 | CM84: Woxan Packaging Solutions Pvt Ltd-Billing | CN84: Plot No.12/46, Site No.2, Loni Road,, Industrial AreaGhaziabad, Uttar Pradesh, State Code: 09, Pincode: 201102, India, GSTIN: 09AADCW4829P1ZJ, | CO84: 09AADCW4829P1ZJ | CP84: Registered Regular | CW84: G.C. Foods Pvt. Ltd.Ghaziabad - Uttar Pradesh-Billing | CX84: C-4, Sector A-2, , Tronica city Indl. Area, LoniGhaziabad, Uttar Pradesh, State Code: 09, Pincode: 201103, India, Phone: 9350041990, GSTIN: 09AACCG2244H1ZS, | CY84: G.C. Foods Pvt. Ltd.Ghaziabad - Uttar Pradesh-Billing | CZ84: C-4, Sector A-2, , Tronica city Indl. Area, LoniGhaziabad, Uttar Pradesh, State Code: 09, Pincode: 201103, India, Phone: 9350041990, GSTIN: 09AACCG2244H1ZS, | DA84: 09AACCG2244H1ZS | DB84: 09-Uttar Pradesh | DD84: 0 | DF84: Being Purchase of 3 HP Pulprizer 1 Nos. Ingate Vch no. 277 Date : 20-06-2025 bill no. 84 Date : 20-06-2025 | DG84: 100 | DH84: INR | DI84: No | DJ84: Stock Received But Not Billed - GCF | DP84: GCF Letterhead | DQ84: 0 | DS84: en | DY84: 0 | EA84: Road | EC84: 45839 | ED84: Regular | EE84: All Other ITC | EG84: Unreconciled | EH84: 0 | EK84: 0 | EM84: Creditors - Others | EO84: 0 | EP84: Against Supplier Invoice 2025-26/84 dated 20-06-2025 | ER84: 1 | ES84: 1 | ET84: 33000 | EU84: 33000 | EV84: 3 HP Pulprizer | EW84: 33000 | EX84: 33000 | EY84: PCS | EZ84: 1 | FA84: Store Ghaziabad - GCF | FB84: 0 | FC84: 1 | FI84: 0 | FJ84: 0 | FK84: 0 | FL84: 0 | FM84: 2970 | FN84: 9 | FO84: Main - GCF | FQ84: 3 HP Pulprizer | FR84: 0 | FS84: 0 | FT84: 0 | FU84: 0 | FV84: Stock Received But Not Billed - GCF | FX84: Taxable | FY84: 84381010 | FZ84: 0 | GA84: 0 | GC84: 0 | GD84: 0 | GE84: 0 | GF84: 0 | GG84: 3 HP Pulprizer | GH84: Primary | GI84: 0 | GJ84: {"Output Tax SGST - GCF": 9.0, "Output Tax CGST - GCF": 9.0, "Output Tax IGST - GCF": 18.0, "Input Tax SGST - GCF": 9.0, "Input Tax CGST - GCF": 9.0, "Input Tax IGST - GCF": 18.0, "Input Tax SGST RCM - GCF": 9.0, "Input Tax CGST RCM - GCF": 9.0, "Input Tax IGST RCM - GCF": 18.0} | GK84: GST 18% - GCF | GL84: 0 | GO84: 0 | GS84: 33000 | GT84: 33000 | GU84: 33000 | GV84: 33000 | GW84: 0 | GX84: 1 | GY84: 33000 | GZ84: 33000 | HE84: PO/G/25-26/0120 | HF84: d5lj1gvda8 | HG84: PR/G/25-26/0153 | HH84: d1pufm9u4j | HJ84: 33000 | HK84: 0 | HL84: 0 | HM84: 0 | HN84: 1 | HP84: 0 | HT84: 0 | IA84: 2970 | IB84: 9 | ID84: PCS | IE84: Ghaziabad | IF84: 33000 | IG84: 0 | IH84: 0 | II84: 33000 | IJ84: 0 | IN84: INR | IO84: Input Tax CGST - GCF | IP84: Add | IQ84: 2970 | IR84: 2970 | IS84: Ghaziabad | IT84: Total | IU84: 0 | IV84: Main - GCF | IW84: Input Tax CGST @ 9.0 | IX84: cgst | IY84: 0 | IZ84: 0 | JA84: {"3 HP Pulprizer":[9.0,2970.0]} | JC84: 2970 | JD84: 2970 | JE84: 0 | JF84: 35970 | JG84: 35970 | JH84: On Net Total | LD84: 0 | LF84: Percentage | LG84: 0 | LH84: 45828 | LI84: 100 | LK84: 38940 | LL84: 38940 | LM84: 0 | LN84: 0 | LO84: 38940 | LP84: 38940
IN85: INR | IO85: Input Tax SGST - GCF | IP85: Add | IQ85: 2970 | IR85: 2970 | IS85: Ghaziabad | IT85: Total | IU85: 0 | IV85: Main - GCF | IW85: Input Tax SGST @ 9.0 | IX85: sgst | IY85: 0 | IZ85: 0 | JA85: {"3 HP Pulprizer":[9.0,2970.0]} | JC85: 2970 | JD85: 2970 | JE85: 0 | JF85: 38940 | JG85: 38940 | JH85: On Net Total
A86: PI/G/25-26/0191 | B86: PI/G/25-26/0191-1 | C86: PINV-.YY.- | D86: AD Trading Co. | E86: 45846 | F86: Ghaziabad | G86: Creditors - GCF | H86: AD Trading Co. | I86: AD Trading Co. | L86: G. C. Foods Pvt. Ltd. | M86: 0.72587396 | N86: 1 | O86: 45846 | Q86: 0 | R86: 0 | T86: 1 | U86: 0 | V86: 1 | W86: 0 | X86: 0 | Z86: 248 | AA86: 45846 | AD86: INR | AE86: 1 | AF86: 1 | AG86: Standard Buying | AH86: INR | AI86: 1 | AJ86: 0 | AL86: 0 | AM86: Store Ghaziabad - GCF | AO86: 0 | AR86: 4050 | AS86: 0 | AT86: 384750 | AU86: 384750 | AV86: 384750 | AW86: 384750 | AX86: 384750 | AY86: 384750 | BE86: 675 | BF86: 0 | BG86: 675 | BH86: 675 | BI86: 0 | BJ86: 675 | BK86: 385425 | BL86: 0 | BM86: 0 | BN86: INR Three Lakh, Eighty Five Thousand, Four Hundred And Twenty Five only. | BO86: 385425 | BP86: 0 | BQ86: 0 | BR86: 0 | BS86: INR Three Lakh, Eighty Five Thousand, Four Hundred And Twenty Five only. | BT86: 0 | BU86: 385425 | BV86: 1 | BW86: Grand Total | BX86: 0 | BY86: 0 | BZ86: 0 | CA86: | HSN/SAC | Taxable Amount | Labour charges | | --- | --- | --- | | 071320 | ₹ 3,84,750.00 | ₹ 675.00 | | CC86: 0 | CF86: 0 | CG86: 0 | CH86: 0 | CI86: 0 | CJ86: 0 | CM86: AD Trading Co.-Billing | CN86: 4051/5, ( Opposite. Grain Merchants Association), Naya Bzar, Delhi, Delhi, State Code: 07, Pincode: 110006, India, | CP86: Unregistered | CU86: AD Trading Co.-Billing | CV86: 4051/5, ( Opposite. Grain Merchants Association), Naya Bzar, Delhi, Delhi, State Code: 07, Pincode: 110006, India, | CW86: G.C. Foods Pvt. Ltd.Ghaziabad - Uttar Pradesh-Billing | CX86: C-4, Sector A-2, , Tronica city Indl. Area, LoniGhaziabad, Uttar Pradesh, State Code: 09, Pincode: 201103, India, Phone: 9350041990, GSTIN: 09AACCG2244H1ZS, | CY86: G.C. Foods Pvt. Ltd.Ghaziabad - Uttar Pradesh-Billing | CZ86: C-4, Sector A-2, , Tronica city Indl. Area, LoniGhaziabad, Uttar Pradesh, State Code: 09, Pincode: 201103, India, Phone: 9350041990, GSTIN: 09AACCG2244H1ZS, | DA86: 09AACCG2244H1ZS | DB86: 09-Uttar Pradesh | DD86: 0 | DF86: Being Purchase of Chana 135 Bags PBWT : 4050 Kg & PKWT : Nil & FKWT : 3970 Kg Ingate Vch no. 325 Date : 08-07-2025 | DG86: 100 | DH86: INR | DI86: No | DJ86: Stock Received But Not Billed - GCF | DQ86: 0 | DS86: en | DY86: 0 | EA86: Road | EC86: 45846 | ED86: Regular | EE86: All Other ITC | EG86: Not Applicable | EH86: 0 | EK86: 0 | EM86: Creditors - Raw Material | EO86: 0 | EP86: Against Supplier Invoice 248 dated 08-07-2025 | ER86: 4050 | ES86: 4050 | ET86: 384750 | EU86: 384750 | EV86: Chana New-Gujrat No.1 | EW86: 95 | EX86: 95 | EY86: KGS | EZ86: 1 | FA86: Store Ghaziabad - GCF | FB86: 0 | FC86: 1 | FI86: 0 | FJ86: 0 | FK86: 0 | FL86: 0 | FM86: 0 | FN86: 0 | FO86: Main - GCF | FQ86: Chana New-Gujrat No.1 | FR86: 0 | FS86: 0 | FT86: 0 | FU86: 0 | FV86: Stock Received But Not Billed - GCF | FX86: Exempted | FY86: 071320 | FZ86: 0 | GA86: 0 | GC86: 0 | GD86: 0 | GE86: 0 | GF86: 0 | GG86: Chana -Gujrat No.1 | GH86: Sattu and Chana - RM | GI86: 0 | GJ86: {"Input Tax CGST - GCF": 0.0, "Input Tax SGST - GCF": 0.0, "Input Tax IGST - GCF": 0.0, "Output Tax CGST - GCF": 0.0, "Output Tax SGST - GCF": 0.0, "Output Tax IGST - GCF": 0.0, "Input Tax CGST RCM - GCF": 0.0, "Input Tax SGST RCM - GCF": 0.0, "Input Tax IGST RCM - GCF": 0.0} | GK86: Exempted - GCF | GL86: 0 | GO86: 0 | GS86: 384750 | GT86: 384750 | GU86: 95 | GV86: 95 | GW86: 0 | GX86: 4050 | GY86: 0 | GZ86: 0 | HG86: PR/G/25-26/0188 | HH86: deubko90jq | HJ86: 95 | HK86: 0 | HL86: 0 | HM86: 0 | HN86: 4050 | HP86: 0 | HT86: 0 | IA86: 0 | IB86: 0 | ID86: KGS | IE86: Ghaziabad | IF86: 385425 | IG86: 0 | IH86: 0 | II86: 95 | IJ86: 0 | IN86: INR | IO86: Labour charges - GCF | IP86: Add | IQ86: 675 | IR86: 675 | IT86: Total | IU86: 0 | IV86: Main - GCF | IW86: Labour charges | IY86: 0 | IZ86: 0 | JA86: {"Chana -Gujrat No.1": [0.0, 675.0]} | JC86: 675 | JD86: 675 | JE86: 0 | JF86: 385425 | JG86: 385425 | JH86: Actual | LD86: 0 | LF86: Percentage | LG86: 0 | LH86: 45846 | LI86: 100 | LK86: 385425 | LL86: 385425 | LM86: 0 | LN86: 0 | LO86: 385425 | LP86: 385425
A87: PI/G/25-26/0190 | B87: PI/G/25-26/0190-1 | C87: PINV-.YY.- | D87: AD Trading Co. | E87: 45847 | F87: Ghaziabad | G87: Creditors - GCF | H87: AD Trading Co. | I87: AD Trading Co. | L87: G. C. Foods Pvt. Ltd. | M87: 0.72551886 | N87: 1 | O87: 45847 | Q87: 0 | R87: 0 | T87: 1 | U87: 0 | V87: 1 | W87: 0 | X87: 0 | Z87: 249 | AA87: 45847 | AD87: INR | AE87: 1 | AF87: 1 | AG87: Standard Buying | AH87: INR | AI87: 1 | AJ87: 0 | AL87: 0 | AM87: Store Ghaziabad - GCF | AO87: 0 | AR87: 1950 | AS87: 0 | AT87: 185250 | AU87: 185250 | AV87: 185250 | AW87: 185250 | AX87: 185250 | AY87: 185250 | BE87: 325 | BF87: 0 | BG87: 325 | BH87: 325 | BI87: 0 | BJ87: 325 | BK87: 185575 | BL87: 0 | BM87: 0 | BN87: INR One Lakh, Eighty Five Thousand, Five Hundred And Seventy Five only. | BO87: 185575 | BP87: 0 | BQ87: 0 | BR87: 0 | BS87: INR One Lakh, Eighty Five Thousand, Five Hundred And Seventy Five only. | BT87: 0 | BU87: 185575 | BV87: 1 | BW87: Grand Total | BX87: 0 | BY87: 0 | BZ87: 0 | CA87: | HSN/SAC | Taxable Amount | Labour charges | | --- | --- | --- | | 071320 | ₹ 1,85,250.00 | ₹ 325.00 | | CC87: 0 | CF87: 0 | CG87: 0 | CH87: 0 | CI87: 0 | CJ87: 0 | CM87: AD Trading Co.-Billing | CN87: 4051/5, ( Opposite. Grain Merchants Association), Naya Bzar, Delhi, Delhi, State Code: 07, Pincode: 110006, India, | CP87: Unregistered | CU87: AD Trading Co.-Billing | CV87: 4051/5, ( Opposite. Grain Merchants Association), Naya Bzar, Delhi, Delhi, State Code: 07, Pincode: 110006, India, | CW87: G.C. Foods Pvt. Ltd.Ghaziabad - Uttar Pradesh-Billing | CX87: C-4, Sector A-2, , Tronica city Indl. Area, LoniGhaziabad, Uttar Pradesh, State Code: 09, Pincode: 201103, India, Phone: 9350041990, GSTIN: 09AACCG2244H1ZS, | CY87: G.C. Foods Pvt. Ltd.Ghaziabad - Uttar Pradesh-Billing | CZ87: C-4, Sector A-2, , Tronica city Indl. Area, LoniGhaziabad, Uttar Pradesh, State Code: 09, Pincode: 201103, India, Phone: 9350041990, GSTIN: 09AACCG2244H1ZS, | DA87: 09AACCG2244H1ZS | DB87: 09-Uttar Pradesh | DD87: 0 | DF87: Being Purchase of Chana 65 Bags PBWT : 1950 Kg & PKWT : Nil & FKWT : 1970 Kg Ingate Vch no. 324 Date : 09-07-2025 | DG87: 100 | DH87: INR | DI87: No | DJ87: Stock Received But Not Billed - GCF | DQ87: 0 | DS87: en | DY87: 0 | EA87: Road | EC87: 45847 | ED87: Regular | EE87: All Other ITC | EG87: Not Applicable | EH87: 0 | EK87: 0 | EM87: Creditors - Raw Material | EO87: 0 | EP87: Against Supplier Invoice 249 dated 09-07-2025 | ER87: 1950 | ES87: 1950 | ET87: 185250 | EU87: 185250 | EV87: Chana New-Gujrat No.1 | EW87: 95 | EX87: 95 | EY87: KGS | EZ87: 1 | FA87: Store Ghaziabad - GCF | FB87: 0 | FC87: 1 | FI87: 0 | FJ87: 0 | FK87: 0 | FL87: 0 | FM87: 0 | FN87: 0 | FO87: Main - GCF | FQ87: Chana New-Gujrat No.1 | FR87: 0 | FS87: 0 | FT87: 0 | FU87: 0 | FV87: Stock Received But Not Billed - GCF | FX87: Exempted | FY87: 071320 | FZ87: 0 | GA87: 0 | GC87: 0 | GD87: 0 | GE87: 0 | GF87: 0 | GG87: Chana -Gujrat No.1 | GH87: Sattu and Chana - RM | GI87: 0 | GJ87: {"Input Tax CGST - GCF": 0.0, "Input Tax SGST - GCF": 0.0, "Input Tax IGST - GCF": 0.0, "Output Tax CGST - GCF": 0.0, "Output Tax SGST - GCF": 0.0, "Output Tax IGST - GCF": 0.0, "Input Tax CGST RCM - GCF": 0.0, "Input Tax SGST RCM - GCF": 0.0, "Input Tax IGST RCM - GCF": 0.0} | GK87: Exempted - GCF | GL87: 0 | GO87: 0 | GS87: 185250 | GT87: 185250 | GU87: 95 | GV87: 95 | GW87: 0 | GX87: 1950 | GY87: 0 | GZ87: 0 | HG87: PR/G/25-26/0189 | HH87: 4grup5vi6q | HJ87: 95 | HK87: 0 | HL87: 0 | HM87: 0 | HN87: 1950 | HP87: 0 | HT87: 0 | IA87: 0 | IB87: 0 | ID87: KGS | IE87: Ghaziabad | IF87: 185575 | IG87: 0 | IH87: 0 | II87: 95 | IJ87: 0 | IN87: INR | IO87: Labour charges - GCF | IP87: Add | IQ87: 325 | IR87: 325 | IT87: Total | IU87: 0 | IV87: Main - GCF | IW87: Labour charges | IY87: 0 | IZ87: 0 | JA87: {"Chana -Gujrat No.1": [0.0, 325.0]} | JC87: 325 | JD87: 325 | JE87: 0 | JF87: 185575 | JG87: 185575 | JH87: Actual | LD87: 0 | LF87: Percentage | LG87: 0 | LH87: 45847 | LI87: 100 | LK87: 185575 | LL87: 185575 | LM87: 0 | LN87: 0 | LO87: 185575 | LP87: 185575
A88: PI/G/25-26/0189 | B88: PI/G/25-26/0189-1 | C88: PINV-.YY.- | D88: AD Trading Co. | E88: 45848 | F88: Ghaziabad | G88: Creditors - GCF | H88: AD Trading Co. | I88: AD Trading Co. | L88: G. C. Foods Pvt. Ltd. | M88: 0.72526521 | N88: 1 | O88: 45848 | Q88: 0 | R88: 0 | T88: 1 | U88: 0 | V88: 1 | W88: 0 | X88: 0 | Z88: 251 | AA88: 45848 | AD88: INR | AE88: 1 | AF88: 1 | AG88: Standard Buying | AH88: INR | AI88: 1 | AJ88: 0 | AL88: 0 | AM88: Store Ghaziabad - GCF | AO88: 0 | AR88: 2100 | AS88: 0 | AT88: 199500 | AU88: 199500 | AV88: 199500 | AW88: 199500 | AX88: 199500 | AY88: 199500 | BE88: 350 | BF88: 0 | BG88: 350 | BH88: 350 | BI88: 0 | BJ88: 350 | BK88: 199850 | BL88: 0 | BM88: 0 | BN88: INR One Lakh, Ninety Nine Thousand, Eight Hundred And Fifty only. | BO88: 199850 | BP88: 0 | BQ88: 0 | BR88: 0 | BS88: INR One Lakh, Ninety Nine Thousand, Eight Hundred And Fifty only. | BT88: 0 | BU88: 199850 | BV88: 1 | BW88: Grand Total | BX88: 0 | BY88: 0 | BZ88: 0 | CA88: | HSN/SAC | Taxable Amount | Rounded Off | | --- | --- | --- | | 071320 | ₹ 1,99,500.00 | ₹ 350.00 | | CC88: 0 | CF88: 0 | CG88: 0 | CH88: 0 | CI88: 0 | CJ88: 0 | CM88: AD Trading Co.-Billing | CN88: 4051/5, ( Opposite. Grain Merchants Association), Naya Bzar, Delhi, Delhi, State Code: 07, Pincode: 110006, India, | CP88: Unregistered | CU88: AD Trading Co.-Billing | CV88: 4051/5, ( Opposite. Grain Merchants Association), Naya Bzar, Delhi, Delhi, State Code: 07, Pincode: 110006, India, | CW88: G.C. Foods Pvt. Ltd.Ghaziabad - Uttar Pradesh-Billing | CX88: C-4, Sector A-2, , Tronica city Indl. Area, LoniGhaziabad, Uttar Pradesh, State Code: 09, Pincode: 201103, India, Phone: 9350041990, GSTIN: 09AACCG2244H1ZS, | CY88: G.C. Foods Pvt. Ltd.Ghaziabad - Uttar Pradesh-Billing | CZ88: C-4, Sector A-2, , Tronica city Indl. Area, LoniGhaziabad, Uttar Pradesh, State Code: 09, Pincode: 201103, India, Phone: 9350041990, GSTIN: 09AACCG2244H1ZS, | DA88: 09AACCG2244H1ZS | DB88: 09-Uttar Pradesh | DD88: 0 | DF88: Being Purchase of Chana 70 Bags PBWT : 2100 Kg & PKWT : Nil & FKWT : 2095 Kg Ingate Vch no. 337 Date : 10-07-2025 | DG88: 100 | DH88: INR | DI88: No | DJ88: Stock Received But Not Billed - GCF | DQ88: 0 | DS88: en | DY88: 0 | EA88: Road | EC88: 45848 | ED88: Regular | EE88: All Other ITC | EG88: Not Applicable | EH88: 0 | EK88: 0 | EM88: Creditors - Raw Material | EO88: 0 | EP88: Against Supplier Invoice 251 dated 10-07-2025 | ER88: 2100 | ES88: 2100 | ET88: 199500 | EU88: 199500 | EV88: Chana New-Gujrat No.1 | EW88: 95 | EX88: 95 | EY88: KGS | EZ88: 1 | FA88: Store Ghaziabad - GCF | FB88: 0 | FC88: 1 | FI88: 0 | FJ88: 0 | FK88: 0 | FL88: 0 | FM88: 0 | FN88: 0 | FO88: Main - GCF | FQ88: Chana New-Gujrat No.1 | FR88: 0 | FS88: 0 | FT88: 0 | FU88: 0 | FV88: Stock Received But Not Billed - GCF | FX88: Exempted | FY88: 071320 | FZ88: 0 | GA88: 0 | GC88: 0 | GD88: 0 | GE88: 0 | GF88: 0 | GG88: Chana -Gujrat No.1 | GH88: Sattu and Chana - RM | GI88: 0 | GJ88: {"Input Tax CGST - GCF": 0.0, "Input Tax SGST - GCF": 0.0, "Input Tax IGST - GCF": 0.0, "Output Tax CGST - GCF": 0.0, "Output Tax SGST - GCF": 0.0, "Output Tax IGST - GCF": 0.0, "Input Tax CGST RCM - GCF": 0.0, "Input Tax SGST RCM - GCF": 0.0, "Input Tax IGST RCM - GCF": 0.0} | GK88: Exempted - GCF | GL88: 0 | GO88: 0 | GS88: 199500 | GT88: 199500 | GU88: 95 | GV88: 95 | GW88: 0 | GX88: 2100 | GY88: 0 | GZ88: 0 | HG88: PR/G/25-26/0190 | HH88: cicv41hf99 | HJ88: 95 | HK88: 0 | HL88: 0 | HM88: 0 | HN88: 2100 | HP88: 0 | HT88: 0 | IA88: 0 | IB88: 0 | ID88: KGS | IE88: Ghaziabad | IF88: 199850 | IG88: 0 | IH88: 0 | II88: 95 | IJ88: 0 | IN88: INR | IO88: Rounded Off - GCF | IP88: Add | IQ88: 350 | IR88: 350 | IT88: Total | IU88: 0 | IV88: Main - GCF | IW88: Rounded Off | IY88: 0 | IZ88: 0 | JA88: {"Chana -Gujrat No.1": [0.0, 350.0]} | JC88: 350 | JD88: 350 | JE88: 0 | JF88: 199850 | JG88: 199850 | JH88: Actual | LD88: 0 | LF88: Percentage | LG88: 0 | LH88: 45848 | LI88: 100 | LK88: 199850 | LL88: 199850 | LM88: 0 | LN88: 0 | LO88: 199850 | LP88: 199850
A89: PI/G/25-26/0188 | B89: PI/G/25-26/0188-1 | C89: PINV-.YY.- | D89: CHHOTELAL MOTILAL AGRAWAL | E89: 45846 | F89: Ghaziabad | G89: Creditors - GCF | H89: CHHOTELAL MOTILAL AGRAWAL | I89: CHHOTELAL MOTILAL AGRAWAL | L89: G. C. Foods Pvt. Ltd. | M89: 0.72416827 | N89: 1 | O89: 45846 | Q89: 0 | R89: 0 | T89: 1 | U89: 0 | V89: 1 | W89: 0 | X89: 0 | Z89: 122 | AA89: 45846 | AD89: INR | AE89: 1 | AF89: 1 | AG89: Standard Buying | AH89: INR | AI89: 1 | AJ89: 0 | AL89: 0 | AM89: Store Ghaziabad - GCF | AO89: 0 | AR89: 32245 | AS89: 0 | AT89: 1822164.9 | AU89: 1822164.9 | AV89: 1822164.9 | AW89: 1822164.9 | AX89: 1822164.9 | AY89: 1822164.9 | BE89: 8178.05 | BF89: 0 | BG89: 8178.05 | BH89: 8178.05 | BI89: 0 | BJ89: 8178.05 | BK89: 1830343 | BL89: 0 | BM89: 0 | BN89: INR Eighteen Lakh, Thirty Thousand, Three Hundred And Forty Three only. | BO89: 1830343 | BP89: 0 | BQ89: 0 | BR89: 0 | BS89: INR Eighteen Lakh, Thirty Thousand, Three Hundred And Forty Three only. | BT89: 0 | BU89: 1830343 | BV89: 1 | BW89: Grand Total | BX89: 0 | BY89: 0 | BZ89: 0 | CA89: | HSN/SAC | Taxable Amount | Freight Inward | TDS on purchase | Rounded Off | | --- | --- | --- | --- | --- | | 071320 | ₹ 18,22,164.95 | ₹ 10,000.00 | ₹ -1,822.00 | ₹ 0.05 | | CC89: 0 | CF89: 0 | CG89: 0 | CH89: 0 | CI89: 0 | CJ89: 0 | CO89: 23AKFPA9505M1Z8 | CP89: Registered Regular | CW89: G.C. Foods Pvt. Ltd.Ghaziabad - Uttar Pradesh-Billing | CX89: C-4, Sector A-2, , Tronica city Indl. Area, LoniGhaziabad, Uttar Pradesh, State Code: 09, Pincode: 201103, India, Phone: 9350041990, GSTIN: 09AACCG2244H1ZS, | CY89: G.C. Foods Pvt. Ltd.Ghaziabad - Uttar Pradesh-Billing | CZ89: C-4, Sector A-2, , Tronica city Indl. Area, LoniGhaziabad, Uttar Pradesh, State Code: 09, Pincode: 201103, India, Phone: 9350041990, GSTIN: 09AACCG2244H1ZS, | DA89: 09AACCG2244H1ZS | DB89: 09-Uttar Pradesh | DD89: 0 | DF89: Being Purchase of Chana 633 Bags PBWT : 32245 Kg & PKWT : 32245 Kg & PREET KWT : 32400 Kg Ingate Vch no.332 Date : 08-07-2025 | DG89: 100 | DH89: INR | DI89: No | DJ89: Stock Received But Not Billed - GCF | DQ89: 0 | DS89: en | DY89: 0 | EA89: Road | EC89: 45846 | ED89: Regular | EE89: All Other ITC | EG89: Unreconciled | EH89: 0 | EK89: 0 | EM89: Creditors - Raw Material | EO89: 0 | EP89: Against Supplier Invoice 122 dated 08-07-2025 | ER89: 32245 | ES89: 32245 | ET89: 1822164.9 | EU89: 1822164.9 | EV89: Chana New-Annagiri | EW89: 56.51 | EX89: 56.51 | EY89: KGS | EZ89: 1 | FA89: Store Ghaziabad - GCF | FB89: 0 | FC89: 1 | FI89: 0 | FJ89: 0 | FK89: 0 | FL89: 0 | FM89: 0 | FN89: 0 | FO89: Main - GCF | FQ89: Chana New-Annagiri | FR89: 1.24 | FS89: 2.147 | FT89: 0 | FU89: 0 | FV89: Stock Received But Not Billed - GCF | FX89: Exempted | FY89: 071320 | FZ89: 0 | GA89: 0 | GC89: 0 | GD89: 0 | GE89: 0 | GF89: 0 | GG89: Chana -Annagiri | GH89: Sattu and Chana - RM | GI89: 0 | GJ89: {"Input Tax CGST - GCF": 0.0, "Input Tax SGST - GCF": 0.0, "Input Tax IGST - GCF": 0.0, "Output Tax CGST - GCF": 0.0, "Output Tax SGST - GCF": 0.0, "Output Tax IGST - GCF": 0.0, "Input Tax CGST RCM - GCF": 0.0, "Input Tax SGST RCM - GCF": 0.0, "Input Tax IGST RCM - GCF": 0.0} | GK89: Exempted - GCF | GL89: 0 | GO89: 0 | GS89: 1822164.9 | GT89: 1822164.9 | GU89: 56.51 | GV89: 56.51 | GW89: 0 | GX89: 32245 | GY89: 57.75 | GZ89: 57.75 | HG89: PR/G/25-26/0191 | HH89: 2m7t4aj857 | HJ89: 56.51 | HK89: 0 | HL89: 0 | HM89: 0 | HN89: 32245 | HP89: 0 | HT89: 0 | IA89: 0 | IB89: 0 | ID89: KGS | IE89: Ghaziabad | IF89: 1830343 | IG89: 0 | IH89: 0 | II89: 56.51 | IJ89: 0 | IN89: INR | IO89: Freight Inward - GCF | IP89: Add | IQ89: 10000 | IR89: 10000 | IT89: Total | IU89: 0 | IV89: Main - GCF | IW89: Freight Inward | IY89: 0 | IZ89: 0 | JA89: {"Chana -Annagiri": [0.0, 10000.0]} | JC89: 10000 | JD89: 10000 | JE89: 0 | JF89: 1832164.9 | JG89: 1832164.9 | JH89: Actual | LD89: 0 | LF89: Percentage | LG89: 0 | LH89: 45846 | LI89: 100 | LK89: 1830343 | LL89: 1830343 | LM89: 0 | LN89: 0 | LO89: 1830343 | LP89: 1830343
IN90: INR | IO90: TDS - TDS on purchase - GCF | IP90: Add | IQ90: -1822 | IR90: -1822 | IT90: Total | IU90: 0 | IV90: Main - GCF | IW90: TDS on purchase | IY90: 0 | IZ90: 0 | JA90: {"Chana -Annagiri": [0.0, -1822.0]} | JC90: -1822 | JD90: -1822 | JE90: 0 | JF90: 1830342.9 | JG90: 1830342.9 | JH90: Actual
IN91: INR | IO91: Rounded Off - GCF | IP91: Add | IQ91: 0.05 | IR91: 0.05 | IT91: Total | IU91: 0 | IV91: Main - GCF | IW91: Rounded Off | IY91: 0 | IZ91: 0 | JA91: {"Chana -Annagiri": [0.0, 0.05]} | JC91: 0.05 | JD91: 0.05 | JE91: 0 | JF91: 1830343 | JG91: 1830343 | JH91: Actual
A92: PI/G/25-26/0187 | B92: PI/G/25-26/0187-1 | C92: PINV-.YY.- | D92: Daulat Ram Rakesh Kumar | E92: 45850 | F92: Ghaziabad | G92: Creditors - GCF | H92: Daulat Ram Rakesh Kumar | I92: Daulat Ram Rakesh Kumar | L92: G. C. Foods Pvt. Ltd. | M92: 0.72238855 | N92: 1 | O92: 45850 | Q92: 0 | R92: 1 | S92: PI/G/25-26/0186 | T92: 1 | U92: 0 | V92: 1 | W92: 1 | X92: 0 | Y92: TDS - 194C - Individual | Z92: GST/25-26/136 | AA92: 45850 | AD92: INR | AE92: 1 | AF92: 1 | AG92: Standard Buying | AH92: INR | AI92: 1 | AJ92: 1 | AL92: 0 | AO92: 0 | AR92: -7.3 | AS92: 0 | AT92: -1007.4 | AU92: -1007.4 | AV92: -1007.4 | AW92: -1007.4 | AX92: -1007.4 | AY92: -1007.4 | BA92: Input GST Out-state - GCF | BE92: -1.6 | BF92: 0 | BG92: -1.6 | BH92: -1.6 | BI92: 0 | BJ92: -1.6 | BK92: -1009 | BL92: 0 | BM92: 0 | BN92: INR One Thousand And Nine only. | BO92: -1009 | BP92: 0 | BQ92: 0 | BR92: 0 | BS92: INR One Thousand And Nine only. | BT92: 0 | BU92: -1009 | BV92: 1 | BW92: Grand Total | BX92: 0 | BY92: 0 | BZ92: 0 | CA92: | HSN/SAC | Taxable Amount | Rounded Off | | --- | --- | --- | | 09103030 | ₹ 1,007.40 | ₹ 1.60 | | CC92: 0 | CF92: 0 | CG92: 0 | CH92: 0 | CI92: 0 | CJ92: 0 | CM92: Daulat Ram Rakesh Kumar-Billing | CN92: 6232, Kucha Shiv Mandir, Gali Batashan, Khari BaoliNorth Delhi, Delhi, State Code: 07, Pincode: 110006, India, GSTIN: 07AAJPK0095L1ZG, | CO92: 07AAJPK0095L1ZG | CP92: Registered Regular | CU92: Daulat Ram Rakesh Kumar-Billing | CV92: 6232, Kucha Shiv Mandir, Gali Batashan, Khari BaoliNorth Delhi, Delhi, State Code: 07, Pincode: 110006, India, GSTIN: 07AAJPK0095L1ZG, | CW92: G.C. Foods Pvt. Ltd.Ghaziabad - Uttar Pradesh-Billing | CX92: C-4, Sector A-2, , Tronica city Indl. Area, LoniGhaziabad, Uttar Pradesh, State Code: 09, Pincode: 201103, India, Phone: 9350041990, GSTIN: 09AACCG2244H1ZS, | CY92: G.C. Foods Pvt. Ltd.Ghaziabad - Uttar Pradesh-Billing | CZ92: C-4, Sector A-2, , Tronica city Indl. Area, LoniGhaziabad, Uttar Pradesh, State Code: 09, Pincode: 201103, India, Phone: 9350041990, GSTIN: 09AACCG2244H1ZS, | DA92: 09AACCG2244H1ZS | DB92: 10-Bihar | DD92: 0 | DF92: Being Purchase of Mirch & Amchur & Haldi Ingate Vch no. 349 Date : 12-07-2025 bill no. 136 Date : 11-07-2025 | DG92: 6794.5205 | DH92: INR | DI92: No | DJ92: Stock Received But Not Billed - GCF | DQ92: 0 | DR92: Debit Note | DS92: en | DY92: 0 | EA92: Road | EC92: 45856 | ED92: Regular | EE92: All Other ITC | EF92: ITC restricted due to PoS rules | EG92: Unreconciled | EH92: 0 | EK92: 0 | EM92: Creditors - Raw Material | EO92: 0 | EP92: Against Supplier Invoice GST/25-26/136 dated 12-07-2025 | ER92: -7.3 | ES92: -7.3 | ET92: -1007.4 | EU92: -1007.4 | EV92: Haldi / Turmeric | EW92: 138 | EX92: 138 | EY92: KGS | EZ92: 1 | FA92: Store Ghaziabad - GCF | FB92: 0 | FC92: 1 | FI92: 0 | FJ92: 0 | FK92: 0 | FL92: 0 | FM92: 0 | FN92: 0 | FO92: Main - GCF | FQ92: Haldi | FR92: 0 | FS92: 0 | FT92: 0 | FU92: 0 | FV92: Stock Received But Not Billed - GCF | FX92: Nil-Rated | FY92: 09103030 | FZ92: 0 | GA92: 0 | GC92: 0 | GD92: 0 | GE92: 0 | GF92: 0 | GG92: Haldi | GH92: Spices and Seasoning - RM | GI92: 0 | GJ92: {} | GL92: 0 | GO92: 0 | GS92: -1007.4 | GT92: -1007.4 | GU92: 138 | GV92: 138 | GW92: 0 | GX92: -7.3 | GY92: 0 | GZ92: 0 | HD92: 73o2iogt15 | HG92: PR/G/25-26/0193 | HH92: 8g942pf1bo | HJ92: 138 | HK92: 0 | HL92: 0 | HM92: 0 | HN92: -496 | HP92: 0 | HT92: 0 | IA92: 0 | IB92: 0 | ID92: KGS | IE92: Ghaziabad | IF92: -1009 | IG92: 0 | IH92: 0 | II92: 138 | IJ92: 0 | IN92: INR | IO92: Rounded Off - GCF | IP92: Add | IQ92: -1.6 | IR92: -1.6 | IT92: Total | IU92: 0 | IV92: Main - GCF | IW92: Rounded Off | IY92: 0 | IZ92: 0 | JA92: {"Haldi":[0.0,-1.6]} | JC92: -1.6 | JD92: -1.6 | JE92: 0 | JF92: -1009 | JG92: -1009 | JH92: Actual
A93: PI/G/25-26/0185 | B93: PI/G/25-26/0185-1 | C93: PINV-.YY.- | D93: Harlalji Sons Packaging Pvt. Ltd | E93: 45843 | F93: Ghaziabad | G93: Creditors - GCF | H93: Harlalji Sons Packaging Pvt. Ltd | I93: Harlalji Sons Packaging Pvt. Ltd | L93: G. C. Foods Pvt. Ltd. | M93: 0.72119821 | N93: 1 | O93: 45843 | Q93: 0 | R93: 0 | T93: 1 | U93: 0 | V93: 1 | W93: 0 | X93: 0 | Z93: 2025-26/584 | AA93: 45843 | AD93: INR | AE93: 1 | AF93: 1 | AG93: Standard Buying | AH93: INR | AI93: 1 | AJ93: 0 | AL93: 0 | AM93: Store Ghaziabad - GCF | AO93: 0 | AR93: 400 | AS93: 0 | AT93: 7500 | AU93: 7500 | AV93: 7500 | AW93: 7500 | AX93: 7500 | AY93: 7500 | AZ93: In-State | BA93: Input GST In-state - GCF | BE93: 1350 | BF93: 0 | BG93: 1350 | BH93: 1350 | BI93: 0 | BJ93: 1350 | BK93: 8850 | BL93: 0 | BM93: 0 | BN93: INR Eight Thousand, Eight Hundred And Fifty only. | BO93: 8850 | BP93: 0 | BQ93: 0 | BR93: 0 | BS93: INR Eight Thousand, Eight Hundred And Fifty only. | BT93: 0 | BU93: 8850 | BV93: 1 | BW93: Grand Total | BX93: 0 | BY93: 0 | BZ93: 0 | CA93: | HSN/SAC | Taxable Amount | Input Tax CGST @ 9.0 | Input Tax SGST @ 9.0 | | --- | --- | --- | --- | | 39232990 | ₹ 7,500.00 | (9.0%) ₹ 675.00 | (9.0%) ₹ 675.00 | | CC93: 0 | CF93: 0 | CG93: 0 | CH93: 0 | CI93: 0 | CJ93: 0 | CM93: Harlalji Sons Packaging Pvt. Ltd-Billing | CN93: C-6, A-3, Tronica City, Loni Ghaziabad, Uttar Pradesh, State Code: 09, Pincode: 201103, India, GSTIN: 09AAACH9843F1ZE, | CO93: 09AAACH9843F1ZE | CP93: Registered Regular | CU93: Harlalji Sons Packaging Pvt. Ltd-Billing | CV93: C-6, A-3, Tronica City, Loni Ghaziabad, Uttar Pradesh, State Code: 09, Pincode: 201103, India, GSTIN: 09AAACH9843F1ZE, | CW93: G.C. Foods Pvt. Ltd.Ghaziabad - Uttar Pradesh-Billing | CX93: C-4, Sector A-2, , Tronica city Indl. Area, LoniGhaziabad, Uttar Pradesh, State Code: 09, Pincode: 201103, India, Phone: 9350041990, GSTIN: 09AACCG2244H1ZS, | CY93: G.C. Foods Pvt. Ltd.Ghaziabad - Uttar Pradesh-Billing | CZ93: C-4, Sector A-2, , Tronica city Indl. Area, LoniGhaziabad, Uttar Pradesh, State Code: 09, Pincode: 201103, India, Phone: 9350041990, GSTIN: 09AACCG2244H1ZS, | DA93: 09AACCG2244H1ZS | DB93: 09-Uttar Pradesh | DD93: 0 | DF93: Being Purchase of HDPE Bags 24'' X 37'' ( 200 Pcs Ingate no. 311 Date : 31-07-2025 ) Ingate no. 326 Date : 05-07-2025 | DG93: 100 | DH93: INR | DI93: No | DJ93: Stock Received But Not Billed - GCF | DQ93: 0 | DS93: en | DY93: 0 | EA93: Road | EC93: 45843 | ED93: Regular | EE93: All Other ITC | EG93: Unreconciled | EH93: 0 | EK93: 0 | EM93: Creditors - Raw Material | EO93: 0 | EP93: Against Supplier Invoice 2025-26/584 dated 05-07-2025 | ER93: 400 | ES93: 400 | ET93: 7500 | EU93: 7500 | EV93: Plastic Bag Chana Plain 26 kg | EW93: 18.75 | EX93: 18.75 | EY93: PCS | EZ93: 1 | FA93: Store Ghaziabad - GCF | FB93: 0 | FC93: 1 | FI93: 0 | FJ93: 0 | FK93: 0 | FL93: 0 | FM93: 675 | FN93: 9 | FO93: Main - GCF | FQ93: Plastic Plain Bag 26 kg | FR93: 96.25 | FS93: 83.696 | FT93: 0 | FU93: 0 | FV93: Stock Received But Not Billed - GCF | FX93: Taxable | FY93: 39232990 | FZ93: 0 | GA93: 0 | GC93: 0 | GD93: 0 | GE93: 0 | GF93: 0 | GG93: Plastic Bag Chana Plain 26 kg | GH93: Sattu and Chana - PM | GI93: 0 | GJ93: {} | GL93: 0 | GO93: 0 | GS93: 7500 | GT93: 7500 | GU93: 18.75 | GV93: 18.75 | GW93: 0 | GX93: 400 | GY93: 115 | GZ93: 115 | HG93: PR/G/25-26/0194 | HH93: 55qmqc3eka | HJ93: 18.75 | HK93: 0 | HL93: 0 | HM93: 0 | HN93: 400 | HP93: 0 | HT93: 0 | IA93: 675 | IB93: 9 | ID93: PCS | IE93: Ghaziabad | IF93: 7500 | IG93: 0 | IH93: 0 | II93: 18.75 | IJ93: 0 | IN93: INR | IO93: Input Tax CGST - GCF | IP93: Add | IQ93: 675 | IR93: 675 | IT93: Total | IU93: 0 | IV93: Main - GCF | IW93: Input Tax CGST @ 9.0 | IX93: cgst | IY93: 0 | IZ93: 0 | JA93: {"Plastic Bag Chana Plain 26 kg":[9.0,675.0]} | JC93: 675 | JD93: 675 | JE93: 9 | JF93: 8175 | JG93: 8175 | JH93: On Net Total | LD93: 0 | LF93: Percentage | LG93: 0 | LH93: 45843 | LI93: 100 | LK93: 8850 | LL93: 8850 | LM93: 0 | LN93: 0 | LO93: 8850 | LP93: 8850
IN94: INR | IO94: Input Tax SGST - GCF | IP94: Add | IQ94: 675 | IR94: 675 | IT94: Total | IU94: 0 | IV94: Main - GCF | IW94: Input Tax SGST @ 9.0 | IX94: sgst | IY94: 0 | IZ94: 0 | JA94: {"Plastic Bag Chana Plain 26 kg":[9.0,675.0]} | JC94: 675 | JD94: 675 | JE94: 9 | JF94: 8850 | JG94: 8850 | JH94: On Net Total
A95: PI/G/25-26/0184 | B95: PI/G/25-26/0184-1 | C95: PINV-.YY.- | D95: Harlalji Sons Packaging Pvt. Ltd | E95: 45843 | F95: Ghaziabad | G95: Creditors - GCF | H95: Harlalji Sons Packaging Pvt. Ltd | I95: Harlalji Sons Packaging Pvt. Ltd | L95: G. C. Foods Pvt. Ltd. | M95: 0.72097797 | N95: 1 | O95: 45843 | Q95: 0 | R95: 0 | T95: 1 | U95: 0 | V95: 1 | W95: 0 | X95: 0 | Z95: 2025-26/586 | AA95: 45843 | AD95: INR | AE95: 1 | AF95: 1 | AG95: Standard Buying | AH95: INR | AI95: 1 | AJ95: 0 | AL95: 0 | AM95: Store Ghaziabad - GCF | AO95: 0 | AR95: 1473 | AS95: 0 | AT95: 27618.75 | AU95: 27618.75 | AV95: 27618.75 | AW95: 27618.75 | AX95: 27618.75 | AY95: 27618.75 | AZ95: In-State | BA95: Input GST In-state - GCF | BE95: 4971.25 | BF95: 0 | BG95: 4971.25 | BH95: 4971.25 | BI95: 0 | BJ95: 4971.25 | BK95: 32590 | BL95: 0 | BM95: 0 | BN95: INR Thirty Two Thousand, Five Hundred And Ninety only. | BO95: 32590 | BP95: 0 | BQ95: 0 | BR95: 0 | BS95: INR Thirty Two Thousand, Five Hundred And Ninety only. | BT95: 0 | BU95: 32590 | BV95: 1 | BW95: Grand Total | BX95: 0 | BY95: 0 | BZ95: 0 | CA95: | HSN/SAC | Taxable Amount | Input Tax CGST @ 9.0 | Input Tax SGST @ 9.0 | Rounded Off | | --- | --- | --- | --- | --- | | 39232990 | ₹ 27,618.75 | (9.0%) ₹ 2,485.69 | (9.0%) ₹ 2,485.69 | ₹ -0.13 | | CC95: 0 | CF95: 0 | CG95: 0 | CH95: 0 | CI95: 0 | CJ95: 0 | CM95: Harlalji Sons Packaging Pvt. Ltd-Billing | CN95: C-6, A-3, Tronica City, Loni Ghaziabad, Uttar Pradesh, State Code: 09, Pincode: 201103, India, GSTIN: 09AAACH9843F1ZE, | CO95: 09AAACH9843F1ZE | CP95: Registered Regular | CU95: Harlalji Sons Packaging Pvt. Ltd-Billing | CV95: C-6, A-3, Tronica City, Loni Ghaziabad, Uttar Pradesh, State Code: 09, Pincode: 201103, India, GSTIN: 09AAACH9843F1ZE, | CW95: G.C. Foods Pvt. Ltd.Ghaziabad - Uttar Pradesh-Billing | CX95: C-4, Sector A-2, , Tronica city Indl. Area, LoniGhaziabad, Uttar Pradesh, State Code: 09, Pincode: 201103, India, Phone: 9350041990, GSTIN: 09AACCG2244H1ZS, | CY95: G.C. Foods Pvt. Ltd.Ghaziabad - Uttar Pradesh-Billing | CZ95: C-4, Sector A-2, , Tronica city Indl. Area, LoniGhaziabad, Uttar Pradesh, State Code: 09, Pincode: 201103, India, Phone: 9350041990, GSTIN: 09AACCG2244H1ZS, | DA95: 09AACCG2244H1ZS | DB95: 09-Uttar Pradesh | DD95: 0 | DF95: Being Purchase of 18 Bundle Ingate Vch no. 327 Date : 05-07-2025- PLAIN BAGS 26 KG 18 Bundle ( 26 Kg Bag Plain ) | DG95: 100 | DH95: INR | DI95: No | DJ95: Stock Received But Not Billed - GCF | DQ95: 0 | DS95: en | DY95: 0 | EA95: Road | EC95: 45843 | ED95: Regular | EE95: All Other ITC | EG95: Unreconciled | EH95: 0 | EK95: 0 | EM95: Creditors - Raw Material | EO95: 0 | EP95: Against Supplier Invoice 2025-26/586 dated 05-07-2025 | ER95: 1473 | ES95: 1473 | ET95: 27618.75 | EU95: 27618.75 | EV95: Plastic Bag Chana Plain 26 kg | EW95: 18.75 | EX95: 18.75 | EY95: PCS | EZ95: 1 | FA95: Store Ghaziabad - GCF | FB95: 0 | FC95: 1 | FI95: 0 | FJ95: 0 | FK95: 0 | FL95: 0 | FM95: 2485.69 | FN95: 9 | FO95: Main - GCF | FQ95: Plastic Plain Bag 26 kg | FR95: 96.25 | FS95: 83.696 | FT95: 0 | FU95: 0 | FV95: Stock Received But Not Billed - GCF | FX95: Taxable | FY95: 39232990 | FZ95: 0 | GA95: 0 | GC95: 0 | GD95: 0 | GE95: 0 | GF95: 0 | GG95: Plastic Bag Chana Plain 26 kg | GH95: Sattu and Chana - PM | GI95: 0 | GJ95: {} | GL95: 0 | GO95: 0 | GS95: 27618.75 | GT95: 27618.75 | GU95: 18.75 | GV95: 18.75 | GW95: 0 | GX95: 1473 | GY95: 115 | GZ95: 115 | HG95: PR/G/25-26/0195 | HH95: 87sf67bice | HJ95: 18.75 | HK95: 0 | HL95: 0 | HM95: 0 | HN95: 1473 | HP95: 0 | HT95: 0 | IA95: 2485.69 | IB95: 9 | ID95: PCS | IE95: Ghaziabad | IF95: 27618.75 | IG95: 0 | IH95: 0 | II95: 18.75 | IJ95: 0 | IN95: INR | IO95: Input Tax CGST - GCF | IP95: Add | IQ95: 2485.69 | IR95: 2485.69 | IT95: Total | IU95: 0 | IV95: Main - GCF | IW95: Input Tax CGST @ 9.0 | IX95: cgst | IY95: 0 | IZ95: 0 | JA95: {"Plastic Bag Chana Plain 26 kg":[9.0,2485.69]} | JC95: 2485.69 | JD95: 2485.69 | JE95: 9 | JF95: 30104.44 | JG95: 30104.44 | JH95: On Net Total | LD95: 0 | LF95: Percentage | LG95: 0 | LH95: 45843 | LI95: 100 | LK95: 32590 | LL95: 32590 | LM95: 0 | LN95: 0 | LO95: 32590 | LP95: 32590
IN96: INR | IO96: Input Tax SGST - GCF | IP96: Add | IQ96: 2485.69 | IR96: 2485.69 | IT96: Total | IU96: 0 | IV96: Main - GCF | IW96: Input Tax SGST @ 9.0 | IX96: sgst | IY96: 0 | IZ96: 0 | JA96: {"Plastic Bag Chana Plain 26 kg":[9.0,2485.69]} | JC96: 2485.69 | JD96: 2485.69 | JE96: 9 | JF96: 32590.13 | JG96: 32590.13 | JH96: On Net Total
IN97: INR | IO97: Rounded Off - GCF | IP97: Add | IQ97: -0.13 | IR97: -0.13 | IT97: Total | IU97: 0 | IV97: Main - GCF | IW97: Rounded Off | IY97: 0 | IZ97: 0 | JA97: {"Plastic Bag Chana Plain 26 kg":[0.0,-0.13]} | JC97: -0.13 | JD97: -0.13 | JE97: 0 | JF97: 32590 | JG97: 32590 | JH97: Actual
A98: PI/G/25-26/0183 | B98: PI/G/25-26/0183-1 | C98: PINV-.YY.- | D98: ONKAR SINGH MANJEET SINGH | E98: 45849 | F98: Ghaziabad | G98: Creditors - GCF | H98: ONKAR SINGH MANJEET SINGH | I98: ONKAR SINGH MANJEET SINGH | L98: G. C. Foods Pvt. Ltd. | M98: 0.72071709 | N98: 1 | O98: 45849 | Q98: 0 | R98: 0 | T98: 1 | U98: 0 | V98: 1 | W98: 0 | X98: 0 | Z98: OSMS-2021/25-26 | AA98: 45849 | AD98: INR | AE98: 1 | AF98: 1 | AG98: Standard Buying | AH98: INR | AI98: 1 | AJ98: 0 | AL98: 0 | AM98: Store Ghaziabad - GCF | AO98: 0 | AR98: 600 | AS98: 0 | AT98: 20200 | AU98: 20200 | AV98: 20200 | AW98: 20200 | AX98: 20200 | AY98: 20200 | BA98: Input GST In-state - GCF | BE98: 0 | BF98: 0 | BG98: 0 | BH98: 0 | BI98: 0 | BJ98: 0 | BK98: 20200 | BL98: 0 | BM98: 0 | BN98: INR Twenty Thousand, Two Hundred only. | BO98: 20200 | BP98: 0 | BQ98: 0 | BR98: 0 | BS98: INR Twenty Thousand, Two Hundred only. | BT98: 0 | BU98: 20200 | BV98: 1 | BW98: Grand Total | BX98: 0 | BY98: 0 | BZ98: 0 | CA98: | HSN/SAC | Taxable Amount | Input Tax CGST @ 9.0 | Input Tax SGST @ 9.0 | | --- | --- | --- | --- | | 25010010 | ₹ 13,600.00 | (0.0%) ₹ 0.00 | (0.0%) ₹ 0.00 | | 25010090 | ₹ 6,600.00 | (0.0%) ₹ 0.00 | (0.0%) ₹ 0.00 | | CC98: 0 | CF98: 0 | CG98: 0 | CH98: 0 | CI98: 0 | CJ98: 0 | CM98: ONKAR SINGH MANJEET SINGH-Billing | CN98: D-49,50 & 56 SECTOR-A-5/6, TRONICA CITY, LONIGHAZIABAD, Uttar Pradesh, State Code: 09, Pincode: 201102, India, GSTIN: 09AADFO6036D1ZF, | CO98: 09AADFO6036D1ZF | CP98: Registered Regular | CQ98: ONKAR SINGH MANJEET SINGH-ONKAR SINGH MANJEET SINGH | CR98: ONKAR SINGH MANJEET SINGH | CS98: 9811055952 | CT98: tenonkarmanjeet@gmail.com | CU98: ONKAR SINGH MANJEET SINGH-Billing | CV98: D-49,50 & 56 SECTOR-A-5/6, TRONICA CITY, LONIGHAZIABAD, Uttar Pradesh, State Code: 09, Pincode: 201102, India, GSTIN: 09AADFO6036D1ZF, | CW98: G.C. Foods Pvt. Ltd.Ghaziabad - Uttar Pradesh-Billing | CX98: C-4, Sector A-2, , Tronica city Indl. Area, LoniGhaziabad, Uttar Pradesh, State Code: 09, Pincode: 201103, India, Phone: 9350041990, GSTIN: 09AACCG2244H1ZS, | CY98: G.C. Foods Pvt. Ltd.Ghaziabad - Uttar Pradesh-Billing | CZ98: C-4, Sector A-2, , Tronica city Indl. Area, LoniGhaziabad, Uttar Pradesh, State Code: 09, Pincode: 201103, India, Phone: 9350041990, GSTIN: 09AACCG2244H1ZS, | DA98: 09AACCG2244H1ZS | DB98: 09-Uttar Pradesh | DD98: 0 | DF98: Being Purchase of Namak Ingate Vch no. 343 Date : 11-07-2025 8 Bags ( Lahauri Crystal Khula Namak ) 4 Bags ( Kala Crystal Khula ) | DG98: 100 | DH98: INR | DI98: No | DJ98: Stock Received But Not Billed - GCF | DQ98: 0 | DS98: en | DY98: 0 | EA98: Road | EC98: 45849 | ED98: Regular | EE98: All Other ITC | EG98: Unreconciled | EH98: 0 | EK98: 0 | EM98: Creditors - Raw Material | EO98: 0 | EP98: Against Supplier Invoice OSMS-2021/25-26 dated 11-07-2025 | ER98: 400 | ES98: 400 | ET98: 13600 | EU98: 13600 | EV98: Sendha Namak | EW98: 34 | EX98: 34 | EY98: KGS | EZ98: 1 | FA98: Store Ghaziabad - GCF | FB98: 0 | FC98: 1 | FI98: 0 | FJ98: 0 | FK98: 0 | FL98: 0 | FM98: 0 | FN98: 0 | FO98: Main - GCF | FQ98: Sendha Namak | FR98: -4 | FS98: 0 | FT98: 0 | FU98: 0 | FV98: Stock Received But Not Billed - GCF | FX98: Exempted | FY98: 25010010 | FZ98: 0 | GA98: 0 | GC98: 0 | GD98: 0 | GE98: 0 | GF98: 0 | GG98: Sendha Namak | GH98: Spices and Seasoning - RM | GI98: 0 | GJ98: {"Input Tax CGST - GCF": 0.0, "Input Tax SGST - GCF": 0.0, "Input Tax IGST - GCF": 0.0, "Output Tax CGST - GCF": 0.0, "Output Tax SGST - GCF": 0.0, "Output Tax IGST - GCF": 0.0, "Input Tax CGST RCM - GCF": 0.0, "Input Tax SGST RCM - GCF": 0.0, "Input Tax IGST RCM - GCF": 0.0} | GK98: Exempted - GCF | GL98: 0 | GO98: 4 | GP98: Amount | GS98: 13600 | GT98: 13600 | GU98: 34 | GV98: 34 | GW98: 0 | GX98: 400 | GY98: 30 | GZ98: 30 | HG98: PR/G/25-26/0196 | HH98: b9sq9jdjrt | HJ98: 34 | HK98: 0 | HL98: 0 | HM98: 0 | HN98: 400 | HP98: 0 | HT98: 0 | IA98: 0 | IB98: 0 | ID98: KGS | IE98: Ghaziabad | IF98: 13600 | IG98: 0 | IH98: 0 | II98: 34 | IJ98: 0 | IN98: INR | IO98: Input Tax CGST - GCF | IP98: Add | IQ98: 0 | IR98: 0 | IT98: Total | IU98: 0 | IV98: Main - GCF | IW98: Input Tax CGST @ 9.0 | IX98: cgst | IY98: 0 | IZ98: 0 | JA98: {"Sendha Namak":[0.0,0.0],"Kala Namak / Black Salt":[0.0,0.0]} | JC98: 0 | JD98: 0 | JE98: 0 | JF98: 20200 | JG98: 20200 | JH98: On Net Total | LD98: 0 | LF98: Percentage | LG98: 0 | LH98: 45849 | LI98: 100 | LK98: 20200 | LL98: 20200 | LM98: 0 | LN98: 0 | LO98: 20200 | LP98: 20200
ER99: 200 | ES99: 200 | ET99: 6600 | EU99: 6600 | EV99: Kala Namak / Black Salt | EW99: 33 | EX99: 33 | EY99: KGS | EZ99: 1 | FA99: Store Ghaziabad - GCF | FB99: 0 | FC99: 1 | FI99: 0 | FJ99: 0 | FK99: 0 | FL99: 0 | FM99: 0 | FN99: 0 | FO99: Main - GCF | FQ99: Black Salt / Kala Namak | FR99: 0 | FS99: 0 | FT99: 0 | FU99: 0 | FV99: Stock Received But Not Billed - GCF | FX99: Exempted | FY99: 25010090 | FZ99: 0 | GA99: 0 | GC99: 0 | GD99: 0 | GE99: 0 | GF99: 0 | GG99: Kala Namak / Black Salt | GH99: Spices and Seasoning - FG | GI99: 0 | GJ99: {"Input Tax CGST - GCF": 0.0, "Input Tax SGST - GCF": 0.0, "Input Tax IGST - GCF": 0.0, "Output Tax CGST - GCF": 0.0, "Output Tax SGST - GCF": 0.0, "Output Tax IGST - GCF": 0.0, "Input Tax CGST RCM - GCF": 0.0, "Input Tax SGST RCM - GCF": 0.0, "Input Tax IGST RCM - GCF": 0.0} | GK99: Exempted - GCF | GL99: 0 | GO99: 0 | GS99: 6600 | GT99: 6600 | GU99: 33 | GV99: 33 | GW99: 0 | GX99: 200 | GY99: 0 | GZ99: 0 | HG99: PR/G/25-26/0196 | HH99: b9sqdqk286 | HJ99: 33 | HK99: 0 | HL99: 0 | HM99: 0 | HN99: 200 | HP99: 0 | HT99: 0 | IA99: 0 | IB99: 0 | ID99: KGS | IE99: Ghaziabad | IF99: 6600 | IG99: 0 | IH99: 0 | II99: 33 | IJ99: 0 | IN99: INR | IO99: Input Tax SGST - GCF | IP99: Add | IQ99: 0 | IR99: 0 | IT99: Total | IU99: 0 | IV99: Main - GCF | IW99: Input Tax SGST @ 9.0 | IX99: sgst | IY99: 0 | IZ99: 0 | JA99: {"Sendha Namak":[0.0,0.0],"Kala Namak / Black Salt":[0.0,0.0]} | JC99: 0 | JD99: 0 | JE99: 0 | JF99: 20200 | JG99: 20200 | JH99: On Net Total
A100: PI/G/25-26/0182 | B100: PI/G/25-26/0182-1 | C100: PINV-.YY.- | D100: Harlalji Sons Packaging Pvt. Ltd | E100: 45852 | F100: Ghaziabad | G100: Creditors - GCF | H100: Harlalji Sons Packaging Pvt. Ltd | I100: Harlalji Sons Packaging Pvt. Ltd | L100: G. C. Foods Pvt. Ltd. | M100: 0.72042381 | N100: 1 | O100: 45852 | Q100: 0 | R100: 0 | T100: 1 | U100: 0 | V100: 1 | W100: 0 | X100: 0 | Z100: 2025-26/642 | AA100: 45852 | AD100: INR | AE100: 1 | AF100: 1 | AG100: Standard Buying | AH100: INR | AI100: 1 | AJ100: 0 | AL100: 0 | AM100: Store Ghaziabad - GCF | AO100: 0 | AR100: 9400 | AS100: 0 | AT100: 176250 | AU100: 176250 | AV100: 176250 | AW100: 176250 | AX100: 176250 | AY100: 176250 | AZ100: In-State | BA100: Input GST In-state - GCF | BE100: 31725 | BF100: 0 | BG100: 31725 | BH100: 31725 | BI100: 0 | BJ100: 31725 | BK100: 207975 | BL100: 0 | BM100: 0 | BN100: INR Two Lakh, Seven Thousand, Nine Hundred And Seventy Five only. | BO100: 207975 | BP100: 0 | BQ100: 0 | BR100: 0 | BS100: INR Two Lakh, Seven Thousand, Nine Hundred And Seventy Five only. | BT100: 0 | BU100: 207975 | BV100: 1 | BW100: Grand Total | BX100: 0 | BY100: 0 | BZ100: 0 | CA100: | HSN/SAC | Taxable Amount | Input Tax CGST @ 9.0 | Input Tax SGST @ 9.0 | | --- | --- | --- | --- | | 39232990 | ₹ 1,76,250.00 | (9.0%) ₹ 15,862.50 | (9.0%) ₹ 15,862.50 | | CC100: 0 | CF100: 0 | CG100: 0 | CH100: 0 | CI100: 0 | CJ100: 0 | CM100: Harlalji Sons Packaging Pvt. Ltd-Billing | CN100: C-6, A-3, Tronica City, Loni Ghaziabad, Uttar Pradesh, State Code: 09, Pincode: 201103, India, GSTIN: 09AAACH9843F1ZE, | CO100: 09AAACH9843F1ZE | CP100: Registered Regular | CU100: Harlalji Sons Packaging Pvt. Ltd-Billing | CV100: C-6, A-3, Tronica City, Loni Ghaziabad, Uttar Pradesh, State Code: 09, Pincode: 201103, India, GSTIN: 09AAACH9843F1ZE, | CW100: G.C. Foods Pvt. Ltd.Ghaziabad - Uttar Pradesh-Billing | CX100: C-4, Sector A-2, , Tronica city Indl. Area, LoniGhaziabad, Uttar Pradesh, State Code: 09, Pincode: 201103, India, Phone: 9350041990, GSTIN: 09AACCG2244H1ZS, | CY100: G.C. Foods Pvt. Ltd.Ghaziabad - Uttar Pradesh-Billing | CZ100: C-4, Sector A-2, , Tronica city Indl. Area, LoniGhaziabad, Uttar Pradesh, State Code: 09, Pincode: 201103, India, Phone: 9350041990, GSTIN: 09AACCG2244H1ZS, | DA100: 09AACCG2244H1ZS | DB100: 09-Uttar Pradesh | DD100: 0 | DF100: Ingate Vch no. 355 Date : 14-07-2025 Plain 26 Kg Bag = 94 Nos LD Plain 26 Kg = 19 Nos. | DG100: 100 | DH100: INR | DI100: No | DJ100: Stock Received But Not Billed - GCF | DQ100: 0 | DS100: en | DY100: 0 | EA100: Road | EC100: 45852 | ED100: Regular | EE100: All Other ITC | EG100: Unreconciled | EH100: 0 | EK100: 0 | EM100: Creditors - Raw Material | EO100: 0 | EP100: Against Supplier Invoice 2025-26/642 dated 14-07-2025 | ER100: 9400 | ES100: 9400 | ET100: 176250 | EU100: 176250 | EV100: Plastic Bag Chana Plain 26 kg | EW100: 18.75 | EX100: 18.75 | EY100: PCS | EZ100: 1 | FA100: Store Ghaziabad - GCF | FB100: 0 | FC100: 1 | FI100: 0 | FJ100: 0 | FK100: 0 | FL100: 0 | FM100: 15862.5 | FN100: 9 | FO100: Main - GCF | FQ100: Plastic Plain Bag 26 kg | FR100: 96.25 | FS100: 83.696 | FT100: 0 | FU100: 0 | FV100: Stock Received But Not Billed - GCF | FX100: Taxable | FY100: 39232990 | FZ100: 0 | GA100: 0 | GC100: 0 | GD100: 0 | GE100: 0 | GF100: 0 | GG100: Plastic Bag Chana Plain 26 kg | GH100: Sattu and Chana - PM | GI100: 0 | GJ100: {} | GL100: 0 | GO100: 0 | GS100: 176250 | GT100: 176250 | GU100: 18.75 | GV100: 18.75 | GW100: 0 | GX100: 9400 | GY100: 115 | GZ100: 115 | HG100: PR/G/25-26/0197 | HH100: aq1io6qbc4 | HJ100: 18.75 | HK100: 0 | HL100: 0 | HM100: 0 | HN100: 9400 | HP100: 0 | HT100: 0 | IA100: 15862.5 | IB100: 9 | ID100: PCS | IE100: Ghaziabad | IF100: 176250 | IG100: 0 | IH100: 0 | II100: 18.75 | IJ100: 0 | IN100: INR | IO100: Input Tax CGST - GCF | IP100: Add | IQ100: 15862.5 | IR100: 15862.5 | IT100: Total | IU100: 0 | IV100: Main - GCF | IW100: Input Tax CGST @ 9.0 | IX100: cgst | IY100: 0 | IZ100: 0 | JA100: {"Plastic Bag Chana Plain 26 kg":[9.0,15862.5]} | JC100: 15862.5 | JD100: 15862.5 | JE100: 9 | JF100: 192112.5 | JG100: 192112.5 | JH100: On Net Total | LD100: 0 | LF100: Percentage | LG100: 0 | LH100: 45852 | LI100: 100 | LK100: 207975 | LL100: 207975 | LM100: 0 | LN100: 0 | LO100: 207975 | LP100: 207975
...

Sheet Old Status from Backup
A1: Sr | B1: ID | C1: Status | D1: Supplier | E1: Company | F1: Date | G1: Branch | H1: Net Total | I1: Outstanding Amount | J1: Currency | K1: Party Account Currency | L1: Supplier Name | M1: Grand Total (Company Currency) | N1: Due Date | O1: Is Return (Debit Note) | P1: Release Date | Q1: Hold Invoice | R1: Represents Company | S1: Is Internal Supplier | T1: Purchase Order (Purchase Invoice Item) | U1: Purchase Receipt (Purchase Invoice Item) | V1: name (Purchase Invoice Item) | W1: owner
A2: 1 | B2: PI/M/25-26/0132 | C2: Overdue | D2: Jogi Jee Patna | E2: G. C. Foods Pvt. Ltd. | F2: 45866 | G2: Muzaffarpur | H2: 26544 | I2: 26550 | J2: INR | K2: INR | L2: Jogi Jee Patna | M2: 26550 | N2: 45866 | O2: 0 | Q2: 0 | S2: 0 | U2: PR/M/25-26/0128 | V2: b83tc27f82 | W2: gcsanjeet@rediffmail.com
A3: 2 | B3: PI/N/25-26/0042 | C3: Overdue | D3: Bajrang Traders | E3: G. C. Foods Pvt. Ltd. | F3: 45860 | G3: Noida | H3: 38060 | I3: 38060 | J3: INR | K3: INR | L3: Bajrang Traders | M3: 38060 | N3: 45860 | O3: 0 | Q3: 0 | S3: 0 | T3: PO/N/25-26/0032 | U3: PR/N/25-26/0082 | V3: 3ddn1f8bd9 | W3: nitinchaudhary0911@gmail.com
A4: 3 | B4: PI/N/25-26/0042 | C4: Overdue | D4: Bajrang Traders | E4: G. C. Foods Pvt. Ltd. | F4: 45860 | G4: Noida | H4: 38060 | I4: 38060 | J4: INR | K4: INR | L4: Bajrang Traders | M4: 38060 | N4: 45860 | O4: 0 | Q4: 0 | S4: 0 | T4: PO/N/25-26/0032 | U4: PR/N/25-26/0082 | V4: 3ddn4k6uhh | W4: nitinchaudhary0911@gmail.com
A5: 4 | B5: PI/N/25-26/0042 | C5: Overdue | D5: Bajrang Traders | E5: G. C. Foods Pvt. Ltd. | F5: 45860 | G5: Noida | H5: 38060 | I5: 38060 | J5: INR | K5: INR | L5: Bajrang Traders | M5: 38060 | N5: 45860 | O5: 0 | Q5: 0 | S5: 0 | T5: PO/N/25-26/0032 | U5: PR/N/25-26/0082 | V5: 3ddn8pi0qp | W5: nitinchaudhary0911@gmail.com
A6: 5 | B6: PI/N/25-26/0041 | C6: Overdue | D6: Bajrang Traders | E6: G. C. Foods Pvt. Ltd. | F6: 45855 | G6: Noida | H6: 36610 | I6: 36610 | J6: INR | K6: INR | L6: Bajrang Traders | M6: 36610 | N6: 45855 | O6: 0 | Q6: 0 | S6: 0 | T6: PO/N/25-26/0031 | V6: eaajjc93ia | W6: nitinchaudhary0911@gmail.com
A7: 6 | B7: PI/N/25-26/0041 | C7: Overdue | D7: Bajrang Traders | E7: G. C. Foods Pvt. Ltd. | F7: 45855 | G7: Noida | H7: 36610 | I7: 36610 | J7: INR | K7: INR | L7: Bajrang Traders | M7: 36610 | N7: 45855 | O7: 0 | Q7: 0 | S7: 0 | T7: PO/N/25-26/0031 | V7: eaajosnfuv | W7: nitinchaudhary0911@gmail.com
A8: 7 | B8: PI/N/25-26/0034-1 | C8: Overdue | D8: Om Mithila Industries | E8: G. C. Foods Pvt. Ltd. | F8: 45850 | G8: Noida | H8: 29640 | I8: 33197 | J8: INR | K8: INR | L8: Om Mithila Industries | M8: 33197 | N8: 45850 | O8: 0 | Q8: 0 | S8: 0 | U8: PR/N/25-26/0074 | V8: 9j46ico2dp | W8: nitinchaudhary0911@gmail.com
A9: 8 | B9: PI/N/25-26/0034 | C9: Cancelled | D9: Om Mithila Industries | E9: G. C. Foods Pvt. Ltd. | F9: 45859 | G9: Noida | H9: 29640 | I9: 33197 | J9: INR | K9: INR | L9: Om Mithila Industries | M9: 33197 | N9: 45859 | O9: 0 | Q9: 0 | S9: 0 | U9: PR/N/25-26/0074 | V9: esc9svdpqj | W9: nitinchaudhary0911@gmail.com
A10: 9 | B10: PI/M/25-26/0131 | C10: Overdue | D10: Dev Shri Road Line | E10: G. C. Foods Pvt. Ltd. | F10: 45862 | G10: Muzaffarpur | H10: 126728 | I10: 126728 | J10: INR | K10: INR | L10: Dev Shri Road Line | M10: 126728 | N10: 45862 | O10: 0 | Q10: 0 | S10: 0 | U10: PR/M/25-26/0127 | V10: 85k3p3eq7n | W10: gcsanjeet@rediffmail.com
A11: 10 | B11: PI/M/25-26/0130 | C11: Overdue | D11: Goyal Proteins Limited | E11: G. C. Foods Pvt. Ltd. | F11: 45862 | G11: Muzaffarpur | H11: 1538527 | I11: 1613915 | J11: INR | K11: INR | L11: Goyal Proteins Limited | M11: 1613915 | N11: 45862 | O11: 0 | Q11: 0 | S11: 0 | U11: PR/M/25-26/0124 | V11: es2dh5k3mn | W11: gcsanjeet@rediffmail.com
